Workbook
Name million: 1000000
Name thousand: 1000

Sheet Check
B2: By Tab
B4: Consolidated | D4: =+#REF! -> #REF!
B5: Organic | D5: =+#REF! -> #REF!
B6: Food Systems | D6: =+#REF! -> #REF!
B7: Frulact Portugal | D7: =+#REF! -> #REF!
B8: Frulact France | D8: =+#REF! -> #REF!
B9: Frulact Germany | D9: =+#REF! -> #REF!
B10: Frulact Switzerland | D10: =+#REF! -> #REF!
B11: Frulact Maroc | D11: =+#REF! -> #REF!
B12: Frulact South Africa | D12: =+#REF! -> #REF!
B13: Frulact Canada | D13: =+#REF! -> #REF!
B14: Frulact USA | D14: =+#REF! -> #REF!
B15: Plant-Based | D15: =+#REF! -> #REF!
... B20: Add-ons | D20: =+#REF! -> #REF!
B21: Master Check | D21: =SUM(D4:D20) -> #REF!

Sheet Cover
K4: Strictly Private and Confidential

Sheet LBO Model >

Sheet LBO
B3: Sources & Uses | N3: IRR | O3: =+L43 -> 0.21128524
N4: MOIC | O4: =+M43 -> 2.5047266
B5: Sources | C5: €M | D5: xEBITDA | F5: Uses | G5: €M | H5: xEBITDA
B6: Equity ticket | C6: =+'Debt Summary'!D11 -> 296.4975 | D6: =+'Debt Summary'!E11 -> 5.7796784 | F6: =+'Debt Summary'!G11 -> Purchase Price | G6: =+'Debt Summary'!H11 -> 540 | H6: =+'Debt Summary'!I11 -> 10.526316
B7: TLA | C7: =+'Debt Summary'!D12 -> 0 | D7: =+'Debt Summary'!E12 -> 0
B8: TLB | C8: =+'Debt Summary'!D13 -> 256.5 | D8: =+'Debt Summary'!E13 -> 5 | F8: =+'Debt Summary'!G13 -> Structuring fees | G8: =+'Debt Summary'!H13 -> 4.8975 | H8: =+'Debt Summary'!I13 -> 0.095467836
B9: =+'Debt Summary'!C14 -> Holdco PIK | C9: =+'Debt Summary'!D14 -> 0 | D9: =+'Debt Summary'!E14 -> 0 | F9: =+'Debt Summary'!G14 -> Transaction cost | G9: =+'Debt Summary'!H14 -> 8.1 | H9: =+'Debt Summary'!I14 -> 0.15789474
B10: TOTAL | C10: =+ROUND(SUM(C6:C9),1) -> 553 | D10: =+SUM(D6:D9) -> 10.779678 | F10: TOTAL | G10: =+SUM(G6:G9) -> 552.9975 | H10: =+SUM(H6:H9) -> 10.779678
B11: Equity Cushion | C11: =+C6/C10 -> 0.53616184 | H11: =+ROUND(C10,0)=ROUND(G10,0) -> TRUE
B13: Returns
C15: Entry date | D15: 46022
C16: Exit date | D16: 47848
C17: Exit multiple | D17: 10
B20: Exit valuation analysis | J20: 46022 | K20: =+EOMONTH(J20,12) -> 46387 | L20: =+EOMONTH(K20,12) -> 46752 | M20: =+EOMONTH(L20,12) -> 47118 | N20: =+EOMONTH(M20,12) -> 47483 | O20: =+EOMONTH(N20,12) -> 47848 | P20: =+EOMONTH(O20,12) -> 48213
C22: EBITDA | J22: =+'Debt Summary'!M13 -> 51.3 | K22: =+'Debt Summary'!N13 -> 52.243319 | L22: =+'Debt Summary'!O13 -> 61.713285 | M22: =+'Debt Summary'!P13 -> 73.285082 | N22: =+'Debt Summary'!Q13 -> 79.587752 | O22: =+'Debt Summary'!R13 -> 87.783624 | P22: =+'Debt Summary'!S13 -> 89.539296
C23: EBITDA multiple | J23: =+D17 -> 10 | K23: =+J23 -> 10 | L23: =+K23 -> 10 | M23: =+L23 -> 10 | N23: =+M23 -> 10 | O23: =+N23 -> 10 | P23: =+O23 -> 10
C24: Enterprise Value | J24: =+J22*J23 -> 513 | K24: =+K22*K23 -> 522.43319 | L24: =+L22*L23 -> 617.13285 | M24: =+M22*M23 -> 732.85082 | N24: =+N22*N23 -> 795.87752 | O24: =+O22*O23 -> 877.83624 | P24: =+P22*P23 -> 895.39296
C25: Financial debt | J25: =-'Debt Summary'!M44 -> -256.5 | K25: =-'Debt Summary'!N44 -> -267.14142 | L25: =-'Debt Summary'!O44 -> -291.64354 | M25: =-'Debt Summary'!P44 -> -304.19406 | N25: =-'Debt Summary'!Q44 -> -304.19406 | O25: =-'Debt Summary'!R44 -> -304.19406 | P25: =-'Debt Summary'!S44 -> -304.19406
C26: Cash | J26: =+'Debt Summary'!M33 -> 0 | K26: =+'Debt Summary'!N33 -> 28.530578 | L26: =+'Debt Summary'!O33 -> 62.036428 | M26: =+'Debt Summary'!P33 -> 87.807268 | N26: =+'Debt Summary'!Q33 -> 10 | O26: =+'Debt Summary'!R33 -> 37.531609 | P26: =+'Debt Summary'!S33 -> 67.441735
C27: Transaction expenses | J27: =-J24*1.5% -> -7.695 | K27: =-K24*1.5% -> -7.8364979 | L27: =-L24*1.5% -> -9.2569928 | M27: =-M24*1.5% -> -10.992762 | N27: =-N24*1.5% -> -11.938163 | O27: =-O24*1.5% -> -13.167544 | P27: =-P24*1.5% -> -13.430894
C28: Equity Value | J28: =+SUM(J24:J27) -> 248.805 | K28: =+SUM(K24:K27) -> 275.98585 | L28: =+SUM(L24:L27) -> 378.26875 | M28: =+SUM(M24:M27) -> 505.47127 | N28: =+SUM(N24:N27) -> 489.74529 | O28: =+SUM(O24:O27) -> 598.00624 | P28: =+SUM(P24:P27) -> 645.20974
C30: Dividends received | J30: =+'Debt Summary'!M29 -> 0 | K30: =+'Debt Summary'!N29 -> 0 | L30: =+'Debt Summary'!O29 -> 0 | M30: =+'Debt Summary'!P29 -> 15.77084 | N30: =+'Debt Summary'!Q29 -> 111.33647 | O30: =+'Debt Summary'!R29 -> 17.531609 | P30: =+'Debt Summary'!S29 -> 19.910127
C32: IRR | J32: {=+TRANSPOSE(L38:L44)} -> 0 | K32: -0.069179836 | L32: 0.12950905 | M32: 0.20669718 | N32: 0.20239075 | O32: 0.21128524 | P32: 0.19702684
C33: MOIC | J33: {=+TRANSPOSE(M38:M44)} -> 0.83914704 | K33: 0.93082016 | L33: 1.2757907 | M33: 1.7579983 | N33: 2.0804648 | O33: 2.5047266 | P33: 2.7310813
D36: Funding
D37: =+C38 -> 46022 | E37: =+D37 -> 46022 | F37: =+EOMONTH(E37,12) -> 46387 | G37: =+EOMONTH(F37,12) -> 46752 | H37: =+EOMONTH(G37,12) -> 47118 | I37: =+EOMONTH(H37,12) -> 47483 | J37: =+EOMONTH(I37,12) -> 47848 | K37: =+EOMONTH(J37,12) -> 48213 | L37: IRR | M37: MOIC
C38: =+D15 -> 46022 | D38: =-C6 -> -296.4975 | E38: =+IF($C38=J$20,J$28,0)+IF($C38>=J$20,J$30,0) -> 248.805 | F38: =+IF($C38=K$20,K$28,0)+IF($C38>=K$20,K$30,0) -> 0 | G38: =+IF($C38=L$20,L$28,0)+IF($C38>=L$20,L$30,0) -> 0 | H38: =+IF($C38=M$20,M$28,0)+IF($C38>=M$20,M$30,0) -> 0 | I38: =+IF($C38=N$20,N$28,0)+IF($C38>=N$20,N$30,0) -> 0 | J38: =+IF($C38=O$20,O$28,0)+IF($C38>=O$20,O$30,0) -> 0 | K38: =+IF($C38=P$20,P$28,0)+IF($C38>=P$20,P$30,0) -> 0 | L38: =IFERROR(+XIRR($D38:$K38,$D$37:$K$37),0) -> 0 | M38: =IFERROR(+SUM(E38:K38)/-D38,0) -> 0.83914704
C39: =+EOMONTH(C38,12) -> 46387 | D39: =+D38 -> -296.4975 | E39: =+IF($C39=J$20,J$28,0)+IF($C39>=J$20,J$30,0) -> 0 | F39: =+IF($C39=K$20,K$28,0)+IF($C39>=K$20,K$30,0) -> 275.98585 | G39: =+IF($C39=L$20,L$28,0)+IF($C39>=L$20,L$30,0) -> 0 | H39: =+IF($C39=M$20,M$28,0)+IF($C39>=M$20,M$30,0) -> 0 | I39: =+IF($C39=N$20,N$28,0)+IF($C39>=N$20,N$30,0) -> 0 | J39: =+IF($C39=O$20,O$28,0)+IF($C39>=O$20,O$30,0) -> 0 | K39: =+IF($C39=P$20,P$28,0)+IF($C39>=P$20,P$30,0) -> 0 | L39: =IFERROR(+XIRR($D39:$K39,$D$37:$K$37),0) -> -0.069179836 | M39: =IFERROR(+SUM(E39:K39)/-D39,0) -> 0.93082016
C40: =+EOMONTH(C39,12) -> 46752 | D40: =+D39 -> -296.4975 | E40: =+IF($C40=J$20,J$28,0)+IF($C40>=J$20,J$30,0) -> 0 | F40: =+IF($C40=K$20,K$28,0)+IF($C40>=K$20,K$30,0) -> 0 | G40: =+IF($C40=L$20,L$28,0)+IF($C40>=L$20,L$30,0) -> 378.26875 | H40: =+IF($C40=M$20,M$28,0)+IF($C40>=M$20,M$30,0) -> 0 | I40: =+IF($C40=N$20,N$28,0)+IF($C40>=N$20,N$30,0) -> 0 | J40: =+IF($C40=O$20,O$28,0)+IF($C40>=O$20,O$30,0) -> 0 | K40: =+IF($C40=P$20,P$28,0)+IF($C40>=P$20,P$30,0) -> 0 | L40: =IFERROR(+XIRR($D40:$K40,$D$37:$K$37),0) -> 0.12950905 | M40: =IFERROR(+SUM(E40:K40)/-D40,0) -> 1.2757907
C41: =+EOMONTH(C40,12) -> 47118 | D41: =+D40 -> -296.4975 | E41: =+IF($C41=J$20,J$28,0)+IF($C41>=J$20,J$30,0) -> 0 | F41: =+IF($C41=K$20,K$28,0)+IF($C41>=K$20,K$30,0) -> 0 | G41: =+IF($C41=L$20,L$28,0)+IF($C41>=L$20,L$30,0) -> 0 | H41: =+IF($C41=M$20,M$28,0)+IF($C41>=M$20,M$30,0) -> 521.24211 | I41: =+IF($C41=N$20,N$28,0)+IF($C41>=N$20,N$30,0) -> 0 | J41: =+IF($C41=O$20,O$28,0)+IF($C41>=O$20,O$30,0) -> 0 | K41: =+IF($C41=P$20,P$28,0)+IF($C41>=P$20,P$30,0) -> 0 | L41: =IFERROR(+XIRR($D41:$K41,$D$37:$K$37),0) -> 0.20669718 | M41: =IFERROR(+SUM(E41:K41)/-D41,0) -> 1.7579983
C42: =+EOMONTH(C41,12) -> 47483 | D42: =+D41 -> -296.4975 | E42: =+IF($C42=J$20,J$28,0)+IF($C42>=J$20,J$30,0) -> 0 | F42: =+IF($C42=K$20,K$28,0)+IF($C42>=K$20,K$30,0) -> 0 | G42: =+IF($C42=L$20,L$28,0)+IF($C42>=L$20,L$30,0) -> 0 | H42: =+IF($C42=M$20,M$28,0)+IF($C42>=M$20,M$30,0) -> 15.77084 | I42: =+IF($C42=N$20,N$28,0)+IF($C42>=N$20,N$30,0) -> 601.08176 | J42: =+IF($C42=O$20,O$28,0)+IF($C42>=O$20,O$30,0) -> 0 | K42: =+IF($C42=P$20,P$28,0)+IF($C42>=P$20,P$30,0) -> 0 | L42: =IFERROR(+XIRR($D42:$K42,$D$37:$K$37),0) -> 0.20239075 | M42: =IFERROR(+SUM(E42:K42)/-D42,0) -> 2.0804648
C43: =+EOMONTH(C42,12) -> 47848 | D43: =+D42 -> -296.4975 | E43: =+IF($C43=J$20,J$28,0)+IF($C43>=J$20,J$30,0) -> 0 | F43: =+IF($C43=K$20,K$28,0)+IF($C43>=K$20,K$30,0) -> 0 | G43: =+IF($C43=L$20,L$28,0)+IF($C43>=L$20,L$30,0) -> 0 | H43: =+IF($C43=M$20,M$28,0)+IF($C43>=M$20,M$30,0) -> 15.77084 | I43: =+IF($C43=N$20,N$28,0)+IF($C43>=N$20,N$30,0) -> 111.33647 | J43: =+IF($C43=O$20,O$28,0)+IF($C43>=O$20,O$30,0) -> 615.53785 | K43: =+IF($C43=P$20,P$28,0)+IF($C43>=P$20,P$30,0) -> 0 | L43: =IFERROR(+XIRR($D43:$K43,$D$37:$K$37),0) -> 0.21128524 | M43: =IFERROR(+SUM(E43:K43)/-D43,0) -> 2.5047266
C44: =+EOMONTH(C43,12) -> 48213 | D44: =+D43 -> -296.4975 | E44: =+IF($C44=J$20,J$28,0)+IF($C44>=J$20,J$30,0) -> 0 | F44: =+IF($C44=K$20,K$28,0)+IF($C44>=K$20,K$30,0) -> 0 | G44: =+IF($C44=L$20,L$28,0)+IF($C44>=L$20,L$30,0) -> 0 | H44: =+IF($C44=M$20,M$28,0)+IF($C44>=M$20,M$30,0) -> 15.77084 | I44: =+IF($C44=N$20,N$28,0)+IF($C44>=N$20,N$30,0) -> 111.33647 | J44: =+IF($C44=O$20,O$28,0)+IF($C44>=O$20,O$30,0) -> 17.531609 | K44: =+IF($C44=P$20,P$28,0)+IF($C44>=P$20,P$30,0) -> 665.11987 | L44: =IFERROR(+XIRR($D44:$K44,$D$37:$K$37),0) -> 0.19702684 | M44: =IFERROR(+SUM(E44:K44)/-D44,0) -> 2.7310813

Sheet Debt Summary
C2: =RIGHT(CELL("filename",D1), LEN(CELL("filename", D1))- FIND("]", CELL("filename", D1), 1)) -> Debt Summary
C4: Key output | K4: Revenues & Cashflow Statement
M5: FY25B | N5: FY26F | O5: FY27F | P5: FY28F | Q5: FY29F | R5: FY30F | S5: FY31F | T5: FY32F | U5: 25B-32F | V5: 26B-32F CAGR
C6: Estimated closing | D6: =Model!D4 -> 46022
K7: Revenue | M7: ='Active Case'!F9 -> 267.66926 | N7: ='Active Case'!G9 -> 300.63698 | O7: ='Active Case'!H9 -> 344.37965 | P7: ='Active Case'!I9 -> 386.42074 | Q7: ='Active Case'!J9 -> 411.17115 | R7: ='Active Case'!K9 -> 438.6581 | S7: ='Active Case'!L9 -> 447.43126 | T7: ='Active Case'!M9 -> 456.37989 | U7: =+SUM(M7:T7) -> 3052.747 | V7: =+(T7/M7)^(1/7)-1 -> 0.079205128
C8: Sources & Uses | K8: Revenue growth YoY | N8: =+N7/M7-1 -> 0.1231659 | O8: =+O7/N7-1 -> 0.14549995 | P8: =+P7/O7-1 -> 0.12207776 | Q8: =+Q7/P7-1 -> 0.064050414 | R8: =+R7/Q7-1 -> 0.066850379 | S8: =+S7/R7-1 -> 0.02 | T8: =+T7/S7-1 -> 0.02
K9: EBITDA | M9: ='Active Case'!F12 -> 45.111661 | N9: ='Active Case'!G12 -> 52.243319 | O9: ='Active Case'!H12 -> 61.713285 | P9: ='Active Case'!I12 -> 73.285082 | Q9: ='Active Case'!J12 -> 79.587752 | R9: ='Active Case'!K12 -> 87.783624 | S9: ='Active Case'!L12 -> 89.539296 | T9: ='Active Case'!M12 -> 91.330082 | U9: =+SUM(M9:T9) -> 580.5941 | V9: =+(T9/M9)^(1/7)-1 -> 0.10601424
C10: Sources | D10: €M | E10: xEBITDA | G10: Uses | H10: €M | I10: xEBITDA | K10: EBITDA margin | M10: =+M9/M7 -> 0.16853508 | N10: =+N9/N7 -> 0.17377543 | O10: =+O9/O7 -> 0.17920132 | P10: =+P9/P7 -> 0.18965101 | Q10: =+Q9/Q7 -> 0.19356356 | R10: =+R9/R7 -> 0.20011855 | S10: =+S9/S7 -> 0.20011855 | T10: =+T9/T7 -> 0.20011855
C11: Equity ticket | D11: =+'Debt Structure'!D51 -> 296.4975 | E11: =+D11/$M$13 -> 5.7796784 | G11: =+'Debt Structure'!F51 -> Purchase Price | H11: =+'Debt Structure'!G51 -> 540 | I11: =+H11/$M$13 -> 10.526316
C12: TLA | D12: =+'Debt Structure'!D52 -> 0 | E12: =+D12/$M$13 -> 0 | K12: Adjustments & normalizations | M12: =+'Active Case'!F16 -> 6.1883392 | N12: =+'Active Case'!G16 -> 0 | O12: =+'Active Case'!H16 -> 0 | P12: =+'Active Case'!I16 -> 0 | Q12: =+'Active Case'!J16 -> 0 | R12: =+'Active Case'!K16 -> 0 | S12: =+'Active Case'!L16 -> 0 | T12: =+'Active Case'!M16 -> 0
C13: TLB | D13: =+'Debt Structure'!D53 -> 256.5 | E13: =+D13/$M$13 -> 5 | G13: =+'Debt Structure'!F52 -> Structuring fees | H13: =+'Debt Structure'!G52 -> 4.8975 | I13: =+H13/$M$13 -> 0.095467836 | K13: Adj. normalized EBITDA | M13: =+'Active Case'!F17 -> 51.3 | N13: =+'Active Case'!G17 -> 52.243319 | O13: =+'Active Case'!H17 -> 61.713285 | P13: =+'Active Case'!I17 -> 73.285082 | Q13: =+'Active Case'!J17 -> 79.587752 | R13: =+'Active Case'!K17 -> 87.783624 | S13: =+'Active Case'!L17 -> 89.539296 | T13: =+'Active Case'!M17 -> 91.330082 | U13: =+SUM(M13:T13) -> 586.78244 | V13: =+(T13/M13)^(1/7)-1 -> 0.085888446
C14: =+'Debt Structure'!C54 -> Holdco PIK | D14: =+'Debt Structure'!D54 -> 0 | E14: =+D14/$M$13 -> 0 | G14: =+'Debt Structure'!F54 -> Transaction cost | H14: =+'Debt Structure'!G54 -> 8.1 | I14: =+H14/$M$13 -> 0.15789474 | K14: EBITDA margin | M14: =+M13/M7 -> 0.19165443 | N14: =+N13/N7 -> 0.17377543 | O14: =+O13/O7 -> 0.17920132 | P14: =+P13/P7 -> 0.18965101 | Q14: =+Q13/Q7 -> 0.19356356 | R14: =+R13/R7 -> 0.20011855 | S14: =+S13/S7 -> 0.20011855 | T14: =+T13/T7 -> 0.20011855
C15: TOTAL | D15: =+ROUND(SUM(D11:D14),1) -> 553 | E15: =+SUM(E11:E14) -> 10.779678 | G15: TOTAL | H15: =+SUM(H11:H14) -> 552.9975 | I15: =+SUM(I11:I14) -> 10.779678 | K15: Change in Working Capital | M15: ='Active Case'!F30 -> -5.8299854 | N15: ='Active Case'!G30 -> -5.0017419 | O15: ='Active Case'!H30 -> -6.8476121 | P15: ='Active Case'!I30 -> -6.1780846 | Q15: ='Active Case'!J30 -> -2.5470106 | R15: ='Active Case'!K30 -> -2.9852206 | S15: ='Active Case'!L30 -> -1.5660094 | T15: ='Active Case'!M30 -> -1.5973296 | U15: =+SUM(M15:T15) -> -32.552994 | V15: =+(T15/M15)^(1/7)-1 -> -0.16885787
C16: Equity Cushion | D16: =+D11/D15 -> 0.53616184 | I16: =+ROUND(D15,0)=ROUND(H15,0) -> TRUE | K16: Total Capex | M16: ='Active Case'!F33+'Active Case'!F36 -> -13.806 | N16: ='Active Case'!G33+'Active Case'!G36 -> -10.641421 | O16: ='Active Case'!H33+'Active Case'!H36 -> -24.502119 | P16: ='Active Case'!I33+'Active Case'!I36 -> -12.550525 | Q16: ='Active Case'!J33+'Active Case'!J36 -> -16.469825 | R16: ='Active Case'!K33+'Active Case'!K36 -> -11.001133 | S16: ='Active Case'!L33+'Active Case'!L36 -> -8.773162 | T16: ='Active Case'!M33+'Active Case'!M36 -> -8.773162 | U16: =+SUM(M16:T16) -> -106.51735 | V16: =+(T16/M16)^(1/7)-1 -> -0.062719128
K17: Taxes paid | M17: ='Active Case'!F23 -> -8.2650988 | N17: ='Active Case'!G23 -> -3.7039729 | O17: ='Active Case'!H23 -> -5.6672515 | P17: ='Active Case'!I23 -> -9.1167539 | Q17: ='Active Case'!J23 -> -10.349509 | R17: ='Active Case'!K23 -> -12.041849 | S17: ='Active Case'!L23 -> -12.687668 | T17: ='Active Case'!M23 -> -14.216824 | U17: =+SUM(M17:T17) -> -76.048928 | V17: =+(T17/M17)^(1/7)-1 -> 0.080564384
C18: Capital Structure - Frulact | K18: Operating Free Cash Flow | M18: =+M9+SUM(M15:M17) -> 17.210577 | N18: =+N9+SUM(N15:N17) -> 32.896183 | O18: =+O9+SUM(O15:O17) -> 24.696303 | P18: =+P9+SUM(P15:P17) -> 45.439719 | Q18: =+Q9+SUM(Q15:Q17) -> 50.221407 | R18: =+R9+SUM(R15:R17) -> 61.755421 | S18: =+S9+SUM(S15:S17) -> 66.512457 | T18: =+T9+SUM(T15:T17) -> 66.742767 | U18: =+SUM(M18:T18) -> 365.47483 | V18: =+(T18/M18)^(1/7)-1 -> 0.21363186
K19: % Operating FCF Margin | M19: =IF(+M18/M9<0,"n.m.",M18/M9) -> 0.3815106 | N19: =IF(+N18/N9<0,"n.m.",N18/N9) -> 0.62967254 | O19: =IF(+O18/O9<0,"n.m.",O18/O9) -> 0.40017806 | P19: =IF(+P18/P9<0,"n.m.",P18/P9) -> 0.6200405 | Q19: =IF(+Q18/Q9<0,"n.m.",Q18/Q9) -> 0.63101929 | R19: =IF(+R18/R9<0,"n.m.",R18/R9) -> 0.70349591 | S19: =IF(+S18/S9<0,"n.m.",S18/S9) -> 0.74282979 | T19: =IF(+T18/T9<0,"n.m.",T18/T9) -> 0.73078623
C20: Capital Structure | D20: EURm | E20: xEBITDA | K20: Cash flow available for debt service | M20: =M18 -> 17.210577 | N20: =N18 -> 32.896183 | O20: =O18 -> 24.696303 | P20: =P18 -> 45.439719 | Q20: =Q18 -> 50.221407 | R20: =R18 -> 61.755421 | S20: =S18 -> 66.512457 | T20: =T18 -> 66.742767 | U20: =+SUM(M20:T20) -> 365.47483 | V20: =+(T20/M20)^(1/7)-1 -> 0.21363186
C21: ='Debt Structure'!C22 -> TLA | D21: =+D12 -> 0 | E21: =+D21/$M$13 -> 0 | K21: Debt Service | M21: =+SUM(M22:M25) -> 0 | N21: =+SUM(N22:N25) -> -15.007027 | O21: =+SUM(O22:O25) -> -15.692572 | P21: =+SUM(P22:P25) -> -16.448564 | Q21: =+SUM(Q22:Q25) -> -16.692203 | R21: =+SUM(R22:R25) -> -16.692203 | S21: =+SUM(S22:S25) -> -16.692203 | T21: =+SUM(T22:T25) -> -318.82474
C22: ='Debt Structure'!C23 -> TLB | D22: =+D13 -> 256.5 | E22: =+D22/$M$13 -> 5 | K22: =Model!C81 -> TLA | M22: =Model!L81+Model!L87 -> 0 | N22: =Model!Q81+Model!Q87 -> 0 | O22: =Model!V81+Model!V87 -> 0 | P22: =Model!AA81+Model!AA87 -> 0 | Q22: =Model!AF81+Model!AF87 -> 0 | R22: =Model!AK81+Model!AK87 -> 0 | S22: =Model!AP81+Model!AP87 -> 0 | T22: =Model!AU81+Model!AU87 -> 0
C23: ='Debt Structure'!C24 -> Acquisition debt | D23: =+SUM(D21:D22) -> 256.5 | E23: ='Debt Structure'!E24 -> 5 | K23: =Model!C82 -> TLB | M23: =Model!L82+Model!L88 -> 0 | N23: =Model!Q82+Model!Q88 -> -14.1075 | O23: =Model!V82+Model!V88 -> -14.1075 | P23: =Model!AA82+Model!AA88 -> -14.1075 | Q23: =Model!AF82+Model!AF88 -> -14.1075 | R23: =Model!AK82+Model!AK88 -> -14.1075 | S23: =Model!AP82+Model!AP88 -> -14.1075 | T23: =Model!AU82+Model!AU88 -> -268.84406
K24: =Model!C83 -> CAF | M24: =Model!L83+Model!L89 -> 0 | N24: =Model!Q83+Model!Q89 -> -0.69952664 | O24: =Model!V83+Model!V89 -> -1.3850716 | P24: =Model!AA83+Model!AA89 -> -2.1410639 | Q24: =Model!AF83+Model!AF89 -> -2.3847032 | R24: =Model!AK83+Model!AK89 -> -2.3847032 | S24: =Model!AP83+Model!AP89 -> -2.3847032 | T24: =Model!AU83+Model!AU89 -> -49.78068
C25: ='Debt Structure'!C29 -> PIK | D25: =+D14 -> 0 | E25: =+D25/$M$13 -> 0 | K25: =Model!C84 -> RCF | M25: =Model!L84+Model!L90 -> 0 | N25: =Model!Q84+Model!Q90 -> -0.2 | O25: =Model!V84+Model!V90 -> -0.2 | P25: =Model!AA84+Model!AA90 -> -0.2 | Q25: =Model!AF84+Model!AF90 -> -0.2 | R25: =Model!AK84+Model!AK90 -> -0.2 | S25: =Model!AP84+Model!AP90 -> -0.2 | T25: =Model!AU84+Model!AU90 -> -0.2
C26: ='Debt Structure'!C30 -> Total Net Debt | D26: =+D25+D23 -> 256.5 | E26: ='Debt Structure'!E30 -> 5 | K26: Debt drawdown | M26: =Model!L92*0 -> 0 | N26: =Model!Q92 -> 10.641421 | O26: =Model!V92 -> 24.502119 | P26: =Model!AA92 -> 12.550525 | Q26: =Model!AF92 -> 0 | R26: =Model!AK92 -> 0 | S26: =+Model!AP92 -> 0 | T26: =+Model!AU92 -> 0 | U26: =+SUM(M26:T26) -> 47.694064
K27: Free Cash Flow | M27: =+M20+M21+M26 -> 17.210577 | N27: =+N20+N21+N26 -> 28.530578 | O27: =+O20+O21+O26 -> 33.50585 | P27: =+P20+P21+P26 -> 41.54168 | Q27: =+Q20+Q21+Q26 -> 33.529203 | R27: =+R20+R21+R26 -> 45.063218 | S27: =+S20+S21+S26 -> 49.820253 | T27: =+T20+T21+T26 -> -252.08198 | U27: =+SUM(M27:T27) -> -2.8806164
C28: ='Debt Structure'!C26 -> Cash | D28: ='Debt Structure'!D26 -> 0 | E28: =+D28/$M$13 -> 0 | K28: % Operating FCF Margin | M28: =+M27/M9 -> 0.3815106 | N28: =+N27/N9 -> 0.54610959 | O28: =+O27/O9 -> 0.54292767 | P28: =+P27/P9 -> 0.56685042 | Q28: =+Q27/Q9 -> 0.42128597 | R28: =+R27/R9 -> 0.51334424 | S28: =+S27/S9 -> 0.55640658 | T28: =+T27/T9 -> -2.7601199
C29: ='Debt Structure'!C27 -> Total Net Debt | D29: ='Debt Structure'!D27 -> 256.5 | E29: ='Debt Structure'!E27 -> 5 | K29: Dividends to JDM | N29: =+'Active Case'!G65 -> 0 | O29: =+'Active Case'!H65 -> 0 | P29: =+'Active Case'!I65 -> 15.77084 | Q29: =+'Active Case'!J65 -> 111.33647 | R29: =+'Active Case'!K65 -> 17.531609 | S29: =+'Active Case'!L65 -> 19.910127 | T29: =+'Active Case'!M65 -> 0
C31: ='Debt Structure'!C32 -> RCF | D31: ='Debt Structure'!D32 -> 20 | E31: =+D31/$M$13 -> 0.38986355
C32: ='Debt Structure'!C33 -> CAF | D32: ='Debt Structure'!D33 -> 50 | E32: =+D32/$M$13 -> 0.97465887 | K32: Cash BoP | N32: =+M33 -> 0 | O32: =+N33 -> 28.530578 | P32: =+O33 -> 62.036428 | Q32: =+P33 -> 87.807268 | R32: =+Q33 -> 10 | S32: =+R33 -> 37.531609 | T32: =+S33 -> 67.441735
C33: ='Debt Structure'!C34 -> Total | D33: ='Debt Structure'!D34 -> 326.5 | E33: ='Debt Structure'!E34 -> 6.3645224 | K33: Cash EoP | M33: ='Debt Structure'!D26 -> 0 | N33: =+N27+N32-N29 -> 28.530578 | O33: =+O27+O32-O29 -> 62.036428 | P33: =+P27+P32-P29 -> 87.807268 | Q33: =+Q27+Q32-Q29 -> 10 | R33: =+R27+R32-R29 -> 37.531609 | S33: =+S27+S32-S29 -> 67.441735 | T33: =+T27+T32-T29 -> -184.64024
K34: Check | M34: =ROUND(+Model!L102,1)=ROUND(M33,1) -> TRUE | N34: =ROUND(+Model!Q102,1)=ROUND(N33,1) -> TRUE | O34: =ROUND(+Model!V102,1)=ROUND(O33,1) -> TRUE | P34: =ROUND(+Model!AA102,1)=ROUND(P33,1) -> TRUE | Q34: =ROUND(+Model!AF102,1)=ROUND(Q33,1) -> TRUE | R34: =ROUND(+Model!AK102,1)=ROUND(R33,1) -> TRUE | S34: =ROUND(+Model!AP102,1)=ROUND(S33,1) -> TRUE | T34: =ROUND(+Model!AU102,1)=ROUND(T33,1) -> TRUE
C36: Covenants (Semi-annual) | K36: Net Debt BS Items
M37: FY25B | N37: FY26F | O37: FY27F | P37: FY28F | Q37: FY29F | R37: FY30F | S37: FY31F | T37: FY32F
C38: Dates | D38: Leverage | E38: Covenant | F38: CHECK
C39: {=+TRANSPOSE(Model!L10:AM10)} -> 46112 | D39: =IF(SUMIF(Model!$H$10:$AM$10,C39,Model!$H$12:$AM$12)=0,"n.a.",SUMIF(Model!$H$10:$AM$10,C39,Model!$H$12:$AM$12)) -> 4.8895653 | E39: =IF(SUMIF(Model!$H$10:$AM$10,C39,Model!$H$16:$AM$16)=0,"n.a.",SUMIF(Model!$H$10:$AM$10,C39,Model!$H$16:$AM$16)) -> 8.15 | F39: =+N(E39>D39) -> 1 | K39: Cash EoP | N39: =N33 -> 28.530578 | O39: =O33 -> 62.036428 | P39: =P33 -> 87.807268 | Q39: =Q33 -> 10 | R39: =R33 -> 37.531609 | S39: =S33 -> 67.441735 | T39: =T33 -> -184.64024
C40: 46203 | D40: =IF(SUMIF(Model!$H$10:$AM$10,C40,Model!$H$12:$AM$12)=0,"n.a.",SUMIF(Model!$H$10:$AM$10,C40,Model!$H$12:$AM$12)) -> 4.7806506 | E40: =IF(SUMIF(Model!$H$10:$AM$10,C40,Model!$H$16:$AM$16)=0,"n.a.",SUMIF(Model!$H$10:$AM$10,C40,Model!$H$16:$AM$16)) -> 8 | F40: =+N(E40>D40) -> 1
C41: 46295 | D41: =IF(SUMIF(Model!$H$10:$AM$10,C41,Model!$H$12:$AM$12)=0,"n.a.",SUMIF(Model!$H$10:$AM$10,C41,Model!$H$12:$AM$12)) -> 4.6732351 | E41: =IF(SUMIF(Model!$H$10:$AM$10,C41,Model!$H$16:$AM$16)=0,"n.a.",SUMIF(Model!$H$10:$AM$10,C41,Model!$H$16:$AM$16)) -> 7.8 | F41: =+N(E41>D41) -> 1 | K41: Debt BoP | N41: =+M44 -> 256.5 | O41: =+N44 -> 267.14142 | P41: =+O44 -> 291.64354 | Q41: =+P44 -> 304.19406 | R41: =+Q44 -> 304.19406 | S41: =+R44 -> 304.19406 | T41: =+S44 -> 304.19406
C42: 46387 | D42: =IF(SUMIF(Model!$H$10:$AM$10,C42,Model!$H$12:$AM$12)=0,"n.a.",SUMIF(Model!$H$10:$AM$10,C42,Model!$H$12:$AM$12)) -> 4.5672987 | E42: =IF(SUMIF(Model!$H$10:$AM$10,C42,Model!$H$16:$AM$16)=0,"n.a.",SUMIF(Model!$H$10:$AM$10,C42,Model!$H$16:$AM$16)) -> 7.65 | F42: =+N(E42>D42) -> 1 | K42: Drawdown debt | N42: =Model!Q92 -> 10.641421 | O42: =Model!V92 -> 24.502119 | P42: =Model!AA92 -> 12.550525 | Q42: =Model!AF92 -> 0 | R42: =Model!AK92 -> 0 | S42: =Model!AP92 -> 0 | T42: =Model!AU92 -> 0
C43: 46477 | D43: =IF(SUMIF(Model!$H$10:$AM$10,C43,Model!$H$12:$AM$12)=0,"n.a.",SUMIF(Model!$H$10:$AM$10,C43,Model!$H$12:$AM$12)) -> 4.3263966 | E43: =IF(SUMIF(Model!$H$10:$AM$10,C43,Model!$H$16:$AM$16)=0,"n.a.",SUMIF(Model!$H$10:$AM$10,C43,Model!$H$16:$AM$16)) -> 7.25 | F43: =+N(E43>D43) -> 1 | K43: Amortizations | N43: =Model!Q86 -> 0 | O43: =Model!V86 -> 0 | P43: =Model!AA86 -> 0 | Q43: =Model!AF86 -> 0 | R43: =Model!AK86 -> 0 | S43: =Model!AP86 -> 0 | T43: =Model!AU86 -> -304.19406
C44: 46568 | D44: =IF(SUMIF(Model!$H$10:$AM$10,C44,Model!$H$12:$AM$12)=0,"n.a.",SUMIF(Model!$H$10:$AM$10,C44,Model!$H$12:$AM$12)) -> 4.106589 | E44: =IF(SUMIF(Model!$H$10:$AM$10,C44,Model!$H$16:$AM$16)=0,"n.a.",SUMIF(Model!$H$10:$AM$10,C44,Model!$H$16:$AM$16)) -> 6.85 | F44: =+N(E44>D44) -> 1 | K44: Debt EoP | M44: =Model!L109 -> 256.5 | N44: =+N41+N42+N43 -> 267.14142 | O44: =+O41+O42+O43 -> 291.64354 | P44: =+P41+P42+P43 -> 304.19406 | Q44: =+Q41+Q42+Q43 -> 304.19406 | R44: =+R41+R42+R43 -> 304.19406 | S44: =+S41+S42+S43 -> 304.19406 | T44: =+T41+T42+T43 -> 0
C45: 46660 | D45: =IF(SUMIF(Model!$H$10:$AM$10,C45,Model!$H$12:$AM$12)=0,"n.a.",SUMIF(Model!$H$10:$AM$10,C45,Model!$H$12:$AM$12)) -> 3.9053511 | E45: =IF(SUMIF(Model!$H$10:$AM$10,C45,Model!$H$16:$AM$16)=0,"n.a.",SUMIF(Model!$H$10:$AM$10,C45,Model!$H$16:$AM$16)) -> 6.55 | F45: =+N(E45>D45) -> 1
C46: 46752 | D46: =IF(SUMIF(Model!$H$10:$AM$10,C46,Model!$H$12:$AM$12)=0,"n.a.",SUMIF(Model!$H$10:$AM$10,C46,Model!$H$12:$AM$12)) -> 3.7205459 | E46: =IF(SUMIF(Model!$H$10:$AM$10,C46,Model!$H$16:$AM$16)=0,"n.a.",SUMIF(Model!$H$10:$AM$10,C46,Model!$H$16:$AM$16)) -> 6.25 | F46: =+N(E46>D46) -> 1 | K46: Net Debt | M46: =+M44-M33 -> 256.5 | N46: =+N44-N33 -> 238.61084 | O46: =+O44-O33 -> 229.60711 | P46: =+P44-P33 -> 216.3868 | Q46: =+Q44-Q33 -> 294.19406 | R46: =+R44-R33 -> 266.66246 | S46: =+S44-S33 -> 236.75233 | T46: =+T44-T33 -> 184.64024
C47: 46843 | D47: =IF(SUMIF(Model!$H$10:$AM$10,C47,Model!$H$12:$AM$12)=0,"n.a.",SUMIF(Model!$H$10:$AM$10,C47,Model!$H$12:$AM$12)) -> 3.5020609 | E47: =IF(SUMIF(Model!$H$10:$AM$10,C47,Model!$H$16:$AM$16)=0,"n.a.",SUMIF(Model!$H$10:$AM$10,C47,Model!$H$16:$AM$16)) -> 5.85 | F47: =+N(E47>D47) -> 1 | M47: =ROUND(+Model!L116,2)=ROUND(M46,2) -> TRUE | N47: =ROUND(+Model!Q116,2)=ROUND(N46,2) -> TRUE | O47: =ROUND(+Model!V116,2)=ROUND(O46,2) -> TRUE | P47: =ROUND(+Model!AA116,2)=ROUND(P46,2) -> TRUE | Q47: =ROUND(+Model!AF116,2)=ROUND(Q46,2) -> TRUE | R47: =ROUND(+Model!AK116,2)=ROUND(R46,2) -> TRUE | S47: =ROUND(+Model!AP116,2)=ROUND(S46,2) -> TRUE | T47: =ROUND(+Model!AU116,2)=ROUND(T46,2) -> TRUE
C48: 46934 | D48: =IF(SUMIF(Model!$H$10:$AM$10,C48,Model!$H$12:$AM$12)=0,"n.a.",SUMIF(Model!$H$10:$AM$10,C48,Model!$H$12:$AM$12)) -> 3.3027688 | E48: =IF(SUMIF(Model!$H$10:$AM$10,C48,Model!$H$16:$AM$16)=0,"n.a.",SUMIF(Model!$H$10:$AM$10,C48,Model!$H$16:$AM$16)) -> 5.55 | F48: =+N(E48>D48) -> 1
C49: 47026 | D49: =IF(SUMIF(Model!$H$10:$AM$10,C49,Model!$H$12:$AM$12)=0,"n.a.",SUMIF(Model!$H$10:$AM$10,C49,Model!$H$12:$AM$12)) -> 3.1203034 | E49: =IF(SUMIF(Model!$H$10:$AM$10,C49,Model!$H$16:$AM$16)=0,"n.a.",SUMIF(Model!$H$10:$AM$10,C49,Model!$H$16:$AM$16)) -> 5.25 | F49: =+N(E49>D49) -> 1 | K49: Credit Metrics
C50: 47118 | D50: =IF(SUMIF(Model!$H$10:$AM$10,C50,Model!$H$12:$AM$12)=0,"n.a.",SUMIF(Model!$H$10:$AM$10,C50,Model!$H$12:$AM$12)) -> 2.9526718 | E50: =IF(SUMIF(Model!$H$10:$AM$10,C50,Model!$H$16:$AM$16)=0,"n.a.",SUMIF(Model!$H$10:$AM$10,C50,Model!$H$16:$AM$16)) -> 4.95 | F50: =+N(E50>D50) -> 1 | N50: FY26F | O50: FY27F | P50: FY28F | Q50: FY29F | R50: FY30F | S50: FY31F | T50: FY32F
C51: 47208 | D51: =IF(SUMIF(Model!$H$10:$AM$10,C51,Model!$H$12:$AM$12)=0,"n.a.",SUMIF(Model!$H$10:$AM$10,C51,Model!$H$12:$AM$12)) -> 3.150364 | E51: =IF(SUMIF(Model!$H$10:$AM$10,C51,Model!$H$16:$AM$16)=0,"n.a.",SUMIF(Model!$H$10:$AM$10,C51,Model!$H$16:$AM$16)) -> 5.3 | F51: =+N(E51>D51) -> 1
C52: 47299 | D52: =IF(SUMIF(Model!$H$10:$AM$10,C52,Model!$H$12:$AM$12)=0,"n.a.",SUMIF(Model!$H$10:$AM$10,C52,Model!$H$12:$AM$12)) -> 3.3399058 | E52: =IF(SUMIF(Model!$H$10:$AM$10,C52,Model!$H$16:$AM$16)=0,"n.a.",SUMIF(Model!$H$10:$AM$10,C52,Model!$H$16:$AM$16)) -> 5.6 | F52: =+N(E52>D52) -> 1 | K52: EBITDA | M52: =+'Debt Structure'!D7 -> 51.3 | N52: =N9 -> 52.243319 | O52: =O9 -> 61.713285 | P52: =P9 -> 73.285082 | Q52: =Q9 -> 79.587752 | R52: =R9 -> 87.783624 | S52: =S9 -> 89.539296 | T52: =T9 -> 91.330082
C53: 47391 | D53: =IF(SUMIF(Model!$H$10:$AM$10,C53,Model!$H$12:$AM$12)=0,"n.a.",SUMIF(Model!$H$10:$AM$10,C53,Model!$H$12:$AM$12)) -> 3.5217909 | E53: =IF(SUMIF(Model!$H$10:$AM$10,C53,Model!$H$16:$AM$16)=0,"n.a.",SUMIF(Model!$H$10:$AM$10,C53,Model!$H$16:$AM$16)) -> 5.9 | F53: =+N(E53>D53) -> 1
C54: 47483 | D54: =IF(SUMIF(Model!$H$10:$AM$10,C54,Model!$H$12:$AM$12)=0,"n.a.",SUMIF(Model!$H$10:$AM$10,C54,Model!$H$12:$AM$12)) -> 3.6964741 | E54: =IF(SUMIF(Model!$H$10:$AM$10,C54,Model!$H$16:$AM$16)=0,"n.a.",SUMIF(Model!$H$10:$AM$10,C54,Model!$H$16:$AM$16)) -> 6.2 | F54: =+N(E54>D54) -> 1 | K54: Leverage Ratio | M54: =IF(+M46/M52<0,"n.m.",M46/M52) -> 5 | N54: =IF(+N46/N52<0,"n.m.",N46/N52) -> 4.5672987 | O54: =IF(+O46/O52<0,"n.m.",O46/O52) -> 3.7205459 | P54: =IF(+P46/P52<0,"n.m.",P46/P52) -> 2.9526718 | Q54: =IF(+Q46/Q52<0,"n.m.",Q46/Q52) -> 3.6964741 | R54: =IF(+R46/R52<0,"n.m.",R46/R52) -> 3.0377244 | S54: =IF(+S46/S52<0,"n.m.",S46/S52) -> 2.6441165 | T54: =IF(+T46/T52<0,"n.m.",T46/T52) -> 2.0216804
C55: 47573 | D55: =IF(SUMIF(Model!$H$10:$AM$10,C55,Model!$H$12:$AM$12)=0,"n.a.",SUMIF(Model!$H$10:$AM$10,C55,Model!$H$12:$AM$12)) -> 3.5193864 | E55: =IF(SUMIF(Model!$H$10:$AM$10,C55,Model!$H$16:$AM$16)=0,"n.a.",SUMIF(Model!$H$10:$AM$10,C55,Model!$H$16:$AM$16)) -> 5.9 | F55: =+N(E55>D55) -> 1 | K55: Check | N55: =IFERROR(ROUND(N54,1)=ROUND(Model!O12,1),"n.a.") -> TRUE | O55: =IFERROR(ROUND(O54,1)=ROUND(Model!S12,1),"n.a.") -> TRUE | P55: =IFERROR(ROUND(P54,1)=ROUND(Model!W12,1),"n.a.") -> TRUE | Q55: =IFERROR(ROUND(Q54,1)=ROUND(Model!AA12,1),"n.a.") -> TRUE | R55: =IFERROR(ROUND(R54,1)=ROUND(Model!AE12,1),"n.a.") -> TRUE | S55: =IFERROR(ROUND(S54,1)=ROUND(Model!AI12,1),"n.a.") -> TRUE | T55: =IFERROR(ROUND(T54,1)=ROUND(Model!AM12,1),"n.a.") -> TRUE
C56: 47664 | D56: =IF(SUMIF(Model!$H$10:$AM$10,C56,Model!$H$12:$AM$12)=0,"n.a.",SUMIF(Model!$H$10:$AM$10,C56,Model!$H$12:$AM$12)) -> 3.3509704 | E56: =IF(SUMIF(Model!$H$10:$AM$10,C56,Model!$H$16:$AM$16)=0,"n.a.",SUMIF(Model!$H$10:$AM$10,C56,Model!$H$16:$AM$16)) -> 5.6 | F56: =+N(E56>D56) -> 1
C57: 47756 | D57: =IF(SUMIF(Model!$H$10:$AM$10,C57,Model!$H$12:$AM$12)=0,"n.a.",SUMIF(Model!$H$10:$AM$10,C57,Model!$H$12:$AM$12)) -> 3.1906043 | E57: =IF(SUMIF(Model!$H$10:$AM$10,C57,Model!$H$16:$AM$16)=0,"n.a.",SUMIF(Model!$H$10:$AM$10,C57,Model!$H$16:$AM$16)) -> 5.35 | F57: =+N(E57>D57) -> 1 | K57: Annual Covenants | N57: =E42 -> 7.65 | O57: =E46 -> 6.25 | P57: =E50 -> 4.95 | Q57: =E54 -> 6.2 | R57: =E58 -> 5.1 | S57: =+E62 -> 4.45 | T57: =+E66 -> 3.4
C58: 47848 | D58: =IF(SUMIF(Model!$H$10:$AM$10,C58,Model!$H$12:$AM$12)=0,"n.a.",SUMIF(Model!$H$10:$AM$10,C58,Model!$H$12:$AM$12)) -> 3.0377244 | E58: =IF(SUMIF(Model!$H$10:$AM$10,C58,Model!$H$16:$AM$16)=0,"n.a.",SUMIF(Model!$H$10:$AM$10,C58,Model!$H$16:$AM$16)) -> 5.1 | F58: =+N(E58>D58) -> 1 | K58: Flat-line | L58: =Model!D18 -> 3
C59: 47938 | D59: =IF(SUMIF(Model!$H$10:$AM$10,C59,Model!$H$12:$AM$12)=0,"n.a.",SUMIF(Model!$H$10:$AM$10,C59,Model!$H$12:$AM$12)) -> 2.9378537 | E59: =IF(SUMIF(Model!$H$10:$AM$10,C59,Model!$H$16:$AM$16)=0,"n.a.",SUMIF(Model!$H$10:$AM$10,C59,Model!$H$16:$AM$16)) -> 4.9 | F59: =+N(E59>D59) -> 1
C60: 48029 | D60: =IF(SUMIF(Model!$H$10:$AM$10,C60,Model!$H$12:$AM$12)=0,"n.a.",SUMIF(Model!$H$10:$AM$10,C60,Model!$H$12:$AM$12)) -> 2.8389719 | E60: =IF(SUMIF(Model!$H$10:$AM$10,C60,Model!$H$16:$AM$16)=0,"n.a.",SUMIF(Model!$H$10:$AM$10,C60,Model!$H$16:$AM$16)) -> 4.75 | F60: =+N(E60>D60) -> 1 | K60: CFADS (exc. expansion capex) | N60: =+N20-'Active Case'!G36 -> 37.524865 | O60: =+O20-'Active Case'!H36 -> 42.310829 | P60: =+P20-'Active Case'!I36 -> 50.261829 | Q60: =+Q20-'Active Case'!J36 -> 58.467809 | R60: =+R20-'Active Case'!K36 -> 63.983392 | S60: =+S20-'Active Case'!L36 -> 66.512457 | T60: =+T20-'Active Case'!M36 -> 66.742767
C61: 48121 | D61: =IF(SUMIF(Model!$H$10:$AM$10,C61,Model!$H$12:$AM$12)=0,"n.a.",SUMIF(Model!$H$10:$AM$10,C61,Model!$H$12:$AM$12)) -> 2.7410642 | E61: =IF(SUMIF(Model!$H$10:$AM$10,C61,Model!$H$16:$AM$16)=0,"n.a.",SUMIF(Model!$H$10:$AM$10,C61,Model!$H$16:$AM$16)) -> 4.6 | F61: =+N(E61>D61) -> 1 | K61: Debt Service | N61: =-N21 -> 15.007027 | O61: =-O21 -> 15.692572 | P61: =-P21 -> 16.448564 | Q61: =-Q21 -> 16.692203 | R61: =-R21 -> 16.692203 | S61: =-S21 -> 16.692203 | T61: =-T21 -> 318.82474
C62: 48213 | D62: =IF(SUMIF(Model!$H$10:$AM$10,C62,Model!$H$12:$AM$12)=0,"n.a.",SUMIF(Model!$H$10:$AM$10,C62,Model!$H$12:$AM$12)) -> 2.6441165 | E62: =IF(SUMIF(Model!$H$10:$AM$10,C62,Model!$H$16:$AM$16)=0,"n.a.",SUMIF(Model!$H$10:$AM$10,C62,Model!$H$16:$AM$16)) -> 4.45 | F62: =+N(E62>D62) -> 1 | K62: DSCR | N62: =+N60/N61 -> 2.5004863 | O62: =+O60/O61 -> 2.696233 | P62: =+P60/P61 -> 3.0556971 | Q62: =+Q60/Q61 -> 3.5027017 | R62: =+R60/R61 -> 3.8331304 | S62: =+S60/S61 -> 3.9846422 | T62: =+T60/T61 -> 0.20933998
C63: 48304 | D63: =IF(SUMIF(Model!$H$10:$AM$10,C63,Model!$H$12:$AM$12)=0,"n.a.",SUMIF(Model!$H$10:$AM$10,C63,Model!$H$12:$AM$12)) -> 2.4919122 | E63: =IF(SUMIF(Model!$H$10:$AM$10,C63,Model!$H$16:$AM$16)=0,"n.a.",SUMIF(Model!$H$10:$AM$10,C63,Model!$H$16:$AM$16)) -> 4.2 | F63: =+N(E63>D63) -> 1
C64: 48395 | D64: =IF(SUMIF(Model!$H$10:$AM$10,C64,Model!$H$12:$AM$12)=0,"n.a.",SUMIF(Model!$H$10:$AM$10,C64,Model!$H$12:$AM$12)) -> 2.341215 | E64: =IF(SUMIF(Model!$H$10:$AM$10,C64,Model!$H$16:$AM$16)=0,"n.a.",SUMIF(Model!$H$10:$AM$10,C64,Model!$H$16:$AM$16)) -> 3.95 | F64: =+N(E64>D64) -> 1
C65: 48487 | D65: =IF(SUMIF(Model!$H$10:$AM$10,C65,Model!$H$12:$AM$12)=0,"n.a.",SUMIF(Model!$H$10:$AM$10,C65,Model!$H$12:$AM$12)) -> 2.1920024 | E65: =IF(SUMIF(Model!$H$10:$AM$10,C65,Model!$H$16:$AM$16)=0,"n.a.",SUMIF(Model!$H$10:$AM$10,C65,Model!$H$16:$AM$16)) -> 3.7 | F65: =+N(E65>D65) -> 1
C66: 48579 | D66: =IF(SUMIF(Model!$H$10:$AM$10,C66,Model!$H$12:$AM$12)=0,"n.a.",SUMIF(Model!$H$10:$AM$10,C66,Model!$H$12:$AM$12)) -> 2.0216804 | E66: =IF(SUMIF(Model!$H$10:$AM$10,C66,Model!$H$16:$AM$16)=0,"n.a.",SUMIF(Model!$H$10:$AM$10,C66,Model!$H$16:$AM$16)) -> 3.4 | F66: =+N(E66>D66) -> 1

Sheet Model
C2: =RIGHT(CELL("filename",C1), LEN(CELL("filename", C1))- FIND("]", CELL("filename", C1), 1)) -> Model
C4: Closing | D4: 46022
C5: Year End | D5: 44561
C7: Credit metrics | H7: 2025 | L7: =+H7+1 -> 2026 | P7: =+L7+1 -> 2027 | T7: =+P7+1 -> 2028 | X7: =+T7+1 -> 2029 | AB7: =+X7+1 -> 2030 | AF7: =+AB7+1 -> 2031 | AJ7: =+AF7+1 -> 2032
H9: Q1 | I9: Q2 | J9: Q3 | K9: Closing | L9: Q1 | M9: Q2 | N9: Q3 | O9: Q4 | P9: Q1 | Q9: Q2 | R9: Q3 | S9: Q4 | T9: Q1 | U9: Q2 | V9: Q3 | W9: Q4 | X9: Q1 | Y9: Q2 | Z9: Q3 | AA9: Q4 | AB9: Q1 | AC9: Q2 | AD9: Q3 | AE9: Q4 | AF9: Q1 | AG9: Q2 | AH9: Q3 | AI9: Q4 | AJ9: Q1 | AK9: Q2 | AL9: Q3 | AM9: Q4
H10: 45747 | I10: 45838 | J10: 45930 | K10: 46022 | L10: =EOMONTH(K10,3) -> 46112 | M10: =EOMONTH(L10,3) -> 46203 | N10: =EOMONTH(M10,3) -> 46295 | O10: =EOMONTH(N10,3) -> 46387 | P10: =EOMONTH(O10,3) -> 46477 | Q10: =EOMONTH(P10,3) -> 46568 | R10: =EOMONTH(Q10,3) -> 46660 | S10: =EOMONTH(R10,3) -> 46752 | ... AM10: =EOMONTH(AL10,3) -> 48579
C12: Net leverage ratio (ND/EBITDA) | K12: =IF(K29=0,"n.a.",IF(K29<0,"n.a.",K29/K26)) -> 5 | L12: =IF(L29=0,"n.a.",IF(L29<0,"n.a.",L29/L26)) -> 4.8895653 | M12: =IF(M29=0,"n.a.",IF(M29<0,"n.a.",M29/M26)) -> 4.7806506 | N12: =IF(N29=0,"n.a.",IF(N29<0,"n.a.",N29/N26)) -> 4.6732351 | O12: =IF(O29=0,"n.a.",IF(O29<0,"n.a.",O29/O26)) -> 4.5672987 | P12: =IF(P29=0,"n.a.",IF(P29<0,"n.a.",P29/P26)) -> 4.3263966 | Q12: =IF(Q29=0,"n.a.",IF(Q29<0,"n.a.",Q29/Q26)) -> 4.106589 | R12: =IF(R29=0,"n.a.",IF(R29<0,"n.a.",R29/R26)) -> 3.9053511 | ... AM12: =IF(AM29=0,"n.a.",IF(AM29<0,"n.a.",AM29/AM26)) -> 2.0216804
C14: Headroom | D14: =+'Debt Structure'!D142 -> 0.4 | K14: =IF(K29=0,"n.a.",IF(K29<0,"n.a.",(K29/(K26*(1-$D$14))))) -> 8.3333333 | L14: =IF(L29=0,"n.a.",IF(L29<0,"n.a.",(L29/(L26*(1-$D$14))))) -> 8.1492755 | M14: =IF(M29=0,"n.a.",IF(M29<0,"n.a.",(M29/(M26*(1-$D$14))))) -> 7.967751 | N14: =IF(N29=0,"n.a.",IF(N29<0,"n.a.",(N29/(N26*(1-$D$14))))) -> 7.7887252 | O14: =IF(O29=0,"n.a.",IF(O29<0,"n.a.",(O29/(O26*(1-$D$14))))) -> 7.6121645 | P14: =IF(P29=0,"n.a.",IF(P29<0,"n.a.",(P29/(P26*(1-$D$14))))) -> 7.210661 | Q14: =IF(Q29=0,"n.a.",IF(Q29<0,"n.a.",(Q29/(Q26*(1-$D$14))))) -> 6.8443149 | R14: =IF(R29=0,"n.a.",IF(R29<0,"n.a.",(R29/(R26*(1-$D$14))))) -> 6.5089185 | ... AM14: =IF(AM29=0,"n.a.",IF(AM29<0,"n.a.",(AM29/(AM26*(1-$D$14))))) -> 3.3694674
C16: SFA Net Leverage Covenant | K16: =IFERROR(MAX($D$18,ROUNDUP((K14*100/5),0)*5/100),"n.a") -> 8.35 | L16: =IFERROR(MAX($D$18,ROUNDUP((L14*100/5),0)*5/100),"n.a") -> 8.15 | M16: =IFERROR(MAX($D$18,ROUNDUP((M14*100/5),0)*5/100),"n.a") -> 8 | N16: =IFERROR(MAX($D$18,ROUNDUP((N14*100/5),0)*5/100),"n.a") -> 7.8 | O16: =IFERROR(MAX($D$18,ROUNDUP((O14*100/5),0)*5/100),"n.a") -> 7.65 | P16: =IFERROR(MAX($D$18,ROUNDUP((P14*100/5),0)*5/100),"n.a") -> 7.25 | Q16: =IFERROR(MAX($D$18,ROUNDUP((Q14*100/5),0)*5/100),"n.a") -> 6.85 | R16: =IFERROR(MAX($D$18,ROUNDUP((R14*100/5),0)*5/100),"n.a") -> 6.55 | ... AM16: =IFERROR(MAX($D$18,ROUNDUP((AM14*100/5),0)*5/100),"n.a") -> 3.4
L17: =+L16>L12 -> TRUE | M17: =+M16>M12 -> TRUE | N17: =+N16>N12 -> TRUE | O17: =+O16>O12 -> TRUE | P17: =+P16>P12 -> TRUE | Q17: =+Q16>Q12 -> TRUE | R17: =+R16>R12 -> TRUE | S17: =+S16>S12 -> TRUE | ... AM17: =+AM16>AM12 -> TRUE
C18: Flattening of Net Leverage Covenant | D18: 3
C20: Covenant Source Data | H20: 2025 | L20: =+H20+1 -> 2026 | P20: =+L20+1 -> 2027 | T20: =+P20+1 -> 2028 | X20: =+T20+1 -> 2029 | AB20: =+X20+1 -> 2030 | AF20: =+AB20+1 -> 2031 | AJ20: =+AF20+1 -> 2032
H22: Q1 | I22: Q2 | J22: Q3 | K22: Closing | L22: Q1 | M22: Q2 | N22: Q3 | O22: Q4 | P22: Q1 | Q22: Q2 | R22: Q3 | S22: Q4 | T22: Q1 | U22: Q2 | V22: Q3 | W22: Q4 | X22: Q1 | Y22: Q2 | Z22: Q3 | AA22: Q4 | AB22: Q1 | AC22: Q2 | AD22: Q3 | AE22: Q4 | AF22: Q1 | AG22: Q2 | AH22: Q3 | AI22: Q4 | AJ22: Q1 | AK22: Q2 | AL22: Q3 | AM22: Q4
H23: 45747 | I23: 45838 | J23: 45930 | K23: 46022 | L23: =EOMONTH(K23,3) -> 46112 | M23: =EOMONTH(L23,3) -> 46203 | N23: =EOMONTH(M23,3) -> 46295 | O23: =EOMONTH(N23,3) -> 46387 | P23: =EOMONTH(O23,3) -> 46477 | Q23: =EOMONTH(P23,3) -> 46568 | R23: =EOMONTH(Q23,3) -> 46660 | S23: =EOMONTH(R23,3) -> 46752 | ... AM23: =EOMONTH(AL23,3) -> 48579
C25: EBITDA | H25: =H54 -> 12.825 | I25: =I54 -> 12.825 | J25: =J54 -> 12.825 | K25: =K54 -> 12.825 | L25: =M54 -> 13.06083 | M25: =N54 -> 13.06083 | N25: =O54 -> 13.06083 | O25: =P54 -> 13.06083 | P25: =R54 -> 15.428321 | Q25: =S54 -> 15.428321 | R25: =T54 -> 15.428321 | S25: =U54 -> 15.428321 | T25: =W54 -> 18.321271 | U25: =X54 -> 18.321271 | V25: =Y54 -> 18.321271 | W25: =Z54 -> 18.321271 | X25: =AB54 -> 19.896938 | Y25: =AC54 -> 19.896938 | Z25: =AD54 -> 19.896938 | AA25: =AE54 -> 19.896938 | AB25: =AG54 -> 21.945906 | AC25: =AH54 -> 21.945906 | AD25: =AI54 -> 21.945906 | AE25: =AJ54 -> 21.945906 | AF25: =AL54 -> 22.384824 | AG25: =AM54 -> 22.384824 | AH25: =AN54 -> 22.384824 | AI25: =AO54 -> 22.384824 | AJ25: =+AQ54 -> 22.832521 | AK25: =+AR54 -> 22.832521 | AL25: =+AS54 -> 22.832521 | AM25: =+AT54 -> 22.832521
C26: LTM EBITDA | H26: =H25+G25+F25+E25 -> 12.825 | I26: =I25+H25+G25+F25 -> 25.65 | J26: =J25+I25+H25+G25 -> 38.475 | K26: =+'Active Case'!F17 -> 51.3 | L26: =L25+K25+J25+I25 -> 51.53583 | M26: =M25+L25+K25+J25 -> 51.77166 | N26: =N25+M25+L25+K25 -> 52.007489 | O26: =O25+N25+M25+L25 -> 52.243319 | P26: =P25+O25+N25+M25 -> 54.610811 | Q26: =Q25+P25+O25+N25 -> 56.978302 | R26: =R25+Q25+P25+O25 -> 59.345794 | S26: =S25+R25+Q25+P25 -> 61.713285 | ... AM26: =AM25+AL25+AK25+AJ25 -> 91.330082
C27: Cash Balance | H27: =H102 -> 0 | I27: =I102 -> 0 | J27: =J102 -> 0 | K27: =L102 -> 0 | L27: =M102 -> 7.1725498 | M27: =N102 -> 14.318496 | N27: =O102 -> 21.437839 | O27: =Q102 -> 28.530578 | P27: =R102 -> 36.998923 | Q27: =S102 -> 45.406014 | R27: =T102 -> 53.751848 | S27: =V102 -> 62.036428 | T27: =W102 -> 68.526203 | U27: =X102 -> 74.984601 | V27: =Y102 -> 81.411623 | W27: =AA102 -> 87.807268 | X27: =AB102 -> 68.355451 | Y27: =AC102 -> 48.903634 | Z27: =AD102 -> 29.451817 | AA27: =AF102 -> 10 | AB27: =AG102 -> 16.882902 | AC27: =AH102 -> 23.765804 | AD27: =AI102 -> 30.648707 | AE27: =AK102 -> 37.531609 | AF27: =AL102 -> 45.00914 | AG27: =AM102 -> 52.486672 | AH27: =AN102 -> 59.964204 | AI27: =AP102 -> 67.441735 | AJ27: =AQ102 -> 79.954376 | AK27: =AR102 -> 92.467017 | AL27: =AS102 -> 104.97966 | AM27: =AU102 -> -184.64024
C28: Total Debt | H28: =H109 -> 0 | I28: =I109 -> 0 | J28: =J109 -> 0 | K28: =L109 -> 256.5 | L28: =M109 -> 259.16036 | M28: =N109 -> 261.82071 | N28: =O109 -> 264.48107 | O28: =Q109 -> 267.14142 | P28: =R109 -> 273.26695 | Q28: =S109 -> 279.39248 | R28: =T109 -> 285.51801 | S28: =V109 -> 291.64354 | T28: =W109 -> 294.78117 | U28: =X109 -> 297.9188 | V28: =Y109 -> 301.05643 | W28: =AA109 -> 304.19406 | X28: =AB109 -> 304.19406 | Y28: =AC109 -> 304.19406 | Z28: =AD109 -> 304.19406 | AA28: =AF109 -> 304.19406 | AB28: =AG109 -> 304.19406 | AC28: =AH109 -> 304.19406 | AD28: =AI109 -> 304.19406 | AE28: =AK109 -> 304.19406 | AF28: =AL109 -> 304.19406 | AG28: =AM109 -> 304.19406 | AH28: =AN109 -> 304.19406 | AI28: =AP109 -> 304.19406 | AJ28: =AQ109 -> 304.19406 | AK28: =AR109 -> 304.19406 | AL28: =AS109 -> 304.19406 | AM28: =AU109 -> 0
C29: Net Total Debt | H29: =H28-H27 -> 0 | I29: =I28-I27 -> 0 | J29: =J28-J27 -> 0 | K29: =K28-K27 -> 256.5 | L29: =L28-L27 -> 251.98781 | M29: =M28-M27 -> 247.50221 | N29: =N28-N27 -> 243.04323 | O29: =O28-O27 -> 238.61084 | ... AM29: =AM28-AM27 -> 184.64024
C31: Quarterly Model | H31: 2025 | M31: =+H31+1 -> 2026 | R31: =+M31+1 -> 2027 | W31: =+R31+1 -> 2028 | AB31: =+W31+1 -> 2029 | AG31: =+AB31+1 -> 2030 | AL31: =+AG31+1 -> 2031 | AQ31: =+AL31+1 -> 2032
C33: Seasonality
H35: Q1 | I35: Q2 | J35: Q3 | K35: Closing | L35: FY | M35: Q1 | N35: Q2 | O35: Q3 | P35: Q4 | Q35: FY | R35: Q1 | S35: Q2 | T35: Q3 | U35: Q4 | V35: FY | W35: Q1 | X35: Q2 | Y35: Q3 | Z35: Q4 | AA35: FY | AB35: Q1 | AC35: Q2 | AD35: Q3 | AE35: Q4 | AF35: FY | AG35: Q1 | AH35: Q2 | AI35: Q3 | AJ35: Q4 | AK35: FY | AL35: Q1 | AM35: Q2 | AN35: Q3 | AO35: Q4 | AP35: FY | AQ35: Q1 | AR35: Q2 | AS35: Q3 | AT35: Q4 | AU35: FY
H36: 45747 | I36: 45838 | J36: 45930 | K36: 46022 | L36: =K36 -> 46022 | M36: =EOMONTH(L36,3) -> 46112 | N36: =EOMONTH(M36,3) -> 46203 | O36: =EOMONTH(N36,3) -> 46295 | P36: =EOMONTH(O36,3) -> 46387 | Q36: =P36 -> 46387 | R36: =EOMONTH(Q36,3) -> 46477 | S36: =EOMONTH(R36,3) -> 46568 | T36: =EOMONTH(S36,3) -> 46660 | U36: =EOMONTH(T36,3) -> 46752 | V36: =U36 -> 46752 | W36: =EOMONTH(V36,3) -> 46843 | X36: =EOMONTH(W36,3) -> 46934 | Y36: =EOMONTH(X36,3) -> 47026 | Z36: =EOMONTH(Y36,3) -> 47118 | AA36: =Z36 -> 47118 | AB36: =EOMONTH(AA36,3) -> 47208 | AC36: =EOMONTH(AB36,3) -> 47299 | AD36: =EOMONTH(AC36,3) -> 47391 | AE36: =EOMONTH(AD36,3) -> 47483 | AF36: =AE36 -> 47483 | AG36: =EOMONTH(AF36,3) -> 47573 | AH36: =EOMONTH(AG36,3) -> 47664 | AI36: =EOMONTH(AH36,3) -> 47756 | AJ36: =EOMONTH(AI36,3) -> 47848 | AK36: =AJ36 -> 47848 | AL36: =EOMONTH(AK36,3) -> 47938 | AM36: =EOMONTH(AL36,3) -> 48029 | AN36: =EOMONTH(AM36,3) -> 48121 | AO36: =EOMONTH(AN36,3) -> 48213 | AP36: =AO36 -> 48213 | AQ36: =EOMONTH(AP36,3) -> 48304 | AR36: =EOMONTH(AQ36,3) -> 48395 | AS36: =EOMONTH(AR36,3) -> 48487 | AT36: =EOMONTH(AS36,3) -> 48579 | AU36: =AT36 -> 48579
C38: Revenue | H38: 0.25 | I38: 0.25 | J38: 0.25 | K38: 0.25 | L38: =SUM(H38:K38) -> 1 | M38: 0.25 | N38: 0.25 | O38: 0.25 | P38: 0.25 | Q38: =SUM(M38:P38) -> 1 | R38: 0.25 | S38: 0.25 | T38: 0.25 | U38: 0.25 | V38: =SUM(R38:U38) -> 1 | W38: 0.25 | X38: 0.25 | Y38: 0.25 | Z38: 0.25 | AA38: =SUM(W38:Z38) -> 1 | AB38: 0.25 | AC38: 0.25 | AD38: 0.25 | AE38: 0.25 | AF38: =SUM(AB38:AE38) -> 1 | AG38: 0.25 | AH38: 0.25 | AI38: 0.25 | AJ38: 0.25 | AK38: =SUM(AG38:AJ38) -> 1 | AL38: 0.25 | AM38: 0.25 | AN38: 0.25 | AO38: 0.25 | AP38: =SUM(AL38:AO38) -> 1 | AQ38: 0.25 | AR38: 0.25 | AS38: 0.25 | AT38: 0.25 | AU38: =SUM(AQ38:AT38) -> 1
C39: EBITDA | H39: 0.25 | I39: 0.25 | J39: 0.25 | K39: 0.25 | L39: =SUM(H39:K39) -> 1 | M39: 0.25 | N39: 0.25 | O39: 0.25 | P39: 0.25 | Q39: =SUM(M39:P39) -> 1 | R39: 0.25 | S39: 0.25 | T39: 0.25 | U39: 0.25 | V39: =SUM(R39:U39) -> 1 | W39: 0.25 | X39: 0.25 | Y39: 0.25 | Z39: 0.25 | AA39: =SUM(W39:Z39) -> 1 | AB39: 0.25 | AC39: 0.25 | AD39: 0.25 | AE39: 0.25 | AF39: =SUM(AB39:AE39) -> 1 | AG39: 0.25 | AH39: 0.25 | AI39: 0.25 | AJ39: 0.25 | AK39: =SUM(AG39:AJ39) -> 1 | AL39: 0.25 | AM39: 0.25 | AN39: 0.25 | AO39: 0.25 | AP39: =SUM(AL39:AO39) -> 1 | AQ39: 0.25 | AR39: 0.25 | AS39: 0.25 | AT39: 0.25 | AU39: =SUM(AQ39:AT39) -> 1
C40: D&A | H40: 0.25 | I40: 0.25 | J40: 0.25 | K40: 0.25 | L40: =SUM(H40:K40) -> 1 | M40: 0.25 | N40: 0.25 | O40: 0.25 | P40: 0.25 | Q40: =SUM(M40:P40) -> 1 | R40: 0.25 | S40: 0.25 | T40: 0.25 | U40: 0.25 | V40: =SUM(R40:U40) -> 1 | W40: 0.25 | X40: 0.25 | Y40: 0.25 | Z40: 0.25 | AA40: =SUM(W40:Z40) -> 1 | AB40: 0.25 | AC40: 0.25 | AD40: 0.25 | AE40: 0.25 | AF40: =SUM(AB40:AE40) -> 1 | AG40: 0.25 | AH40: 0.25 | AI40: 0.25 | AJ40: 0.25 | AK40: =SUM(AG40:AJ40) -> 1 | AL40: 0.25 | AM40: 0.25 | AN40: 0.25 | AO40: 0.25 | AP40: =SUM(AL40:AO40) -> 1 | AQ40: 0.25 | AR40: 0.25 | AS40: 0.25 | AT40: 0.25 | AU40: =SUM(AQ40:AT40) -> 1
C41: Taxes | H41: 0.25 | I41: 0.25 | J41: 0.25 | K41: 0.25 | L41: =SUM(H41:K41) -> 1 | M41: 0.25 | N41: 0.25 | O41: 0.25 | P41: 0.25 | Q41: =SUM(M41:P41) -> 1 | R41: 0.25 | S41: 0.25 | T41: 0.25 | U41: 0.25 | V41: =SUM(R41:U41) -> 1 | W41: 0.25 | X41: 0.25 | Y41: 0.25 | Z41: 0.25 | AA41: =SUM(W41:Z41) -> 1 | AB41: 0.25 | AC41: 0.25 | AD41: 0.25 | AE41: 0.25 | AF41: =SUM(AB41:AE41) -> 1 | AG41: 0.25 | AH41: 0.25 | AI41: 0.25 | AJ41: 0.25 | AK41: =SUM(AG41:AJ41) -> 1 | AL41: 0.25 | AM41: 0.25 | AN41: 0.25 | AO41: 0.25 | AP41: =SUM(AL41:AO41) -> 1 | AQ41: 0.25 | AR41: 0.25 | AS41: 0.25 | AT41: 0.25 | AU41: =SUM(AQ41:AT41) -> 1
C42: Working Capital | H42: 0.25 | I42: 0.25 | J42: 0.25 | K42: 0.25 | L42: =SUM(H42:K42) -> 1 | M42: 0.25 | N42: 0.25 | O42: 0.25 | P42: 0.25 | Q42: =SUM(M42:P42) -> 1 | R42: 0.25 | S42: 0.25 | T42: 0.25 | U42: 0.25 | V42: =SUM(R42:U42) -> 1 | W42: 0.25 | X42: 0.25 | Y42: 0.25 | Z42: 0.25 | AA42: =SUM(W42:Z42) -> 1 | AB42: 0.25 | AC42: 0.25 | AD42: 0.25 | AE42: 0.25 | AF42: =SUM(AB42:AE42) -> 1 | AG42: 0.25 | AH42: 0.25 | AI42: 0.25 | AJ42: 0.25 | AK42: =SUM(AG42:AJ42) -> 1 | AL42: 0.25 | AM42: 0.25 | AN42: 0.25 | AO42: 0.25 | AP42: =SUM(AL42:AO42) -> 1 | AQ42: 0.25 | AR42: 0.25 | AS42: 0.25 | AT42: 0.25 | AU42: =SUM(AQ42:AT42) -> 1
C43: Capex | H43: 0.25 | I43: 0.25 | J43: 0.25 | K43: 0.25 | L43: =SUM(H43:K43) -> 1 | M43: 0.25 | N43: 0.25 | O43: 0.25 | P43: 0.25 | Q43: =SUM(M43:P43) -> 1 | R43: 0.25 | S43: 0.25 | T43: 0.25 | U43: 0.25 | V43: =SUM(R43:U43) -> 1 | W43: 0.25 | X43: 0.25 | Y43: 0.25 | Z43: 0.25 | AA43: =SUM(W43:Z43) -> 1 | AB43: 0.25 | AC43: 0.25 | AD43: 0.25 | AE43: 0.25 | AF43: =SUM(AB43:AE43) -> 1 | AG43: 0.25 | AH43: 0.25 | AI43: 0.25 | AJ43: 0.25 | AK43: =SUM(AG43:AJ43) -> 1 | AL43: 0.25 | AM43: 0.25 | AN43: 0.25 | AO43: 0.25 | AP43: =SUM(AL43:AO43) -> 1 | AQ43: 0.25 | AR43: 0.25 | AS43: 0.25 | AT43: 0.25 | AU43: =SUM(AQ43:AT43) -> 1
C44: Dividends | H44: 0.25 | I44: 0.25 | J44: 0.25 | K44: 0.25 | L44: =SUM(H44:K44) -> 1 | M44: 0.25 | N44: 0.25 | O44: 0.25 | P44: 0.25 | Q44: =SUM(M44:P44) -> 1 | R44: 0.25 | S44: 0.25 | T44: 0.25 | U44: 0.25 | V44: =SUM(R44:U44) -> 1 | W44: 0.25 | X44: 0.25 | Y44: 0.25 | Z44: 0.25 | AA44: =SUM(W44:Z44) -> 1 | AB44: 0.25 | AC44: 0.25 | AD44: 0.25 | AE44: 0.25 | AF44: =SUM(AB44:AE44) -> 1 | AG44: 0.25 | AH44: 0.25 | AI44: 0.25 | AJ44: 0.25 | AK44: =SUM(AG44:AJ44) -> 1 | AL44: 0.25 | AM44: 0.25 | AN44: 0.25 | AO44: 0.25 | AP44: =SUM(AL44:AO44) -> 1 | AQ44: 0.25 | AR44: 0.25 | AS44: 0.25 | AT44: 0.25 | AU44: =SUM(AQ44:AT44) -> 1
C45: Current debt | H45: 0.25 | I45: 0.25 | J45: 0.25 | K45: 0.25 | L45: =SUM(H45:K45) -> 1 | M45: 0.25 | N45: 0.25 | O45: 0.25 | P45: 0.25 | Q45: =SUM(M45:P45) -> 1 | R45: 0.25 | S45: 0.25 | T45: 0.25 | U45: 0.25 | V45: =SUM(R45:U45) -> 1 | W45: 0.25 | X45: 0.25 | Y45: 0.25 | Z45: 0.25 | AA45: =SUM(W45:Z45) -> 1 | AB45: 0.25 | AC45: 0.25 | AD45: 0.25 | AE45: 0.25 | AF45: =SUM(AB45:AE45) -> 1 | AG45: 0.25 | AH45: 0.25 | AI45: 0.25 | AJ45: 0.25 | AK45: =SUM(AG45:AJ45) -> 1 | AL45: 0.25 | AM45: 0.25 | AN45: 0.25 | AO45: 0.25 | AP45: =SUM(AL45:AO45) -> 1 | AQ45: 0.25 | AR45: 0.25 | AS45: 0.25 | AT45: 0.25 | AU45: =SUM(AQ45:AT45) -> 1
C47: P&L
H49: Q1 | I49: Q2 | J49: Q3 | K49: Closing | L49: FY | M49: Q1 | N49: Q2 | O49: Q3 | P49: Q4 | Q49: FY | R49: Q1 | S49: Q2 | T49: Q3 | U49: Q4 | V49: FY | W49: Q1 | X49: Q2 | Y49: Q3 | Z49: Q4 | AA49: FY | AB49: Q1 | AC49: Q2 | AD49: Q3 | AE49: Q4 | AF49: FY | AG49: Q1 | AH49: Q2 | AI49: Q3 | AJ49: Q4 | AK49: FY | AL49: Q1 | AM49: Q2 | AN49: Q3 | AO49: Q4 | AP49: FY | AQ49: Q1 | AR49: Q2 | AS49: Q3 | AT49: Q4 | AU49: FY
H50: 45747 | I50: 45838 | J50: 45930 | K50: 46022 | L50: =K50 -> 46022 | M50: =EOMONTH(L50,3) -> 46112 | N50: =EOMONTH(M50,3) -> 46203 | O50: =EOMONTH(N50,3) -> 46295 | P50: =EOMONTH(O50,3) -> 46387 | Q50: =P50 -> 46387 | R50: =EOMONTH(Q50,3) -> 46477 | S50: =EOMONTH(R50,3) -> 46568 | T50: =EOMONTH(S50,3) -> 46660 | U50: =EOMONTH(T50,3) -> 46752 | V50: =U50 -> 46752 | W50: =EOMONTH(V50,3) -> 46843 | X50: =EOMONTH(W50,3) -> 46934 | Y50: =EOMONTH(X50,3) -> 47026 | Z50: =EOMONTH(Y50,3) -> 47118 | AA50: =Z50 -> 47118 | AB50: =EOMONTH(AA50,3) -> 47208 | AC50: =EOMONTH(AB50,3) -> 47299 | AD50: =EOMONTH(AC50,3) -> 47391 | AE50: =EOMONTH(AD50,3) -> 47483 | AF50: =AE50 -> 47483 | AG50: =EOMONTH(AF50,3) -> 47573 | AH50: =EOMONTH(AG50,3) -> 47664 | AI50: =EOMONTH(AH50,3) -> 47756 | AJ50: =EOMONTH(AI50,3) -> 47848 | AK50: =AJ50 -> 47848 | AL50: =EOMONTH(AK50,3) -> 47938 | AM50: =EOMONTH(AL50,3) -> 48029 | AN50: =EOMONTH(AM50,3) -> 48121 | AO50: =EOMONTH(AN50,3) -> 48213 | AP50: =AO50 -> 48213 | AQ50: =EOMONTH(AP50,3) -> 48304 | AR50: =EOMONTH(AQ50,3) -> 48395 | AS50: =EOMONTH(AR50,3) -> 48487 | AT50: =EOMONTH(AS50,3) -> 48579 | AU50: =AT50 -> 48579
C52: Total Revenue | H52: =L52*H38 -> 66.917314 | I52: =L52*I38 -> 66.917314 | J52: =L52*J38 -> 66.917314 | K52: =L52*K38 -> 66.917314 | L52: ='Active Case'!F9 -> 267.66926 | M52: =Q52*M38 -> 75.159245 | N52: =Q52*N38 -> 75.159245 | O52: =Q52*O38 -> 75.159245 | P52: =Q52*P38 -> 75.159245 | Q52: ='Active Case'!G9 -> 300.63698 | R52: =V52*R38 -> 86.094911 | S52: =V52*S38 -> 86.094911 | T52: =V52*T38 -> 86.094911 | U52: =V52*U38 -> 86.094911 | V52: ='Active Case'!H9 -> 344.37965 | W52: =AA52*W38 -> 96.605186 | X52: =AA52*X38 -> 96.605186 | Y52: =AA52*Y38 -> 96.605186 | Z52: =AA52*Z38 -> 96.605186 | AA52: ='Active Case'!I9 -> 386.42074 | AB52: =AF52*AB38 -> 102.79279 | AC52: =AF52*AC38 -> 102.79279 | AD52: =AF52*AD38 -> 102.79279 | AE52: =AF52*AE38 -> 102.79279 | AF52: ='Active Case'!J9 -> 411.17115 | AG52: =AK52*AG38 -> 109.66452 | AH52: =AK52*AH38 -> 109.66452 | AI52: =AK52*AI38 -> 109.66452 | AJ52: =AK52*AJ38 -> 109.66452 | AK52: ='Active Case'!K9 -> 438.6581 | AL52: =AP52*AL38 -> 111.85782 | AM52: =AP52*AM38 -> 111.85782 | AN52: =AP52*AN38 -> 111.85782 | AO52: =AP52*AO38 -> 111.85782 | AP52: ='Active Case'!L9 -> 447.43126 | AQ52: =AU52*AQ38 -> 114.09497 | AR52: =AU52*AR38 -> 114.09497 | AS52: =AU52*AS38 -> 114.09497 | AT52: =AU52*AT38 -> 114.09497 | AU52: ='Active Case'!M9 -> 456.37989
C54: EBITDA | H54: =L54*H39 -> 12.825 | I54: =L54*I39 -> 12.825 | J54: =L54*J39 -> 12.825 | K54: =L54*K39 -> 12.825 | L54: =+'Active Case'!F17 -> 51.3 | M54: =Q54*M39 -> 13.06083 | N54: =Q54*N39 -> 13.06083 | O54: =Q54*O39 -> 13.06083 | P54: =Q54*P39 -> 13.06083 | Q54: ='Active Case'!G17 -> 52.243319 | R54: =V54*R39 -> 15.428321 | S54: =V54*S39 -> 15.428321 | T54: =V54*T39 -> 15.428321 | U54: =V54*U39 -> 15.428321 | V54: ='Active Case'!H17 -> 61.713285 | W54: =AA54*W39 -> 18.321271 | X54: =AA54*X39 -> 18.321271 | Y54: =AA54*Y39 -> 18.321271 | Z54: =AA54*Z39 -> 18.321271 | AA54: ='Active Case'!I17 -> 73.285082 | AB54: =AF54*AB39 -> 19.896938 | AC54: =AF54*AC39 -> 19.896938 | AD54: =AF54*AD39 -> 19.896938 | AE54: =AF54*AE39 -> 19.896938 | AF54: ='Active Case'!J17 -> 79.587752 | AG54: =AK54*AG39 -> 21.945906 | AH54: =AK54*AH39 -> 21.945906 | AI54: =AK54*AI39 -> 21.945906 | AJ54: =AK54*AJ39 -> 21.945906 | AK54: ='Active Case'!K17 -> 87.783624 | AL54: =AP54*AL39 -> 22.384824 | AM54: =AP54*AM39 -> 22.384824 | AN54: =AP54*AN39 -> 22.384824 | AO54: =AP54*AO39 -> 22.384824 | AP54: ='Active Case'!L17 -> 89.539296 | AQ54: =AU54*AQ39 -> 22.832521 | AR54: =AU54*AR39 -> 22.832521 | AS54: =AU54*AS39 -> 22.832521 | AT54: =AU54*AT39 -> 22.832521 | AU54: ='Active Case'!M17 -> 91.330082
C55: D&A | H55: =L55*H40 -> -3.29669 | I55: =L55*I40 -> -3.29669 | J55: =L55*J40 -> -3.29669 | K55: =L55*K40 -> -3.29669 | L55: ='Active Case'!F20 -> -13.18676 | M55: =Q55*M40 -> -3.441725 | N55: =Q55*N40 -> -3.441725 | O55: =Q55*O40 -> -3.441725 | P55: =Q55*P40 -> -3.441725 | Q55: ='Active Case'!G20 -> -13.7669 | R55: =V55*R40 -> -3.6943183 | S55: =V55*S40 -> -3.6943183 | T55: =V55*T40 -> -3.6943183 | U55: =V55*U40 -> -3.6943183 | V55: ='Active Case'!H20 -> -14.777273 | W55: =AA55*W40 -> -3.9373269 | X55: =AA55*X40 -> -3.9373269 | Y55: =AA55*Y40 -> -3.9373269 | Z55: =AA55*Z40 -> -3.9373269 | AA55: ='Active Case'!I20 -> -15.749308 | AB55: =AF55*AB40 -> -4.0301323 | AC55: =AF55*AC40 -> -4.0301323 | AD55: =AF55*AD40 -> -4.0301323 | AE55: =AF55*AE40 -> -4.0301323 | AF55: ='Active Case'!J20 -> -16.120529 | AG55: =AK55*AG40 -> -4.077246 | AH55: =AK55*AH40 -> -4.077246 | AI55: =AK55*AI40 -> -4.077246 | AJ55: =AK55*AJ40 -> -4.077246 | AK55: ='Active Case'!K20 -> -16.308984 | AL55: =AP55*AL40 -> -4.077246 | AM55: =AP55*AM40 -> -4.077246 | AN55: =AP55*AN40 -> -4.077246 | AO55: =AP55*AO40 -> -4.077246 | AP55: ='Active Case'!L20 -> -16.308984 | AQ55: =AU55*AQ40 -> -4.077246 | AR55: =AU55*AR40 -> -4.077246 | AS55: =AU55*AS40 -> -4.077246 | AT55: =AU55*AT40 -> -4.077246 | AU55: ='Active Case'!M20 -> -16.308984
C56: EBIT | H56: =SUM(H54:H55) -> 9.52831 | I56: =SUM(I54:I55) -> 9.52831 | J56: =SUM(J54:J55) -> 9.52831 | K56: =SUM(K54:K55) -> 9.52831 | L56: =SUM(L54:L55) -> 38.11324 | M56: =SUM(M54:M55) -> 9.6191048 | N56: =SUM(N54:N55) -> 9.6191048 | O56: =SUM(O54:O55) -> 9.6191048 | ... AU56: =SUM(AU54:AU55) -> 75.021098
C58: Interest Expense (incl. commitment fees) | H58: =SUM(H59:H62) -> 0 | I58: =SUM(I59:I62) -> 0 | J58: =SUM(J59:J62) -> 0 | K58: =SUM(K59:K62) -> 0 | L58: =SUM(L59:L62) -> 0 | M58: =SUM(M59:M62) -> -3.7118513 | N58: =SUM(N59:N62) -> -3.7384549 | O58: =SUM(O59:O62) -> -3.7650584 | ... AU58: =SUM(AU59:AU62) -> -14.630678
C59: ='Debt Structure'!C22 -> TLA | H59: =H129 -> 0 | I59: =I129 -> 0 | J59: =J129 -> 0 | K59: =K129 -> 0 | L59: =SUM(H59:K59) -> 0 | M59: =M129 -> 0 | N59: =N129 -> 0 | O59: =O129 -> 0 | P59: =P129 -> 0 | Q59: =SUM(M59:P59) -> 0 | R59: =R129 -> 0 | S59: =S129 -> 0 | T59: =T129 -> 0 | U59: =U129 -> 0 | V59: =SUM(R59:U59) -> 0 | W59: =W129 -> 0 | X59: =X129 -> 0 | Y59: =Y129 -> 0 | Z59: =Z129 -> 0 | AA59: =SUM(W59:Z59) -> 0 | AB59: =AB129 -> 0 | AC59: =AC129 -> 0 | AD59: =AD129 -> 0 | AE59: =AE129 -> 0 | AF59: =SUM(AB59:AE59) -> 0 | AG59: =AG129 -> 0 | AH59: =AH129 -> 0 | AI59: =AI129 -> 0 | AJ59: =AJ129 -> 0 | AK59: =SUM(AG59:AJ59) -> 0 | AL59: =AL129 -> 0 | AM59: =AM129 -> 0 | AN59: =AN129 -> 0 | AO59: =AO129 -> 0 | AP59: =SUM(AL59:AO59) -> 0 | AQ59: =AQ129 -> 0 | AR59: =AR129 -> 0 | AS59: =AS129 -> 0 | AT59: =AT129 -> 0 | AU59: =SUM(AQ59:AT59) -> 0
C60: ='Debt Structure'!C23 -> TLB | H60: =H146 -> 0 | I60: =I146 -> 0 | J60: =J146 -> 0 | K60: =K146 -> 0 | L60: =SUM(H60:K60) -> 0 | M60: =M146 -> -3.526875 | N60: =N146 -> -3.526875 | O60: =O146 -> -3.526875 | P60: =P146 -> -3.526875 | Q60: =SUM(M60:P60) -> -14.1075 | R60: =R146 -> -3.526875 | S60: =S146 -> -3.526875 | T60: =T146 -> -3.526875 | U60: =U146 -> -3.526875 | V60: =SUM(R60:U60) -> -14.1075 | W60: =W146 -> -3.526875 | X60: =X146 -> -3.526875 | Y60: =Y146 -> -3.526875 | Z60: =Z146 -> -3.526875 | AA60: =SUM(W60:Z60) -> -14.1075 | AB60: =AB146 -> -3.526875 | AC60: =AC146 -> -3.526875 | AD60: =AD146 -> -3.526875 | AE60: =AE146 -> -3.526875 | AF60: =SUM(AB60:AE60) -> -14.1075 | AG60: =AG146 -> -3.526875 | AH60: =AH146 -> -3.526875 | AI60: =AI146 -> -3.526875 | AJ60: =AJ146 -> -3.526875 | AK60: =SUM(AG60:AJ60) -> -14.1075 | AL60: =AL146 -> -3.526875 | AM60: =AM146 -> -3.526875 | AN60: =AN146 -> -3.526875 | AO60: =AO146 -> -3.526875 | AP60: =SUM(AL60:AO60) -> -14.1075 | AQ60: =AQ146 -> -3.526875 | AR60: =AR146 -> -3.526875 | AS60: =AS146 -> -3.526875 | AT60: =AT146 -> -1.7634375 | AU60: =SUM(AQ60:AT60) -> -12.344063
C61: ='Debt Structure'!C33 -> CAF | H61: =H172+H178 -> 0 | I61: =I172+I178 -> 0 | J61: =J172+J178 -> 0 | K61: =K172+K178 -> 0 | L61: =SUM(H61:K61) -> 0 | M61: =M172+M178 -> -0.13497633 | N61: =N172+N178 -> -0.16157988 | O61: =O172+O178 -> -0.18818344 | P61: =P172+P178 -> -0.21478699 | Q61: =SUM(M61:P61) -> -0.69952664 | R61: =R172+R178 -> -0.25438495 | S61: =S172+S178 -> -0.31564024 | T61: =T172+T178 -> -0.37689554 | U61: =U172+U178 -> -0.43815084 | V61: =SUM(R61:U61) -> -1.3850716 | W61: =W172+W178 -> -0.48820152 | X61: =X172+X178 -> -0.51957783 | Y61: =Y172+Y178 -> -0.55095414 | Z61: =Z172+Z178 -> -0.58233045 | AA61: =SUM(W61:Z61) -> -2.1410639 | AB61: =AB172+AB178 -> -0.59617581 | AC61: =AC172+AC178 -> -0.59617581 | AD61: =AD172+AD178 -> -0.59617581 | AE61: =AE172+AE178 -> -0.59617581 | AF61: =SUM(AB61:AE61) -> -2.3847032 | AG61: =AG172+AG178 -> -0.59617581 | AH61: =AH172+AH178 -> -0.59617581 | AI61: =AI172+AI178 -> -0.59617581 | AJ61: =AJ172+AJ178 -> -0.59617581 | AK61: =SUM(AG61:AJ61) -> -2.3847032 | AL61: =AL172+AL178 -> -0.59617581 | AM61: =AM172+AM178 -> -0.59617581 | AN61: =AN172+AN178 -> -0.59617581 | AO61: =AO172+AO178 -> -0.59617581 | AP61: =SUM(AL61:AO61) -> -2.3847032 | AQ61: =AQ172+AQ178 -> -0.59617581 | AR61: =AR172+AR178 -> -0.59617581 | AS61: =AS172+AS178 -> -0.59617581 | AT61: =AT172+AT178 -> -0.2980879 | AU61: =SUM(AQ61:AT61) -> -2.0866153
C62: RCF | H62: =H197+H204 -> 0 | I62: =I197+I204 -> 0 | J62: =J197+J204 -> 0 | K62: =K197+K204 -> 0 | L62: =SUM(H62:K62) -> 0 | M62: =M197+M204 -> -0.05 | N62: =N197+N204 -> -0.05 | O62: =O197+O204 -> -0.05 | P62: =P197+P204 -> -0.05 | Q62: =SUM(M62:P62) -> -0.2 | R62: =R197+R204 -> -0.05 | S62: =S197+S204 -> -0.05 | T62: =T197+T204 -> -0.05 | U62: =U197+U204 -> -0.05 | V62: =SUM(R62:U62) -> -0.2 | W62: =W197+W204 -> -0.05 | X62: =X197+X204 -> -0.05 | Y62: =Y197+Y204 -> -0.05 | Z62: =Z197+Z204 -> -0.05 | AA62: =SUM(W62:Z62) -> -0.2 | AB62: =AB197+AB204 -> -0.05 | AC62: =AC197+AC204 -> -0.05 | AD62: =AD197+AD204 -> -0.05 | AE62: =AE197+AE204 -> -0.05 | AF62: =SUM(AB62:AE62) -> -0.2 | AG62: =AG197+AG204 -> -0.05 | AH62: =AH197+AH204 -> -0.05 | AI62: =AI197+AI204 -> -0.05 | AJ62: =AJ197+AJ204 -> -0.05 | AK62: =SUM(AG62:AJ62) -> -0.2 | AL62: =AL197+AL204 -> -0.05 | AM62: =AM197+AM204 -> -0.05 | AN62: =AN197+AN204 -> -0.05 | AO62: =AO197+AO204 -> -0.05 | AP62: =SUM(AL62:AO62) -> -0.2 | AQ62: =AQ197+AQ204 -> -0.05 | AR62: =AR197+AR204 -> -0.05 | AS62: =AS197+AS204 -> -0.05 | AT62: =AT197+AT204 -> -0.05 | AU62: =SUM(AQ62:AT62) -> -0.2
C64: Tax Payable | H64: =L64*H41 -> -2.0662747 | I64: =L64*I41 -> -2.0662747 | J64: =L64*J41 -> -2.0662747 | K64: =L64*K41 -> -2.0662747 | L64: ='Active Case'!F23 -> -8.2650988 | M64: =Q64*M41 -> -0.92599323 | N64: =Q64*N41 -> -0.92599323 | O64: =Q64*O41 -> -0.92599323 | P64: =Q64*P41 -> -0.92599323 | Q64: ='Active Case'!G23 -> -3.7039729 | R64: =V64*R41 -> -1.4168129 | S64: =V64*S41 -> -1.4168129 | T64: =V64*T41 -> -1.4168129 | U64: =V64*U41 -> -1.4168129 | V64: ='Active Case'!H23 -> -5.6672515 | W64: =AA64*W41 -> -2.2791885 | X64: =AA64*X41 -> -2.2791885 | Y64: =AA64*Y41 -> -2.2791885 | Z64: =AA64*Z41 -> -2.2791885 | AA64: ='Active Case'!I23 -> -9.1167539 | AB64: =AF64*AB41 -> -2.5873773 | AC64: =AF64*AC41 -> -2.5873773 | AD64: =AF64*AD41 -> -2.5873773 | AE64: =AF64*AE41 -> -2.5873773 | AF64: ='Active Case'!J23 -> -10.349509 | AG64: =AK64*AG41 -> -3.0104623 | AH64: =AK64*AH41 -> -3.0104623 | AI64: =AK64*AI41 -> -3.0104623 | AJ64: =AK64*AJ41 -> -3.0104623 | AK64: ='Active Case'!K23 -> -12.041849 | AL64: =AP64*AL41 -> -3.1719171 | AM64: =AP64*AM41 -> -3.1719171 | AN64: =AP64*AN41 -> -3.1719171 | AO64: =AP64*AO41 -> -3.1719171 | AP64: ='Active Case'!L23 -> -12.687668 | AQ64: =AU64*AQ41 -> -3.554206 | AR64: =AU64*AR41 -> -3.554206 | AS64: =AU64*AS41 -> -3.554206 | AT64: =AU64*AT41 -> -3.554206 | AU64: ='Active Case'!M23 -> -14.216824
C66: Net Income | H66: =H56+H58+H64 -> 7.4620353 | I66: =I56+I58+I64 -> 7.4620353 | J66: =J56+J58+J64 -> 7.4620353 | K66: =K56+K58+K64 -> 7.4620353 | L66: =L56+L58+L64 -> 29.848141 | M66: =M56+M58+M64 -> 4.9812603 | N66: =N56+N58+N64 -> 4.9546567 | O66: =O56+O58+O64 -> 4.9280532 | ... AU66: =AU56+AU58+AU64 -> 46.173596
C69: Cash Flow
H71: Q1 | I71: Q2 | J71: Q3 | K71: Closing | L71: FY | M71: Q1 | N71: Q2 | O71: Q3 | P71: Q4 | Q71: FY | R71: Q1 | S71: Q2 | T71: Q3 | U71: Q4 | V71: FY | W71: Q1 | X71: Q2 | Y71: Q3 | Z71: Q4 | AA71: FY | AB71: Q1 | AC71: Q2 | AD71: Q3 | AE71: Q4 | AF71: FY | AG71: Q1 | AH71: Q2 | AI71: Q3 | AJ71: Q4 | AK71: FY | AL71: Q1 | AM71: Q2 | AN71: Q3 | AO71: Q4 | AP71: FY | AQ71: Q1 | AR71: Q2 | AS71: Q3 | AT71: Q4 | AU71: FY
H72: 45747 | I72: 45838 | J72: 45930 | K72: 46022 | L72: =K72 -> 46022 | M72: =EOMONTH(L72,3) -> 46112 | N72: =EOMONTH(M72,3) -> 46203 | O72: =EOMONTH(N72,3) -> 46295 | P72: =EOMONTH(O72,3) -> 46387 | Q72: =P72 -> 46387 | R72: =EOMONTH(Q72,3) -> 46477 | S72: =EOMONTH(R72,3) -> 46568 | T72: =EOMONTH(S72,3) -> 46660 | U72: =EOMONTH(T72,3) -> 46752 | V72: =U72 -> 46752 | W72: =EOMONTH(V72,3) -> 46843 | X72: =EOMONTH(W72,3) -> 46934 | Y72: =EOMONTH(X72,3) -> 47026 | Z72: =EOMONTH(Y72,3) -> 47118 | AA72: =Z72 -> 47118 | AB72: =EOMONTH(AA72,3) -> 47208 | AC72: =EOMONTH(AB72,3) -> 47299 | AD72: =EOMONTH(AC72,3) -> 47391 | AE72: =EOMONTH(AD72,3) -> 47483 | AF72: =AE72 -> 47483 | AG72: =EOMONTH(AF72,3) -> 47573 | AH72: =EOMONTH(AG72,3) -> 47664 | AI72: =EOMONTH(AH72,3) -> 47756 | AJ72: =EOMONTH(AI72,3) -> 47848 | AK72: =AJ72 -> 47848 | AL72: =EOMONTH(AK72,3) -> 47938 | AM72: =EOMONTH(AL72,3) -> 48029 | AN72: =EOMONTH(AM72,3) -> 48121 | AO72: =EOMONTH(AN72,3) -> 48213 | AP72: =AO72 -> 48213 | AQ72: =EOMONTH(AP72,3) -> 48304 | AR72: =EOMONTH(AQ72,3) -> 48395 | AS72: =EOMONTH(AR72,3) -> 48487 | AT72: =EOMONTH(AS72,3) -> 48579 | AU72: =AT72 -> 48579
C74: EBITDA | M74: =M54 -> 13.06083 | N74: =N54 -> 13.06083 | O74: =O54 -> 13.06083 | P74: =P54 -> 13.06083 | Q74: =Q54 -> 52.243319 | R74: =R54 -> 15.428321 | S74: =S54 -> 15.428321 | T74: =T54 -> 15.428321 | ... AU74: =AU54 -> 91.330082
C75: Change in Working Capital | M75: =Q75*M42 -> -1.2504355 | N75: =Q75*N42 -> -1.2504355 | O75: =Q75*O42 -> -1.2504355 | P75: =Q75*P42 -> -1.2504355 | Q75: ='Active Case'!G30 -> -5.0017419 | R75: =V75*R42 -> -1.711903 | S75: =V75*S42 -> -1.711903 | T75: =V75*T42 -> -1.711903 | U75: =V75*U42 -> -1.711903 | V75: ='Active Case'!H30 -> -6.8476121 | W75: =AA75*W42 -> -1.5445211 | X75: =AA75*X42 -> -1.5445211 | Y75: =AA75*Y42 -> -1.5445211 | Z75: =AA75*Z42 -> -1.5445211 | AA75: ='Active Case'!I30 -> -6.1780846 | AB75: =AF75*AB42 -> -0.63675264 | AC75: =AF75*AC42 -> -0.63675264 | AD75: =AF75*AD42 -> -0.63675264 | AE75: =AF75*AE42 -> -0.63675264 | AF75: ='Active Case'!J30 -> -2.5470106 | AG75: =AK75*AG42 -> -0.74630515 | AH75: =AK75*AH42 -> -0.74630515 | AI75: =AK75*AI42 -> -0.74630515 | AJ75: =AK75*AJ42 -> -0.74630515 | AK75: ='Active Case'!K30 -> -2.9852206 | AL75: =AP75*AL42 -> -0.39150235 | AM75: =AP75*AM42 -> -0.39150235 | AN75: =AP75*AN42 -> -0.39150235 | AO75: =AP75*AO42 -> -0.39150235 | AP75: ='Active Case'!L30 -> -1.5660094 | AQ75: =AU75*AQ42 -> -0.3993324 | AR75: =AU75*AR42 -> -0.3993324 | AS75: =AU75*AS42 -> -0.3993324 | AT75: =AU75*AT42 -> -0.3993324 | AU75: ='Active Case'!M30 -> -1.5973296
C76: Capex | M76: =Q76*M43 -> -2.6603553 | N76: =Q76*N43 -> -2.6603553 | O76: =Q76*O43 -> -2.6603553 | P76: =Q76*P43 -> -2.6603553 | Q76: ='Active Case'!G33+'Active Case'!G36 -> -10.641421 | R76: =V76*R43 -> -6.1255297 | S76: =V76*S43 -> -6.1255297 | T76: =V76*T43 -> -6.1255297 | U76: =V76*U43 -> -6.1255297 | V76: ='Active Case'!H33+'Active Case'!H36 -> -24.502119 | W76: =AA76*W43 -> -3.1376312 | X76: =AA76*X43 -> -3.1376312 | Y76: =AA76*Y43 -> -3.1376312 | Z76: =AA76*Z43 -> -3.1376312 | AA76: ='Active Case'!I33+'Active Case'!I36 -> -12.550525 | AB76: =AF76*AB43 -> -4.1174563 | AC76: =AF76*AC43 -> -4.1174563 | AD76: =AF76*AD43 -> -4.1174563 | AE76: =AF76*AE43 -> -4.1174563 | AF76: ='Active Case'!J33+'Active Case'!J36 -> -16.469825 | AG76: =AK76*AG43 -> -2.7502833 | AH76: =AK76*AH43 -> -2.7502833 | AI76: =AK76*AI43 -> -2.7502833 | AJ76: =AK76*AJ43 -> -2.7502833 | AK76: ='Active Case'!K33+'Active Case'!K36 -> -11.001133 | AL76: =AP76*AL43 -> -2.1932905 | AM76: =AP76*AM43 -> -2.1932905 | AN76: =AP76*AN43 -> -2.1932905 | AO76: =AP76*AO43 -> -2.1932905 | AP76: ='Active Case'!L33+'Active Case'!L36 -> -8.773162 | AQ76: =AU76*AQ43 -> -2.1932905 | AR76: =AU76*AR43 -> -2.1932905 | AS76: =AU76*AS43 -> -2.1932905 | AT76: =AU76*AT43 -> -2.1932905 | AU76: ='Active Case'!M33+'Active Case'!M36 -> -8.773162
C77: Tax Payable | M77: =M64 -> -0.92599323 | N77: =N64 -> -0.92599323 | O77: =O64 -> -0.92599323 | P77: =P64 -> -0.92599323 | Q77: =SUM(M77:P77) -> -3.7039729 | R77: =R64 -> -1.4168129 | S77: =S64 -> -1.4168129 | T77: =T64 -> -1.4168129 | U77: =U64 -> -1.4168129 | V77: =SUM(R77:U77) -> -5.6672515 | W77: =W64 -> -2.2791885 | X77: =X64 -> -2.2791885 | Y77: =Y64 -> -2.2791885 | Z77: =Z64 -> -2.2791885 | AA77: =SUM(W77:Z77) -> -9.1167539 | AB77: =AB64 -> -2.5873773 | AC77: =AC64 -> -2.5873773 | AD77: =AD64 -> -2.5873773 | AE77: =AE64 -> -2.5873773 | AF77: =SUM(AB77:AE77) -> -10.349509 | AG77: =AG64 -> -3.0104623 | AH77: =AH64 -> -3.0104623 | AI77: =AI64 -> -3.0104623 | AJ77: =AJ64 -> -3.0104623 | AK77: =SUM(AG77:AJ77) -> -12.041849 | AL77: =AL64 -> -3.1719171 | AM77: =AM64 -> -3.1719171 | AN77: =AN64 -> -3.1719171 | AO77: =AO64 -> -3.1719171 | AP77: =SUM(AL77:AO77) -> -12.687668 | AQ77: =AQ64 -> -3.554206 | AR77: =AR64 -> -3.554206 | AS77: =AS64 -> -3.554206 | AT77: =AT64 -> -3.554206 | AU77: =SUM(AQ77:AT77) -> -14.216824
C78: Cash Flow Before Debt Service | M78: =SUM(M74:M77) -> 8.2240459 | N78: =SUM(N74:N77) -> 8.2240459 | O78: =SUM(O74:O77) -> 8.2240459 | P78: =SUM(P74:P77) -> 8.2240459 | Q78: =SUM(Q74:Q77) -> 32.896183 | R78: =SUM(R74:R77) -> 6.1740758 | S78: =SUM(S74:S77) -> 6.1740758 | T78: =SUM(T74:T77) -> 6.1740758 | ... AU78: =SUM(AU74:AU77) -> 66.742767
C80: Cash Paid Interest (incl. Commitment fees) | M80: =SUM(M81:M84) -> -3.7118513 | N80: =SUM(N81:N84) -> -3.7384549 | O80: =SUM(O81:O84) -> -3.7650584 | P80: =SUM(P81:P84) -> -3.791662 | Q80: =SUM(Q81:Q84) -> -15.007027 | R80: =SUM(R81:R84) -> -3.8312599 | S80: =SUM(S81:S84) -> -3.8925152 | T80: =SUM(T81:T84) -> -3.9537705 | ... AU80: =SUM(AU81:AU84) -> -14.630678
C81: =$C$59 -> TLA | M81: =M59 -> 0 | N81: =N59 -> 0 | O81: =O59 -> 0 | P81: =P59 -> 0 | Q81: =Q59 -> 0 | R81: =R59 -> 0 | S81: =S59 -> 0 | T81: =T59 -> 0 | ... AU81: =AU59 -> 0
C82: =$C$60 -> TLB | M82: =M60 -> -3.526875 | N82: =N60 -> -3.526875 | O82: =O60 -> -3.526875 | P82: =P60 -> -3.526875 | Q82: =Q60 -> -14.1075 | R82: =R60 -> -3.526875 | S82: =S60 -> -3.526875 | T82: =T60 -> -3.526875 | ... AU82: =AU60 -> -12.344063
C83: =$C$61 -> CAF | M83: =M61 -> -0.13497633 | N83: =N61 -> -0.16157988 | O83: =O61 -> -0.18818344 | P83: =P61 -> -0.21478699 | Q83: =Q61 -> -0.69952664 | R83: =R61 -> -0.25438495 | S83: =S61 -> -0.31564024 | T83: =T61 -> -0.37689554 | ... AU83: =AU61 -> -2.0866153
C84: =$C$62 -> RCF | M84: =M62 -> -0.05 | N84: =N62 -> -0.05 | O84: =O62 -> -0.05 | P84: =P62 -> -0.05 | Q84: =Q62 -> -0.2 | R84: =R62 -> -0.05 | S84: =S62 -> -0.05 | T84: =T62 -> -0.05 | ... AU84: =AU62 -> -0.2
C86: Scheduled Amortisation | M86: =SUM(M87:M90) -> 0 | N86: =SUM(N87:N90) -> 0 | O86: =SUM(O87:O90) -> 0 | P86: =SUM(P87:P90) -> 0 | Q86: =SUM(Q87:Q90) -> 0 | R86: =SUM(R87:R90) -> 0 | S86: =SUM(S87:S90) -> 0 | T86: =SUM(T87:T90) -> 0 | ... AU86: =SUM(AU87:AU90) -> -304.19406
C87: =$C$59 -> TLA | M87: =M125 -> 0 | N87: =N125 -> 0 | O87: =O125 -> 0 | P87: =P125 -> 0 | Q87: =SUM(M87:P87) -> 0 | R87: =R125 -> 0 | S87: =S125 -> 0 | T87: =T125 -> 0 | U87: =U125 -> 0 | V87: =SUM(R87:U87) -> 0 | W87: =W125 -> 0 | X87: =X125 -> 0 | Y87: =Y125 -> 0 | Z87: =Z125 -> 0 | AA87: =SUM(W87:Z87) -> 0 | AB87: =AB125 -> 0 | AC87: =AC125 -> 0 | AD87: =AD125 -> 0 | AE87: =AE125 -> 0 | AF87: =SUM(AB87:AE87) -> 0 | AG87: =AG125 -> 0 | AH87: =AH125 -> 0 | AI87: =AI125 -> 0 | AJ87: =AJ125 -> 0 | AK87: =SUM(AG87:AJ87) -> 0 | AL87: =AL125 -> 0 | AM87: =AM125 -> 0 | AN87: =AN125 -> 0 | AO87: =AO125 -> 0 | AP87: =SUM(AL87:AO87) -> 0 | AQ87: =AQ125 -> 0 | AR87: =AR125 -> 0 | AS87: =AS125 -> 0 | AT87: =AT125 -> 0 | AU87: =SUM(AQ87:AT87) -> 0
C88: =$C$60 -> TLB | M88: =M142 -> 0 | N88: =N142 -> 0 | O88: =O142 -> 0 | P88: =P142 -> 0 | Q88: =SUM(M88:P88) -> 0 | R88: =R142 -> 0 | S88: =S142 -> 0 | T88: =T142 -> 0 | U88: =U142 -> 0 | V88: =SUM(R88:U88) -> 0 | W88: =W142 -> 0 | X88: =X142 -> 0 | Y88: =Y142 -> 0 | Z88: =Z142 -> 0 | AA88: =SUM(W88:Z88) -> 0 | AB88: =AB142 -> 0 | AC88: =AC142 -> 0 | AD88: =AD142 -> 0 | AE88: =AE142 -> 0 | AF88: =SUM(AB88:AE88) -> 0 | AG88: =AG142 -> 0 | AH88: =AH142 -> 0 | AI88: =AI142 -> 0 | AJ88: =AJ142 -> 0 | AK88: =SUM(AG88:AJ88) -> 0 | AL88: =AL142 -> 0 | AM88: =AM142 -> 0 | AN88: =AN142 -> 0 | AO88: =AO142 -> 0 | AP88: =SUM(AL88:AO88) -> 0 | AQ88: =AQ142 -> 0 | AR88: =AR142 -> 0 | AS88: =AS142 -> 0 | AT88: =AT142 -> -256.5 | AU88: =SUM(AQ88:AT88) -> -256.5
C89: =$C$61 -> CAF | M89: =M168 -> 0 | N89: =N168 -> 0 | O89: =O168 -> 0 | P89: =P168 -> 0 | Q89: =SUM(M89:P89) -> 0 | R89: =R168 -> 0 | S89: =S168 -> 0 | T89: =T168 -> 0 | U89: =U168 -> 0 | V89: =SUM(R89:U89) -> 0 | W89: =W168 -> 0 | X89: =X168 -> 0 | Y89: =Y168 -> 0 | Z89: =Z168 -> 0 | AA89: =SUM(W89:Z89) -> 0 | AB89: =AB168 -> 0 | AC89: =AC168 -> 0 | AD89: =AD168 -> 0 | AE89: =AE168 -> 0 | AF89: =SUM(AB89:AE89) -> 0 | AG89: =AG168 -> 0 | AH89: =AH168 -> 0 | AI89: =AI168 -> 0 | AJ89: =AJ168 -> 0 | AK89: =SUM(AG89:AJ89) -> 0 | AL89: =AL168 -> 0 | AM89: =AM168 -> 0 | AN89: =AN168 -> 0 | AO89: =AO168 -> 0 | AP89: =SUM(AL89:AO89) -> 0 | AQ89: =AQ168 -> 0 | AR89: =AR168 -> 0 | AS89: =AS168 -> 0 | AT89: =AT168 -> -47.694064 | AU89: =SUM(AQ89:AT89) -> -47.694064
C90: =$C$62 -> RCF | M90: =M194 -> 0 | N90: =N194 -> 0 | O90: =O194 -> 0 | P90: =P194 -> 0 | Q90: =SUM(M90:P90) -> 0 | R90: =R194 -> 0 | S90: =S194 -> 0 | T90: =T194 -> 0 | U90: =U194 -> 0 | V90: =SUM(R90:U90) -> 0 | W90: =W194 -> 0 | X90: =X194 -> 0 | Y90: =Y194 -> 0 | Z90: =Z194 -> 0 | AA90: =SUM(W90:Z90) -> 0 | AB90: =AB194 -> 0 | AC90: =AC194 -> 0 | AD90: =AD194 -> 0 | AE90: =AE194 -> 0 | AF90: =SUM(AB90:AE90) -> 0 | AG90: =AG194 -> 0 | AH90: =AH194 -> 0 | AI90: =AI194 -> 0 | AJ90: =AJ194 -> 0 | AK90: =SUM(AG90:AJ90) -> 0 | AL90: =AL194 -> 0 | AM90: =AM194 -> 0 | AN90: =AN194 -> 0 | AO90: =AO194 -> 0 | AP90: =SUM(AL90:AO90) -> 0 | AQ90: =AQ194 -> 0 | AR90: =AR194 -> 0 | AS90: =AS194 -> 0 | AT90: =AT194 -> 0 | AU90: =SUM(AQ90:AT90) -> 0
C92: Debt Drawdown | M92: =SUM(M93:M95) -> 2.6603553 | N92: =SUM(N93:N95) -> 2.6603553 | O92: =SUM(O93:O95) -> 2.6603553 | P92: =SUM(P93:P95) -> 2.6603553 | Q92: =SUM(Q93:Q95) -> 10.641421 | R92: =SUM(R93:R95) -> 6.1255297 | S92: =SUM(S93:S95) -> 6.1255297 | T92: =SUM(T93:T95) -> 6.1255297 | ... AU92: =SUM(AU93:AU95) -> 0
C93: =$C$59 -> TLA | M93: =M126 -> 0 | N93: =N126 -> 0 | O93: =O126 -> 0 | P93: =P126 -> 0 | Q93: =Q126 -> 0 | R93: =R126 -> 0 | S93: =S126 -> 0 | T93: =T126 -> 0 | ... AU93: =AU126 -> 0
C94: =$C$60 -> TLB | M94: =M143 -> 0 | N94: =N143 -> 0 | O94: =O143 -> 0 | P94: =P143 -> 0 | Q94: =Q143 -> 0 | R94: =R143 -> 0 | S94: =S143 -> 0 | T94: =T143 -> 0 | ... AU94: =AU143 -> 0
C95: =$C$61 -> CAF | M95: =M169 -> 2.6603553 | N95: =N169 -> 2.6603553 | O95: =O169 -> 2.6603553 | P95: =P169 -> 2.6603553 | Q95: =Q169 -> 10.641421 | R95: =R169 -> 6.1255297 | S95: =S169 -> 6.1255297 | T95: =T169 -> 6.1255297 | ... AU95: =AU169 -> 0
C97: Net Cash Flow | M97: =M78+M80+M86+M92 -> 7.1725498 | N97: =N78+N80+N86+N92 -> 7.1459462 | O97: =O78+O80+O86+O92 -> 7.1193427 | P97: =P78+P80+P86+P92 -> 7.0927391 | Q97: =Q78+Q80+Q86+Q92 -> 28.530578 | R97: =R78+R80+R86+R92 -> 8.4683455 | S97: =S78+S80+S86+S92 -> 8.4070902 | T97: =T78+T80+T86+T92 -> 8.3458349 | ... AU97: =AU78+AU80+AU86+AU92 -> -252.08198
C99: Opening Cash | M99: =L102 -> 0 | N99: =M102 -> 7.1725498 | O99: =N102 -> 14.318496 | P99: =O102 -> 21.437839 | Q99: =L102 -> 0 | R99: =Q102 -> 28.530578 | S99: =R102 -> 36.998923 | T99: =S102 -> 45.406014 | U99: =T102 -> 53.751848 | V99: =Q102 -> 28.530578 | W99: =V102 -> 62.036428 | X99: =W102 -> 68.526203 | Y99: =X102 -> 74.984601 | Z99: =Y102 -> 81.411623 | AA99: =V102 -> 62.036428 | AB99: =AA102 -> 87.807268 | AC99: =AB102 -> 68.355451 | AD99: =AC102 -> 48.903634 | AE99: =AD102 -> 29.451817 | AF99: =AA102 -> 87.807268 | AG99: =AF102 -> 10 | AH99: =AG102 -> 16.882902 | AI99: =AH102 -> 23.765804 | AJ99: =AI102 -> 30.648707 | AK99: =AF102 -> 10 | AL99: =AK102 -> 37.531609 | AM99: =AL102 -> 45.00914 | AN99: =AM102 -> 52.486672 | AO99: =AN102 -> 59.964204 | AP99: =AK102 -> 37.531609 | AQ99: =AP102 -> 67.441735 | AR99: =AQ102 -> 79.954376 | AS99: =AR102 -> 92.467017 | AT99: =AS102 -> 104.97966 | AU99: =AP102 -> 67.441735
C100: Net Cash Flow | M100: =M97 -> 7.1725498 | N100: =N97 -> 7.1459462 | O100: =O97 -> 7.1193427 | P100: =P97 -> 7.0927391 | Q100: =SUM(M100:P100) -> 28.530578 | R100: =R97 -> 8.4683455 | S100: =S97 -> 8.4070902 | T100: =T97 -> 8.3458349 | U100: =U97 -> 8.2845796 | V100: =SUM(R100:U100) -> 33.50585 | W100: =W97 -> 10.432484 | X100: =X97 -> 10.401108 | Y100: =Y97 -> 10.369732 | Z100: =Z97 -> 10.338356 | AA100: =SUM(W100:Z100) -> 41.54168 | AB100: =AB97 -> 8.3823008 | AC100: =AC97 -> 8.3823008 | AD100: =AD97 -> 8.3823008 | AE100: =AE97 -> 8.3823008 | AF100: =SUM(AB100:AE100) -> 33.529203 | AG100: =AG97 -> 11.265804 | AH100: =AH97 -> 11.265804 | AI100: =AI97 -> 11.265804 | AJ100: =AJ97 -> 11.265804 | AK100: =SUM(AG100:AJ100) -> 45.063218 | AL100: =AL97 -> 12.455063 | AM100: =AM97 -> 12.455063 | AN100: =AN97 -> 12.455063 | AO100: =AO97 -> 12.455063 | AP100: =SUM(AL100:AO100) -> 49.820253 | AQ100: =AQ97 -> 12.512641 | AR100: =AR97 -> 12.512641 | AS100: =AS97 -> 12.512641 | AT100: =AT97 -> -289.6199 | AU100: =SUM(AQ100:AT100) -> -252.08198
C101: Dividends to JDM | M101: =+M44*$Q101 -> 0 | N101: =+N44*$Q101 -> 0 | O101: =+O44*$Q101 -> 0 | P101: =+P44*$Q101 -> 0 | Q101: =-'Active Case'!G65 -> 0 | R101: =+R44*$V101 -> 0 | S101: =+S44*$V101 -> 0 | T101: =+T44*$V101 -> 0 | U101: =+U44*$V101 -> 0 | V101: =-'Active Case'!H65 -> 0 | W101: =+W44*$AA101 -> -3.94271 | X101: =+X44*$AA101 -> -3.94271 | Y101: =+Y44*$AA101 -> -3.94271 | Z101: =+Z44*$AA101 -> -3.94271 | AA101: =-'Active Case'!I65 -> -15.77084 | AB101: =+AB44*$AF101 -> -27.834118 | AC101: =+AC44*$AF101 -> -27.834118 | AD101: =+AD44*$AF101 -> -27.834118 | AE101: =+AE44*$AF101 -> -27.834118 | AF101: =-'Active Case'!J65 -> -111.33647 | AG101: =+AG44*$AK101 -> -4.3829022 | AH101: =+AH44*$AK101 -> -4.3829022 | AI101: =+AI44*$AK101 -> -4.3829022 | AJ101: =+AJ44*$AK101 -> -4.3829022 | AK101: =-'Active Case'!K65 -> -17.531609 | AL101: =+AL44*$AP101 -> -4.9775317 | AM101: =+AM44*$AP101 -> -4.9775317 | AN101: =+AN44*$AP101 -> -4.9775317 | AO101: =+AO44*$AP101 -> -4.9775317 | AP101: =-'Active Case'!L65 -> -19.910127 | AQ101: =+AQ44*$AU101 -> 0 | AR101: =+AR44*$AU101 -> 0 | AS101: =+AS44*$AU101 -> 0 | AT101: =+AT44*$AU101 -> 0 | AU101: =-'Active Case'!M65 -> 0
C102: Closing cash balance | K102: =-'Debt Structure'!D26 -> 0 | L102: =+'Debt Structure'!D26 -> 0 | M102: =SUM(M99:M100,M101) -> 7.1725498 | N102: =SUM(N99:N100,N101) -> 14.318496 | O102: =SUM(O99:O100,O101) -> 21.437839 | P102: =SUM(P99:P100,P101) -> 28.530578 | Q102: =SUM(Q99:Q100,Q101) -> 28.530578 | R102: =SUM(R99:R100,R101) -> 36.998923 | S102: =SUM(S99:S100,S101) -> 45.406014 | T102: =SUM(T99:T100,T101) -> 53.751848 | ... AU102: =SUM(AU99:AU100,AU101) -> -184.64024
C104: Summary Debt Schedule
H106: Q1 | I106: Q2 | J106: Q3 | K106: Closing | L106: FY | M106: Q1 | N106: Q2 | O106: Q3 | P106: Q4 | Q106: FY | R106: Q1 | S106: Q2 | T106: Q3 | U106: Q4 | V106: FY | W106: Q1 | X106: Q2 | Y106: Q3 | Z106: Q4 | AA106: FY | AB106: Q1 | AC106: Q2 | AD106: Q3 | AE106: Q4 | AF106: FY | AG106: Q1 | AH106: Q2 | AI106: Q3 | AJ106: Q4 | AK106: FY | AL106: Q1 | AM106: Q2 | AN106: Q3 | AO106: Q4 | AP106: FY | AQ106: Q1 | AR106: Q2 | AS106: Q3 | AT106: Q4 | AU106: FY
H107: 45747 | I107: 45838 | J107: 45930 | K107: 46022 | L107: =K107 -> 46022 | M107: =EOMONTH(L107,3) -> 46112 | N107: =EOMONTH(M107,3) -> 46203 | O107: =EOMONTH(N107,3) -> 46295 | P107: =EOMONTH(O107,3) -> 46387 | Q107: =P107 -> 46387 | R107: =EOMONTH(Q107,3) -> 46477 | S107: =EOMONTH(R107,3) -> 46568 | T107: =EOMONTH(S107,3) -> 46660 | U107: =EOMONTH(T107,3) -> 46752 | V107: =U107 -> 46752 | W107: =EOMONTH(V107,3) -> 46843 | X107: =EOMONTH(W107,3) -> 46934 | Y107: =EOMONTH(X107,3) -> 47026 | Z107: =EOMONTH(Y107,3) -> 47118 | AA107: =Z107 -> 47118 | AB107: =EOMONTH(AA107,3) -> 47208 | AC107: =EOMONTH(AB107,3) -> 47299 | AD107: =EOMONTH(AC107,3) -> 47391 | AE107: =EOMONTH(AD107,3) -> 47483 | AF107: =AE107 -> 47483 | AG107: =EOMONTH(AF107,3) -> 47573 | AH107: =EOMONTH(AG107,3) -> 47664 | AI107: =EOMONTH(AH107,3) -> 47756 | AJ107: =EOMONTH(AI107,3) -> 47848 | AK107: =AJ107 -> 47848 | AL107: =EOMONTH(AK107,3) -> 47938 | AM107: =EOMONTH(AL107,3) -> 48029 | AN107: =EOMONTH(AM107,3) -> 48121 | AO107: =EOMONTH(AN107,3) -> 48213 | AP107: =AO107 -> 48213 | AQ107: =EOMONTH(AP107,3) -> 48304 | AR107: =EOMONTH(AQ107,3) -> 48395 | AS107: =EOMONTH(AR107,3) -> 48487 | AT107: =EOMONTH(AS107,3) -> 48579 | AU107: =AT107 -> 48579
C109: Total Debt | L109: =SUM(L110:L113) -> 256.5 | M109: =SUM(M110:M113) -> 259.16036 | N109: =SUM(N110:N113) -> 261.82071 | O109: =SUM(O110:O113) -> 264.48107 | P109: =SUM(P110:P113) -> 267.14142 | Q109: =SUM(Q110:Q113) -> 267.14142 | R109: =SUM(R110:R113) -> 273.26695 | S109: =SUM(S110:S113) -> 279.39248 | ... AU109: =SUM(AU110:AU113) -> 0
C110: =$C$59 -> TLA | L110: =L127 -> 0 | M110: =M127 -> 0 | N110: =N127 -> 0 | O110: =O127 -> 0 | P110: =P127 -> 0 | Q110: =Q127 -> 0 | R110: =R127 -> 0 | S110: =S127 -> 0 | ... AU110: =AU127 -> 0
C111: =$C$60 -> TLB | L111: =L144 -> 256.5 | M111: =M144 -> 256.5 | N111: =N144 -> 256.5 | O111: =O144 -> 256.5 | P111: =P144 -> 256.5 | Q111: =Q144 -> 256.5 | R111: =R144 -> 256.5 | S111: =S144 -> 256.5 | ... AU111: =AU144 -> 0
C112: =$C$61 -> CAF | L112: =L170 -> 0 | M112: =M170 -> 2.6603553 | N112: =N170 -> 5.3207105 | O112: =O170 -> 7.9810658 | P112: =P170 -> 10.641421 | Q112: =Q170 -> 10.641421 | R112: =R170 -> 16.766951 | S112: =S170 -> 22.89248 | ... AU112: =AU170 -> 0
C113: =$C$62 -> RCF | L113: =L195 -> 0 | M113: =M195 -> 0 | N113: =N195 -> 0 | O113: =O195 -> 0 | P113: =P195 -> 0 | Q113: =Q195 -> 0 | R113: =R195 -> 0 | S113: =S195 -> 0 | ... AU113: =AU195 -> 0
C115: Cash | L115: =L102 -> 0 | M115: =M102 -> 7.1725498 | N115: =N102 -> 14.318496 | O115: =O102 -> 21.437839 | P115: =P102 -> 28.530578 | Q115: =Q102 -> 28.530578 | R115: =R102 -> 36.998923 | S115: =S102 -> 45.406014 | ... AU115: =AU102 -> -184.64024
C116: Net Total Debt | L116: =SUM(L110:L113)-L115 -> 256.5 | M116: =SUM(M110:M113)-M115 -> 251.98781 | N116: =SUM(N110:N113)-N115 -> 247.50221 | O116: =SUM(O110:O113)-O115 -> 243.04323 | P116: =SUM(P110:P113)-P115 -> 238.61084 | Q116: =SUM(Q110:Q113)-Q115 -> 238.61084 | R116: =SUM(R110:R113)-R115 -> 236.26803 | S116: =SUM(S110:S113)-S115 -> 233.98647 | ... AU116: =SUM(AU110:AU113)-AU115 -> 184.64024
C118: =C110 -> TLA
H120: Q1 | I120: Q2 | J120: Q3 | K120: Closing | L120: FY | M120: Q1 | N120: Q2 | O120: Q3 | P120: Q4 | Q120: FY | R120: Q1 | S120: Q2 | T120: Q3 | U120: Q4 | V120: FY | W120: Q1 | X120: Q2 | Y120: Q3 | Z120: Q4 | AA120: FY | AB120: Q1 | AC120: Q2 | AD120: Q3 | AE120: Q4 | AF120: FY | AG120: Q1 | AH120: Q2 | AI120: Q3 | AJ120: Q4 | AK120: FY | AL120: Q1 | AM120: Q2 | AN120: Q3 | AO120: Q4 | AP120: FY | AQ120: Q1 | AR120: Q2 | AS120: Q3 | AT120: Q4 | AU120: FY
H121: 45747 | I121: 45838 | J121: 45930 | K121: 46022 | L121: =K121 -> 46022 | M121: =EOMONTH(L121,3) -> 46112 | N121: =EOMONTH(M121,3) -> 46203 | O121: =EOMONTH(N121,3) -> 46295 | P121: =EOMONTH(O121,3) -> 46387 | Q121: =P121 -> 46387 | R121: =EOMONTH(Q121,3) -> 46477 | S121: =EOMONTH(R121,3) -> 46568 | T121: =EOMONTH(S121,3) -> 46660 | U121: =EOMONTH(T121,3) -> 46752 | V121: =U121 -> 46752 | W121: =EOMONTH(V121,3) -> 46843 | X121: =EOMONTH(W121,3) -> 46934 | Y121: =EOMONTH(X121,3) -> 47026 | Z121: =EOMONTH(Y121,3) -> 47118 | AA121: =Z121 -> 47118 | AB121: =EOMONTH(AA121,3) -> 47208 | AC121: =EOMONTH(AB121,3) -> 47299 | AD121: =EOMONTH(AC121,3) -> 47391 | AE121: =EOMONTH(AD121,3) -> 47483 | AF121: =AE121 -> 47483 | AG121: =EOMONTH(AF121,3) -> 47573 | AH121: =EOMONTH(AG121,3) -> 47664 | AI121: =EOMONTH(AH121,3) -> 47756 | AJ121: =EOMONTH(AI121,3) -> 47848 | AK121: =AJ121 -> 47848 | AL121: =EOMONTH(AK121,3) -> 47938 | AM121: =EOMONTH(AL121,3) -> 48029 | AN121: =EOMONTH(AM121,3) -> 48121 | AO121: =EOMONTH(AN121,3) -> 48213 | AP121: =AO121 -> 48213 | AQ121: =EOMONTH(AP121,3) -> 48304 | AR121: =EOMONTH(AQ121,3) -> 48395 | AS121: =EOMONTH(AR121,3) -> 48487 | AT121: =EOMONTH(AS121,3) -> 48579 | AU121: =AT121 -> 48579
C123: Repayment Flag | D123: =SUM(E123:AK123) -> 0 | M123: ='Debt Structure'!D65 -> 0 | N123: ='Debt Structure'!D66 -> 0 | O123: ='Debt Structure'!D67 -> 0 | P123: ='Debt Structure'!D68 -> 0 | R123: ='Debt Structure'!D69 -> 0 | S123: ='Debt Structure'!D70 -> 0 | T123: ='Debt Structure'!D71 -> 0 | U123: ='Debt Structure'!D72 -> 0 | W123: ='Debt Structure'!D73 -> 0 | X123: ='Debt Structure'!D74 -> 0 | Y123: ='Debt Structure'!D75 -> 0 | Z123: ='Debt Structure'!D76 -> 0 | AB123: ='Debt Structure'!D77 -> 0 | AC123: ='Debt Structure'!D78 -> 0 | AD123: ='Debt Structure'!D79 -> 0 | AE123: ='Debt Structure'!D80 -> 0 | AG123: ='Debt Structure'!D81 -> 0 | AH123: ='Debt Structure'!D82 -> 0 | AI123: ='Debt Structure'!D83 -> 0 | AJ123: ='Debt Structure'!D84 -> 0 | AL123: =+'Debt Structure'!D85 -> 0 | AM123: =+'Debt Structure'!D86 -> 0 | AN123: =+'Debt Structure'!D87 -> 0 | AO123: =+'Debt Structure'!D88 -> 0 | AQ123: =+'Debt Structure'!D89 -> 0 | AR123: =+'Debt Structure'!D90 -> 0 | AS123: =+'Debt Structure'!D91 -> 0 | AT123: =+'Debt Structure'!D92 -> 0
C124: Opening Debt Balance | M124: =L127 -> 0 | N124: =M127 -> 0 | O124: =N127 -> 0 | P124: =O127 -> 0 | Q124: =L127 -> 0 | R124: =Q127 -> 0 | S124: =R127 -> 0 | T124: =S127 -> 0 | U124: =T127 -> 0 | V124: =Q127 -> 0 | W124: =V127 -> 0 | X124: =W127 -> 0 | Y124: =X127 -> 0 | Z124: =Y127 -> 0 | AA124: =V127 -> 0 | AB124: =AA127 -> 0 | AC124: =AB127 -> 0 | AD124: =AC127 -> 0 | AE124: =AD127 -> 0 | AF124: =AA127 -> 0 | AG124: =AF127 -> 0 | AH124: =AG127 -> 0 | AI124: =AH127 -> 0 | AJ124: =AI127 -> 0 | AK124: =AF127 -> 0 | AL124: =AK127 -> 0 | AM124: =AL127 -> 0 | AN124: =AM127 -> 0 | AO124: =AN127 -> 0 | AP124: =AK127 -> 0 | AQ124: =AP127 -> 0 | AR124: =AQ127 -> 0 | AS124: =AR127 -> 0 | AT124: =AS127 -> 0 | AU124: =AP127 -> 0
C125: Contractual Amortisation | M125: =-M123*$D$126 -> 0 | N125: =-N123*$D$126 -> 0 | O125: =-O123*$D$126 -> 0 | P125: =-P123*$D$126 -> 0 | Q125: =SUM(M125:P125) -> 0 | R125: =-R123*$D$126 -> 0 | S125: =-S123*$D$126 -> 0 | T125: =-T123*$D$126 -> 0 | U125: =-U123*$D$126 -> 0 | V125: =SUM(R125:U125) -> 0 | W125: =-W123*$D$126 -> 0 | X125: =-X123*$D$126 -> 0 | Y125: =-Y123*$D$126 -> 0 | Z125: =-Z123*$D$126 -> 0 | AA125: =SUM(W125:Z125) -> 0 | AB125: =-AB123*$D$126 -> 0 | AC125: =-AC123*$D$126 -> 0 | AD125: =-AD123*$D$126 -> 0 | AE125: =-AE123*$D$126 -> 0 | AF125: =SUM(AB125:AE125) -> 0 | AG125: =-AG123*$D$126 -> 0 | AH125: =-AH123*$D$126 -> 0 | AI125: =-AI123*$D$126 -> 0 | AJ125: =-AJ123*$D$126 -> 0 | AK125: =SUM(AG125:AJ125) -> 0 | AL125: =-AL123*$D$126 -> 0 | AM125: =-AM123*$D$126 -> 0 | AN125: =-AN123*$D$126 -> 0 | AO125: =-AO123*$D$126 -> 0 | AP125: =SUM(AL125:AO125) -> 0 | AQ125: =-AQ123*$D$126 -> 0 | AR125: =-AR123*$D$126 -> 0 | AS125: =-AS123*$D$126 -> 0 | AT125: =-AT123*$D$126 -> 0 | AU125: =SUM(AQ125:AT125) -> 0
C126: Drawdown | D126: ='Debt Structure'!D12 -> 0 | L126: =D126 -> 0 | Q126: =SUM(M126:P126) -> 0 | V126: =SUM(R126:U126) -> 0 | AA126: =SUM(W126:Z126) -> 0 | AF126: =SUM(AB126:AE126) -> 0 | AK126: =SUM(AG126:AJ126) -> 0 | AP126: =SUM(AL126:AO126) -> 0 | AU126: =SUM(AQ126:AT126) -> 0
C127: Closing Debt Balance | L127: =L124+L125+L126 -> 0 | M127: =M124+M125+M126 -> 0 | N127: =N124+N125+N126 -> 0 | O127: =O124+O125+O126 -> 0 | P127: =P124+P125+P126 -> 0 | Q127: =Q124+Q125+Q126 -> 0 | R127: =R124+R125+R126 -> 0 | S127: =S124+S125+S126 -> 0 | ... AU127: =AU124+AU125+AU126 -> 0
C129: Interest Expense | M129: =(-M131*AVERAGE(M124,M127)) -> 0 | N129: =(-N131*AVERAGE(N124,N127)) -> 0 | O129: =(-O131*AVERAGE(O124,O127)) -> 0 | P129: =(-P131*AVERAGE(P124,P127)) -> 0 | Q129: =SUM(M129:P129) -> 0 | R129: =(-R131*AVERAGE(R124,R127)) -> 0 | S129: =(-S131*AVERAGE(S124,S127)) -> 0 | T129: =(-T131*AVERAGE(T124,T127)) -> 0 | U129: =(-U131*AVERAGE(U124,U127)) -> 0 | V129: =SUM(R129:U129) -> 0 | W129: =(-W131*AVERAGE(W124,W127)) -> 0 | X129: =(-X131*AVERAGE(X124,X127)) -> 0 | Y129: =(-Y131*AVERAGE(Y124,Y127)) -> 0 | Z129: =(-Z131*AVERAGE(Z124,Z127)) -> 0 | AA129: =SUM(W129:Z129) -> 0 | AB129: =(-AB131*AVERAGE(AB124,AB127)) -> 0 | AC129: =(-AC131*AVERAGE(AC124,AC127)) -> 0 | AD129: =(-AD131*AVERAGE(AD124,AD127)) -> 0 | AE129: =(-AE131*AVERAGE(AE124,AE127)) -> 0 | AF129: =SUM(AB129:AE129) -> 0 | AG129: =(-AG131*AVERAGE(AG124,AG127)) -> 0 | AH129: =(-AH131*AVERAGE(AH124,AH127)) -> 0 | AI129: =(-AI131*AVERAGE(AI124,AI127)) -> 0 | AJ129: =(-AJ131*AVERAGE(AJ124,AJ127)) -> 0 | AK129: =SUM(AG129:AJ129) -> 0 | AL129: =(-AL131*AVERAGE(AL124,AL127)) -> 0 | AM129: =(-AM131*AVERAGE(AM124,AM127)) -> 0 | AN129: =(-AN131*AVERAGE(AN124,AN127)) -> 0 | AO129: =(-AO131*AVERAGE(AO124,AO127)) -> 0 | AP129: =SUM(AL129:AO129) -> 0 | AQ129: =(-AQ131*AVERAGE(AQ124,AQ127)) -> 0 | AR129: =(-AR131*AVERAGE(AR124,AR127)) -> 0 | AS129: =(-AS131*AVERAGE(AS124,AS127)) -> 0 | AT129: =(-AT131*AVERAGE(AT124,AT127)) -> 0 | AU129: =SUM(AQ129:AT129) -> 0
C131: All-In-Margin | M131: =M132+M133 -> 0.005 | N131: =N132+N133 -> 0.005 | O131: =O132+O133 -> 0.005 | P131: =P132+P133 -> 0.005 | Q131: =SUM(M131:P131) -> 0.02 | R131: =R132+R133 -> 0.005 | S131: =S132+S133 -> 0.005 | T131: =T132+T133 -> 0.005 | U131: =U132+U133 -> 0.005 | V131: =SUM(R131:U131) -> 0.02 | W131: =W132+W133 -> 0.005 | X131: =X132+X133 -> 0.005 | Y131: =Y132+Y133 -> 0.005 | Z131: =Z132+Z133 -> 0.005 | AA131: =SUM(W131:Z131) -> 0.02 | AB131: =AB132+AB133 -> 0.005 | AC131: =AC132+AC133 -> 0.005 | AD131: =AD132+AD133 -> 0.005 | AE131: =AE132+AE133 -> 0.005 | AF131: =SUM(AB131:AE131) -> 0.02 | AG131: =AG132+AG133 -> 0.005 | AH131: =AH132+AH133 -> 0.005 | AI131: =AI132+AI133 -> 0.005 | AJ131: =AJ132+AJ133 -> 0.005 | AK131: =SUM(AG131:AJ131) -> 0.02 | AL131: =AL132+AL133 -> 0.005 | AM131: =AM132+AM133 -> 0.005 | AN131: =AN132+AN133 -> 0.005 | AO131: =AO132+AO133 -> 0.005 | AP131: =SUM(AL131:AO131) -> 0.02 | AQ131: =AQ132+AQ133 -> 0.005 | AR131: =AR132+AR133 -> 0.005 | AS131: =AS132+AS133 -> 0.005 | AT131: =AT132+AT133 -> 0.005 | AU131: =SUM(AQ131:AT131) -> 0.02
C132: Margin | D132: ='Debt Structure'!F22 -> 0 | M132: =$D$132/4 -> 0 | N132: =$D$132/4 -> 0 | O132: =$D$132/4 -> 0 | P132: =$D$132/4 -> 0 | Q132: =SUM(M132:P132) -> 0 | R132: =$D$132/4 -> 0 | S132: =$D$132/4 -> 0 | T132: =$D$132/4 -> 0 | U132: =$D$132/4 -> 0 | V132: =SUM(R132:U132) -> 0 | W132: =$D$132/4 -> 0 | X132: =$D$132/4 -> 0 | Y132: =$D$132/4 -> 0 | Z132: =$D$132/4 -> 0 | AA132: =SUM(W132:Z132) -> 0 | AB132: =$D$132/4 -> 0 | AC132: =$D$132/4 -> 0 | AD132: =$D$132/4 -> 0 | AE132: =$D$132/4 -> 0 | AF132: =SUM(AB132:AE132) -> 0 | AG132: =$D$132/4 -> 0 | AH132: =$D$132/4 -> 0 | AI132: =$D$132/4 -> 0 | AJ132: =$D$132/4 -> 0 | AK132: =SUM(AG132:AJ132) -> 0 | AL132: =$D$132/4 -> 0 | AM132: =$D$132/4 -> 0 | AN132: =$D$132/4 -> 0 | AO132: =$D$132/4 -> 0 | AP132: =SUM(AL132:AO132) -> 0 | AQ132: =$D$132/4 -> 0 | AR132: =$D$132/4 -> 0 | AS132: =$D$132/4 -> 0 | AT132: =$D$132/4 -> 0 | AU132: =SUM(AQ132:AT132) -> 0
C133: Euribor Fwd | M133: {=TRANSPOSE('Debt Structure'!I65:I68)} -> 0.005 | N133: 0.005 | O133: 0.005 | P133: 0.005 | Q133: =SUM(M133:P133) -> 0.02 | R133: {=TRANSPOSE('Debt Structure'!I69:I72)} -> 0.005 | S133: 0.005 | T133: 0.005 | U133: 0.005 | V133: =SUM(R133:U133) -> 0.02 | W133: {=TRANSPOSE('Debt Structure'!I73:I76)} -> 0.005 | X133: 0.005 | Y133: 0.005 | Z133: 0.005 | AA133: =SUM(W133:Z133) -> 0.02 | AB133: {=TRANSPOSE('Debt Structure'!I77:I80)} -> 0.005 | AC133: 0.005 | AD133: 0.005 | AE133: 0.005 | AF133: =SUM(AB133:AE133) -> 0.02 | AG133: {=TRANSPOSE('Debt Structure'!I81:I84)} -> 0.005 | AH133: 0.005 | AI133: 0.005 | AJ133: 0.005 | AK133: =SUM(AG133:AJ133) -> 0.02 | AL133: {=+TRANSPOSE('Debt Structure'!$I$85:$I$88)} -> 0.005 | AM133: 0.005 | AN133: 0.005 | AO133: 0.005 | AP133: =SUM(AL133:AO133) -> 0.02 | AQ133: {=+TRANSPOSE('Debt Structure'!$I$89:$I$92)} -> 0.005 | AR133: 0.005 | AS133: 0.005 | AT133: 0.005 | AU133: =SUM(AQ133:AT133) -> 0.02
C135: =C111 -> TLB
H137: Q1 | I137: Q2 | J137: Q3 | K137: Closing | L137: FY | M137: Q1 | N137: Q2 | O137: Q3 | P137: Q4 | Q137: FY | R137: Q1 | S137: Q2 | T137: Q3 | U137: Q4 | V137: FY | W137: Q1 | X137: Q2 | Y137: Q3 | Z137: Q4 | AA137: FY | AB137: Q1 | AC137: Q2 | AD137: Q3 | AE137: Q4 | AF137: FY | AG137: Q1 | AH137: Q2 | AI137: Q3 | AJ137: Q4 | AK137: FY | AL137: Q1 | AM137: Q2 | AN137: Q3 | AO137: Q4 | AP137: FY | AQ137: Q1 | AR137: Q2 | AS137: Q3 | AT137: Q4 | AU137: FY
H138: 45747 | I138: 45838 | J138: 45930 | K138: 46022 | L138: =K138 -> 46022 | M138: =EOMONTH(L138,3) -> 46112 | N138: =EOMONTH(M138,3) -> 46203 | O138: =EOMONTH(N138,3) -> 46295 | P138: =EOMONTH(O138,3) -> 46387 | Q138: =P138 -> 46387 | R138: =EOMONTH(Q138,3) -> 46477 | S138: =EOMONTH(R138,3) -> 46568 | T138: =EOMONTH(S138,3) -> 46660 | U138: =EOMONTH(T138,3) -> 46752 | V138: =U138 -> 46752 | W138: =EOMONTH(V138,3) -> 46843 | X138: =EOMONTH(W138,3) -> 46934 | Y138: =EOMONTH(X138,3) -> 47026 | Z138: =EOMONTH(Y138,3) -> 47118 | AA138: =Z138 -> 47118 | AB138: =EOMONTH(AA138,3) -> 47208 | AC138: =EOMONTH(AB138,3) -> 47299 | AD138: =EOMONTH(AC138,3) -> 47391 | AE138: =EOMONTH(AD138,3) -> 47483 | AF138: =AE138 -> 47483 | AG138: =EOMONTH(AF138,3) -> 47573 | AH138: =EOMONTH(AG138,3) -> 47664 | AI138: =EOMONTH(AH138,3) -> 47756 | AJ138: =EOMONTH(AI138,3) -> 47848 | AK138: =AJ138 -> 47848 | AL138: =EOMONTH(AK138,3) -> 47938 | AM138: =EOMONTH(AL138,3) -> 48029 | AN138: =EOMONTH(AM138,3) -> 48121 | AO138: =EOMONTH(AN138,3) -> 48213 | AP138: =AO138 -> 48213 | AQ138: =EOMONTH(AP138,3) -> 48304 | AR138: =EOMONTH(AQ138,3) -> 48395 | AS138: =EOMONTH(AR138,3) -> 48487 | AT138: =EOMONTH(AS138,3) -> 48579 | AU138: =AT138 -> 48579
C140: Repayment Flag | D140: 1 | E140: =+'Debt Structure'!G23 -> 48579 | M140: =+N(M138=$E140)*$D140 -> 0 | N140: =+N(N138=$E140)*$D140 -> 0 | O140: =+N(O138=$E140)*$D140 -> 0 | P140: =+N(P138=$E140)*$D140 -> 0 | R140: =+N(R138=$E140)*$D140 -> 0 | S140: =+N(S138=$E140)*$D140 -> 0 | T140: =+N(T138=$E140)*$D140 -> 0 | U140: =+N(U138=$E140)*$D140 -> 0 | W140: =+N(W138=$E140)*$D140 -> 0 | X140: =+N(X138=$E140)*$D140 -> 0 | Y140: =+N(Y138=$E140)*$D140 -> 0 | Z140: =+N(Z138=$E140)*$D140 -> 0 | AB140: =+N(AB138=$E140)*$D140 -> 0 | AC140: =+N(AC138=$E140)*$D140 -> 0 | AD140: =+N(AD138=$E140)*$D140 -> 0 | AE140: =+N(AE138=$E140)*$D140 -> 0 | AG140: =+N(AG138=$E140)*$D140 -> 0 | AH140: =+N(AH138=$E140)*$D140 -> 0 | AI140: =+N(AI138=$E140)*$D140 -> 0 | AJ140: =+N(AJ138=$E140)*$D140 -> 0 | AL140: =+N(AL138=$E140)*$D140 -> 0 | AM140: =+N(AM138=$E140)*$D140 -> 0 | AN140: =+N(AN138=$E140)*$D140 -> 0 | AO140: =+N(AO138=$E140)*$D140 -> 0 | AQ140: =+N(AQ138=$E140)*$D140 -> 0 | AR140: =+N(AR138=$E140)*$D140 -> 0 | AS140: =+N(AS138=$E140)*$D140 -> 0 | AT140: =+N(AT138=$E140)*$D140 -> 1
C141: Opening Debt Balance | M141: =L144 -> 256.5 | N141: =M144 -> 256.5 | O141: =N144 -> 256.5 | P141: =O144 -> 256.5 | Q141: =L144 -> 256.5 | R141: =Q144 -> 256.5 | S141: =R144 -> 256.5 | T141: =S144 -> 256.5 | U141: =T144 -> 256.5 | V141: =Q144 -> 256.5 | W141: =V144 -> 256.5 | X141: =W144 -> 256.5 | Y141: =X144 -> 256.5 | Z141: =Y144 -> 256.5 | AA141: =V144 -> 256.5 | AB141: =AA144 -> 256.5 | AC141: =AB144 -> 256.5 | AD141: =AC144 -> 256.5 | AE141: =AD144 -> 256.5 | AF141: =AA144 -> 256.5 | AG141: =AF144 -> 256.5 | AH141: =AG144 -> 256.5 | AI141: =AH144 -> 256.5 | AJ141: =AI144 -> 256.5 | AK141: =AF144 -> 256.5 | AL141: =AK144 -> 256.5 | AM141: =AL144 -> 256.5 | AN141: =AM144 -> 256.5 | AO141: =AN144 -> 256.5 | AP141: =AK144 -> 256.5 | AQ141: =AP144 -> 256.5 | AR141: =AQ144 -> 256.5 | AS141: =AR144 -> 256.5 | AT141: =AS144 -> 256.5 | AU141: =AP144 -> 256.5
C142: Contractual Amortisation | M142: =-M140*$D$143 -> 0 | N142: =-N140*$D$143 -> 0 | O142: =-O140*$D$143 -> 0 | P142: =-P140*$D$143 -> 0 | Q142: =SUM(M142:P142) -> 0 | R142: =-R140*$D$143 -> 0 | S142: =-S140*$D$143 -> 0 | T142: =-T140*$D$143 -> 0 | U142: =-U140*$D$143 -> 0 | V142: =SUM(R142:U142) -> 0 | W142: =-W140*$D$143 -> 0 | X142: =-X140*$D$143 -> 0 | Y142: =-Y140*$D$143 -> 0 | Z142: =-Z140*$D$143 -> 0 | AA142: =SUM(W142:Z142) -> 0 | AB142: =-AB140*$D$143 -> 0 | AC142: =-AC140*$D$143 -> 0 | AD142: =-AD140*$D$143 -> 0 | AE142: =-AE140*$D$143 -> 0 | AF142: =SUM(AB142:AE142) -> 0 | AG142: =-AG140*$D$143 -> 0 | AH142: =-AH140*$D$143 -> 0 | AI142: =-AI140*$D$143 -> 0 | AJ142: =-AJ140*$D$143 -> 0 | AK142: =SUM(AG142:AJ142) -> 0 | AL142: =-AL140*$D$143 -> 0 | AM142: =-AM140*$D$143 -> 0 | AN142: =-AN140*$D$143 -> 0 | AO142: =-AO140*$D$143 -> 0 | AP142: =SUM(AL142:AO142) -> 0 | AQ142: =-AQ140*$D$143 -> 0 | AR142: =-AR140*$D$143 -> 0 | AS142: =-AS140*$D$143 -> 0 | AT142: =-AT140*$D$143 -> -256.5 | AU142: =SUM(AQ142:AT142) -> -256.5
...

Sheet Debt Structure
C2: =RIGHT(CELL("filename",D1), LEN(CELL("filename", D1))- FIND("]", CELL("filename", D1), 1)) -> Debt Structure | M2: TLB Only
C4: =+'Debt Summary'!D6 -> 46022 | M4: =+C4 -> 46022
C5: ACTIVE SCENARIO | M5: TLB
C7: Adj. normalized EBITDA | D7: =+'Active Case'!F17 -> 51.3 | M7: Adj. normalized EBITDA | N7: =+'Active Case'!F17 -> 51.3
C9: UPFRONT FEES | M9: UPFRONT FEES
D11: Amount | E11: UF Fees | F11: UF Fees (€k) | N11: Amount | O11: UF Fees | P11: UF Fees (€k)
C12: TLA | D12: =+N12 -> 0 | E12: =+O12 -> 0.015 | F12: =+P12 -> 0 | M12: TLA | N12: =N22 -> 0 | O12: 0.015 | P12: =O12*N12 -> 0
C13: TLB | D13: =+N13 -> 256.5 | E13: =+O13 -> 0.015 | F13: =+P13 -> 3.8475 | M13: TLB | N13: =N23 -> 256.5 | O13: 0.015 | P13: =O13*N13 -> 3.8475
C14: CAF | D14: =+N14 -> 50 | E14: =+O14 -> 0.015 | F14: =+P14 -> 0.75 | M14: CAF | N14: =N33 -> 50 | O14: 0.015 | P14: =O14*N14 -> 0.75
C15: RCF | D15: =+N15 -> 20 | E15: =+O15 -> 0.015 | F15: =+P15 -> 0.3 | M15: RCF | N15: =N32 -> 20 | O15: 0.015 | P15: =O15*N15 -> 0.3
C16: TOTAL | D16: =SUM(D12:D15) -> 326.5 | E16: =+O16 -> 0.015 | F16: =SUM(F12:F15) -> 4.8975 | M16: TOTAL | N16: =SUM(N12:N15) -> 326.5 | O16: =+P16/N16 -> 0.015 | P16: =SUM(P12:P15) -> 4.8975
C19: FINAL CAPITAL STRUCTURE | M19: FINAL CAPITAL STRUCTURE
C21: Capital Structure | D21: EURm | E21: xEBITDA | F21: Margin | G21: Maturity | M21: Capital Structure | N21: EURm | O21: xEBITDA | P21: Margin | Q21: Maturity
C22: TLA | D22: =+N22 -> 0 | E22: =+O22 -> 0 | F22: =+P22 -> 0 | G22: =+Q22 -> 46022 | H22: =+R22 -> 0 | M22: TLA | N22: =N7*O22 -> 0 | O22: 0 | P22: 0 | Q22: =+EOMONTH($M$4,R22*12) -> 46022 | R22: 0
C23: TLB | D23: =+N23 -> 256.5 | E23: =+O23 -> 5 | F23: =+P23 -> 0.035 | G23: =+Q23 -> 48579 | H23: =+R23 -> 7 | M23: TLB | N23: =N7*O23 -> 256.5 | O23: 5 | P23: 0.035 | Q23: =+EOMONTH($M$4,R23*12) -> 48579 | R23: 7
C24: Acquisition debt | D24: =SUM(D22:D23) -> 256.5 | E24: =+D24/D$7 -> 5 | M24: Acquisition debt | N24: =SUM(N22:N23) -> 256.5 | O24: =+N24/N$7 -> 5
C26: Cash | D26: =+N26 -> 0 | E26: =+O26 -> 0 | M26: Cash | N26: 0 | O26: =+N26/N$7 -> 0
C27: Total Net Debt | D27: =+D24+D26 -> 256.5 | E27: =+D27/D$7 -> 5 | M27: Total Net Debt | N27: =+N24+N26 -> 256.5 | O27: =+N27/$N7 -> 5
I28: C. Fee | S28: C. Fee
C29: PIK | D29: =+N29 -> 0 | E29: =+O29 -> 0 | M29: PIK | N29: =N7*O29 -> 0 | O29: 0
C30: Total Net Debt | D30: =+D27+D29 -> 256.5 | E30: =+D30/D$7 -> 5 | M30: Total Net Debt | N30: =+N27+N29 -> 256.5 | O30: =+N30/N$7 -> 5
C32: RCF | D32: =+N32 -> 20 | E32: =+O32 -> 0.38986355 | F32: =+P32 -> 0.03 | I32: =+S32 -> 0.01 | M32: RCF | N32: 20 | O32: =+N32/N$7 -> 0.38986355 | P32: 0.03 | S32: 0.01
C33: CAF | D33: =+N33 -> 50 | E33: =+O33 -> 0.97465887 | F33: =+P33 -> 0.03 | H33: =+R33 -> 3 | I33: =+S33 -> 0.01 | M33: CAF | N33: 50 | O33: =+N33/N$7 -> 0.97465887 | P33: 0.03 | R33: 3 | S33: 0.01
C34: Total | D34: =+D27+SUM(D32:D33) -> 326.5 | E34: =+D34/D$7 -> 6.3645224 | M34: Total | N34: =+N27+SUM(N32:N33) -> 326.5 | O34: =+N34/N$7 -> 6.3645224
C37: PERMITTED PAYMENTS/DIVIDENDS MECHANISIM | M37: PERMITTED PAYMENTS/DIVIDENDS MECHANISIM
D39: =+N39 -> Higher than | E39: =+O39 -> Lower than | F39: =+P39 -> % of FCF | N39: Higher than | O39: Lower than | P39: % of FCF
C40: =+M40 -> Range 1 | D40: =+N40 -> 4 | F40: =+P40 -> 0 | M40: Range 1 | N40: 4 | P40: 0
C41: =+M41 -> Range 2 | D41: =+N41 -> 3 | E41: =+O41 -> 4 | F41: =+P41 -> 0.5 | M41: Range 2 | N41: 3 | O41: =+N40 -> 4 | P41: 0.5
C42: =+M42 -> Range 3 | E42: =+O42 -> 3 | F42: =+P42 -> 1 | M42: Range 3 | O42: =+N41 -> 3 | P42: 1
C44: =+M44 -> Min Cash on Balance (€m) | D44: =+N44 -> 10 | M44: Min Cash on Balance (€m) | N44: 10
C47: SOURCES & USES | M47: SOURCES & USES
C49: Sources | D49: €m | F49: Uses | G49: €m | M49: Sources | N49: €m | P49: Uses | Q49: €m
C51: Equity ticket | D51: =+N51 -> 296.4975 | F51: Purchase Price | G51: 540 | M51: Equity ticket | N51: =+N56-SUM(N52:N55) -> 296.4975 | P51: Purchase Price | Q51: =+$G51 -> 540
C52: TLA | D52: =+N52 -> 0 | F52: Structuring fees | G52: =+Q52 -> 4.8975 | M52: TLA | N52: =+N22 -> 0 | P52: Structuring fees | Q52: =+P16 -> 4.8975
C53: TLB | D53: =+N53 -> 256.5 | M53: TLB | N53: =+N23 -> 256.5
C54: Holdco PIK | D54: =+N54 -> 0 | F54: Transaction cost | G54: =+Q54 -> 8.1 | M54: Holdco PIK | N54: =+N29 -> 0 | P54: Transaction cost | Q54: 8.1
C56: Total | D56: =+G56 -> 552.9975 | F56: Total | G56: =+SUM(G51:G55) -> 552.9975 | M56: Total | N56: =+Q56 -> 552.9975 | P56: Total | Q56: =+SUM(Q51:Q55) -> 552.9975
C59: AMORTIZATION PROFILE | M59: AMORTIZATION PROFILE
C61: Swap Rate (annual %) | D61: 0.02
C63: =C22 -> TLA | D63: % | F63: =C23 -> TLB | G63: % | I63: Euribor fwd | M63: =M22 -> TLA | N63: % | P63: =M23 -> TLB | Q63: %
D64: =+SUM(D65:D84) -> 0 | G64: =+SUM(G65:G84) -> 0 | N64: =+SUM(N65:N92) -> 0 | Q64: =+SUM(Q65:Q92) -> 1
B65: 3 | C65: =+M65 -> 46752 | D65: =+N65 -> 0 | F65: =+P65 -> 46752 | G65: =+Q65 -> 0 | I65: =+$D$61/4 -> 0.005 | M65: =Model!U36 -> 46752 | N65: 0 | P65: =Model!U36 -> 46752 | Q65: 0
B66: =B65+3 -> 6 | C66: =+M66 -> 46843 | D66: =+N66 -> 0 | F66: =+P66 -> 46843 | G66: =+Q66 -> 0 | I66: =+$D$61/4 -> 0.005 | M66: =EOMONTH(M65,3) -> 46843 | N66: 0 | P66: =EOMONTH(P65,3) -> 46843 | Q66: 0
B67: =B66+3 -> 9 | C67: =+M67 -> 46934 | D67: =+N67 -> 0 | F67: =+P67 -> 46934 | G67: =+Q67 -> 0 | I67: =+$D$61/4 -> 0.005 | M67: =EOMONTH(M66,3) -> 46934 | N67: 0 | P67: =EOMONTH(P66,3) -> 46934 | Q67: 0
B68: =B67+3 -> 12 | C68: =+M68 -> 47026 | D68: =+N68 -> 0 | F68: =+P68 -> 47026 | G68: =+Q68 -> 0 | I68: =+$D$61/4 -> 0.005 | M68: =EOMONTH(M67,3) -> 47026 | N68: 0 | P68: =EOMONTH(P67,3) -> 47026 | Q68: 0
B69: =B68+3 -> 15 | C69: =+M69 -> 47118 | D69: =+N69 -> 0 | F69: =+P69 -> 47118 | G69: =+Q69 -> 0 | I69: =+$D$61/4 -> 0.005 | M69: =EOMONTH(M68,3) -> 47118 | N69: 0 | P69: =EOMONTH(P68,3) -> 47118 | Q69: 0
B70: =B69+3 -> 18 | C70: =+M70 -> 47208 | D70: =+N70 -> 0 | F70: =+P70 -> 47208 | G70: =+Q70 -> 0 | I70: =+$D$61/4 -> 0.005 | M70: =EOMONTH(M69,3) -> 47208 | N70: 0 | P70: =EOMONTH(P69,3) -> 47208 | Q70: 0
B71: =B70+3 -> 21 | C71: =+M71 -> 47299 | D71: =+N71 -> 0 | F71: =+P71 -> 47299 | G71: =+Q71 -> 0 | I71: =+$D$61/4 -> 0.005 | M71: =EOMONTH(M70,3) -> 47299 | N71: 0 | P71: =EOMONTH(P70,3) -> 47299 | Q71: 0
B72: =B71+3 -> 24 | C72: =+M72 -> 47391 | D72: =+N72 -> 0 | F72: =+P72 -> 47391 | G72: =+Q72 -> 0 | I72: =+$D$61/4 -> 0.005 | M72: =EOMONTH(M71,3) -> 47391 | N72: 0 | P72: =EOMONTH(P71,3) -> 47391 | Q72: 0
B73: =B72+3 -> 27 | C73: =+M73 -> 47483 | D73: =+N73 -> 0 | F73: =+P73 -> 47483 | G73: =+Q73 -> 0 | I73: =+$D$61/4 -> 0.005 | M73: =EOMONTH(M72,3) -> 47483 | N73: 0 | P73: =EOMONTH(P72,3) -> 47483 | Q73: 0
B74: =B73+3 -> 30 | C74: =+M74 -> 47573 | D74: =+N74 -> 0 | F74: =+P74 -> 47573 | G74: =+Q74 -> 0 | I74: =+$D$61/4 -> 0.005 | M74: =EOMONTH(M73,3) -> 47573 | N74: 0 | P74: =EOMONTH(P73,3) -> 47573 | Q74: 0
B75: =B74+3 -> 33 | C75: =+M75 -> 47664 | D75: =+N75 -> 0 | F75: =+P75 -> 47664 | G75: =+Q75 -> 0 | I75: =+$D$61/4 -> 0.005 | M75: =EOMONTH(M74,3) -> 47664 | N75: 0 | P75: =EOMONTH(P74,3) -> 47664 | Q75: 0
B76: =B75+3 -> 36 | C76: =+M76 -> 47756 | D76: =+N76 -> 0 | F76: =+P76 -> 47756 | G76: =+Q76 -> 0 | I76: =+$D$61/4 -> 0.005 | M76: =EOMONTH(M75,3) -> 47756 | N76: 0 | P76: =EOMONTH(P75,3) -> 47756 | Q76: 0
B77: =B76+3 -> 39 | C77: =+M77 -> 47848 | D77: =+N77 -> 0 | F77: =+P77 -> 47848 | G77: =+Q77 -> 0 | I77: =+$D$61/4 -> 0.005 | M77: =EOMONTH(M76,3) -> 47848 | N77: 0 | P77: =EOMONTH(P76,3) -> 47848 | Q77: 0
... B92: =B91+3 -> 84 | C92: =+M92 -> 49217 | D92: =+N92 -> 0 | F92: =+P92 -> 49217 | G92: =+Q92 -> 1 | I92: =+$D$61/4 -> 0.005 | M92: =EOMONTH(M91,3) -> 49217 | N92: 0 | P92: =EOMONTH(P91,3) -> 49217 | Q92: 1
C95: WALL | D95: =+SUMPRODUCT(D65:D92,$B65:$B92)/12 -> 0 | F95: WALL | G95: =+SUMPRODUCT(G65:G92,$B65:$B92)/12 -> 7 | M95: WALL | N95: =+SUMPRODUCT(N65:N92,$B65:$B92)/12 -> 0 | P95: WALL | Q95: =+SUMPRODUCT(Q65:Q92,$B65:$B92)/12 -> 7
C97: Amount | D97: =+D22 -> 0 | F97: Amount | G97: =+D23 -> 256.5 | M97: Amount | N97: =+N22 -> 0 | P97: Amount | Q97: =+N23 -> 256.5
C99: Avg WALL | D99: =+(D95*D97+G95*G97)/SUM(D97,G97) -> 7 | M99: Avg WALL | N99: =+(N95*N97+Q95*Q97)/SUM(N97,Q97) -> 7
C101: AMORTIZATION PROFILE | M101: AMORTIZATION PROFILE
C104: =C33 -> CAF | D104: % | M104: =M33 -> CAF | N104: %
D105: =+SUM(D106:D133) -> 1 | N105: =+SUM(N106:N133) -> 1
B106: 3 | C106: =+M106 -> 46752 | D106: =+N106 -> 0 | M106: =Model!U72 -> 46752 | N106: 0
B107: =B106+3 -> 6 | C107: =+M107 -> 46843 | D107: =+N107 -> 0 | M107: =EOMONTH(M106,3) -> 46843 | N107: 0
B108: =B107+3 -> 9 | C108: =+M108 -> 46934 | D108: =+N108 -> 0 | M108: =EOMONTH(M107,3) -> 46934 | N108: 0
B109: =B108+3 -> 12 | C109: =+M109 -> 47026 | D109: =+N109 -> 0 | M109: =EOMONTH(M108,3) -> 47026 | N109: 0
B110: =B109+3 -> 15 | C110: =+M110 -> 47118 | D110: =+N110 -> 0 | M110: =EOMONTH(M109,3) -> 47118 | N110: 0
B111: =B110+3 -> 18 | C111: =+M111 -> 47208 | D111: =+N111 -> 0 | M111: =EOMONTH(M110,3) -> 47208 | N111: 0
B112: =B111+3 -> 21 | C112: =+M112 -> 47299 | D112: =+N112 -> 0 | M112: =EOMONTH(M111,3) -> 47299 | N112: 0
B113: =B112+3 -> 24 | C113: =+M113 -> 47391 | D113: =+N113 -> 0 | M113: =EOMONTH(M112,3) -> 47391 | N113: 0
B114: =B113+3 -> 27 | C114: =+M114 -> 47483 | D114: =+N114 -> 0 | M114: =EOMONTH(M113,3) -> 47483 | N114: 0
B115: =B114+3 -> 30 | C115: =+M115 -> 47573 | D115: =+N115 -> 0 | M115: =EOMONTH(M114,3) -> 47573 | N115: 0
B116: =B115+3 -> 33 | C116: =+M116 -> 47664 | D116: =+N116 -> 0 | M116: =EOMONTH(M115,3) -> 47664 | N116: 0
B117: =B116+3 -> 36 | C117: =+M117 -> 47756 | D117: =+N117 -> 0 | M117: =EOMONTH(M116,3) -> 47756 | N117: 0
B118: =B117+3 -> 39 | C118: =+M118 -> 47848 | D118: =+N118 -> 0 | M118: =EOMONTH(M117,3) -> 47848 | N118: 0
... B133: =B132+3 -> 84 | C133: =+M133 -> 49217 | D133: =+N133 -> 1 | M133: =EOMONTH(M132,3) -> 49217 | N133: 1
C135: WALL | D135: =+SUMPRODUCT(D106:D133,$B106:$B133)/12 -> 7 | M135: WALL | N135: =+SUMPRODUCT(N106:N133,$B106:$B133)/12 -> 7
C137: Amount | D137: =+D33 -> 50 | M137: Amount | N137: =+N33 -> 50
C140: OTHER | M140: OTHER
C142: Headroom | D142: =+N142 -> 0.4 | M142: Headroom | N142: 0.4

Sheet Active Case
C2: =RIGHT(CELL("filename",C1), LEN(CELL("filename", C1))- FIND("]", CELL("filename", C1), 1)) -> Active Case
C4: FYE Dec (€m) | F4: FY25B | G4: FY26F | H4: FY27F | I4: FY28F | J4: FY29F | K4: FY30F | L4: FY31F | M4: FY32F | O4: FY25B-32F
F5: Seller case | G5: Seller case | H5: Seller case | I5: Seller case | J5: Seller case | K5: Seller case | L5: Seller case | M5: Seller case | O5: Cum. | P5: CAGR
B7: A. | C7: Income Statement
B9: 1. | C9: Net Revenues | F9: 267.66926 | G9: 300.63698 | H9: 344.37965 | I9: 386.42074 | J9: 411.17115 | K9: 438.6581 | L9: 447.43126 | M9: 456.37989 | O9: =+SUM(F9:K9) -> 2148.9359 | P9: =+IFERROR((K9/F9)^(1/5)-1,0) -> 0.10383849
C10: % Growth | G10: =G9/F9-1 -> 0.1231659 | H10: =H9/G9-1 -> 0.14549995 | I10: =I9/H9-1 -> 0.12207776 | J10: =J9/I9-1 -> 0.064050414 | K10: =K9/J9-1 -> 0.066850379 | L10: =L9/K9-1 -> 0.02 | M10: =M9/L9-1 -> 0.02
B12: 3. | C12: Reported EBITDA | F12: 45.111661 | G12: 52.243319 | H12: 61.713285 | I12: 73.285082 | J12: 79.587752 | K12: 87.783624 | L12: 89.539296 | M12: 91.330082 | O12: =+SUM(F12:K12) -> 399.72472 | P12: =+IFERROR((K12/F12)^(1/5)-1,0) -> 0.14241774
C13: % Margin | F13: =F12/F$9 -> 0.16853508 | G13: =G12/G$9 -> 0.17377543 | H13: =H12/H$9 -> 0.17920132 | I13: =I12/I$9 -> 0.18965101 | J13: =J12/J$9 -> 0.19356356 | K13: =K12/K$9 -> 0.20011855 | L13: =L12/L$9 -> 0.20011855 | M13: =M12/M$9 -> 0.20011855
C14: % Growth | G14: =G12/F12-1 -> 0.15808902 | H14: =H12/G12-1 -> 0.18126655 | I14: =I12/H12-1 -> 0.18750901 | J14: =J12/I12-1 -> 0.086002077 | K14: =K12/J12-1 -> 0.10297906 | L14: =L12/K12-1 -> 0.02 | M14: =M12/L12-1 -> 0.02
C16: Adjustments & normalizations | F16: 6.1883392 | G16: 0 | H16: 0 | I16: 0 | J16: 0 | K16: 0 | L16: 0 | M16: 0
B17: 3. | C17: Adj. normalized EBITDA | F17: =+F16+F12 -> 51.3 | G17: =+G16+G12 -> 52.243319 | H17: =+H16+H12 -> 61.713285 | I17: =+I16+I12 -> 73.285082 | J17: =+J16+J12 -> 79.587752 | K17: =+K16+K12 -> 87.783624 | L17: =+L16+L12 -> 89.539296 | M17: =+M16+M12 -> 91.330082 | O17: =+SUM(F17:K17) -> 405.91306 | P17: =+IFERROR((K17/F17)^(1/5)-1,0) -> 0.11342054
C20: D&A | F20: -13.18676 | G20: -13.7669 | H20: -14.777273 | I20: -15.749308 | J20: -16.120529 | K20: -16.308984 | L20: -16.308984 | M20: -16.308984 | O20: =+SUM(F20:K20) -> -89.909754 | P20: =+IFERROR((K20/F20)^(1/5)-1,0) -> 0.043416651
C21: % of Revenues | F21: =-F20/F$9 -> 0.049265127 | G21: =-G20/G$9 -> 0.045792437 | H21: =-H20/H$9 -> 0.042909834 | I21: =-I20/I$9 -> 0.04075689 | J21: =-J20/J$9 -> 0.039206372 | K21: =-K20/K$9 -> 0.037179262 | L21: =-L20/L$9 -> 0.036450256 | M21: =-M20/M$9 -> 0.035735546
C23: Taxes | F23: -8.2650988 | G23: -3.7039729 | H23: -5.6672515 | I23: -9.1167539 | J23: -10.349509 | K23: -12.041849 | L23: -12.687668 | M23: -14.216824 | O23: =+SUM(F23:K23) -> -49.144436 | P23: =+IFERROR((K23/F23)^(1/5)-1,0) -> 0.07817443
C24: % of Revenues | F24: =-F23/F$9 -> 0.030878028 | G24: =-G23/G$9 -> 0.012320417 | H24: =-H23/H$9 -> 0.016456407 | I24: =-I23/I$9 -> 0.023592817 | J24: =-J23/J$9 -> 0.025170806 | K24: =-K23/K$9 -> 0.02745156 | L24: =-L23/L$9 -> 0.028356688 | M24: =-M23/M$9 -> 0.031151294
B26: B. | C26: Cash Flow Statement
B28: 1. | C28: Reported EBITDA | F28: =+F12 -> 45.111661 | G28: =+G12 -> 52.243319 | H28: =+H12 -> 61.713285 | I28: =+I12 -> 73.285082 | J28: =+J12 -> 79.587752 | K28: =+K12 -> 87.783624 | L28: =+L12 -> 89.539296 | M28: =+M12 -> 91.330082 | O28: =+SUM(F28:K28) -> 399.72472 | P28: =+IFERROR((K28/F28)^(1/5)-1,0) -> 0.14241774
C30: Change in Working Capital | F30: -5.8299854 | G30: -5.0017419 | H30: -6.8476121 | I30: -6.1780846 | J30: -2.5470106 | K30: -2.9852206 | L30: -1.5660094 | M30: -1.5973296 | O30: =+SUM(F30:K30) -> -29.389655 | P30: =+IFERROR((K30/F30)^(1/5)-1,0) -> -0.12529463
C31: % of Total Revenues | F31: =F30/F$9 -> -0.021780557 | G31: =G30/G$9 -> -0.016637148 | H31: =H30/H$9 -> -0.019883905 | I31: =I30/I$9 -> -0.015987973 | J31: =J30/J$9 -> -0.0061945264 | K31: =K30/K$9 -> -0.0068053471 | L31: =L30/L$9 -> -0.0035 | M31: =M30/M$9 -> -0.0035
C33: Maintenance Capex | F33: -4.186 | G33: -6.0127396 | H33: -6.8875929 | I33: -7.7284148 | J33: -8.223423 | K33: -8.773162 | L33: -8.773162 | M33: -8.773162 | O33: =+SUM(F33:K33) -> -41.811332 | P33: =+IFERROR((K33/F33)^(1/5)-1,0) -> 0.15950169
C34: % of Total Revenues | F34: =F33/F$9 -> -0.015638703 | G34: =G33/G$9 -> -0.02 | H34: =H33/H$9 -> -0.02 | I34: =I33/I$9 -> -0.02 | J34: =J33/J$9 -> -0.02 | K34: =K33/K$9 -> -0.02 | L34: =L33/L$9 -> -0.019607843 | M34: =M33/M$9 -> -0.019223376
C36: Expansion Capex (no M&A) | F36: -9.62 | G36: -4.6286815 | H36: -17.614526 | I36: -4.8221098 | J36: -8.2464023 | K36: -2.2279714 | L36: 0 | M36: 0 | O36: =+SUM(F36:K36) -> -47.159691 | P36: =+IFERROR((K36/F36)^(1/5)-1,0) -> -0.25364249
C37: % of Total Revenues | F37: =F36/F$9 -> -0.035939876 | G37: =G36/G$9 -> -0.015396248 | H37: =H36/H$9 -> -0.051148568 | I37: =I36/I$9 -> -0.01247891 | J37: =J36/J$9 -> -0.020055888 | K37: =K36/K$9 -> -0.0050790613 | L37: =L36/L$9 -> 0 | M37: =M36/M$9 -> 0
B39: 2. | C39: Operating Pre-Tax Free Cash Flow | F39: =F28+F30+F33+F36 -> 25.475675 | G39: =G28+G30+G33+G36 -> 36.600156 | H39: =H28+H30+H33+H36 -> 30.363555 | I39: =I28+I30+I33+I36 -> 54.556473 | J39: =J28+J30+J33+J36 -> 60.570916 | K39: =K28+K30+K33+K36 -> 73.79727 | L39: =L28+L30+L33+L36 -> 79.200125 | M39: =M28+M30+M33+M36 -> 80.959591 | O39: =+SUM(F39:K39) -> 281.36405 | P39: =+IFERROR((K39/F39)^(1/5)-1,0) -> 0.23703765
C40: % Operating Pre-Tax FCF Margin | F40: =F39/F28 -> 0.56472484 | G40: =G39/G28 -> 0.70057104 | H40: =H39/H28 -> 0.49201002 | I40: =I39/I28 -> 0.74444173 | J40: =J39/J28 -> 0.76105826 | K40: =K39/K28 -> 0.8406724 | L40: =L39/L28 -> 0.88452923 | M40: =M39/M28 -> 0.88645043
B42: C. | C42: End
B48: D. | C48: Dividends
C51: Previous Year Leverage | G51: =+'Debt Summary'!M54 -> 5 | H51: =+'Debt Summary'!N54 -> 4.5672987 | I51: =+'Debt Summary'!O54 -> 3.7205459 | J51: =+'Debt Summary'!P54 -> 2.9526718 | K51: =+'Debt Summary'!Q54 -> 3.6964741 | L51: =+'Debt Summary'!R54 -> 3.0377244 | M51: =+'Debt Summary'!S54 -> 2.6441165
C52: Free Cash Flow | G52: =+N('Debt Summary'!N27>0)*'Debt Summary'!N27 -> 28.530578 | H52: =+N('Debt Summary'!O27>0)*'Debt Summary'!O27 -> 33.50585 | I52: =+N('Debt Summary'!P27>0)*'Debt Summary'!P27 -> 41.54168 | J52: =+N('Debt Summary'!Q27>0)*'Debt Summary'!Q27 -> 33.529203 | K52: =+N('Debt Summary'!R27>0)*'Debt Summary'!R27 -> 45.063218 | L52: =+N('Debt Summary'!S27>0)*'Debt Summary'!S27 -> 49.820253 | M52: =+N('Debt Summary'!T27>0)*'Debt Summary'!T27 -> 0
C53: Cash Balance BoP | G53: =+N('Debt Summary'!N32>0)*'Debt Summary'!N32 -> 0 | H53: =+N('Debt Summary'!O32>0)*'Debt Summary'!O32 -> 28.530578 | I53: =+N('Debt Summary'!P32>0)*'Debt Summary'!P32 -> 62.036428 | J53: =+N('Debt Summary'!Q32>0)*'Debt Summary'!Q32 -> 87.807268 | K53: =+N('Debt Summary'!R32>0)*'Debt Summary'!R32 -> 10 | L53: =+N('Debt Summary'!S32>0)*'Debt Summary'!S32 -> 37.531609 | M53: =+N('Debt Summary'!T32>0)*'Debt Summary'!T32 -> 67.441735
C54: Max Distributable Cash | G54: =+SUM(G52:G53)*N(G52>0) -> 28.530578 | H54: =+SUM(H52:H53)*N(H52>0) -> 62.036428 | I54: =+SUM(I52:I53)*N(I52>0) -> 103.57811 | J54: =+SUM(J52:J53)*N(J52>0) -> 121.33647 | K54: =+SUM(K52:K53)*N(K52>0) -> 55.063218 | L54: =+SUM(L52:L53)*N(L52>0) -> 87.351862 | M54: =+SUM(M52:M53)*N(M52>0) -> 0
C55: Minimum Cash on Balance | F55: =+'Debt Structure'!$D$44 -> 10 | G55: =+$F55 -> 10 | H55: =+$F55 -> 10 | I55: =+$F55 -> 10 | J55: =+$F55 -> 10 | K55: =+$F55 -> 10 | L55: =+$F55 -> 10 | M55: =+$F55 -> 10
C56: Distributable Cash | G56: =+MAX(G54-G55,0) -> 18.530578 | H56: =+MAX(H54-H55,0) -> 52.036428 | I56: =+MAX(I54-I55,0) -> 93.578108 | J56: =+MAX(J54-J55,0) -> 111.33647 | K56: =+MAX(K54-K55,0) -> 45.063218 | L56: =+MAX(L54-L55,0) -> 77.351862 | M56: =+MAX(M54-M55,0) -> 0
C58: Permitted Distributions under TLB Only structure:
D59: Higher than | E59: Lower than | F59: % Div | O59: Total
C60: Dividend Distribution - Range 1 | D60: =+'Debt Structure'!$D$40 -> 4 | F60: =+'Debt Structure'!$F$40 -> 0 | G60: =+N(G$51>$D60)*$F60*(G$56-G53) -> 0 | H60: =+N(H$51>$D60)*$F60*(H$56-H53) -> 0 | I60: =+N(I$51>$D60)*$F60*(I$56-I53) -> 0 | J60: =+N(J$51>$D60)*$F60*(J$56-J53) -> 0 | K60: =+N(K$51>$D60)*$F60*(K$56-K53) -> 0 | L60: =+N(L$51>$D60)*$F60*(L$56-L53) -> 0 | M60: =+N(M$51>$D60)*$F60*(M$56-M53) -> 0
C61: Dividend Distribution - Range 2 | D61: =+'Debt Structure'!$D$41 -> 3 | E61: =+'Debt Structure'!$E$41 -> 4 | F61: =+'Debt Structure'!$F$41 -> 0.5 | G61: =+N(AND(G$51>$D61,G$51<=$E61))*(G$56-G53)*$F61 -> 0 | H61: =+N(AND(H$51>$D61,H$51<=$E61))*(H$56-H53)*$F61 -> 0 | I61: =+N(AND(I$51>$D61,I$51<=$E61))*(I$56-I53)*$F61 -> 15.77084 | J61: =+N(AND(J$51>$D61,J$51<=$E61))*(J$56-J53)*$F61 -> 0 | K61: =+N(AND(K$51>$D61,K$51<=$E61))*(K$56-K53)*$F61 -> 17.531609 | L61: =+N(AND(L$51>$D61,L$51<=$E61))*(L$56-L53)*$F61 -> 19.910127 | M61: =+N(AND(M$51>$D61,M$51<=$E61))*(M$56-M53)*$F61 -> 0
C62: Dividend Distribution - Range 3 | E62: =+'Debt Structure'!$E$42 -> 3 | F62: =+'Debt Structure'!$F$42 -> 1 | G62: =+N(G$51<=$E62)*$F62*(G$56) -> 0 | H62: =+N(H$51<=$E62)*$F62*(H$56) -> 0 | I62: =+N(I$51<=$E62)*$F62*(I$56) -> 0 | J62: =+N(J$51<=$E62)*$F62*(J$56) -> 111.33647 | K62: =+N(K$51<=$E62)*$F62*(K$56) -> 0 | L62: =+N(L$51<=$E62)*$F62*(L$56) -> 0 | M62: =+N(M$51<=$E62)*$F62*(M$56) -> 0
C63: Applicable Dividend Distribution | G63: =+MAX(SUM(G60:G62),0) -> 0 | H63: =+MAX(SUM(H60:H62),0) -> 0 | I63: =+MAX(SUM(I60:I62),0) -> 15.77084 | J63: =+MAX(SUM(J60:J62),0) -> 111.33647 | K63: =+MAX(SUM(K60:K62),0) -> 17.531609 | L63: =+MAX(SUM(L60:L62),0) -> 19.910127 | M63: =+MAX(SUM(M60:M62),0) -> 0 | O63: =+SUM(G63:M63) -> 164.54905
C65: Active Case Distributions | G65: =+G63 -> 0 | H65: =+H63 -> 0 | I65: =+I63 -> 15.77084 | J65: =+J63 -> 111.33647 | K65: =+K63 -> 17.531609 | L65: =+L63 -> 19.910127 | M65: =+M63 -> 0 | O65: =+SUM(G65:M65) -> 164.54905

Sheet Tax Model
B2: =RIGHT(CELL("filename",B1), LEN(CELL("filename", B1))- FIND("]", CELL("filename", B1), 1)) -> Tax Model
H4: 45657 | I4: =EDATE(H4,12) -> 46022 | J4: =EDATE(I4,12) -> 46387 | K4: =EDATE(J4,12) -> 46752 | L4: =EDATE(K4,12) -> 47118 | M4: =EDATE(L4,12) -> 47483 | N4: =EDATE(M4,12) -> 47848 | O4: =EDATE(N4,12) -> 48213 | P4: =EDATE(O4,12) -> 48579
B6: 1 | D6: CIT Calculation
D8: EBITDA | I8: ='Active Case'!F28 -> 45.111661 | J8: ='Active Case'!G28 -> 52.243319 | K8: ='Active Case'!H28 -> 61.713285 | L8: ='Active Case'!I28 -> 73.285082 | M8: ='Active Case'!J28 -> 79.587752 | N8: ='Active Case'!K28 -> 87.783624 | O8: ='Active Case'!L28 -> 89.539296 | P8: ='Active Case'!M28 -> 91.330082
D9: D&A | I9: ='Active Case'!F20 -> -13.18676 | J9: ='Active Case'!G20 -> -13.7669 | K9: ='Active Case'!H20 -> -14.777273 | L9: ='Active Case'!I20 -> -15.749308 | M9: ='Active Case'!J20 -> -16.120529 | N9: ='Active Case'!K20 -> -16.308984 | O9: ='Active Case'!L20 -> -16.308984 | P9: ='Active Case'!M20 -> -16.308984
D10: Net financial expenses | I10: =Model!L58 -> 0 | J10: =Model!Q58 -> -15.007027 | K10: =Model!V58 -> -15.692572 | L10: =Model!AA58 -> -16.448564 | M10: =Model!AF58 -> -16.692203 | N10: =Model!AK58 -> -16.692203 | O10: =+Model!AP58 -> -16.692203 | P10: =+Model!AU58 -> -14.630678
D11: Other deductible expenses | I11: =-I130 -> 0 | J11: =-J130 -> -0.42857143 | K11: =-K130 -> -0.42857143 | L11: =-L130 -> -0.4297456 | M11: =-M130 -> -0.42857143 | N11: =-N130 -> -0.42857143 | O11: =-O130 -> -0.42857143 | P11: =-P130 -> -0.42739726
D12: Tax Base Rate - Before Goodwill Amortization | I12: =+I8+I9+I10+I11 -> 31.924901 | J12: =+J8+J9+J10+J11 -> 23.040821 | K12: =+K8+K9+K10+K11 -> 30.814869 | L12: =+L8+L9+L10+L11 -> 40.657465 | M12: =+M8+M9+M10+M11 -> 46.346448 | N12: =+N8+N9+N10+N11 -> 54.353865 | O12: =+O8+O9+O10+O11 -> 56.109538 | P12: =+P8+P9+P10+P11 -> 59.963023
D13: EBITDA Limit Tax Base Increase | I13: =+I43+I47 -> 0 | J13: =+J43+J47 -> 0 | K13: =+K43+K47 -> 0 | L13: =+L43+L47 -> 0 | M13: =+M43+M47 -> 0 | N13: =+N43+N47 -> 0 | O13: =+O43+O47 -> 0 | P13: =+P43+P47 -> 0
D14: SHLs Tax Base Adjustment
D15: Tax Losses Carried Forward Compensation | I15: =+I102 -> 0 | J15: =+J102 -> 0 | K15: =+K102 -> 0 | L15: =+L102 -> 0 | M15: =+M102 -> 0 | N15: =+N102 -> 0 | O15: =+O102 -> 0 | P15: =+P102 -> 0
D16: Adjusted Tax Base Rate | I16: =+SUM(I12:I15) -> 31.924901 | J16: =+SUM(J12:J15) -> 23.040821 | K16: =+SUM(K12:K15) -> 30.814869 | L16: =+SUM(L12:L15) -> 40.657465 | M16: =+SUM(M12:M15) -> 46.346448 | N16: =+SUM(N12:N15) -> 54.353865 | O16: =+SUM(O12:O15) -> 56.109538 | P16: =+SUM(P12:P15) -> 59.963023
D18: Municipal tax surcharge (Derrama municipal) | E18: 0.015 | I18: =+-MAX(0,I16)*$E$18 -> -0.47887351 | J18: =+-MAX(0,J16)*$E$18 -> -0.34561232 | K18: =+-MAX(0,K16)*$E$18 -> -0.46222304 | L18: =+-MAX(0,L16)*$E$18 -> -0.60986198 | M18: =+-MAX(0,M16)*$E$18 -> -0.69519672 | N18: =+-MAX(0,N16)*$E$18 -> -0.81530798 | O18: =+-MAX(0,O16)*$E$18 -> -0.84164306 | P18: =+-MAX(0,P16)*$E$18 -> -0.89944535
D20: National tax surcharge (Derrama estadual) | E20: rate
D21: Bracket 1 | E21: 0.03 | F21: 1.5 | I21: =+IF(I$16>$F21,MIN($F22,I$16)-$F21,0) -> 6 | J21: =+IF(J$16>$F21,MIN($F22,J$16)-$F21,0) -> 6 | K21: =+IF(K$16>$F21,MIN($F22,K$16)-$F21,0) -> 6 | L21: =+IF(L$16>$F21,MIN($F22,L$16)-$F21,0) -> 6 | M21: =+IF(M$16>$F21,MIN($F22,M$16)-$F21,0) -> 6 | N21: =+IF(N$16>$F21,MIN($F22,N$16)-$F21,0) -> 6 | O21: =+IF(O$16>$F21,MIN($F22,O$16)-$F21,0) -> 6 | P21: =+IF(P$16>$F21,MIN($F22,P$16)-$F21,0) -> 6
D22: Bracket 2 | E22: 0.05 | F22: 7.5 | I22: =+IF(I$16>$F22,MIN($F23,I$16)-$F22,0) -> 24.424901 | J22: =+IF(J$16>$F22,MIN($F23,J$16)-$F22,0) -> 15.540821 | K22: =+IF(K$16>$F22,MIN($F23,K$16)-$F22,0) -> 23.314869 | L22: =+IF(L$16>$F22,MIN($F23,L$16)-$F22,0) -> 27.5 | M22: =+IF(M$16>$F22,MIN($F23,M$16)-$F22,0) -> 27.5 | N22: =+IF(N$16>$F22,MIN($F23,N$16)-$F22,0) -> 27.5 | O22: =+IF(O$16>$F22,MIN($F23,O$16)-$F22,0) -> 27.5 | P22: =+IF(P$16>$F22,MIN($F23,P$16)-$F22,0) -> 27.5
D23: Bracket 3 | E23: 0.09 | F23: 35 | I23: =+IF(I$16>$F23,I$16-$F23,0) -> 0 | J23: =+IF(J$16>$F23,J$16-$F23,0) -> 0 | K23: =+IF(K$16>$F23,K$16-$F23,0) -> 0 | L23: =+IF(L$16>$F23,L$16-$F23,0) -> 5.6574654 | M23: =+IF(M$16>$F23,M$16-$F23,0) -> 11.346448 | N23: =+IF(N$16>$F23,N$16-$F23,0) -> 19.353865 | O23: =+IF(O$16>$F23,O$16-$F23,0) -> 21.109538 | P23: =+IF(P$16>$F23,P$16-$F23,0) -> 24.963023
D24: National tax surcharge | I24: =-+SUMPRODUCT($E$21:$E$23,I21:I23) -> -1.401245 | J24: =-+SUMPRODUCT($E$21:$E$23,J21:J23) -> -0.95704107 | K24: =-+SUMPRODUCT($E$21:$E$23,K21:K23) -> -1.3457435 | L24: =-+SUMPRODUCT($E$21:$E$23,L21:L23) -> -2.0641719 | M24: =-+SUMPRODUCT($E$21:$E$23,M21:M23) -> -2.5761803 | N24: =-+SUMPRODUCT($E$21:$E$23,N21:N23) -> -3.2968479 | O24: =-+SUMPRODUCT($E$21:$E$23,O21:O23) -> -3.4548584 | P24: =-+SUMPRODUCT($E$21:$E$23,P21:P23) -> -3.8016721
D26: Total surcharges | I26: =+I18+I24 -> -1.8801186 | J26: =+J18+J24 -> -1.3026534 | K26: =+K18+K24 -> -1.8079665 | L26: =+L18+L24 -> -2.6740339 | M26: =+M18+M24 -> -3.271377 | N26: =+N18+N24 -> -4.1121558 | O26: =+O18+O24 -> -4.2965014 | P26: =+P18+P24 -> -4.7011174
D28: Corporate tax | E28: 0.2 | I28: =+MAX(0,I16)*-$E$28 -> -6.3849802 | J28: =+MAX(0,J16)*-$E$28 -> -4.6081643 | K28: =+MAX(0,K16)*-$E$28 -> -6.1629738 | L28: =+MAX(0,L16)*-$E$28 -> -8.1314931 | M28: =+MAX(0,M16)*-$E$28 -> -9.2692896 | N28: =+MAX(0,N16)*-$E$28 -> -10.870773 | O28: =+MAX(0,O16)*-$E$28 -> -11.221908 | P28: =+MAX(0,P16)*-$E$28 -> -11.992605
D30: Cash CIT to be Paid | I30: =+I28+I26 -> -8.2650988 | J30: =+J28+J26 -> -5.9108176 | K30: =+K28+K26 -> -7.9709403 | L30: =+L28+L26 -> -10.805527 | M30: =+M28+M26 -> -12.540667 | N30: =+N28+N26 -> -14.982929 | O30: =+O28+O26 -> -15.518409 | P30: =+P28+P26 -> -16.693722
I31: =-I30/I12 -> 0.25889192 | J31: =-J30/J12 -> 0.25653676 | K31: =-K30/K12 -> 0.25867189 | L31: =-L30/L12 -> 0.26576981 | M31: =-M30/M12 -> 0.27058528 | N31: =-N30/N12 -> 0.27565526 | O31: =-O30/O12 -> 0.27657346 | P31: =-P30/P12 -> 0.27840027
B33: x | D33: Rule of the 30% EBITDA Limit
D35: EBITDA | I35: =+I8 -> 45.111661 | J35: =+J8 -> 52.243319 | K35: =+K8 -> 61.713285 | L35: =+L8 -> 73.285082 | M35: =+M8 -> 79.587752 | N35: =+N8 -> 87.783624 | O35: =+O8 -> 89.539296 | P35: =+P8 -> 91.330082
D37: Minimum Deductible Net Fin. Expenses | G37: 1 | I37: =G37 -> 1 | J37: =I37 -> 1 | K37: =J37 -> 1 | L37: =K37 -> 1 | M37: =L37 -> 1 | N37: =M37 -> 1 | O37: =N37 -> 1 | P37: =O37 -> 1
D38: EBITDA Limit | G38: 0.3 | I38: =G38 -> 0.3 | J38: =I38 -> 0.3 | K38: =J38 -> 0.3 | L38: =K38 -> 0.3 | M38: =L38 -> 0.3 | N38: =M38 -> 0.3 | O38: =N38 -> 0.3 | P38: =O38 -> 0.3
D39: EBITDA Limit - Threshold | I39: =IF(I35<0,0,+I38*I35) -> 13.533498 | J39: =IF(J35<0,0,+J38*J35) -> 15.672996 | K39: =IF(K35<0,0,+K38*K35) -> 18.513986 | L39: =IF(L35<0,0,+L38*L35) -> 21.985525 | M39: =IF(M35<0,0,+M38*M35) -> 23.876326 | N39: =IF(N35<0,0,+N38*N35) -> 26.335087 | O39: =IF(O35<0,0,+O38*O35) -> 26.861789 | P39: =IF(P35<0,0,+P38*P35) -> 27.399025
D41: Net Financial Expenses | I41: =I10 -> 0 | J41: =J10 -> -15.007027 | K41: =K10 -> -15.692572 | L41: =L10 -> -16.448564 | M41: =M10 -> -16.692203 | N41: =N10 -> -16.692203 | O41: =O10 -> -16.692203 | P41: =P10 -> -14.630678
D42: EBITDA Limit | I42: =MAX(+I39,I37) -> 13.533498 | J42: =MAX(+J39,J37) -> 15.672996 | K42: =MAX(+K39,K37) -> 18.513986 | L42: =MAX(+L39,L37) -> 21.985525 | M42: =MAX(+M39,M37) -> 23.876326 | N42: =MAX(+N39,N37) -> 26.335087 | O42: =MAX(+O39,O37) -> 26.861789 | P42: =MAX(+P39,P37) -> 27.399025
D43: Excess on EBITDA Limit to be Carried Forward | I43: =IF(-I41-I42<0,0,-I41-I42) -> 0 | J43: =IF(-J41-J42<0,0,-J41-J42) -> 0 | K43: =IF(-K41-K42<0,0,-K41-K42) -> 0 | L43: =IF(-L41-L42<0,0,-L41-L42) -> 0 | M43: =IF(-M41-M42<0,0,-M41-M42) -> 0 | N43: =IF(-N41-N42<0,0,-N41-N42) -> 0 | O43: =IF(-O41-O42<0,0,-O41-O42) -> 0 | P43: =IF(-P41-P42<0,0,-P41-P42) -> 0
D44: EBITDA Limit not applied (to be used in 5 Yrs) | I44: =-+IF(-I41-I42>0,0,-I41-I42) -> 13.533498 | J44: =-+IF(-J41-J42>0,0,-J41-J42) -> 0.66596913 | K44: =-+IF(-K41-K42>0,0,-K41-K42) -> 2.821414 | L44: =-+IF(-L41-L42>0,0,-L41-L42) -> 5.5369608 | M44: =-+IF(-M41-M42>0,0,-M41-M42) -> 7.1841223 | N44: =-+IF(-N41-N42>0,0,-N41-N42) -> 9.642884 | O44: =-+IF(-O41-O42>0,0,-O41-O42) -> 10.169586 | P44: =-+IF(-P41-P42>0,0,-P41-P42) -> 12.768347
D46: Net Fin. Exp. Non Deducted Carried Forward | I46: =+H46+I43+I47 -> 0 | J46: =+I46+J43+J47 -> 0 | K46: =+J46+K43+K47 -> 0 | L46: =+K46+L43+L47 -> 0 | M46: =+L46+M43+M47 -> 0 | N46: =+M46+N43+N47 -> 0 | O46: =+N46+O43+O47 -> 0 | P46: =+O46+P43+P47 -> 0
D47: Increase in EBITDA Limit Applied in the Period | I47: =I58+I65+I72+I79+I86+I93 -> 0 | J47: =J58+J65+J72+J79+J86+J93 -> 0 | K47: =K58+K65+K72+K79+K86+K93 -> 0 | L47: =L58+L65+L72+L79+L86+L93 -> 0 | M47: =M58+M65+M72+M79+M86+M93 -> 0 | N47: =N58+N65+N72+N79+N86+N93 -> 0 | O47: =O58+O65+O72+O79+O86+O93 -> 0 | P47: =P58+P65+P72+P79+P86+P93 -> 0
D49: EBITDA Limit Excess in the Period | I49: =+I44 -> 13.533498 | J49: =+J44 -> 0.66596913 | K49: =+K44 -> 2.821414 | L49: =+L44 -> 5.5369608 | M49: =+M44 -> 7.1841223 | N49: =+N44 -> 9.642884 | O49: =+O44 -> 10.169586 | P49: =+P44 -> 12.768347
D50: EBITDA Limit Excess Pending to Be Applied | I50: =I60+I67+I74+I81+I88+I95 -> 13.533498 | J50: =J60+J67+J74+J81+J88+J95 -> 14.199467 | K50: =K60+K67+K74+K81+K88+K95 -> 17.020881 | L50: =L60+L67+L74+L81+L88+L95 -> 22.557842 | M50: =M60+M67+M74+M81+M88+M95 -> 29.741965 | N50: =N60+N67+N74+N81+N88+N95 -> 25.85135 | O50: =O60+O67+O74+O81+O88+O95 -> 15.542497 | P50: =P60+P67+P74+P81+P88+P95 -> 12.721083
B52: x | D52: EBITDA Limit Increase from Previous 5 Years
H53: =+H4 -> 45657 | I53: =+I4 -> 46022 | J53: =+J4 -> 46387 | K53: =+K4 -> 46752 | L53: =+L4 -> 47118 | M53: =+M4 -> 47483 | N53: =+N4 -> 47848 | O53: =+O4 -> 48213 | P53: =+P4 -> 48579
D55: =+I53 -> 46022
D56: BoP | J56: =+I60 -> 13.533498 | K56: =+J60 -> 13.533498 | L56: =+K60 -> 13.533498 | M56: =+L60 -> 13.533498 | N56: =+M60 -> 13.533498 | O56: =+N60 -> 0 | P56: =+O60 -> 0
D57: Excess in the Period | I57: =+IF(I$53=$D55,I$49,0) -> 13.533498 | J57: =+IF(J$53=$D55,J$49,0) -> 0 | K57: =+IF(K$53=$D55,K$49,0) -> 0 | L57: =+IF(L$53=$D55,L$49,0) -> 0 | M57: =+IF(M$53=$D55,M$49,0) -> 0 | N57: =+IF(N$53=$D55,N$49,0) -> 0 | O57: =+IF(O$53=$D55,O$49,0) -> 0 | P57: =+IF(P$53=$D55,P$49,0) -> 0
D58: Excess Applied | I58: =-IF(I$43+H$46>0,MIN(I$43+H$46,I56+I57),0) -> 0 | J58: =-IF(J$43+I$46>0,MIN(J$43+I$46,J56+J57),0) -> 0 | K58: =-IF(K$43+J$46>0,MIN(K$43+J$46,K56+K57),0) -> 0 | L58: =-IF(L$43+K$46>0,MIN(L$43+K$46,L56+L57),0) -> 0 | M58: =-IF(M$43+L$46>0,MIN(M$43+L$46,M56+M57),0) -> 0 | N58: =-IF(N$43+M$46>0,MIN(N$43+M$46,N56+N57),0) -> 0 | O58: =-IF(O$43+N$46>0,MIN(O$43+N$46,O56+O57),0) -> 0 | P58: =-IF(P$43+O$46>0,MIN(P$43+O$46,P56+P57),0) -> 0
D59: Excess Expired | I59: =+IF(I$4-$D55>DATE(5,0,1),-SUM(I56:I58),0) -> 0 | J59: =+IF(J$4-$D55>DATE(5,0,1),-SUM(J56:J58),0) -> 0 | K59: =+IF(K$4-$D55>DATE(5,0,1),-SUM(K56:K58),0) -> 0 | L59: =+IF(L$4-$D55>DATE(5,0,1),-SUM(L56:L58),0) -> 0 | M59: =+IF(M$4-$D55>DATE(5,0,1),-SUM(M56:M58),0) -> 0 | N59: =+IF(N$4-$D55>DATE(5,0,1),-SUM(N56:N58),0) -> -13.533498 | O59: =+IF(O$4-$D55>DATE(5,0,1),-SUM(O56:O58),0) -> 0 | P59: =+IF(P$4-$D55>DATE(5,0,1),-SUM(P56:P58),0) -> 0
D60: EoP | H60: =+SUM(H56:H59) -> 0 | I60: =+SUM(I56:I59) -> 13.533498 | J60: =+SUM(J56:J59) -> 13.533498 | K60: =+SUM(K56:K59) -> 13.533498 | L60: =+SUM(L56:L59) -> 13.533498 | M60: =+SUM(M56:M59) -> 13.533498 | N60: =+SUM(N56:N59) -> 0 | O60: =+SUM(O56:O59) -> 0 | P60: =+SUM(P56:P59) -> 0
D62: =+J53 -> 46387
D63: BoP | K63: =+J67 -> 0.66596913 | L63: =+K67 -> 0.66596913 | M63: =+L67 -> 0.66596913 | N63: =+M67 -> 0.66596913 | O63: =+N67 -> 0.66596913 | P63: =+O67 -> 0
D64: Excess in the Period | J64: =+IF(J$53=$D62,J$49,0) -> 0.66596913 | K64: =+IF(K$53=$D62,K$49,0) -> 0 | L64: =+IF(L$53=$D62,L$49,0) -> 0 | M64: =+IF(M$53=$D62,M$49,0) -> 0 | N64: =+IF(N$53=$D62,N$49,0) -> 0 | O64: =+IF(O$53=$D62,O$49,0) -> 0 | P64: =+IF(P$53=$D62,P$49,0) -> 0
D65: Excess Applied | J65: =-IF(J$43+I$46>0,MIN(J$43+I$46+J58,J63+J64),0) -> 0 | K65: =-IF(K$43+J$46>0,MIN(K$43+J$46+K58,K63+K64),0) -> 0 | L65: =-IF(L$43+K$46>0,MIN(L$43+K$46+L58,L63+L64),0) -> 0 | M65: =-IF(M$43+L$46>0,MIN(M$43+L$46+M58,M63+M64),0) -> 0 | N65: =-IF(N$43+M$46>0,MIN(N$43+M$46+N58,N63+N64),0) -> 0 | O65: =-IF(O$43+N$46>0,MIN(O$43+N$46+O58,O63+O64),0) -> 0 | P65: =-IF(P$43+O$46>0,MIN(P$43+O$46+P58,P63+P64),0) -> 0
D66: Excess Expired | J66: =+IF(J$4-$D62>DATE(5,0,1),-SUM(J63:J65),0) -> 0 | K66: =+IF(K$4-$D62>DATE(5,0,1),-SUM(K63:K65),0) -> 0 | L66: =+IF(L$4-$D62>DATE(5,0,1),-SUM(L63:L65),0) -> 0 | M66: =+IF(M$4-$D62>DATE(5,0,1),-SUM(M63:M65),0) -> 0 | N66: =+IF(N$4-$D62>DATE(5,0,1),-SUM(N63:N65),0) -> 0 | O66: =+IF(O$4-$D62>DATE(5,0,1),-SUM(O63:O65),0) -> -0.66596913 | P66: =+IF(P$4-$D62>DATE(5,0,1),-SUM(P63:P65),0) -> 0
D67: EoP | H67: =+SUM(H63:H66) -> 0 | I67: =+SUM(I63:I66) -> 0 | J67: =+SUM(J63:J66) -> 0.66596913 | K67: =+SUM(K63:K66) -> 0.66596913 | L67: =+SUM(L63:L66) -> 0.66596913 | M67: =+SUM(M63:M66) -> 0.66596913 | N67: =+SUM(N63:N66) -> 0.66596913 | O67: =+SUM(O63:O66) -> 0 | P67: =+SUM(P63:P66) -> 0
D69: =+K53 -> 46752
D70: BoP | L70: =+K74 -> 2.821414 | M70: =+L74 -> 2.821414 | N70: =+M74 -> 2.821414 | O70: =+N74 -> 2.821414 | P70: =+O74 -> 2.821414
D71: Excess in the Period | K71: =+IF(K$53=$D69,K$49,0) -> 2.821414 | L71: =+IF(L$53=$D69,L$49,0) -> 0 | M71: =+IF(M$53=$D69,M$49,0) -> 0 | N71: =+IF(N$53=$D69,N$49,0) -> 0 | O71: =+IF(O$53=$D69,O$49,0) -> 0 | P71: =+IF(P$53=$D69,P$49,0) -> 0
D72: Excess Applied | K72: =-IF(K$43+J$46>0,MIN(K$43+J$46+K58+K65,K70+K71),0) -> 0 | L72: =-IF(L$43+K$46>0,MIN(L$43+K$46+L58+L65,L70+L71),0) -> 0 | M72: =-IF(M$43+L$46>0,MIN(M$43+L$46+M58+M65,M70+M71),0) -> 0 | N72: =-IF(N$43+M$46>0,MIN(N$43+M$46+N58+N65,N70+N71),0) -> 0 | O72: =-IF(O$43+N$46>0,MIN(O$43+N$46+O58+O65,O70+O71),0) -> 0 | P72: =-IF(P$43+O$46>0,MIN(P$43+O$46+P58+P65,P70+P71),0) -> 0
D73: Excess Expired | K73: =+IF(K$4-$D69>DATE(5,0,1),-SUM(K70:K72),0) -> 0 | L73: =+IF(L$4-$D69>DATE(5,0,1),-SUM(L70:L72),0) -> 0 | M73: =+IF(M$4-$D69>DATE(5,0,1),-SUM(M70:M72),0) -> 0 | N73: =+IF(N$4-$D69>DATE(5,0,1),-SUM(N70:N72),0) -> 0 | O73: =+IF(O$4-$D69>DATE(5,0,1),-SUM(O70:O72),0) -> 0 | P73: =+IF(P$4-$D69>DATE(5,0,1),-SUM(P70:P72),0) -> -2.821414
D74: EoP | H74: =+SUM(H70:H73) -> 0 | I74: =+SUM(I70:I73) -> 0 | J74: =+SUM(J70:J73) -> 0 | K74: =+SUM(K70:K73) -> 2.821414 | L74: =+SUM(L70:L73) -> 2.821414 | M74: =+SUM(M70:M73) -> 2.821414 | N74: =+SUM(N70:N73) -> 2.821414 | O74: =+SUM(O70:O73) -> 2.821414 | P74: =+SUM(P70:P73) -> 0
D76: =+L53 -> 47118
D77: BoP | M77: =+L81 -> 5.5369608 | N77: =+M81 -> 5.5369608 | O77: =+N81 -> 5.5369608 | P77: =+O81 -> 5.5369608
D78: Excess in the Period | L78: =+IF(L$53=$D76,L$49,0) -> 5.5369608 | M78: =+IF(M$53=$D76,M$49,0) -> 0 | N78: =+IF(N$53=$D76,N$49,0) -> 0 | O78: =+IF(O$53=$D76,O$49,0) -> 0 | P78: =+IF(P$53=$D76,P$49,0) -> 0
D79: Excess Applied | L79: =-IF(L$43+K$46>0,MIN(L$43+K$46+L58+L65+L72,L77+L78),0) -> 0 | M79: =-IF(M$43+L$46>0,MIN(M$43+L$46+M58+M65+M72,M77+M78),0) -> 0 | N79: =-IF(N$43+M$46>0,MIN(N$43+M$46+N58+N65+N72,N77+N78),0) -> 0 | O79: =-IF(O$43+N$46>0,MIN(O$43+N$46+O58+O65+O72,O77+O78),0) -> 0 | P79: =-IF(P$43+O$46>0,MIN(P$43+O$46+P58+P65+P72,P77+P78),0) -> 0
D80: Excess Expired | L80: =+IF(L$4-$D76>DATE(5,0,1),-SUM(L77:L79),0) -> 0 | M80: =+IF(M$4-$D76>DATE(5,0,1),-SUM(M77:M79),0) -> 0 | N80: =+IF(N$4-$D76>DATE(5,0,1),-SUM(N77:N79),0) -> 0 | O80: =+IF(O$4-$D76>DATE(5,0,1),-SUM(O77:O79),0) -> 0 | P80: =+IF(P$4-$D76>DATE(5,0,1),-SUM(P77:P79),0) -> 0
D81: EoP | H81: =+SUM(H77:H80) -> 0 | I81: =+SUM(I77:I80) -> 0 | J81: =+SUM(J77:J80) -> 0 | K81: =+SUM(K77:K80) -> 0 | L81: =+SUM(L77:L80) -> 5.5369608 | M81: =+SUM(M77:M80) -> 5.5369608 | N81: =+SUM(N77:N80) -> 5.5369608 | O81: =+SUM(O77:O80) -> 5.5369608 | P81: =+SUM(P77:P80) -> 5.5369608
D83: =+M53 -> 47483
D84: BoP | N84: =+M88 -> 7.1841223 | O84: =+N88 -> 7.1841223 | P84: =+O88 -> 7.1841223
D85: Excess in the Period | M85: =+IF(M$53=$D83,M$49,0) -> 7.1841223 | N85: =+IF(N$53=$D83,N$49,0) -> 0 | O85: =+IF(O$53=$D83,O$49,0) -> 0 | P85: =+IF(P$53=$D83,P$49,0) -> 0
D86: Excess Applied | M86: =-IF(M$43+L$46>0,MIN(M$43+L$46+M58+M65+M72+M79,M84+M85),0) -> 0 | N86: =-IF(N$43+M$46>0,MIN(N$43+M$46+N58+N65+N72+N79,N84+N85),0) -> 0 | O86: =-IF(O$43+N$46>0,MIN(O$43+N$46+O58+O65+O72+O79,O84+O85),0) -> 0 | P86: =-IF(P$43+O$46>0,MIN(P$43+O$46+P58+P65+P72+P79,P84+P85),0) -> 0
D87: Excess Expired | M87: =+IF(M$4-$D83>DATE(5,0,1),-SUM(M84:M86),0) -> 0 | N87: =+IF(N$4-$D83>DATE(5,0,1),-SUM(N84:N86),0) -> 0 | O87: =+IF(O$4-$D83>DATE(5,0,1),-SUM(O84:O86),0) -> 0 | P87: =+IF(P$4-$D83>DATE(5,0,1),-SUM(P84:P86),0) -> 0
D88: EoP | H88: =+SUM(H84:H87) -> 0 | I88: =+SUM(I84:I87) -> 0 | J88: =+SUM(J84:J87) -> 0 | K88: =+SUM(K84:K87) -> 0 | L88: =+SUM(L84:L87) -> 0 | M88: =+SUM(M84:M87) -> 7.1841223 | N88: =+SUM(N84:N87) -> 7.1841223 | O88: =+SUM(O84:O87) -> 7.1841223 | P88: =+SUM(P84:P87) -> 7.1841223
D90: =+$N$53 -> 47848
D91: BoP
D92: Excess in the Period | N92: =+IF(N$53=$D90,N$49,0) -> 9.642884 | O92: =+IF(O$53=$D90,O$49,0) -> 0 | P92: =+IF(P$53=$D90,P$49,0) -> 0
D93: Excess Applied | N93: =-IF(N$43+M$46>0,MIN(N$43+M$46+N58+N65+N72+N79+N86,N91+N92),0) -> 0 | O93: =-IF(O$43+N$46>0,MIN(O$43+N$46+O58+O65+O72+O79+O86,O91+O92),0) -> 0 | P93: =-IF(P$43+O$46>0,MIN(P$43+O$46+P58+P65+P72+P79+P86,P91+P92),0) -> 0
D94: Excess Expired | N94: =+IF(N$4-$D90>DATE(5,0,1),-SUM(N91:N93),0) -> 0 | O94: =+IF(O$4-$D90>DATE(5,0,1),-SUM(O91:O93),0) -> 0 | P94: =+IF(P$4-$D90>DATE(5,0,1),-SUM(P91:P93),0) -> 0
D95: EoP | H95: =+SUM(H91:H94) -> 0 | I95: =+SUM(I91:I94) -> 0 | J95: =+SUM(J91:J94) -> 0 | K95: =+SUM(K91:K94) -> 0 | L95: =+SUM(L91:L94) -> 0 | M95: =+SUM(M91:M94) -> 0 | N95: =+SUM(N91:N94) -> 9.642884 | O95: =+SUM(O91:O94) -> 0 | P95: =+SUM(P91:P94) -> 0
B97: x | D97: Tax Losses Carried Forward
D99: Tax Losses Carried Forward
D100: Beginning of Period | I100: =+H103 -> 0 | J100: =+I103 -> 0 | K100: =+J103 -> 0 | L100: =+K103 -> 0 | M100: =+L103 -> 0 | N100: =+M103 -> 0 | O100: =+N103 -> 0 | P100: =+O103 -> 0
D101: New Tax Losses | I101: =+IF(I111>0,0,-I111) -> 0 | J101: =+IF(J111>0,0,-J111) -> 0 | K101: =+IF(K111>0,0,-K111) -> 0 | L101: =+IF(L111>0,0,-L111) -> 0 | M101: =+IF(M111>0,0,-M111) -> 0 | N101: =+IF(N111>0,0,-N111) -> 0 | O101: =+IF(O111>0,0,-O111) -> 0 | P101: =+IF(P111>0,0,-P111) -> 0
D102: Applied in the Period | I102: =-MIN(I100,I113) -> 0 | J102: =-MIN(J100,J113) -> 0 | K102: =-MIN(K100,K113) -> 0 | L102: =-MIN(L100,L113) -> 0 | M102: =-MIN(M100,M113) -> 0 | N102: =-MIN(N100,N113) -> 0 | O102: =-MIN(O100,O113) -> 0 | P102: =-MIN(P100,P113) -> 0
D103: Tax Losses Carried Forward End of Period | H103: 0 | I103: =+I100+I101+I102 -> 0 | J103: =+J100+J101+J102 -> 0 | K103: =+K100+K101+K102 -> 0 | L103: =+L100+L101+L102 -> 0 | M103: =+M100+M101+M102 -> 0 | N103: =+N100+N101+N102 -> 0 | O103: =+O100+O101+O102 -> 0 | P103: =+P100+P101+P102 -> 0
D105: Percentage of Tax Losses Carried Forward
D106: =+"Revenues <"&+G106 & "m" -> Revenues <20m | G106: 20 | H106: 0.7 | I106: =H106 -> 0.7 | J106: =I106 -> 0.7 | K106: =J106 -> 0.7 | L106: =K106 -> 0.7 | M106: =L106 -> 0.7 | N106: =M106 -> 0.7 | O106: =N106 -> 0.7 | P106: =O106 -> 0.7
D107: =+"Revenues "&+G106 & "m-"&G108&"m" -> Revenues 20m-60m | H107: 0.5 | I107: =H107 -> 0.5 | J107: =I107 -> 0.5 | K107: =J107 -> 0.5 | L107: =K107 -> 0.5 | M107: =L107 -> 0.5 | N107: =M107 -> 0.5 | O107: =N107 -> 0.5 | P107: =O107 -> 0.5
D108: =+"Revenues >"&+G108 & "m" -> Revenues >60m | G108: 60 | H108: 0.25 | I108: =H108 -> 0.25 | J108: =I108 -> 0.25 | K108: =J108 -> 0.25 | L108: =K108 -> 0.25 | M108: =L108 -> 0.25 | N108: =M108 -> 0.25 | O108: =N108 -> 0.25 | P108: =O108 -> 0.25
D109: Applicable Percentage | H109: 0.25 | I109: 0.25 | J109: 0.25 | K109: 0.25 | L109: 0.25 | M109: 0.25 | N109: 0.25 | O109: 0.25 | P109: 0.25
D111: Tax Base | H111: =+H12+H13 -> 0 | I111: =+I12+I13 -> 31.924901 | J111: =+J12+J13 -> 23.040821 | K111: =+K12+K13 -> 30.814869 | L111: =+L12+L13 -> 40.657465 | M111: =+M12+M13 -> 46.346448 | N111: =+N12+N13 -> 54.353865 | O111: =+O12+O13 -> 56.109538 | P111: =+P12+P13 -> 59.963023
D112: Minimum Tax Loss Compensation | H112: 1 | I112: =H112 -> 1 | J112: =I112 -> 1 | K112: =J112 -> 1 | L112: =K112 -> 1 | M112: =L112 -> 1 | N112: =M112 -> 1 | O112: =N112 -> 1 | P112: =O112 -> 1
D113: Tax Base for Tax Losses Compensation | H113: =IF(H111>0,MAX(+H111*H109,H112),0) -> 0 | I113: =IF(I111>0,MAX(+I111*I109,I112),0) -> 7.9812252 | J113: =IF(J111>0,MAX(+J111*J109,J112),0) -> 5.7602053 | K113: =IF(K111>0,MAX(+K111*K109,K112),0) -> 7.7037173 | L113: =IF(L111>0,MAX(+L111*L109,L112),0) -> 10.164366 | M113: =IF(M111>0,MAX(+M111*M109,M112),0) -> 11.586612 | N113: =IF(N111>0,MAX(+N111*N109,N112),0) -> 13.588466 | O113: =IF(O111>0,MAX(+O111*O109,O112),0) -> 14.027384 | P113: =IF(P111>0,MAX(+P111*P109,P112),0) -> 14.990756
B115: x | D115: New Goodwill Amortization Tax Deductibility
D117: Tax Deductibility of Goodwill | G117: 0
D118: Period | G118: 20
D119: First Period Impact | G119: 0.5
D121: Tax Amoritzation of Goodwill | H121: 0 | I121: 0 | J121: 0 | K121: 0 | L121: 0 | M121: 0 | N121: 0 | O121: 0 | P121: 0
B123: x | D123: Transaction expenses
D125: Closing | G125: ='Debt Summary'!D6 -> 46022
D126: Flag years | I126: =+(I4-$G$125)/365 -> 0 | J126: =+(J4-$G$125)/365 -> 1 | K126: =+(K4-$G$125)/365 -> 2 | L126: =+(L4-$G$125)/365 -> 3.0027397 | M126: =+(M4-$G$125)/365 -> 4.0027397 | N126: =+(N4-$G$125)/365 -> 5.0027397 | O126: =+(O4-$G$125)/365 -> 6.0027397 | P126: =+(P4-$G$125)/365 -> 7.0054795
D127: Flag active | I127: =+IF(YEAR(I4)>YEAR($H$130),0,1) -> 1 | J127: =+IF(YEAR(J4)>YEAR($H$130),0,1) -> 1 | K127: =+IF(YEAR(K4)>YEAR($H$130),0,1) -> 1 | L127: =+IF(YEAR(L4)>YEAR($H$130),0,1) -> 1 | M127: =+IF(YEAR(M4)>YEAR($H$130),0,1) -> 1 | N127: =+IF(YEAR(N4)>YEAR($H$130),0,1) -> 1 | O127: =+IF(YEAR(O4)>YEAR($H$130),0,1) -> 1 | P127: =+IF(YEAR(P4)>YEAR($H$130),0,1) -> 1
D129: Transaction expenses | G129: 3 | I129: =+IF(AND(I126>$G$130,YEAR(I4)=YEAR($H$130)),$G$129/$G$130*$G$130,IF(YEAR(I4)>YEAR($H$130),0,$G$129/$G$130*I126)) -> 0 | J129: =+IF(AND(J126>$G$130,YEAR(J4)=YEAR($H$130)),$G$129/$G$130*$G$130,IF(YEAR(J4)>YEAR($H$130),0,$G$129/$G$130*J126)) -> 0.42857143 | K129: =+IF(AND(K126>$G$130,YEAR(K4)=YEAR($H$130)),$G$129/$G$130*$G$130,IF(YEAR(K4)>YEAR($H$130),0,$G$129/$G$130*K126)) -> 0.85714286 | L129: =+IF(AND(L126>$G$130,YEAR(L4)=YEAR($H$130)),$G$129/$G$130*$G$130,IF(YEAR(L4)>YEAR($H$130),0,$G$129/$G$130*L126)) -> 1.2868885 | M129: =+IF(AND(M126>$G$130,YEAR(M4)=YEAR($H$130)),$G$129/$G$130*$G$130,IF(YEAR(M4)>YEAR($H$130),0,$G$129/$G$130*M126)) -> 1.7154599 | N129: =+IF(AND(N126>$G$130,YEAR(N4)=YEAR($H$130)),$G$129/$G$130*$G$130,IF(YEAR(N4)>YEAR($H$130),0,$G$129/$G$130*N126)) -> 2.1440313 | O129: =+IF(AND(O126>$G$130,YEAR(O4)=YEAR($H$130)),$G$129/$G$130*$G$130,IF(YEAR(O4)>YEAR($H$130),0,$G$129/$G$130*O126)) -> 2.5726027 | P129: =+IF(AND(P126>$G$130,YEAR(P4)=YEAR($H$130)),$G$129/$G$130*$G$130,IF(YEAR(P4)>YEAR($H$130),0,$G$129/$G$130*P126)) -> 3
D130: Years of amortization | G130: 7 | H130: =+EOMONTH(G125,G130*12) -> 48579 | I130: =+(I129-H129)*I127 -> 0 | J130: =+(J129-I129)*J127 -> 0.42857143 | K130: =+(K129-J129)*K127 -> 0.42857143 | L130: =+(L129-K129)*L127 -> 0.4297456 | M130: =+(M129-L129)*M127 -> 0.42857143 | N130: =+(N129-M129)*N127 -> 0.42857143 | O130: =+(O129-N129)*O127 -> 0.42857143 | P130: =+(P129-O129)*P127 -> 0.42739726

Sheet UPSLIDE_UndoFormatting
A1: 43 | B1: 22

Sheet UPSLIDE_Undo
A1: 43 | B1: 22
