Workbook

Sheet Instructions
B1: Project Galicia — Inditex (ITX.MC) | F1: Private & Confidential
B2: LBO Model — Instructions & Architecture Guide
C4: Step | D4: Reference Block (Linked) | E4: Explanation & Modeling Guidelines (Blue Font = User Input)
C5: 1 | D5: =+LBO!D9 -> Active Scenario Selector | E5: Scenario & Operating Drivers (Rows 7-17): Select Active Case in cell F9 (1 = Base, 2 = Bull, 3 = Bear) and customize scenario presets in E10:G17 (blue cells). Historical FY22A-FY25A figures are audited from Inditex Consolidated Annual Reports.
C6: 2 | D6: =+LBO!D21 -> Revenues | E6: Operating P&L & Pre-IFRS 16 Cash EBITDA Bridge (Rows 19-36): Projects Revenues, Gross Margin, and OpEx across FY26E-FY30E. Reconciles Reported Post-IFRS 16 EBITDA to Pre-IFRS 16 Cash EBITDA by deducting Fixed Cash Lease Outflows (Note 16 / CF Statement: €1,834m in FY25A; variable turnover rent of €670m is already inside OpEx).
C7: 3 | D7: =+LBO!D42 -> WK (Operating Working Capital) | E7: Operating Working Capital Schedule (Rows 42-48): Models Inventory, Receivables, and Payables as % of Revenues. Inditex operates with structural negative working capital (-€4,172m in FY25A, -10.5% of sales), so top-line growth generates positive cash inflows (-ΔWK).
C8: 4 | D8: =+LBO!D51 -> Capex & D&A (Owned PP&E + Intangibles) | E8: Capex & D&A Schedule (Rows 51-72): Tracks Owned PP&E and Intangible Assets (€12,778m at FY25A close, excluding IFRS 16 RoU assets). Depreciates existing net assets over E64 (10 yrs) and each new Capex vintage with half-year convention (E65 = 50%), linking total D&A directly to P&L Row 31.
C9: 5 | D9: =+LBO!D75 -> Debt Schedule (Senior TLA, Senior TLB & RCF with Cash Sweep) | E9: Multi-Tranche Debt & Cash Sweep Schedule (Rows 75-117): Models Senior TLA (1.5x EBITDA, E+2.75%, amortising 10/15/20/25/30%), Senior TLB (2.5x EBITDA, E+4.00%, 1% p.a. mandatory amortisation + 50% excess-cash sweep), and €3,000m RCF (auto-drawn if cash < minimum cash and repaid first).
C10: 6 | D10: =+LBO!D146 -> EBITDA reference (FY25A Pre-IFRS 16 Cash EBITDA) | E10: Free-Float Take-Private Perimeter & Sources & Uses (Rows 145-189): Acquires only the 35.65% free float at Offer Price = €55.42 * (1 + Premium %). The Ortega family (64.35%: Pontegadea 59.29% + Rosp Corunna 5.05%) rolls over 100% into Newco at the offer price. Excess cash above Minimum Cash (€3,000m) is deployed as a closing source.
C11: 7 | D11: =+LBO!D195 -> EBITDA Exit Multiple (Pre-IFRS 16) | E11: Exit Valuation, Returns (IRR / MoM) & Integrity Checks (Rows 192-232): Evaluates exit EV, net debt, and Sponsor/Family proceeds across FY26E-FY30E. Changing Exit Year (K149) dynamically updates headline IRR (F209) and MoM (F210). Includes a 3x3 sensitivity table (Premium x Leverage) and 6 automated integrity checks.

Sheet LBO
B1: Project Galicia — Inditex (ITX.MC)
A2: > | B2: LBO Model (Free-Float Take-Private & Family Rollover) | U2: Private & Confidential
A5: > | B5: > | C5: Operating model
B7: > | C7: Drivers | E7: 1 | F7: 2 | G7: 3 | H7: Active Case: | J7: 31-Jan | K7: 31-Jan | L7: 31-Jan | M7: 31-Jan | N7: 31-Jan | O7: 31-Jan | P7: 31-Jan | Q7: 31-Jan | R7: 31-Jan
D8: Operating Driver / Scenario Presets | E8: Base Case | F8: Bull Case | G8: Bear Case | H8: =CHOOSE($F$9,E8,F8,G8) -> Base Case | J8: 2022 | K8: =+J8+1 -> 2023 | L8: =+K8+1 -> 2024 | M8: =+L8+1 -> 2025 | N8: =+M8+1 -> 2026 | O8: =+N8+1 -> 2027 | P8: =+O8+1 -> 2028 | Q8: =+P8+1 -> 2029 | R8: =+Q8+1 -> 2030
B9: 1 | D9: Active Scenario Selector | F9: 1 | H9: =CHOOSE($F$9,E8,F8,G8) -> Base Case
D10: Revenue growth (% YoY) | E10: 0.055 | F10: 0.08 | G10: 0.0225 | H10: =CHOOSE($F$9,E10,F10,G10) -> 0.055 | J10: 0.175 | K10: 0.104 | L10: 0.075 | M10: 0.032 | N10: =+$H10 -> 0.055 | O10: =+$H10 -> 0.055 | P10: =+$H10 -> 0.055 | Q10: =+$H10 -> 0.055 | R10: =+$H10 -> 0.055
D11: Gross margin (% of revenues) | E11: 0.582 | F11: 0.59 | G11: 0.57 | H11: =CHOOSE($F$9,E11,F11,G11) -> 0.582 | J11: =+J23/J$21 -> 0.56983635 | K11: =+K23/K$21 -> 0.57757254 | L11: =+L23/L$21 -> 0.57835473 | M11: =+M23/M$21 -> 0.5825306 | N11: =+$H11 -> 0.582 | O11: =+$H11 -> 0.582 | P11: =+$H11 -> 0.582 | Q11: =+$H11 -> 0.582 | R11: =+$H11 -> 0.582
D12: OpEx growth (% YoY) | E12: 0.0425 | F12: 0.055 | G12: 0.0325 | H12: =CHOOSE($F$9,E12,F12,G12) -> 0.0425 | J12: 0.109 | K12: 0.1 | L12: 0.065 | M12: 0.028 | N12: =+$H12 -> 0.0425 | O12: =+$H12 -> 0.0425 | P12: =+$H12 -> 0.0425 | Q12: =+$H12 -> 0.0425 | R12: =+$H12 -> 0.0425
D13: Fixed lease cash outflow growth (%) | E13: 0.02 | F13: 0.03 | G13: 0.01 | H13: =CHOOSE($F$9,E13,F13,G13) -> 0.02 | J13: 0.05 | K13: =+K28/J28-1 -> 0.069093152 | L13: =+L28/K28-1 -> 0.039815349 | M13: =+M28/L28-1 -> 0.017758047 | N13: =+$H13 -> 0.02 | O13: =+$H13 -> 0.02 | P13: =+$H13 -> 0.02 | Q13: =+$H13 -> 0.02 | R13: =+$H13 -> 0.02
D14: Capex (% of revenues) | E14: 0.052 | F14: 0.0535 | G14: 0.049 | H14: =CHOOSE($F$9,E14,F14,G14) -> 0.052 | J14: =+J57/J$21 -> 0.043446222 | K14: =+K57/K$21 -> 0.052076668 | L14: =+L57/L$21 -> 0.069165459 | M14: =+M57/M$21 -> 0.068031306 | N14: =+$H14 -> 0.052 | O14: =+$H14 -> 0.052 | P14: =+$H14 -> 0.052 | Q14: =+$H14 -> 0.052 | R14: =+$H14 -> 0.052
D15: Inventory (% of revenues) | E15: 0.0815 | F15: 0.079 | G15: 0.085 | H15: =CHOOSE($F$9,E15,F15,G15) -> 0.0815 | J15: =+J43/J$21 -> 0.097976604 | K15: =+K43/K$21 -> 0.082510362 | L15: =+L43/L$21 -> 0.085965003 | M15: =+M43/M$21 -> 0.081502107 | N15: =+$H15 -> 0.0815 | O15: =+$H15 -> 0.0815 | P15: =+$H15 -> 0.0815 | Q15: =+$H15 -> 0.0815 | R15: =+$H15 -> 0.0815
D16: Receivables (% of revenues) | E16: 0.0292 | F16: 0.0285 | G16: 0.03 | H16: =CHOOSE($F$9,E16,F16,G16) -> 0.0292 | J16: =+J44/J$21 -> 0.026129141 | K16: =+K44/K$21 -> 0.028875845 | L16: =+L44/L$21 -> 0.028163181 | M16: =+M44/M$21 -> 0.029249448 | N16: =+$H16 -> 0.0292 | O16: =+$H16 -> 0.0292 | P16: =+$H16 -> 0.0292 | Q16: =+$H16 -> 0.0292 | R16: =+$H16 -> 0.0292
D17: Payables (% of revenues, negative) | E17: -0.2154 | F17: -0.2155 | G17: -0.213 | H17: =CHOOSE($F$9,E17,F17,G17) -> -0.2154 | J17: =+J45/J$21 -> -0.20144923 | K17: =+K45/K$21 -> -0.20772248 | L17: =+L45/L$21 -> -0.22235452 | M17: =+M45/M$21 -> -0.21540739 | N17: =+$H17 -> -0.2154 | O17: =+$H17 -> -0.2154 | P17: =+$H17 -> -0.2154 | Q17: =+$H17 -> -0.2154 | R17: =+$H17 -> -0.2154
B19: > | C19: P&L | J19: 31-Jan | K19: 31-Jan | L19: 31-Jan | M19: 31-Jan | N19: 31-Jan | O19: 31-Jan | P19: 31-Jan | Q19: 31-Jan | R19: 31-Jan | U19: CAGR 22A-25A | V19: CAGR 25A-30E
C20: €m | J20: 2022 | K20: =+J20+1 -> 2023 | L20: =+K20+1 -> 2024 | M20: =+L20+1 -> 2025 | N20: =+M20+1 -> 2026 | O20: =+N20+1 -> 2027 | P20: =+O20+1 -> 2028 | Q20: =+P20+1 -> 2029 | R20: =+Q20+1 -> 2030
B21: 2 | D21: Revenues | J21: 32569 | K21: 35947 | L21: 38632 | M21: 39864 | N21: =+M21*(1+N10) -> 42056.52 | O21: =+N21*(1+O10) -> 44369.629 | P21: =+O21*(1+P10) -> 46809.958 | Q21: =+P21*(1+Q10) -> 49384.506 | R21: =+Q21*(1+R10) -> 52100.654 | U21: =+IFERROR((M21/J21)^(1/(M$20-J$20))-1,0) -> 0.06969217 | V21: =+IFERROR((R21/M21)^(1/(R$20-M$20))-1,"n.a.") -> 0.055
D22: COGS | J22: =+J23-J21 -> -14010 | K22: =+K23-K21 -> -15185 | L22: =+L23-L21 -> -16289 | M22: =+M23-M21 -> -16642 | N22: =+N23-N21 -> -17579.625 | O22: =+O23-O21 -> -18546.505 | P22: =+P23-P21 -> -19566.563 | Q22: =+Q23-Q21 -> -20642.723 | R22: =+R23-R21 -> -21778.073 | U22: =+IFERROR((M22/J22)^(1/(M$20-J$20))-1,0) -> 0.059064622 | V22: =+IFERROR((R22/M22)^(1/(R$20-M$20))-1,"n.a.") -> 0.055268045
D23: Gross margin | J23: 18559 | K23: 20762 | L23: 22343 | M23: 23222 | N23: =+N21*N11 -> 24476.895 | O23: =+O21*O11 -> 25823.124 | P23: =+P21*P11 -> 27243.396 | Q23: =+Q21*Q11 -> 28741.782 | R23: =+R21*R11 -> 30322.58 | U23: =+IFERROR((M23/J23)^(1/(M$20-J$20))-1,0) -> 0.077577091 | V23: =+IFERROR((R23/M23)^(1/(R$20-M$20))-1,"n.a.") -> 0.054807738
D24: % margin | J24: =+IFERROR(J23/J$21,0) -> 0.56983635 | K24: =+IFERROR(K23/K$21,0) -> 0.57757254 | L24: =+IFERROR(L23/L$21,0) -> 0.57835473 | M24: =+IFERROR(M23/M$21,0) -> 0.5825306 | N24: =+IFERROR(N23/N$21,0) -> 0.582 | O24: =+IFERROR(O23/O$21,0) -> 0.582 | P24: =+IFERROR(P23/P$21,0) -> 0.582 | Q24: =+IFERROR(Q23/Q$21,0) -> 0.582 | R24: =+IFERROR(R23/R$21,0) -> 0.582 | U24: =+IFERROR((M24/J24)^(1/(M$20-J$20))-1,0) -> 0.0073712057 | V24: =+IFERROR((R24/M24)^(1/(R$20-M$20))-1,"n.a.") -> -0.00018223849
D25: Opex (incl. variable turnover rent) | J25: -9910 | K25: -10912 | L25: -11615 | M25: -11955 | N25: =+M25*(1+N12) -> -12463.087 | O25: =+N25*(1+O12) -> -12992.769 | P25: =+O25*(1+P12) -> -13544.961 | Q25: =+P25*(1+Q12) -> -14120.622 | R25: =+Q25*(1+R12) -> -14720.749 | U25: =+IFERROR((M25/J25)^(1/(M$20-J$20))-1,0) -> 0.064531806 | V25: =+IFERROR((R25/M25)^(1/(R$20-M$20))-1,"n.a.") -> 0.0425
D26: Reported EBITDA (Post-IFRS 16) | J26: =+J23+J25 -> 8649 | K26: =+K23+K25 -> 9850 | L26: =+L23+L25 -> 10728 | M26: =+M23+M25 -> 11267 | N26: =+N23+N25 -> 12013.807 | O26: =+O23+O25 -> 12830.355 | P26: =+P23+P25 -> 13698.434 | Q26: =+Q23+Q25 -> 14621.16 | R26: =+R23+R25 -> 15601.832 | U26: =+IFERROR((M26/J26)^(1/(M$20-J$20))-1,0) -> 0.09214625 | V26: =+IFERROR((R26/M26)^(1/(R$20-M$20))-1,"n.a.") -> 0.067267929
D27: % margin (Post-IFRS 16) | J27: =+IFERROR(J26/J$21,0) -> 0.26555927 | K27: =+IFERROR(K26/K$21,0) -> 0.27401452 | L27: =+IFERROR(L26/L$21,0) -> 0.27769725 | M27: =+IFERROR(M26/M$21,0) -> 0.28263596 | N27: =+IFERROR(N26/N$21,0) -> 0.28565861 | O27: =+IFERROR(O26/O$21,0) -> 0.28916977 | P27: =+IFERROR(P26/P$21,0) -> 0.29263932 | Q27: =+IFERROR(Q26/Q$21,0) -> 0.29606776 | R27: =+IFERROR(R26/R$21,0) -> 0.29945559 | U27: =+IFERROR((M27/J27)^(1/(M$20-J$20))-1,0) -> 0.020991161 | V27: =+IFERROR((R27/M27)^(1/(R$20-M$20))-1,"n.a.") -> 0.011628369
D28: Less: Fixed cash lease outflow (IFRS 16 adj.) | J28: -1621 | K28: -1733 | L28: -1802 | M28: -1834 | N28: =+M28*(1+N13) -> -1870.68 | O28: =+N28*(1+O13) -> -1908.0936 | P28: =+O28*(1+P13) -> -1946.2555 | Q28: =+P28*(1+Q13) -> -1985.1806 | R28: =+Q28*(1+R13) -> -2024.8842 | U28: =+IFERROR((M28/J28)^(1/(M$20-J$20))-1,0) -> 0.042010525 | V28: =+IFERROR((R28/M28)^(1/(R$20-M$20))-1,"n.a.") -> 0.02
D29: Pre-IFRS 16 Cash EBITDA (LBO Driver) | J29: =+J26+J28 -> 7028 | K29: =+K26+K28 -> 8117 | L29: =+L26+L28 -> 8926 | M29: =+M26+M28 -> 9433 | N29: =+N26+N28 -> 10143.127 | O29: =+O26+O28 -> 10922.262 | P29: =+P26+P28 -> 11752.179 | Q29: =+Q26+Q28 -> 12635.98 | R29: =+R26+R28 -> 13576.948 | U29: =+IFERROR((M29/J29)^(1/(M$20-J$20))-1,0) -> 0.1030775 | V29: =+IFERROR((R29/M29)^(1/(R$20-M$20))-1,"n.a.") -> 0.075549645
D30: % margin (Pre-IFRS 16) | J30: =+IFERROR(J29/J$21,0) -> 0.21578802 | K30: =+IFERROR(K29/K$21,0) -> 0.22580466 | L30: =+IFERROR(L29/L$21,0) -> 0.23105198 | M30: =+IFERROR(M29/M$21,0) -> 0.23662954 | N30: =+IFERROR(N29/N$21,0) -> 0.24117847 | O30: =+IFERROR(O29/O$21,0) -> 0.24616527 | P30: =+IFERROR(P29/P$21,0) -> 0.25106151 | Q30: =+IFERROR(Q29/Q$21,0) -> 0.25586931 | R30: =+IFERROR(R29/R$21,0) -> 0.26059073 | U30: =+IFERROR((M30/J30)^(1/(M$20-J$20))-1,0) -> 0.031210225 | V30: =+IFERROR((R30/M30)^(1/(R$20-M$20))-1,"n.a.") -> 0.019478336
D31: D&A (Owned PP&E & intangibles) | J31: =+J55 -> -1417 | K31: =+K55 -> -1558 | L31: =+L55 -> -1638 | M31: =+M55 -> -1674 | N31: =+N55 -> -1387.147 | O31: =+O55 -> -1611.8549 | P31: =+P55 -> -1848.9219 | Q31: =+Q55 -> -2099.0275 | R31: =+R55 -> -2362.8889 | U31: =+IFERROR((M31/J31)^(1/(M$20-J$20))-1,0) -> 0.057130333 | V31: =+IFERROR((R31/M31)^(1/(R$20-M$20))-1,"n.a.") -> 0.071365283
D32: Adj. EBIT (Pre-IFRS 16) | J32: =+J29+J31 -> 5611 | K32: =+K29+K31 -> 6559 | L32: =+L29+L31 -> 7288 | M32: =+M29+M31 -> 7759 | N32: =+N29+N31 -> 8755.9802 | O32: =+O29+O31 -> 9310.4066 | P32: =+P29+P31 -> 9903.2569 | Q32: =+Q29+Q31 -> 10536.952 | R32: =+R29+R31 -> 11214.059 | U32: =+IFERROR((M32/J32)^(1/(M$20-J$20))-1,0) -> 0.11409398 | V32: =+IFERROR((R32/M32)^(1/(R$20-M$20))-1,"n.a.") -> 0.076443933
D33: Interests (LBO debt & RCF fees) | F33: =+F160 -> 0.0653125 | J33: -69 | K33: 61 | L33: 23 | M33: 23 | N33: =+N116 -> -2425.9376 | O33: =+O116 -> -2213.4801 | P33: =+P116 -> -1913.1155 | Q33: =+Q116 -> -1544.6372 | R33: =+R116 -> -1114.745
D34: EBT | J34: =+SUM(J32:J33) -> 5542 | K34: =+SUM(K32:K33) -> 6620 | L34: =+SUM(L32:L33) -> 7311 | M34: =+SUM(M32:M33) -> 7782 | N34: =+SUM(N32:N33) -> 6330.0426 | O34: =+SUM(O32:O33) -> 7096.9265 | P34: =+SUM(P32:P33) -> 7990.1414 | Q34: =+SUM(Q32:Q33) -> 8992.3149 | R34: =+SUM(R32:R33) -> 10099.314 | U34: =+IFERROR((M34/J34)^(1/(M$20-J$20))-1,0) -> 0.11980285 | V34: =+IFERROR((R34/M34)^(1/(R$20-M$20))-1,"n.a.") -> 0.053513553
D35: Tax | F35: 0.224 | J35: -1211 | K35: -1475 | L35: -1700 | M35: -1800 | N35: =+IF(N34>0,-N34*$F$35,0) -> -1417.9295 | O35: =+IF(O34>0,-O34*$F$35,0) -> -1589.7115 | P35: =+IF(P34>0,-P34*$F$35,0) -> -1789.7917 | Q35: =+IF(Q34>0,-Q34*$F$35,0) -> -2014.2785 | R35: =+IF(R34>0,-R34*$F$35,0) -> -2262.2463 | U35: =+IFERROR((M35/J35)^(1/(M$20-J$20))-1,0) -> 0.14123773 | V35: =+IFERROR((R35/M35)^(1/(R$20-M$20))-1,"n.a.") -> 0.046775321
D36: Net income | J36: =+SUM(J34:J35) -> 4331 | K36: =+SUM(K34:K35) -> 5145 | L36: =+SUM(L34:L35) -> 5611 | M36: =+SUM(M34:M35) -> 5982 | N36: =+SUM(N34:N35) -> 4912.1131 | O36: =+SUM(O34:O35) -> 5507.215 | P36: =+SUM(P34:P35) -> 6200.3498 | Q36: =+SUM(Q34:Q35) -> 6978.0363 | R36: =+SUM(R34:R35) -> 7837.0674 | U36: =+IFERROR((M36/J36)^(1/(M$20-J$20))-1,0) -> 0.11366031 | V36: =+IFERROR((R36/M36)^(1/(R$20-M$20))-1,"n.a.") -> 0.05550777
B39: > | C39: BS | J39: 31-Jan | K39: 31-Jan | L39: 31-Jan | M39: 31-Jan | N39: 31-Jan | O39: 31-Jan | P39: 31-Jan | Q39: 31-Jan | R39: 31-Jan
C40: €m | J40: =+J20 -> 2022 | K40: =+J40+1 -> 2023 | L40: =+K40+1 -> 2024 | M40: =+L40+1 -> 2025 | N40: =+M40+1 -> 2026 | O40: =+N40+1 -> 2027 | P40: =+O40+1 -> 2028 | Q40: =+P40+1 -> 2029 | R40: =+Q40+1 -> 2030
B42: 3 | C42: > | D42: WK (Operating Working Capital)
D43: Inventory | J43: 3191 | K43: 2966 | L43: 3321 | M43: 3249 | N43: =+N$21*N15 -> 3427.6064 | O43: =+O$21*O15 -> 3616.1247 | P43: =+P$21*P15 -> 3815.0116 | Q43: =+Q$21*Q15 -> 4024.8372 | R43: =+R$21*R15 -> 4246.2033
D44: Receivables | J44: 851 | K44: 1038 | L44: 1088 | M44: 1166 | N44: =+N$21*N16 -> 1228.0504 | O44: =+O$21*O16 -> 1295.5932 | P44: =+P$21*P16 -> 1366.8508 | Q44: =+Q$21*Q16 -> 1442.0276 | R44: =+R$21*R16 -> 1521.3391
D45: Payables | J45: -6561 | K45: -7467 | L45: -8590 | M45: -8587 | N45: =+N$21*N17 -> -9058.9744 | O45: =+O$21*O17 -> -9557.218 | P45: =+P$21*P17 -> -10082.865 | Q45: =+Q$21*Q17 -> -10637.423 | R45: =+R$21*R17 -> -11222.481
D46: Total WK (EoP balance) | J46: =+SUM(J43:J45) -> -2519 | K46: =+SUM(K43:K45) -> -3463 | L46: =+SUM(L43:L45) -> -4181 | M46: =+SUM(M43:M45) -> -4172 | N46: =+SUM(N43:N45) -> -4403.3176 | O46: =+SUM(O43:O45) -> -4645.5001 | P46: =+SUM(P43:P45) -> -4901.0026 | Q46: =+SUM(Q43:Q45) -> -5170.5578 | R46: =+SUM(R43:R45) -> -5454.9384
D47: WK % of revenues | J47: =+IFERROR(J46/J$21,0) -> -0.077343486 | K47: =+IFERROR(K46/K$21,0) -> -0.096336273 | L47: =+IFERROR(L46/L$21,0) -> -0.10822634 | M47: =+IFERROR(M46/M$21,0) -> -0.10465583 | N47: =+IFERROR(N46/N$21,0) -> -0.1047 | O47: =+IFERROR(O46/O$21,0) -> -0.1047 | P47: =+IFERROR(P46/P$21,0) -> -0.1047 | Q47: =+IFERROR(Q46/Q$21,0) -> -0.1047 | R47: =+IFERROR(R46/R$21,0) -> -0.1047
D48: Cash flow from WK (-ΔWK) | J48: 0 | K48: =+(J46-K46) -> 944 | L48: =+(K46-L46) -> 718 | M48: =+(L46-M46) -> -9 | N48: =+(M46-N46) -> 231.31764 | O48: =+(N46-O46) -> 242.18247 | P48: =+(O46-P46) -> 255.50251 | Q48: =+(P46-Q46) -> 269.55514 | R48: =+(Q46-R46) -> 284.38068
B51: 4 | C51: > | D51: Capex & D&A (Owned PP&E + Intangibles)
D53: BoP Net Fixed Assets | J53: 8383 | K53: =+J56 -> 8401 | L53: =+K56 -> 9560 | M53: =+L56 -> 11416 | N53: =+M56 -> 12778 | O53: =+N56 -> 13577.792 | P53: =+O56 -> 14273.158 | Q53: =+P56 -> 14858.354 | R53: =+Q56 -> 15327.321
D54: Capex | J54: =+J57 -> 1415 | K54: =+K57 -> 1872 | L54: =+L57 -> 2672 | M54: =+M57 -> 2712 | N54: =+N57 -> 2186.939 | O54: =+O57 -> 2307.2207 | P54: =+P57 -> 2434.1178 | Q54: =+Q57 -> 2567.9943 | R54: =+R57 -> 2709.234
D55: D&A | J55: -1417 | K55: -1558 | L55: -1638 | M55: -1674 | N55: =+N61+N72 -> -1387.147 | O55: =+O61+O72 -> -1611.8549 | P55: =+P61+P72 -> -1848.9219 | Q55: =+Q61+Q72 -> -2099.0275 | R55: =+R61+R72 -> -2362.8889
D56: EoP Net Fixed Assets | J56: 8401 | K56: 9560 | L56: 11416 | M56: 12778 | N56: =+N53+N54+N55 -> 13577.792 | O56: =+O53+O54+O55 -> 14273.158 | P56: =+P53+P54+P55 -> 14858.354 | Q56: =+Q53+Q54+Q55 -> 15327.321 | R56: =+R53+R54+R55 -> 15673.666
D57: Capex (Ordinary + Logistics) | J57: 1415 | K57: 1872 | L57: 2672 | M57: 2712 | N57: =+N21*N14 -> 2186.939 | O57: =+O21*O14 -> 2307.2207 | P57: =+P21*P14 -> 2434.1178 | Q57: =+Q21*Q14 -> 2567.9943 | R57: =+R21*R14 -> 2709.234
D59: Existing fixed assets D&A
D60: BoP existing net assets | N60: =+M62 -> 12778 | O60: =+N62 -> 11500.2 | P60: =+O62 -> 10222.4 | Q60: =+P62 -> 8944.6 | R60: =+Q62 -> 7666.8
D61: D&A of existing assets | N61: =-MIN(N60,$M$62/$E$64) -> -1277.8 | O61: =-MIN(O60,$M$62/$E$64) -> -1277.8 | P61: =-MIN(P60,$M$62/$E$64) -> -1277.8 | Q61: =-MIN(Q60,$M$62/$E$64) -> -1277.8 | R61: =-MIN(R60,$M$62/$E$64) -> -1277.8
D62: EoP existing net assets | M62: =+M56 -> 12778 | N62: =+N60+N61 -> 11500.2 | O62: =+O60+O61 -> 10222.4 | P62: =+P60+P61 -> 8944.6 | Q62: =+Q60+Q61 -> 7666.8 | R62: =+R60+R61 -> 6389
D64: Asset lifetime (years) | E64: 10
D65: First period D&A impact | E65: 0.5
G66: Vintage | H66: Capex (€m)
G67: =+N$20 -> 2026 | H67: =+N$57 -> 2186.939 | N67: =-(($H67/$E$64*$E$65)) -> -109.34695 | O67: =-(MIN(SUM($H67,$N67:N67),$H67/$E$64)) -> -218.6939 | P67: =-(MIN(SUM($H67,$N67:O67),$H67/$E$64)) -> -218.6939 | Q67: =-(MIN(SUM($H67,$N67:P67),$H67/$E$64)) -> -218.6939 | R67: =-(MIN(SUM($H67,$N67:Q67),$H67/$E$64)) -> -218.6939
G68: =+O$20 -> 2027 | H68: =+O$57 -> 2307.2207 | N68: 0 | O68: =-(($H68/$E$64*$E$65)) -> -115.36103 | P68: =-(MIN(SUM($H68,$O68:O68),$H68/$E$64)) -> -230.72207 | Q68: =-(MIN(SUM($H68,$O68:P68),$H68/$E$64)) -> -230.72207 | R68: =-(MIN(SUM($H68,$O68:Q68),$H68/$E$64)) -> -230.72207
G69: =+P$20 -> 2028 | H69: =+P$57 -> 2434.1178 | N69: 0 | O69: 0 | P69: =-(($H69/$E$64*$E$65)) -> -121.70589 | Q69: =-(MIN(SUM($H69,$P69:P69),$H69/$E$64)) -> -243.41178 | R69: =-(MIN(SUM($H69,$P69:Q69),$H69/$E$64)) -> -243.41178
G70: =+Q$20 -> 2029 | H70: =+Q$57 -> 2567.9943 | N70: 0 | O70: 0 | P70: 0 | Q70: =-(($H70/$E$64*$E$65)) -> -128.39972 | R70: =-(MIN(SUM($H70,$Q70:Q70),$H70/$E$64)) -> -256.79943
G71: =+R$20 -> 2030 | H71: =+R$57 -> 2709.234 | N71: 0 | O71: 0 | P71: 0 | Q71: 0 | R71: =-(($H71/$E$64*$E$65)) -> -135.4617
G72: Total new capex D&A | N72: =SUM(N67:N71) -> -109.34695 | O72: =SUM(O67:O71) -> -334.05494 | P72: =SUM(P67:P71) -> -571.12186 | Q72: =SUM(Q67:Q71) -> -821.22747 | R72: =SUM(R67:R71) -> -1085.0889
B75: 5 | C75: > | D75: Debt Schedule (Senior TLA, Senior TLB & RCF with Cash Sweep)
D77: Senior Term Loan A (TLA — Amortising)
D78: BoP TLA | M78: 0 | N78: =+M81 -> 14149.5 | O78: =+N81 -> 12734.55 | P78: =+O81 -> 10612.125 | Q78: =+P81 -> 7782.225 | R78: =+Q81 -> 4244.85
D79: Initial draw / increase | M79: =+E172 -> 14149.5 | N79: 0 | O79: 0 | P79: 0 | Q79: 0 | R79: 0
D80: Scheduled repayment | M80: 0 | N80: =-MIN(N78,$M$81*N$82) -> -1414.95 | O80: =-MIN(O78,$M$81*O$82) -> -2122.425 | P80: =-MIN(P78,$M$81*P$82) -> -2829.9 | Q80: =-MIN(Q78,$M$81*Q$82) -> -3537.375 | R80: =-MIN(R78,$M$81*R$82) -> -4244.85 | T80: =+SUM(N80:R80)+M81 -> 0
D81: EoP TLA | M81: =+SUM(M78:M80) -> 14149.5 | N81: =+SUM(N78:N80) -> 12734.55 | O81: =+SUM(O78:O80) -> 10612.125 | P81: =+SUM(P78:P80) -> 7782.225 | Q81: =+SUM(Q78:Q80) -> 4244.85 | R81: =+SUM(R78:R80) -> 0
D82: TLA scheduled amortisation % | N82: 0.1 | O82: 0.15 | P82: 0.2 | Q82: 0.25 | R82: =1-SUM(N82:Q82) -> 0.3 | T82: =+SUM(N82:R82)-1 -> 0
D83: TLA cash interest | N83: =-$F$161*AVERAGE(N78,N81) -> -772.91644 | O83: =-$F$161*AVERAGE(O78,O81) -> -671.21691 | P83: =-$F$161*AVERAGE(P78,P81) -> -528.83756 | Q83: =-$F$161*AVERAGE(Q78,Q81) -> -345.77841 | R83: =-$F$161*AVERAGE(R78,R81) -> -122.03944
D85: Senior Term Loan B (TLB — 1% Amort + 50% Cash Sweep)
D86: BoP TLB | M86: 0 | N86: =+M91 -> 23582.5 | O86: =+N91 -> 22000.243 | P86: =+O91 -> 19743.311 | Q86: =+P91 -> 17094.467 | R86: =+Q91 -> 14149.421
D87: Initial draw / increase | M87: =+E173 -> 23582.5 | N87: 0 | O87: 0 | P87: 0 | Q87: 0 | R87: 0
D88: Mandatory amortisation (1.0% p.a.) | M88: 0 | N88: =-MIN(N86,$M$91*N$92) -> -235.825 | O88: =-MIN(O86,$M$91*O$92) -> -235.825 | P88: =-MIN(P86,$M$91*P$92) -> -235.825 | Q88: =-MIN(Q86,$M$91*Q$92) -> -235.825 | R88: =-MIN(R86,$M$91*R$92) -> -235.825
D89: TLB balance after mandatory amortisation | M89: =+M86+M87+M88 -> 23582.5 | N89: =+SUM(N86:N88) -> 23346.675 | O89: =+SUM(O86:O88) -> 21764.418 | P89: =+SUM(P86:P88) -> 19507.486 | Q89: =+SUM(Q86:Q88) -> 16858.642 | R89: =+SUM(R86:R88) -> 13913.596
D90: Optional cash sweep repayment (50.0% sweep) | M90: 0 | N90: =-MIN(N89,MAX(0,N133+N134)*$F$164) -> -1346.4318 | O90: =-MIN(O89,MAX(0,O133+O134)*$F$164) -> -2021.1068 | P90: =-MIN(P89,MAX(0,P133+P134)*$F$164) -> -2413.019 | Q90: =-MIN(Q89,MAX(0,Q133+Q134)*$F$164) -> -2709.2218 | R90: =-MIN(R89,MAX(0,R133+R134)*$F$164) -> -3001.8249
D91: EoP TLB | M91: =+M89+M90 -> 23582.5 | N91: =+N89+N90 -> 22000.243 | O91: =+O89+O90 -> 19743.311 | P91: =+P89+P90 -> 17094.467 | Q91: =+Q89+Q90 -> 14149.421 | R91: =+R89+R90 -> 10911.771
D92: TLB mandatory amortisation % | N92: =+$F$163 -> 0.01 | O92: =+$F$163 -> 0.01 | P92: =+$F$163 -> 0.01 | Q92: =+$F$163 -> 0.01 | R92: =+$F$163 -> 0.01
D93: TLB cash interest | N93: =-$F$162*IF($F$168=1,AVERAGE(N86,N91),AVERAGE(N86,N89)) -> -1642.5211 | O93: =-$F$162*IF($F$168=1,AVERAGE(O86,O91),AVERAGE(O86,O89)) -> -1531.7631 | P93: =-$F$162*IF($F$168=1,AVERAGE(P86,P91),AVERAGE(P86,P89)) -> -1373.7779 | Q93: =-$F$162*IF($F$168=1,AVERAGE(Q86,Q91),AVERAGE(Q86,Q89)) -> -1188.3588 | R93: =-$F$162*IF($F$168=1,AVERAGE(R86,R91),AVERAGE(R86,R89)) -> -982.20556
D95: Revolving Credit Facility (RCF — Liquidity Line)
D96: BoP RCF drawn | M96: 0 | N96: =+M98 -> 0 | O96: =+N98 -> 0 | P96: =+O98 -> 0 | Q96: =+P98 -> 0 | R96: =+Q98 -> 0
D97: RCF draw / (repayment) | M97: =+E174 -> 0 | N97: =+IF(N133<0,MIN($F$165-N96,-N133),-MIN(N96,N133)) -> 0 | O97: =+IF(O133<0,MIN($F$165-O96,-O133),-MIN(O96,O133)) -> 0 | P97: =+IF(P133<0,MIN($F$165-P96,-P133),-MIN(P96,P133)) -> 0 | Q97: =+IF(Q133<0,MIN($F$165-Q96,-Q133),-MIN(Q96,Q133)) -> 0 | R97: =+IF(R133<0,MIN($F$165-R96,-R133),-MIN(R96,R133)) -> 0
D98: EoP RCF drawn | M98: =+M96+M97 -> 0 | N98: =+N96+N97 -> 0 | O98: =+O96+O97 -> 0 | P98: =+P96+P97 -> 0 | Q98: =+Q96+Q97 -> 0 | R98: =+R96+R97 -> 0
D99: Undrawn RCF available | M99: =+$F$165-M98 -> 3000 | N99: =+MAX(0,$F$165-N98) -> 3000 | O99: =+MAX(0,$F$165-O98) -> 3000 | P99: =+MAX(0,$F$165-P98) -> 3000 | Q99: =+MAX(0,$F$165-Q98) -> 3000 | R99: =+MAX(0,$F$165-R98) -> 3000
D100: RCF interest & commitment fee | N100: =-(N96*$F$166+MAX(0,$F$165-N96)*$F$167) -> -10.5 | O100: =-(O96*$F$166+MAX(0,$F$165-O96)*$F$167) -> -10.5 | P100: =-(P96*$F$166+MAX(0,$F$165-P96)*$F$167) -> -10.5 | Q100: =-(Q96*$F$166+MAX(0,$F$165-Q96)*$F$167) -> -10.5 | R100: =-(R96*$F$166+MAX(0,$F$165-R96)*$F$167) -> -10.5
D111: Total LBO Debt Summary
D112: BoP total debt | M112: 0 | N112: =+N78+N86+N96 -> 37732 | O112: =+O78+O86+O96 -> 34734.793 | P112: =+P78+P86+P96 -> 30355.436 | Q112: =+Q78+Q86+Q96 -> 24876.692 | R112: =+R78+R86+R96 -> 18394.271
D113: Mandatory debt service (TLA + TLB) | M113: =+M79+M87+M97 -> 37732 | N113: =+N80+N88 -> -1650.775 | O113: =+O80+O88 -> -2358.25 | P113: =+P80+P88 -> -3065.725 | Q113: =+Q80+Q88 -> -3773.2 | R113: =+R80+R88 -> -4480.675
D114: Optional cash sweep & RCF net change | M114: 0 | N114: =+N90+N97 -> -1346.4318 | O114: =+O90+O97 -> -2021.1068 | P114: =+P90+P97 -> -2413.019 | Q114: =+Q90+Q97 -> -2709.2218 | R114: =+R90+R97 -> -3001.8249
D115: EoP total financial debt | M115: =+M81+M91+M98 -> 37732 | N115: =+N81+N91+N98 -> 34734.793 | O115: =+O81+O91+O98 -> 30355.436 | P115: =+P81+P91+P98 -> 24876.692 | Q115: =+Q81+Q91+Q98 -> 18394.271 | R115: =+R81+R91+R98 -> 10911.771
D116: Total cash interest & commitment fees | N116: =+N83+N93+N100 -> -2425.9376 | O116: =+O83+O93+O100 -> -2213.4801 | P116: =+P83+P93+P100 -> -1913.1155 | Q116: =+Q83+Q93+Q100 -> -1544.6372 | R116: =+R83+R93+R100 -> -1114.745
D117: Net Debt / Pre-IFRS 16 EBITDA (x) | M117: =+(M115-M140)/M29 -> 3.6819676 | N117: =+(N115-N140)/N29 -> 2.9959559 | O117: =+(O115-O140)/O29 -> 2.3195132 | P117: =+(P115-P140)/P29 -> 1.6561757 | Q117: =+(Q115-Q140)/Q29 -> 1.0038833 | R117: =+(R115-R140)/R29 -> 0.36163841
B121: > | C121: CF | J121: 31-Jan | K121: 31-Jan | L121: 31-Jan | M121: 31-Jan | N121: 31-Jan | O121: 31-Jan | P121: 31-Jan | Q121: 31-Jan | R121: 31-Jan
C122: €m | J122: =+J20 -> 2022 | K122: =+J122+1 -> 2023 | L122: =+K122+1 -> 2024 | M122: =+L122+1 -> 2025 | N122: =+M122+1 -> 2026 | O122: =+N122+1 -> 2027 | P122: =+O122+1 -> 2028 | Q122: =+P122+1 -> 2029 | R122: =+Q122+1 -> 2030
D124: Pre-IFRS 16 Cash EBITDA | J124: =+J29 -> 7028 | K124: =+K29 -> 8117 | L124: =+L29 -> 8926 | M124: =+M29 -> 9433 | N124: =+N29 -> 10143.127 | O124: =+O29 -> 10922.262 | P124: =+P29 -> 11752.179 | Q124: =+Q29 -> 12635.98 | R124: =+R29 -> 13576.948
D125: Taxes | J125: =+J35 -> -1211 | K125: =+K35 -> -1475 | L125: =+L35 -> -1700 | M125: =+M35 -> -1800 | N125: =+N35 -> -1417.9295 | O125: =+O35 -> -1589.7115 | P125: =+P35 -> -1789.7917 | Q125: =+Q35 -> -2014.2785 | R125: =+R35 -> -2262.2463
D126: Wk (Cash flow from working capital) | J126: =+J48 -> 0 | K126: =+K48 -> 944 | L126: =+L48 -> 718 | M126: =+M48 -> -9 | N126: =+N48 -> 231.31764 | O126: =+O48 -> 242.18247 | P126: =+P48 -> 255.50251 | Q126: =+Q48 -> 269.55514 | R126: =+R48 -> 284.38068
D127: Capex | J127: =-J54 -> -1415 | K127: =-K54 -> -1872 | L127: =-L54 -> -2672 | M127: =-M54 -> -2712 | N127: =-N54 -> -2186.939 | O127: =-O54 -> -2307.2207 | P127: =-P54 -> -2434.1178 | Q127: =-Q54 -> -2567.9943 | R127: =-R54 -> -2709.234
D128: CF for debt service (CFADS) | J128: =+SUM(J124:J127) -> 4402 | K128: =+SUM(K124:K127) -> 5714 | L128: =+SUM(L124:L127) -> 5272 | M128: =+SUM(M124:M127) -> 4912 | N128: =+SUM(N124:N127) -> 6769.5762 | O128: =+SUM(O124:O127) -> 7267.5118 | P128: =+SUM(P124:P127) -> 7783.7718 | Q128: =+SUM(Q124:Q127) -> 8323.2619 | R128: =+SUM(R124:R127) -> 8889.848
D130: Interests & commitment fees | N130: =+N116 -> -2425.9376 | O130: =+O116 -> -2213.4801 | P130: =+P116 -> -1913.1155 | Q130: =+Q116 -> -1544.6372 | R130: =+R116 -> -1114.745
D131: Mandatory debt repayment (TLA + TLB) | N131: =+N113 -> -1650.775 | O131: =+O113 -> -2358.25 | P131: =+P113 -> -3065.725 | Q131: =+Q113 -> -3773.2 | R131: =+R113 -> -4480.675
D132: FCF after mandatory debt service | N132: =+N128+N130+N131 -> 2692.8636 | O132: =+O128+O130+O131 -> 2695.7817 | P132: =+P128+P130+P131 -> 2804.9313 | Q132: =+Q128+Q130+Q131 -> 3005.4246 | R132: =+R128+R130+R131 -> 3294.428
...
