Workbook

Sheet Instructions
B1: Project Galicia v3 — Inditex (ITX.MC) | F1: Strictly Private & Confidential
A2: > | B2: Institutional Multi-Sheet LBO Model — 100% Take-Private + Amancio Ortega Rollover (2025A–2032E)
C4: Tab | D4: Worksheet Name | E4: Key Legal, Financial & Tax Features + Interactive Switches (Blue Font / Soft Yellow Fill)
C5: 1 | D5: LBO Summary | E5: 100% Take-Private Executive Dashboard: Amancio Ortega rolls over 25.0% (F14) into TopCo under the tax-neutral FEAC regime (Art. 87 LIS), while BidCo acquires 75.0% via a Take-Private OPA at a 12.0% premium (€62.07/sh). Includes €1,000m Minimum Operational Cash Floor (F18), TopCo Equity split (55.8% Sponsor PE / 44.2% Amancio), 4-Tier Institutional GP/LP Equity Waterfall (85% Passive LPs / 15% Lead GP, 8% Hurdle, 100% Catch-Up & 20% Carried Interest), 7-Year Exit Matrix (2026E–2032E), and Dual Sensitivity Tables.
C6: 2 | D6: Active Case | E6: 100% Inditex Consolidated Operating Model (2022A–2032E): Because BidCo owns 100.0% of Inditex post-squeeze-out, there is zero minority leakage. Includes Scenario Selector (F8: 1=Base, 2=Bull, 3=Bear), P&L with Pre-IFRS 16 Cash EBITDA Bridge (€9,433m in 2025A), Structural Negative Working Capital (NOF), and Capex split into Maintenance Capex (3.5% rev) vs. US & Logistics Expansion Capex (1.7% rev, funded 100% organically).
C7: 3 | D7: Debt & Covenants | E7: Multi-Tranche Debt & Covenant Schedule (2025A–2032E, 8.13x 100% EBITDA = €76,671m): Reference Euribor Swap (F7 = 3.354%) + Spread, Senior TLA (2.0x, 7y amortising), Senior TLB (3.5x, 7y bullet with 85.0% Optional Cash Sweep in E13), Subordinated Debt (1.5x PIK in H10), Sandra Ortega Vendor Loan (1.13x PIK in H11), €1,000m RCF as Seasonal Negative-NOF Backstop (E14), SFA Net Leverage Covenant, and Bank DSCR.
C8: 4 | D8: Tax & WACC | E8: 100% Fiscal Consolidation (Art. 58, 16.5 & 16.1 LIS) & Dynamic WACC (2025A–2032E): Tests the Spanish Anti-LBO Debt Cap (Art. 16.5 LIS: Acquisition Debt is 28.6% of total purchase value, well below the 70% statutory limit) and applies the 30% Operating EBITDA interest cap (Art. 16.1 LIS) with 5-year carryforwards and 7-year upfront fee amortization. Tracks Dynamic Levered Beta (Beta_L), Cost of Equity (Ke), Effective Tax Shield Rate (t_eff), and Dynamic WACC from 2025A to 2032E.
C9: 5 | D9: Checks | E9: Automated Legal, Financial & Tax Audit Panel: 11 real-time cross-sheet integrity checks verifying Sources & Uses balance, TopCo 100% equity sum, Art. 58 LIS (>=75%) consolidation, Art. 16.5 LIS (<70%) anti-LBO debt cap, TLA 100% amortisation, €1,000m Minimum Cash floor, Non-negative debt balances, D&A reconciliation, SFA Leverage Covenant, DSCR compliance, and GP+LP Waterfall reconciliation.

Sheet LBO Summary
B1: Project Galicia v3 — Inditex (ITX.MC) | N1: Strictly Private & Confidential
A2: > | B2: LBO Summary — 100% Take-Private (OPA Exclusión) with Amancio Ortega Rollover to TopCo (Exits 2026E–2032E)
A4: > | B4: > | C4: 1. Transaction Structure: 100% Take-Private via Free Float + Sandra Buyout & Amancio Rollover
B6: 1 | D6: Deal Valuation & Ownership Perimeter (100% Inditex) | F6: Value / Input | H6: Multiples, Fees & Headline Returns | L6: Value / Input
D7: 100% Inditex FY25A Pre-IFRS 16 Cash EBITDA (€m) | F7: ='Active Case'!L30 -> 9433 | H7: Implied 100% Offer Enterprise Value (EV, €m) | L7: =+F13-F19 -> 182493.84
D8: 100% Inditex FY25A Reported Post-IFRS 16 EBITDA (€m) | F8: ='Active Case'!L26 -> 11267 | H8: Implied Entry EV / Pre-IFRS 16 Cash EBITDA | L8: =+L7/F7 -> 19.34632
D9: Current undisturbed share price (€/sh) | F9: 55.42 | H9: Implied Entry EV / Reported Post-IFRS 16 EBITDA | L9: =+L7/F8 -> 16.197199
D10: Take-Private OPA Offer Premium (%) | F10: 0.12 | H10: Selected Exit Year (2026 to 2032) | L10: 2032
D11: OPA Offer Price per share (€/sh) | F11: =+F9*(1+F10) -> 62.0704 | H11: ="Exit Multiple (Pre-IFRS 16 EBITDA @ "&L10&"E)" -> Exit Multiple (Pre-IFRS 16 EBITDA @ 2032E) | L11: =+L8 -> 19.34632
D12: Total diluted shares outstanding (m) | F12: 3116.652 | H12: M&A / OPA Advisory Entry Fees (% of Cash Takeover) | L12: 0.01
D13: Implied 100% Inditex Offer Equity Value (€m) | F13: =+F11*F12 -> 193451.84 | H13: Exit Transaction / Re-IPO Underwriting Fees (% EV) | L13: 0.0075
D14: Amancio Ortega Rollover Stake to TopCo (%) [Pontegadea] | F14: 0.25 | H14: Upfront Debt Fee Tax Amortization Horizon (years) | L14: 7
D15: Cash Takeover Stake (%) [35.65% Free Float + 5.05% Sandra] | F15: =1-F14 -> 0.75 | H15: Active Operating Scenario | L15: ='Active Case'!H8 -> Base
D16: Amancio Ortega Rollover Equity Value in TopCo (€m) | F16: =+F13*F14 -> 48362.959 | H16: Art. 16.5 LIS Debt / Total Equity Value (< 70% Cap) | L16: =+F30/F13 -> 0.39633044
D17: Cash Takeover Purchase Price (Free Float + Sandra, €m) | F17: =+F13*F15 -> 145088.88 | H17: Gross Sponsor Pool IRR (K17) & MOIC (L17) | K17: =+M69 -> 0.12619725 | L17: =+N69 -> 2.2977418
D18: Minimum operational cash retained on 100% BS (€m) | F18: 1000 | H18: Lead GP Net IRR (w/ 20% Carry) @ Selected Exit | L18: =+M97 -> 0.17414068
D19: Existing statutory net cash on 100% BS (€m) | F19: 10958 | H19: Lead GP Net MOIC (w/ 20% Carry) @ Selected Exit | L19: =+N97 -> 3.0763869
D20: 100% Inditex Excess BS Cash Deployed at Close (€m) | F20: =+MAX(0,F19-F18) -> 9958 | H20: Net Profit (€m): Lead GP (K20) / Gross Pool (L20) | K20: =+INDEX(F84:L84,1,MATCH($L$10,F48:L48,0))-J44 -> 31692.347 | L20: =+INDEX(F56:L56,1,MATCH($L$10,F48:L48,0))-E44 -> 79230.868
H21: Passive LPs Net IRR (K21) & MOIC (L21) @ Exit | K21: =+INDEX(F85:L85,1,MATCH($L$10,F48:L48,0)) -> 0.10707722 | L21: =+INDEX(F86:L86,1,MATCH($L$10,F48:L48,0)) -> 2.0381934
A22: > | B22: > | C22: 2. Debt Package (Sized on 100% EBITDA), Per-Tranche Upfront Fees, Sources & Uses & TopCo Equity
B24: 2 | D24: LBO Debt Tranche / Facility (BidCo — 100% Inditex EBITDA) | E24: Committed (€m) | F24: Drawn (€m) | G24: xEBITDA (100%) | H24: Upfront Fee % | I24: Upfront Fee (€m)
D25: 1A. Senior Term Loan A (TLA — 7y Amortising Bank Debt) | E25: =+F25 -> 18866 | F25: ='Debt & Covenants'!F8*$F$7 -> 18866 | G25: ='Debt & Covenants'!F8 -> 2 | H25: 0.0125 | I25: =+E25*H25 -> 235.825
D26: 1B. Senior Term Loan B (TLB — 7y Institutional Bullet) | E26: =+F26 -> 33015.5 | F26: ='Debt & Covenants'!F9*$F$7 -> 33015.5 | G26: ='Debt & Covenants'!F9 -> 3.5 | H26: 0.0175 | I26: =+E26*H26 -> 577.77125
D27: 2. Subordinated / Mezzanine Debt (7.5y Bullet) | E27: =+F27 -> 14149.5 | F27: ='Debt & Covenants'!F10*$F$7 -> 14149.5 | G27: ='Debt & Covenants'!F10 -> 1.5 | H27: 0.0225 | I27: =+E27*H27 -> 318.36375
D28: 3. Seller Vendor Loan (Sandra Ortega Deferred Note) | E28: =+F28 -> 10639.851 | F28: ='Debt & Covenants'!F11*$F$7 -> 10639.851 | G28: ='Debt & Covenants'!F11 -> 1.1279393 | H28: 0 | I28: =+E28*H28 -> 0
D29: 4. Revolving Credit Facility (RCF — Negative NOF Line) | E29: ='Debt & Covenants'!E14 -> 1000 | F29: 0 | G29: =+E29/$F$7 -> 0.10601081 | H29: 0.01 | I29: =+E29*H29 -> 10
D30: Total LBO Debt Package & Upfront Structuring Fees | E30: =+SUM(E25:E29) -> 77670.851 | F30: =+SUM(F25:F29) -> 76670.851 | G30: =+SUM(G25:G28) -> 8.1279393 | H30: =+I30/E30 -> 0.014702556 | I30: =+SUM(I25:I29) -> 1141.96
D32: Sources of Funds (100% Take-Private) | E32: €m | F32: % | G32: xEBITDA | H32: Uses of Funds (100% Take-Private) | J32: €m | K32: % | L32: xEBITDA
D33: 1A. Senior Term Loan A (TLA) | E33: =+F25 -> 18866 | F33: =+E33/$E$40 -> 0.096233162 | G33: =+E33/$F$7 -> 2 | H33: Cash OPA for Free Float + Partial Family Cash-Out (75.0%) | J33: =+F17 -> 145088.88 | K33: =+J33/$J$40 -> 0.74008065 | L33: =+J33/$F$7 -> 15.38099
D34: 1B. Senior Term Loan B (TLB) | E34: =+F26 -> 33015.5 | F34: =+E34/$E$40 -> 0.16840803 | G34: =+E34/$F$7 -> 3.5 | H34: Amancio Ortega Rollover Shares Contributed (25.0%) | J34: =+F16 -> 48362.959 | K34: =+J34/$J$40 -> 0.24669355 | L34: =+J34/$F$7 -> 5.1269966
D35: 2. Subordinated / Mezzanine Debt | E35: =+F27 -> 14149.5 | F35: =+E35/$E$40 -> 0.072174872 | G35: =+E35/$F$7 -> 1.5 | H35: Upfront Debt Structuring Fees (TLA/TLB/Sub/RCF) | J35: =+I30 -> 1141.96 | K35: =+J35/$J$40 -> 0.0058249985 | L35: =+J35/$F$7 -> 0.12106011
D36: 3. Seller Vendor Loan (Sandra Deferred Note) | E36: =+F28 -> 10639.851 | F36: =+E36/$E$40 -> 0.054272581 | G36: =+E36/$F$7 -> 1.1279393 | H36: M&A, Legal & OPA Advisory Costs (% Cash Takeover) | J36: =+F17*L12 -> 1450.8888 | K36: =+J36/$J$40 -> 0.0074008065 | L36: =+J36/$F$7 -> 0.1538099
D37: 100% Inditex Excess BS Cash Deployed at Close | E37: =+F20 -> 9958 | F37: =+E37/$E$40 -> 0.050794542 | G37: =+E37/$F$7 -> 1.0556557 | H37: Minimum Operational Cash Retained on BS (€1,000m) | J37: 0 | K37: =+J37/$J$40 -> 0 | L37: =+J37/$F$7 -> 0
D38: Amancio Ortega Equity Rollover into TopCo | E38: =+F16 -> 48362.959 | F38: =+E38/$E$40 -> 0.24669355 | G38: =+E38/$F$7 -> 5.1269966
D39: Sponsor Cash Equity Ticket (Plug) | E39: =+E40-SUM(E33:E38) -> 61052.875 | F39: =+E39/$E$40 -> 0.31142326 | G39: =+E39/$F$7 -> 6.4722649
D40: Total Sources of Funds | E40: =+J40 -> 196044.69 | F40: =+SUM(F33:F39) -> 1 | G40: =+SUM(G33:G39) -> 20.782856 | H40: Total Uses of Funds | J40: =+SUM(J33:J37) -> 196044.69 | K40: =+SUM(K33:K37) -> 1 | L40: =+SUM(L33:L37) -> 20.782856
D42: TopCo Common Equity Ownership (100% Owner of BidCo / Inditex) | E42: Equity (€m) | F42: % TopCo | G42: xEBITDA | H42: GP / LP Equity Waterfall & Promote Inputs | J42: Ticket (€m) | K42: % TopCo | L42: Input / %
D43: Amancio Ortega (Pontegadea Rollover Equity in TopCo) | E43: =+E38 -> 48362.959 | F43: =+E43/$E$45 -> 0.44201061 | G43: =+E43/$F$7 -> 5.1269966 | H43: Passive LP Co-Investors (SWFs / Pensions) | J43: =+E44*L43 -> 45789.656 | K43: =+J43/$E$45 -> 0.41849205 | L43: 0.75
D44: Sponsor PE Consortium (Cash Equity Ticket in TopCo) | E44: =+E39 -> 61052.875 | F44: =+E44/$E$45 -> 0.55798939 | G44: =+E44/$F$7 -> 6.4722649 | H44: Lead GP Sponsor Co-Investment Ticket | J44: =+E44*L44 -> 15263.219 | K44: =+J44/$E$45 -> 0.13949735 | L44: =1-L43 -> 0.25
D45: Total TopCo Common Equity (100% Inditex Ownership) | E45: =+E43+E44 -> 109415.83 | F45: =+F43+F44 -> 1 | G45: =+G43+G44 -> 11.599262 | H45: LP Compound Hurdle Rate (L45) & Catch-Up (J45) | J45: 1 | K45: Hurdle -> | L45: 0.1
H46: GP Carried Interest / Promote (% above Hurdle) | J46: =+J43+J44 -> 61052.875 | K46: Carry -> | L46: 0.2
A47: > | B47: > | C47: 3. Multi-Year Exit Valuation (100% Inditex), Exit Fees & Sponsor Returns Matrix (2026E–2032E)
D48: Exit Valuation & Proceeds Breakdown (€m) | E48: 2025 | F48: =+E48+1 -> 2026 | G48: =+F48+1 -> 2027 | H48: =+G48+1 -> 2028 | I48: =+H48+1 -> 2029 | J48: =+I48+1 -> 2030 | K48: =+J48+1 -> 2031 | L48: =+K48+1 -> 2032
B49: 3 | D49: 100% Inditex Pre-IFRS 16 Cash EBITDA (€m) | E49: ='Active Case'!L30 -> 9433 | F49: ='Active Case'!M30 -> 10143.127 | G49: ='Active Case'!N30 -> 10922.262 | H49: ='Active Case'!O30 -> 11752.179 | I49: ='Active Case'!P30 -> 12635.98 | J49: ='Active Case'!Q30 -> 13576.948 | K49: ='Active Case'!R30 -> 14578.56 | L49: ='Active Case'!S30 -> 15644.499
D50: Exit Multiple (Pre-IFRS 16 EBITDAx) | E50: =+$L$11 -> 19.34632 | F50: =+$L$11 -> 19.34632 | G50: =+$L$11 -> 19.34632 | H50: =+$L$11 -> 19.34632 | I50: =+$L$11 -> 19.34632 | J50: =+$L$11 -> 19.34632 | K50: =+$L$11 -> 19.34632 | L50: =+$L$11 -> 19.34632
D51: Gross Enterprise Value at Exit (100% Inditex EV) | E51: =+E49*E50 -> 182493.84 | F51: =+F49*F50 -> 196232.18 | G51: =+G49*G50 -> 211305.57 | H51: =+H49*H50 -> 227361.41 | I51: =+I49*I50 -> 244459.7 | J51: =+J49*J50 -> 262663.97 | K51: =+K49*K50 -> 282041.49 | L51: =+L49*L50 -> 302663.48
D52: Less: Exit Transaction / Re-IPO Fees (% in L13) | E52: =-E51*$L$13 -> -1368.7038 | F52: =-F51*$L$13 -> -1471.7414 | G52: =-G51*$L$13 -> -1584.7917 | H52: =-H51*$L$13 -> -1705.2106 | I52: =-I51*$L$13 -> -1833.4478 | J52: =-J51*$L$13 -> -1969.9798 | K52: =-K51*$L$13 -> -2115.3111 | L52: =-L51*$L$13 -> -2269.9761
D53: Less: EoP Gross LBO Debt (TLA + TLB + Sub + Vendor Loan + RCF) | E53: =-'Debt & Covenants'!E68 -> -76670.851 | F53: =-'Debt & Covenants'!F68 -> -75537.551 | G53: =-'Debt & Covenants'!G68 -> -73421.76 | H53: =-'Debt & Covenants'!H68 -> -70546.989 | I53: =-'Debt & Covenants'!I68 -> -67046.487 | J53: =-'Debt & Covenants'!J68 -> -62568.456 | K53: =-'Debt & Covenants'!K68 -> -57285.901 | L53: =-'Debt & Covenants'!L68 -> -51167.574
D54: Plus: EoP 100% Inditex Cash Balance (incl. €1,000m Min Cash) | E54: =+'Debt & Covenants'!E93 -> 1000 | F54: =+'Debt & Covenants'!F93 -> 1389.5923 | G54: =+'Debt & Covenants'!G93 -> 1428.7315 | H54: =+'Debt & Covenants'!H93 -> 1431.553 | I54: =+'Debt & Covenants'!I93 -> 1580.7649 | J54: =+'Debt & Covenants'!J93 -> 1629.3826 | K54: =+'Debt & Covenants'!K93 -> 1818.1061 | L54: =+'Debt & Covenants'!L93 -> 2183.4038
D55: Total TopCo Net Equity Value at Exit (100% Inditex) | E55: =+SUM(E51:E54) -> 105454.28 | F55: =+SUM(F51:F54) -> 120612.48 | G55: =+SUM(G51:G54) -> 137727.75 | H55: =+SUM(H51:H54) -> 156540.76 | I55: =+SUM(I51:I54) -> 177160.53 | J55: =+SUM(J51:J54) -> 199754.92 | K55: =+SUM(K51:K54) -> 224458.38 | L55: =+SUM(L51:L54) -> 251409.34
D56: Sponsor PE Exit Equity Proceeds (% TopCo in F44) | E56: =+E55*$F$44 -> 58842.371 | F56: =+F55*$F$44 -> 67300.486 | G56: =+G55*$F$44 -> 76850.621 | H56: =+H55*$F$44 -> 87348.087 | I56: =+I55*$F$44 -> 98853.699 | J56: =+J55*$F$44 -> 111461.13 | K56: =+K55*$F$44 -> 125245.4 | L56: =+L55*$F$44 -> 140283.74
D57: Amancio Ortega Rollover Exit Equity Proceeds (% TopCo in F43) | E57: =+E55*$F$43 -> 46611.911 | F57: =+F55*$F$43 -> 53311.997 | G57: =+G55*$F$43 -> 60877.124 | H57: =+H55*$F$43 -> 69192.678 | I57: =+I55*$F$43 -> 78306.835 | J57: =+J55*$F$43 -> 88293.793 | K57: =+K55*$F$43 -> 99212.984 | L57: =+L55*$F$43 -> 111125.59
D58: Implied Sponsor IRR if Exited in Year (%) | F58: =+M62 -> 0.10233116 | G58: =+M63 -> 0.12194258 | H58: =+M64 -> 0.12680585 | I58: =+M65 -> 0.12803273 | J58: =+M66 -> 0.12793341 | K58: =+M67 -> 0.12722153 | L58: =+M68 -> 0.12619725
D59: Implied Sponsor MOIC (Cash-on-Cash) if Exited in Year (x) | F59: =+N62 -> 1.1023312 | G59: =+N63 -> 1.2587552 | H59: =+N64 -> 1.4306957 | I59: =+N65 -> 1.619149 | J59: =+N66 -> 1.8256491 | K59: =+N67 -> 2.051425 | L59: =+N68 -> 2.2977418
D61: Sponsor Cash Flow Schedule by Exit Year (2026E–2032E) | E61: =+E48 -> 2025 | F61: =+F48 -> 2026 | G61: =+G48 -> 2027 | H61: =+H48 -> 2028 | I61: =+I48 -> 2029 | J61: =+J48 -> 2030 | K61: =+K48 -> 2031 | L61: =+L48 -> 2032 | M61: Sponsor IRR | N61: Sponsor MOIC
D62: =+F61 -> 2026 | E62: =-$E$44 -> -61052.875 | F62: =+F$56 -> 67300.486 | G62: 0 | H62: 0 | I62: 0 | J62: 0 | K62: 0 | L62: 0 | M62: =+IFERROR((N62)^(1/(F$61-$E$61))-1,0) -> 0.10233116 | N62: =+IFERROR(-SUM(F62:F62)/E62,0) -> 1.1023312
D63: =+G61 -> 2027 | E63: =-$E$44 -> -61052.875 | F63: 0 | G63: =+G$56 -> 76850.621 | H63: 0 | I63: 0 | J63: 0 | K63: 0 | L63: 0 | M63: =+IFERROR((N63)^(1/(G$61-$E$61))-1,0) -> 0.12194258 | N63: =+IFERROR(-SUM(F63:G63)/E63,0) -> 1.2587552
D64: =+H61 -> 2028 | E64: =-$E$44 -> -61052.875 | F64: 0 | G64: 0 | H64: =+H$56 -> 87348.087 | I64: 0 | J64: 0 | K64: 0 | L64: 0 | M64: =+IFERROR((N64)^(1/(H$61-$E$61))-1,0) -> 0.12680585 | N64: =+IFERROR(-SUM(F64:H64)/E64,0) -> 1.4306957
D65: =+I61 -> 2029 | E65: =-$E$44 -> -61052.875 | F65: 0 | G65: 0 | H65: 0 | I65: =+I$56 -> 98853.699 | J65: 0 | K65: 0 | L65: 0 | M65: =+IFERROR((N65)^(1/(I$61-$E$61))-1,0) -> 0.12803273 | N65: =+IFERROR(-SUM(F65:I65)/E65,0) -> 1.619149
D66: =+J61 -> 2030 | E66: =-$E$44 -> -61052.875 | F66: 0 | G66: 0 | H66: 0 | I66: 0 | J66: =+J$56 -> 111461.13 | K66: 0 | L66: 0 | M66: =+IFERROR((N66)^(1/(J$61-$E$61))-1,0) -> 0.12793341 | N66: =+IFERROR(-SUM(F66:J66)/E66,0) -> 1.8256491
D67: =+K61 -> 2031 | E67: =-$E$44 -> -61052.875 | F67: 0 | G67: 0 | H67: 0 | I67: 0 | J67: 0 | K67: =+K$56 -> 125245.4 | L67: 0 | M67: =+IFERROR((N67)^(1/(K$61-$E$61))-1,0) -> 0.12722153 | N67: =+IFERROR(-SUM(F67:K67)/E67,0) -> 2.051425
D68: =+L61 -> 2032 | E68: =-$E$44 -> -61052.875 | F68: 0 | G68: 0 | H68: 0 | I68: 0 | J68: 0 | K68: 0 | L68: =+L$56 -> 140283.74 | M68: =+IFERROR((N68)^(1/(L$61-$E$61))-1,0) -> 0.12619725 | N68: =+IFERROR(-SUM(F68:L68)/E68,0) -> 2.2977418
D69: ="Active Selected Exit Cash Flows @ "&L10&"E" -> Active Selected Exit Cash Flows @ 2032E | E69: =+INDEX(E62:E68,MATCH($L$10,$D$62:$D$68,0)) -> -61052.875 | F69: =+INDEX(F62:F68,MATCH($L$10,$D$62:$D$68,0)) -> 0 | G69: =+INDEX(G62:G68,MATCH($L$10,$D$62:$D$68,0)) -> 0 | H69: =+INDEX(H62:H68,MATCH($L$10,$D$62:$D$68,0)) -> 0 | I69: =+INDEX(I62:I68,MATCH($L$10,$D$62:$D$68,0)) -> 0 | J69: =+INDEX(J62:J68,MATCH($L$10,$D$62:$D$68,0)) -> 0 | K69: =+INDEX(K62:K68,MATCH($L$10,$D$62:$D$68,0)) -> 0 | L69: =+INDEX(L62:L68,MATCH($L$10,$D$62:$D$68,0)) -> 140283.74 | ... N69: =+INDEX(N62:N68,MATCH($L$10,$D$62:$D$68,0)) -> 2.2977418
A71: > | B71: > | C71: 4. GP / LP Co-Investment Equity Waterfall (8% Compound Hurdle & 20% Carried Interest, 2026E–2032E)
D72: European Deal-by-Deal Waterfall Breakdown (€m) | E72: =+E48 -> 2025 | F72: =+F48 -> 2026 | G72: =+G48 -> 2027 | H72: =+H48 -> 2028 | I72: =+I48 -> 2029 | J72: =+J48 -> 2030 | K72: =+K48 -> 2031 | L72: =+L48 -> 2032
B73: 4 | D73: Total Sponsor PE Gross Exit Proceeds (100% Consortium Pool) | E73: =+E56 -> 58842.371 | F73: =+F56 -> 67300.486 | G73: =+G56 -> 76850.621 | H73: =+H56 -> 87348.087 | I73: =+I56 -> 98853.699 | J73: =+J56 -> 111461.13 | K73: =+K56 -> 125245.4 | L73: =+L56 -> 140283.74
D74: 1. Lead GP Pro-Rata Co-Investment Share (15.0% of Pool) | E74: =+E73*$L$44 -> 14710.593 | F74: =+F73*$L$44 -> 16825.122 | G74: =+G73*$L$44 -> 19212.655 | H74: =+H73*$L$44 -> 21837.022 | I74: =+I73*$L$44 -> 24713.425 | J74: =+J73*$L$44 -> 27865.282 | K74: =+K73*$L$44 -> 31311.349 | L74: =+L73*$L$44 -> 35070.936
D75: 2. Passive LPs Gross Syndicate Pool Before Promote (85.0% of Pool) | E75: =+E73*$L$43 -> 44131.778 | F75: =+F73*$L$43 -> 50475.365 | G75: =+G73*$L$43 -> 57637.966 | H75: =+H73*$L$43 -> 65511.065 | I75: =+I73*$L$43 -> 74140.274 | J75: =+J73*$L$43 -> 83595.845 | K75: =+K73*$L$43 -> 93934.047 | L75: =+L73*$L$43 -> 105212.81
D76: Tier 1 — Return of LP Contributed Capital (100% LP Principal) | E76: =+MIN(E75,$J$43) -> 44131.778 | F76: =+MIN(F75,$J$43) -> 45789.656 | G76: =+MIN(G75,$J$43) -> 45789.656 | H76: =+MIN(H75,$J$43) -> 45789.656 | I76: =+MIN(I75,$J$43) -> 45789.656 | J76: =+MIN(J75,$J$43) -> 45789.656 | K76: =+MIN(K75,$J$43) -> 45789.656 | L76: =+MIN(L75,$J$43) -> 45789.656
D77: Memo: LP Compound Hurdle Target (8.0% p.a. Preferred Return) | E77: 0 | F77: =+$J$43*((1+$L$45)^(F$72-$E$72)-1) -> 4578.9656 | G77: =+$J$43*((1+$L$45)^(G$72-$E$72)-1) -> 9615.8278 | H77: =+$J$43*((1+$L$45)^(H$72-$E$72)-1) -> 15156.376 | I77: =+$J$43*((1+$L$45)^(I$72-$E$72)-1) -> 21250.979 | J77: =+$J$43*((1+$L$45)^(J$72-$E$72)-1) -> 27955.043 | K77: =+$J$43*((1+$L$45)^(K$72-$E$72)-1) -> 35329.513 | L77: =+$J$43*((1+$L$45)^(L$72-$E$72)-1) -> 43441.43
D78: Tier 2 — LP Preferred Return Paid (8.0% p.a. Compound Hurdle) | E78: 0 | F78: =+MIN(MAX(0,F75-F76),F77) -> 4578.9656 | G78: =+MIN(MAX(0,G75-G76),G77) -> 9615.8278 | H78: =+MIN(MAX(0,H75-H76),H77) -> 15156.376 | I78: =+MIN(MAX(0,I75-I76),I77) -> 21250.979 | J78: =+MIN(MAX(0,J75-J76),J77) -> 27955.043 | K78: =+MIN(MAX(0,K75-K76),K77) -> 35329.513 | L78: =+MIN(MAX(0,L75-L76),L77) -> 43441.43
D79: Tier 3 — GP Catch-Up (100% Catch-Up to 20.0% Promote) | E79: 0 | F79: =+MIN(MAX(0,F75-F76-F78),F78*($L$46/(1-$L$46))*$J$45) -> 106.74289 | G79: =+MIN(MAX(0,G75-G76-G78),G78*($L$46/(1-$L$46))*$J$45) -> 2232.482 | H79: =+MIN(MAX(0,H75-H76-H78),H78*($L$46/(1-$L$46))*$J$45) -> 3789.0941 | I79: =+MIN(MAX(0,I75-I76-I78),I78*($L$46/(1-$L$46))*$J$45) -> 5312.7449 | J79: =+MIN(MAX(0,J75-J76-J78),J78*($L$46/(1-$L$46))*$J$45) -> 6988.7608 | K79: =+MIN(MAX(0,K75-K76-K78),K78*($L$46/(1-$L$46))*$J$45) -> 8832.3782 | L79: =+MIN(MAX(0,L75-L76-L78),L78*($L$46/(1-$L$46))*$J$45) -> 10860.357
D80: Tier 4A — Residual Excess Profit to Passive LPs (80.0% Split) | E80: 0 | F80: =+MAX(0,F75-F76-F78-F79)*(1-$L$46) -> 0 | G80: =+MAX(0,G75-G76-G78-G79)*(1-$L$46) -> 0 | H80: =+MAX(0,H75-H76-H78-H79)*(1-$L$46) -> 620.75071 | I80: =+MAX(0,I75-I76-I78-I79)*(1-$L$46) -> 1429.515 | J80: =+MAX(0,J75-J76-J78-J79)*(1-$L$46) -> 2289.9077 | K80: =+MAX(0,K75-K76-K78-K79)*(1-$L$46) -> 3185.9994 | L80: =+MAX(0,L75-L76-L78-L79)*(1-$L$46) -> 4097.0909
D81: Tier 4B — Residual Carried Interest to Lead GP (20.0% Promote) | E81: 0 | F81: =+MAX(0,F75-F76-F78-F79)*$L$46 -> 0 | G81: =+MAX(0,G75-G76-G78-G79)*$L$46 -> 0 | H81: =+MAX(0,H75-H76-H78-H79)*$L$46 -> 155.18768 | I81: =+MAX(0,I75-I76-I78-I79)*$L$46 -> 357.37874 | J81: =+MAX(0,J75-J76-J78-J79)*$L$46 -> 572.47693 | K81: =+MAX(0,K75-K76-K78-K79)*$L$46 -> 796.49984 | L81: =+MAX(0,L75-L76-L78-L79)*$L$46 -> 1024.2727
D82: Passive LPs Net Exit Proceeds (Tier 1 + Tier 2 + Tier 4A) | E82: =+E76+E78+E80 -> 44131.778 | F82: =+F76+F78+F80 -> 50368.622 | G82: =+G76+G78+G80 -> 55405.484 | H82: =+H76+H78+H80 -> 61566.783 | I82: =+I76+I78+I80 -> 68470.151 | J82: =+J76+J78+J80 -> 76034.607 | K82: =+K76+K78+K80 -> 84305.169 | L82: =+L76+L78+L80 -> 93328.177
D83: Total GP Carried Interest / Promote Earned (Tier 3 + Tier 4B) | E83: =+E79+E81 -> 0 | F83: =+F79+F81 -> 106.74289 | G83: =+G79+G81 -> 2232.482 | H83: =+H79+H81 -> 3944.2817 | I83: =+I79+I81 -> 5670.1236 | J83: =+J79+J81 -> 7561.2377 | K83: =+K79+K81 -> 9628.8781 | L83: =+L79+L81 -> 11884.63
D84: Lead GP Total Net Exit Proceeds (Co-Invest Pro-Rata + Carry) | E84: =+E74+E83 -> 14710.593 | F84: =+F74+F83 -> 16931.864 | G84: =+G74+G83 -> 21445.137 | H84: =+H74+H83 -> 25781.303 | I84: =+I74+I83 -> 30383.548 | J84: =+J74+J83 -> 35426.519 | K84: =+K74+K83 -> 40940.227 | L84: =+L74+L83 -> 46955.566
D85: Implied Passive LPs Net IRR if Exited in Year (%) | F85: =+IFERROR((F82/$J$43)^(1/(F$72-$E$72))-1,0) -> 0.1 | G85: =+IFERROR((G82/$J$43)^(1/(G$72-$E$72))-1,0) -> 0.1 | H85: =+IFERROR((H82/$J$43)^(1/(H$72-$E$72))-1,0) -> 0.10372198 | I85: =+IFERROR((I82/$J$43)^(1/(I$72-$E$72))-1,0) -> 0.10581754 | J85: =+IFERROR((J82/$J$43)^(1/(J$72-$E$72))-1,0) -> 0.1067481 | K85: =+IFERROR((K82/$J$43)^(1/(K$72-$E$72))-1,0) -> 0.10708543 | L85: =+IFERROR((L82/$J$43)^(1/(L$72-$E$72))-1,0) -> 0.10707722
D86: Implied Passive LPs Net MOIC (Cash-on-Cash) if Exited in Year (x) | F86: =+IFERROR(F82/$J$43,0) -> 1.1 | G86: =+IFERROR(G82/$J$43,0) -> 1.21 | H86: =+IFERROR(H82/$J$43,0) -> 1.3445566 | I86: =+IFERROR(I82/$J$43,0) -> 1.4953192 | J86: =+IFERROR(J82/$J$43,0) -> 1.6605193 | K86: =+IFERROR(K82/$J$43,0) -> 1.84114 | L86: =+IFERROR(L82/$J$43,0) -> 2.0381934
D87: Implied Lead GP Net IRR (w/ 20% Carry) if Exited in Year (%) | F87: =+M90 -> 0.10932463 | G87: =+M91 -> 0.18533567 | H87: =+M92 -> 0.19093003 | I87: =+M93 -> 0.18781305 | J87: =+M94 -> 0.18341337 | K87: =+M95 -> 0.17873819 | L87: =+M96 -> 0.17414068
D88: Implied Lead GP Net MOIC (w/ 20% Carry) if Exited in Year (x) | F88: =+N90 -> 1.1093246 | G88: =+N91 -> 1.4050206 | H88: =+N92 -> 1.6891131 | I88: =+N93 -> 1.9906383 | J88: =+N94 -> 2.3210386 | K88: =+N95 -> 2.68228 | L88: =+N96 -> 3.0763869
D89: Lead GP Net Cash Flow Schedule (Co-Invest + Carry, 2026E–2032E) | E89: =+E72 -> 2025 | F89: =+F72 -> 2026 | G89: =+G72 -> 2027 | H89: =+H72 -> 2028 | I89: =+I72 -> 2029 | J89: =+J72 -> 2030 | K89: =+K72 -> 2031 | L89: =+L72 -> 2032 | M89: Lead GP IRR | N89: Lead GP MOIC
D90: =+F89 -> 2026 | E90: =-$J$44 -> -15263.219 | F90: =+F$84 -> 16931.864 | G90: 0 | H90: 0 | I90: 0 | J90: 0 | K90: 0 | L90: 0 | M90: =+IFERROR((N90)^(1/(F$89-$E$89))-1,0) -> 0.10932463 | N90: =+IFERROR(-SUM(F90:F90)/E90,0) -> 1.1093246
D91: =+G89 -> 2027 | E91: =-$J$44 -> -15263.219 | F91: 0 | G91: =+G$84 -> 21445.137 | H91: 0 | I91: 0 | J91: 0 | K91: 0 | L91: 0 | M91: =+IFERROR((N91)^(1/(G$89-$E$89))-1,0) -> 0.18533567 | N91: =+IFERROR(-SUM(F91:G91)/E91,0) -> 1.4050206
D92: =+H89 -> 2028 | E92: =-$J$44 -> -15263.219 | F92: 0 | G92: 0 | H92: =+H$84 -> 25781.303 | I92: 0 | J92: 0 | K92: 0 | L92: 0 | M92: =+IFERROR((N92)^(1/(H$89-$E$89))-1,0) -> 0.19093003 | N92: =+IFERROR(-SUM(F92:H92)/E92,0) -> 1.6891131
D93: =+I89 -> 2029 | E93: =-$J$44 -> -15263.219 | F93: 0 | G93: 0 | H93: 0 | I93: =+I$84 -> 30383.548 | J93: 0 | K93: 0 | L93: 0 | M93: =+IFERROR((N93)^(1/(I$89-$E$89))-1,0) -> 0.18781305 | N93: =+IFERROR(-SUM(F93:I93)/E93,0) -> 1.9906383
D94: =+J89 -> 2030 | E94: =-$J$44 -> -15263.219 | F94: 0 | G94: 0 | H94: 0 | I94: 0 | J94: =+J$84 -> 35426.519 | K94: 0 | L94: 0 | M94: =+IFERROR((N94)^(1/(J$89-$E$89))-1,0) -> 0.18341337 | N94: =+IFERROR(-SUM(F94:J94)/E94,0) -> 2.3210386
D95: =+K89 -> 2031 | E95: =-$J$44 -> -15263.219 | F95: 0 | G95: 0 | H95: 0 | I95: 0 | J95: 0 | K95: =+K$84 -> 40940.227 | L95: 0 | M95: =+IFERROR((N95)^(1/(K$89-$E$89))-1,0) -> 0.17873819 | N95: =+IFERROR(-SUM(F95:K95)/E95,0) -> 2.68228
D96: =+L89 -> 2032 | E96: =-$J$44 -> -15263.219 | F96: 0 | G96: 0 | H96: 0 | I96: 0 | J96: 0 | K96: 0 | L96: =+L$84 -> 46955.566 | M96: =+IFERROR((N96)^(1/(L$89-$E$89))-1,0) -> 0.17414068 | N96: =+IFERROR(-SUM(F96:L96)/E96,0) -> 3.0763869
D97: ="Active Selected Exit Lead GP Cash Flows @ "&L10&"E" -> Active Selected Exit Lead GP Cash Flows @ 2032E | E97: =+INDEX(E90:E96,MATCH($L$10,$D$90:$D$96,0)) -> -15263.219 | F97: =+INDEX(F90:F96,MATCH($L$10,$D$90:$D$96,0)) -> 0 | G97: =+INDEX(G90:G96,MATCH($L$10,$D$90:$D$96,0)) -> 0 | H97: =+INDEX(H90:H96,MATCH($L$10,$D$90:$D$96,0)) -> 0 | I97: =+INDEX(I90:I96,MATCH($L$10,$D$90:$D$96,0)) -> 0 | J97: =+INDEX(J90:J96,MATCH($L$10,$D$90:$D$96,0)) -> 0 | K97: =+INDEX(K90:K96,MATCH($L$10,$D$90:$D$96,0)) -> 0 | L97: =+INDEX(L90:L96,MATCH($L$10,$D$90:$D$96,0)) -> 46955.566 | ... N97: =+INDEX(N90:N96,MATCH($L$10,$D$90:$D$96,0)) -> 3.0763869
A99: > | B99: > | C99: 5. Sensitivity Analysis: Lead GP Net IRR/MOIC (LP Syndication vs. Exit Multiple) & Deal Leverage Grid
D100: LP Syndication % \ Exit Multiple (Lead GP Net IRR) | E100: 17.5 | F100: =+$L$11 -> 19.34632 | G100: 21 | I100: =+E100 -> 17.5 | J100: =+F100 -> 19.34632 | K100: =+G100 -> 21
D101: 0.75 | E101: =+(I101)^(1/($L$10-$E$48))-1 -> 0.12612942 | F101: =+(J101)^(1/($L$10-$E$48))-1 -> 0.17414068 | G101: =+(K101)^(1/($L$10-$E$48))-1 -> 0.19361649 | I101: =+(((((INDEX($F$55:$L$55,1,MATCH($L$10,$F$48:$L$48,0))+((E$100-$L$11)*INDEX($F$49:$L$49,1,MATCH($L$10,$F$48:$L$48,0))*(1-$L$13)))*$F$44)*(1-$D101))+MIN(MAX(0,MAX(0,(((INDEX($F$55:$L$55,1,MATCH($L$10,$F$48:$L$48,0))+((E$100-$L$11)*INDEX($F$49:$L$49,1,MATCH($L$10,$F$48:$L$48,0))*(1-$L$13)))*$F$44)*$D101)-($E$44*$D101))-MIN(MAX(0,(((INDEX($F$55:$L$55,1,MATCH($L$10,$F$48:$L$48,0))+((E$100-$L$11)*INDEX($F$49:$L$49,1,MATCH($L$10,$F$48:$L$48,0))*(1-$L$13)))*$F$44)*$D101)-($E$44*$D101)),(($E$44*$D101)*((1+$L$45)^($L$10-$E$48)-1)))),MIN(MAX(0,(((INDEX($F$55:$L$55,1,MATCH($L$10,$F$48:$L$48,0))+((E$100-$L$11)*INDEX($F$49:$L$49,1,MATCH($L$10,$F$48:$L$48,0))*(1-$L$13)))*$F$44)*$D101)-($E$44*$D101)),(($E$44*$D101)*((1+$L$45)^($L$10-$E$48)-1)))*($L$46/(1-$L$46))*$J$45)+(MAX(0,MAX(0,(((INDEX($F$55:$L$55,1,MATCH($L$10,$F$48:$L$48,0))+((E$100-$L$11)*INDEX($F$49:$L$49,1,MATCH($L$10,$F$48:$L$48,0))*(1-$L$13)))*$F$44)*$D101)-($E$44*$D101))-MIN(MAX(0,(((INDEX($F$55:$L$55,1,MATCH($L$10,$F$48:$L$48,0))+((E$100-$L$11)*INDEX($F$49:$L$49,1,MATCH($L$10,$F$48:$L$48,0))*(1-$L$13)))*$F$44)*$D101)-($E$44*$D101)),(($E$44*$D101)*((1+$L$45)^($L$10-$E$48)-1)))-MIN(MAX(0,MAX(0,(((INDEX($F$55:$L$55,1,MATCH($L$10,$F$48:$L$48,0))+((E$100-$L$11)*INDEX($F$49:$L$49,1,MATCH($L$10,$F$48:$L$48,0))*(1-$L$13)))*$F$44)*$D101)-($E$44*$D101))-MIN(MAX(0,(((INDEX($F$55:$L$55,1,MATCH($L$10,$F$48:$L$48,0))+((E$100-$L$11)*INDEX($F$49:$L$49,1,MATCH($L$10,$F$48:$L$48,0))*(1-$L$13)))*$F$44)*$D101)-($E$44*$D101)),(($E$44*$D101)*((1+$L$45)^($L$10-$E$48)-1)))),MIN(MAX(0,(((INDEX($F$55:$L$55,1,MATCH($L$10,$F$48:$L$48,0))+((E$100-$L$11)*INDEX($F$49:$L$49,1,MATCH($L$10,$F$48:$L$48,0))*(1-$L$13)))*$F$44)*$D101)-($E$44*$D101)),(($E$44*$D101)*((1+$L$45)^($L$10-$E$48)-1)))*($L$46/(1-$L$46))*$J$45))*$L$46)))/($E$44*(1-$D101)) -> 2.2967733 | J101: =+(((((INDEX($F$55:$L$55,1,MATCH($L$10,$F$48:$L$48,0))+((F$100-$L$11)*INDEX($F$49:$L$49,1,MATCH($L$10,$F$48:$L$48,0))*(1-$L$13)))*$F$44)*(1-$D101))+MIN(MAX(0,MAX(0,(((INDEX($F$55:$L$55,1,MATCH($L$10,$F$48:$L$48,0))+((F$100-$L$11)*INDEX($F$49:$L$49,1,MATCH($L$10,$F$48:$L$48,0))*(1-$L$13)))*$F$44)*$D101)-($E$44*$D101))-MIN(MAX(0,(((INDEX($F$55:$L$55,1,MATCH($L$10,$F$48:$L$48,0))+((F$100-$L$11)*INDEX($F$49:$L$49,1,MATCH($L$10,$F$48:$L$48,0))*(1-$L$13)))*$F$44)*$D101)-($E$44*$D101)),(($E$44*$D101)*((1+$L$45)^($L$10-$E$48)-1)))),MIN(MAX(0,(((INDEX($F$55:$L$55,1,MATCH($L$10,$F$48:$L$48,0))+((F$100-$L$11)*INDEX($F$49:$L$49,1,MATCH($L$10,$F$48:$L$48,0))*(1-$L$13)))*$F$44)*$D101)-($E$44*$D101)),(($E$44*$D101)*((1+$L$45)^($L$10-$E$48)-1)))*($L$46/(1-$L$46))*$J$45)+(MAX(0,MAX(0,(((INDEX($F$55:$L$55,1,MATCH($L$10,$F$48:$L$48,0))+((F$100-$L$11)*INDEX($F$49:$L$49,1,MATCH($L$10,$F$48:$L$48,0))*(1-$L$13)))*$F$44)*$D101)-($E$44*$D101))-MIN(MAX(0,(((INDEX($F$55:$L$55,1,MATCH($L$10,$F$48:$L$48,0))+((F$100-$L$11)*INDEX($F$49:$L$49,1,MATCH($L$10,$F$48:$L$48,0))*(1-$L$13)))*$F$44)*$D101)-($E$44*$D101)),(($E$44*$D101)*((1+$L$45)^($L$10-$E$48)-1)))-MIN(MAX(0,MAX(0,(((INDEX($F$55:$L$55,1,MATCH($L$10,$F$48:$L$48,0))+((F$100-$L$11)*INDEX($F$49:$L$49,1,MATCH($L$10,$F$48:$L$48,0))*(1-$L$13)))*$F$44)*$D101)-($E$44*$D101))-MIN(MAX(0,(((INDEX($F$55:$L$55,1,MATCH($L$10,$F$48:$L$48,0))+((F$100-$L$11)*INDEX($F$49:$L$49,1,MATCH($L$10,$F$48:$L$48,0))*(1-$L$13)))*$F$44)*$D101)-($E$44*$D101)),(($E$44*$D101)*((1+$L$45)^($L$10-$E$48)-1)))),MIN(MAX(0,(((INDEX($F$55:$L$55,1,MATCH($L$10,$F$48:$L$48,0))+((F$100-$L$11)*INDEX($F$49:$L$49,1,MATCH($L$10,$F$48:$L$48,0))*(1-$L$13)))*$F$44)*$D101)-($E$44*$D101)),(($E$44*$D101)*((1+$L$45)^($L$10-$E$48)-1)))*($L$46/(1-$L$46))*$J$45))*$L$46)))/($E$44*(1-$D101)) -> 3.0763869 | K101: =+(((((INDEX($F$55:$L$55,1,MATCH($L$10,$F$48:$L$48,0))+((G$100-$L$11)*INDEX($F$49:$L$49,1,MATCH($L$10,$F$48:$L$48,0))*(1-$L$13)))*$F$44)*(1-$D101))+MIN(MAX(0,MAX(0,(((INDEX($F$55:$L$55,1,MATCH($L$10,$F$48:$L$48,0))+((G$100-$L$11)*INDEX($F$49:$L$49,1,MATCH($L$10,$F$48:$L$48,0))*(1-$L$13)))*$F$44)*$D101)-($E$44*$D101))-MIN(MAX(0,(((INDEX($F$55:$L$55,1,MATCH($L$10,$F$48:$L$48,0))+((G$100-$L$11)*INDEX($F$49:$L$49,1,MATCH($L$10,$F$48:$L$48,0))*(1-$L$13)))*$F$44)*$D101)-($E$44*$D101)),(($E$44*$D101)*((1+$L$45)^($L$10-$E$48)-1)))),MIN(MAX(0,(((INDEX($F$55:$L$55,1,MATCH($L$10,$F$48:$L$48,0))+((G$100-$L$11)*INDEX($F$49:$L$49,1,MATCH($L$10,$F$48:$L$48,0))*(1-$L$13)))*$F$44)*$D101)-($E$44*$D101)),(($E$44*$D101)*((1+$L$45)^($L$10-$E$48)-1)))*($L$46/(1-$L$46))*$J$45)+(MAX(0,MAX(0,(((INDEX($F$55:$L$55,1,MATCH($L$10,$F$48:$L$48,0))+((G$100-$L$11)*INDEX($F$49:$L$49,1,MATCH($L$10,$F$48:$L$48,0))*(1-$L$13)))*$F$44)*$D101)-($E$44*$D101))-MIN(MAX(0,(((INDEX($F$55:$L$55,1,MATCH($L$10,$F$48:$L$48,0))+((G$100-$L$11)*INDEX($F$49:$L$49,1,MATCH($L$10,$F$48:$L$48,0))*(1-$L$13)))*$F$44)*$D101)-($E$44*$D101)),(($E$44*$D101)*((1+$L$45)^($L$10-$E$48)-1)))-MIN(MAX(0,MAX(0,(((INDEX($F$55:$L$55,1,MATCH($L$10,$F$48:$L$48,0))+((G$100-$L$11)*INDEX($F$49:$L$49,1,MATCH($L$10,$F$48:$L$48,0))*(1-$L$13)))*$F$44)*$D101)-($E$44*$D101))-MIN(MAX(0,(((INDEX($F$55:$L$55,1,MATCH($L$10,$F$48:$L$48,0))+((G$100-$L$11)*INDEX($F$49:$L$49,1,MATCH($L$10,$F$48:$L$48,0))*(1-$L$13)))*$F$44)*$D101)-($E$44*$D101)),(($E$44*$D101)*((1+$L$45)^($L$10-$E$48)-1)))),MIN(MAX(0,(((INDEX($F$55:$L$55,1,MATCH($L$10,$F$48:$L$48,0))+((G$100-$L$11)*INDEX($F$49:$L$49,1,MATCH($L$10,$F$48:$L$48,0))*(1-$L$13)))*$F$44)*$D101)-($E$44*$D101)),(($E$44*$D101)*((1+$L$45)^($L$10-$E$48)-1)))*($L$46/(1-$L$46))*$J$45))*$L$46)))/($E$44*(1-$D101)) -> 3.451864
D102: 0.8 | E102: =+(I102)^(1/($L$10-$E$48))-1 -> 0.13212755 | F102: =+(J102)^(1/($L$10-$E$48))-1 -> 0.18780561 | G102: =+(K102)^(1/($L$10-$E$48))-1 -> 0.20820996 | I102: =+(((((INDEX($F$55:$L$55,1,MATCH($L$10,$F$48:$L$48,0))+((E$100-$L$11)*INDEX($F$49:$L$49,1,MATCH($L$10,$F$48:$L$48,0))*(1-$L$13)))*$F$44)*(1-$D102))+MIN(MAX(0,MAX(0,(((INDEX($F$55:$L$55,1,MATCH($L$10,$F$48:$L$48,0))+((E$100-$L$11)*INDEX($F$49:$L$49,1,MATCH($L$10,$F$48:$L$48,0))*(1-$L$13)))*$F$44)*$D102)-($E$44*$D102))-MIN(MAX(0,(((INDEX($F$55:$L$55,1,MATCH($L$10,$F$48:$L$48,0))+((E$100-$L$11)*INDEX($F$49:$L$49,1,MATCH($L$10,$F$48:$L$48,0))*(1-$L$13)))*$F$44)*$D102)-($E$44*$D102)),(($E$44*$D102)*((1+$L$45)^($L$10-$E$48)-1)))),MIN(MAX(0,(((INDEX($F$55:$L$55,1,MATCH($L$10,$F$48:$L$48,0))+((E$100-$L$11)*INDEX($F$49:$L$49,1,MATCH($L$10,$F$48:$L$48,0))*(1-$L$13)))*$F$44)*$D102)-($E$44*$D102)),(($E$44*$D102)*((1+$L$45)^($L$10-$E$48)-1)))*($L$46/(1-$L$46))*$J$45)+(MAX(0,MAX(0,(((INDEX($F$55:$L$55,1,MATCH($L$10,$F$48:$L$48,0))+((E$100-$L$11)*INDEX($F$49:$L$49,1,MATCH($L$10,$F$48:$L$48,0))*(1-$L$13)))*$F$44)*$D102)-($E$44*$D102))-MIN(MAX(0,(((INDEX($F$55:$L$55,1,MATCH($L$10,$F$48:$L$48,0))+((E$100-$L$11)*INDEX($F$49:$L$49,1,MATCH($L$10,$F$48:$L$48,0))*(1-$L$13)))*$F$44)*$D102)-($E$44*$D102)),(($E$44*$D102)*((1+$L$45)^($L$10-$E$48)-1)))-MIN(MAX(0,MAX(0,(((INDEX($F$55:$L$55,1,MATCH($L$10,$F$48:$L$48,0))+((E$100-$L$11)*INDEX($F$49:$L$49,1,MATCH($L$10,$F$48:$L$48,0))*(1-$L$13)))*$F$44)*$D102)-($E$44*$D102))-MIN(MAX(0,(((INDEX($F$55:$L$55,1,MATCH($L$10,$F$48:$L$48,0))+((E$100-$L$11)*INDEX($F$49:$L$49,1,MATCH($L$10,$F$48:$L$48,0))*(1-$L$13)))*$F$44)*$D102)-($E$44*$D102)),(($E$44*$D102)*((1+$L$45)^($L$10-$E$48)-1)))),MIN(MAX(0,(((INDEX($F$55:$L$55,1,MATCH($L$10,$F$48:$L$48,0))+((E$100-$L$11)*INDEX($F$49:$L$49,1,MATCH($L$10,$F$48:$L$48,0))*(1-$L$13)))*$F$44)*$D102)-($E$44*$D102)),(($E$44*$D102)*((1+$L$45)^($L$10-$E$48)-1)))*($L$46/(1-$L$46))*$J$45))*$L$46)))/($E$44*(1-$D102)) -> 2.3837873 | J102: =+(((((INDEX($F$55:$L$55,1,MATCH($L$10,$F$48:$L$48,0))+((F$100-$L$11)*INDEX($F$49:$L$49,1,MATCH($L$10,$F$48:$L$48,0))*(1-$L$13)))*$F$44)*(1-$D102))+MIN(MAX(0,MAX(0,(((INDEX($F$55:$L$55,1,MATCH($L$10,$F$48:$L$48,0))+((F$100-$L$11)*INDEX($F$49:$L$49,1,MATCH($L$10,$F$48:$L$48,0))*(1-$L$13)))*$F$44)*$D102)-($E$44*$D102))-MIN(MAX(0,(((INDEX($F$55:$L$55,1,MATCH($L$10,$F$48:$L$48,0))+((F$100-$L$11)*INDEX($F$49:$L$49,1,MATCH($L$10,$F$48:$L$48,0))*(1-$L$13)))*$F$44)*$D102)-($E$44*$D102)),(($E$44*$D102)*((1+$L$45)^($L$10-$E$48)-1)))),MIN(MAX(0,(((INDEX($F$55:$L$55,1,MATCH($L$10,$F$48:$L$48,0))+((F$100-$L$11)*INDEX($F$49:$L$49,1,MATCH($L$10,$F$48:$L$48,0))*(1-$L$13)))*$F$44)*$D102)-($E$44*$D102)),(($E$44*$D102)*((1+$L$45)^($L$10-$E$48)-1)))*($L$46/(1-$L$46))*$J$45)+(MAX(0,MAX(0,(((INDEX($F$55:$L$55,1,MATCH($L$10,$F$48:$L$48,0))+((F$100-$L$11)*INDEX($F$49:$L$49,1,MATCH($L$10,$F$48:$L$48,0))*(1-$L$13)))*$F$44)*$D102)-($E$44*$D102))-MIN(MAX(0,(((INDEX($F$55:$L$55,1,MATCH($L$10,$F$48:$L$48,0))+((F$100-$L$11)*INDEX($F$49:$L$49,1,MATCH($L$10,$F$48:$L$48,0))*(1-$L$13)))*$F$44)*$D102)-($E$44*$D102)),(($E$44*$D102)*((1+$L$45)^($L$10-$E$48)-1)))-MIN(MAX(0,MAX(0,(((INDEX($F$55:$L$55,1,MATCH($L$10,$F$48:$L$48,0))+((F$100-$L$11)*INDEX($F$49:$L$49,1,MATCH($L$10,$F$48:$L$48,0))*(1-$L$13)))*$F$44)*$D102)-($E$44*$D102))-MIN(MAX(0,(((INDEX($F$55:$L$55,1,MATCH($L$10,$F$48:$L$48,0))+((F$100-$L$11)*INDEX($F$49:$L$49,1,MATCH($L$10,$F$48:$L$48,0))*(1-$L$13)))*$F$44)*$D102)-($E$44*$D102)),(($E$44*$D102)*((1+$L$45)^($L$10-$E$48)-1)))),MIN(MAX(0,(((INDEX($F$55:$L$55,1,MATCH($L$10,$F$48:$L$48,0))+((F$100-$L$11)*INDEX($F$49:$L$49,1,MATCH($L$10,$F$48:$L$48,0))*(1-$L$13)))*$F$44)*$D102)-($E$44*$D102)),(($E$44*$D102)*((1+$L$45)^($L$10-$E$48)-1)))*($L$46/(1-$L$46))*$J$45))*$L$46)))/($E$44*(1-$D102)) -> 3.3359352 | K102: =+(((((INDEX($F$55:$L$55,1,MATCH($L$10,$F$48:$L$48,0))+((G$100-$L$11)*INDEX($F$49:$L$49,1,MATCH($L$10,$F$48:$L$48,0))*(1-$L$13)))*$F$44)*(1-$D102))+MIN(MAX(0,MAX(0,(((INDEX($F$55:$L$55,1,MATCH($L$10,$F$48:$L$48,0))+((G$100-$L$11)*INDEX($F$49:$L$49,1,MATCH($L$10,$F$48:$L$48,0))*(1-$L$13)))*$F$44)*$D102)-($E$44*$D102))-MIN(MAX(0,(((INDEX($F$55:$L$55,1,MATCH($L$10,$F$48:$L$48,0))+((G$100-$L$11)*INDEX($F$49:$L$49,1,MATCH($L$10,$F$48:$L$48,0))*(1-$L$13)))*$F$44)*$D102)-($E$44*$D102)),(($E$44*$D102)*((1+$L$45)^($L$10-$E$48)-1)))),MIN(MAX(0,(((INDEX($F$55:$L$55,1,MATCH($L$10,$F$48:$L$48,0))+((G$100-$L$11)*INDEX($F$49:$L$49,1,MATCH($L$10,$F$48:$L$48,0))*(1-$L$13)))*$F$44)*$D102)-($E$44*$D102)),(($E$44*$D102)*((1+$L$45)^($L$10-$E$48)-1)))*($L$46/(1-$L$46))*$J$45)+(MAX(0,MAX(0,(((INDEX($F$55:$L$55,1,MATCH($L$10,$F$48:$L$48,0))+((G$100-$L$11)*INDEX($F$49:$L$49,1,MATCH($L$10,$F$48:$L$48,0))*(1-$L$13)))*$F$44)*$D102)-($E$44*$D102))-MIN(MAX(0,(((INDEX($F$55:$L$55,1,MATCH($L$10,$F$48:$L$48,0))+((G$100-$L$11)*INDEX($F$49:$L$49,1,MATCH($L$10,$F$48:$L$48,0))*(1-$L$13)))*$F$44)*$D102)-($E$44*$D102)),(($E$44*$D102)*((1+$L$45)^($L$10-$E$48)-1)))-MIN(MAX(0,MAX(0,(((INDEX($F$55:$L$55,1,MATCH($L$10,$F$48:$L$48,0))+((G$100-$L$11)*INDEX($F$49:$L$49,1,MATCH($L$10,$F$48:$L$48,0))*(1-$L$13)))*$F$44)*$D102)-($E$44*$D102))-MIN(MAX(0,(((INDEX($F$55:$L$55,1,MATCH($L$10,$F$48:$L$48,0))+((G$100-$L$11)*INDEX($F$49:$L$49,1,MATCH($L$10,$F$48:$L$48,0))*(1-$L$13)))*$F$44)*$D102)-($E$44*$D102)),(($E$44*$D102)*((1+$L$45)^($L$10-$E$48)-1)))),MIN(MAX(0,(((INDEX($F$55:$L$55,1,MATCH($L$10,$F$48:$L$48,0))+((G$100-$L$11)*INDEX($F$49:$L$49,1,MATCH($L$10,$F$48:$L$48,0))*(1-$L$13)))*$F$44)*$D102)-($E$44*$D102)),(($E$44*$D102)*((1+$L$45)^($L$10-$E$48)-1)))*($L$46/(1-$L$46))*$J$45))*$L$46)))/($E$44*(1-$D102)) -> 3.758347
D103: 0.85 | E103: =+(I103)^(1/($L$10-$E$48))-1 -> 0.14171965 | F103: =+(J103)^(1/($L$10-$E$48))-1 -> 0.20867642 | G103: =+(K103)^(1/($L$10-$E$48))-1 -> 0.23040703 | I103: =+(((((INDEX($F$55:$L$55,1,MATCH($L$10,$F$48:$L$48,0))+((E$100-$L$11)*INDEX($F$49:$L$49,1,MATCH($L$10,$F$48:$L$48,0))*(1-$L$13)))*$F$44)*(1-$D103))+MIN(MAX(0,MAX(0,(((INDEX($F$55:$L$55,1,MATCH($L$10,$F$48:$L$48,0))+((E$100-$L$11)*INDEX($F$49:$L$49,1,MATCH($L$10,$F$48:$L$48,0))*(1-$L$13)))*$F$44)*$D103)-($E$44*$D103))-MIN(MAX(0,(((INDEX($F$55:$L$55,1,MATCH($L$10,$F$48:$L$48,0))+((E$100-$L$11)*INDEX($F$49:$L$49,1,MATCH($L$10,$F$48:$L$48,0))*(1-$L$13)))*$F$44)*$D103)-($E$44*$D103)),(($E$44*$D103)*((1+$L$45)^($L$10-$E$48)-1)))),MIN(MAX(0,(((INDEX($F$55:$L$55,1,MATCH($L$10,$F$48:$L$48,0))+((E$100-$L$11)*INDEX($F$49:$L$49,1,MATCH($L$10,$F$48:$L$48,0))*(1-$L$13)))*$F$44)*$D103)-($E$44*$D103)),(($E$44*$D103)*((1+$L$45)^($L$10-$E$48)-1)))*($L$46/(1-$L$46))*$J$45)+(MAX(0,MAX(0,(((INDEX($F$55:$L$55,1,MATCH($L$10,$F$48:$L$48,0))+((E$100-$L$11)*INDEX($F$49:$L$49,1,MATCH($L$10,$F$48:$L$48,0))*(1-$L$13)))*$F$44)*$D103)-($E$44*$D103))-MIN(MAX(0,(((INDEX($F$55:$L$55,1,MATCH($L$10,$F$48:$L$48,0))+((E$100-$L$11)*INDEX($F$49:$L$49,1,MATCH($L$10,$F$48:$L$48,0))*(1-$L$13)))*$F$44)*$D103)-($E$44*$D103)),(($E$44*$D103)*((1+$L$45)^($L$10-$E$48)-1)))-MIN(MAX(0,MAX(0,(((INDEX($F$55:$L$55,1,MATCH($L$10,$F$48:$L$48,0))+((E$100-$L$11)*INDEX($F$49:$L$49,1,MATCH($L$10,$F$48:$L$48,0))*(1-$L$13)))*$F$44)*$D103)-($E$44*$D103))-MIN(MAX(0,(((INDEX($F$55:$L$55,1,MATCH($L$10,$F$48:$L$48,0))+((E$100-$L$11)*INDEX($F$49:$L$49,1,MATCH($L$10,$F$48:$L$48,0))*(1-$L$13)))*$F$44)*$D103)-($E$44*$D103)),(($E$44*$D103)*((1+$L$45)^($L$10-$E$48)-1)))),MIN(MAX(0,(((INDEX($F$55:$L$55,1,MATCH($L$10,$F$48:$L$48,0))+((E$100-$L$11)*INDEX($F$49:$L$49,1,MATCH($L$10,$F$48:$L$48,0))*(1-$L$13)))*$F$44)*$D103)-($E$44*$D103)),(($E$44*$D103)*((1+$L$45)^($L$10-$E$48)-1)))*($L$46/(1-$L$46))*$J$45))*$L$46)))/($E$44*(1-$D103)) -> 2.5288107 | J103: =+(((((INDEX($F$55:$L$55,1,MATCH($L$10,$F$48:$L$48,0))+((F$100-$L$11)*INDEX($F$49:$L$49,1,MATCH($L$10,$F$48:$L$48,0))*(1-$L$13)))*$F$44)*(1-$D103))+MIN(MAX(0,MAX(0,(((INDEX($F$55:$L$55,1,MATCH($L$10,$F$48:$L$48,0))+((F$100-$L$11)*INDEX($F$49:$L$49,1,MATCH($L$10,$F$48:$L$48,0))*(1-$L$13)))*$F$44)*$D103)-($E$44*$D103))-MIN(MAX(0,(((INDEX($F$55:$L$55,1,MATCH($L$10,$F$48:$L$48,0))+((F$100-$L$11)*INDEX($F$49:$L$49,1,MATCH($L$10,$F$48:$L$48,0))*(1-$L$13)))*$F$44)*$D103)-($E$44*$D103)),(($E$44*$D103)*((1+$L$45)^($L$10-$E$48)-1)))),MIN(MAX(0,(((INDEX($F$55:$L$55,1,MATCH($L$10,$F$48:$L$48,0))+((F$100-$L$11)*INDEX($F$49:$L$49,1,MATCH($L$10,$F$48:$L$48,0))*(1-$L$13)))*$F$44)*$D103)-($E$44*$D103)),(($E$44*$D103)*((1+$L$45)^($L$10-$E$48)-1)))*($L$46/(1-$L$46))*$J$45)+(MAX(0,MAX(0,(((INDEX($F$55:$L$55,1,MATCH($L$10,$F$48:$L$48,0))+((F$100-$L$11)*INDEX($F$49:$L$49,1,MATCH($L$10,$F$48:$L$48,0))*(1-$L$13)))*$F$44)*$D103)-($E$44*$D103))-MIN(MAX(0,(((INDEX($F$55:$L$55,1,MATCH($L$10,$F$48:$L$48,0))+((F$100-$L$11)*INDEX($F$49:$L$49,1,MATCH($L$10,$F$48:$L$48,0))*(1-$L$13)))*$F$44)*$D103)-($E$44*$D103)),(($E$44*$D103)*((1+$L$45)^($L$10-$E$48)-1)))-MIN(MAX(0,MAX(0,(((INDEX($F$55:$L$55,1,MATCH($L$10,$F$48:$L$48,0))+((F$100-$L$11)*INDEX($F$49:$L$49,1,MATCH($L$10,$F$48:$L$48,0))*(1-$L$13)))*$F$44)*$D103)-($E$44*$D103))-MIN(MAX(0,(((INDEX($F$55:$L$55,1,MATCH($L$10,$F$48:$L$48,0))+((F$100-$L$11)*INDEX($F$49:$L$49,1,MATCH($L$10,$F$48:$L$48,0))*(1-$L$13)))*$F$44)*$D103)-($E$44*$D103)),(($E$44*$D103)*((1+$L$45)^($L$10-$E$48)-1)))),MIN(MAX(0,(((INDEX($F$55:$L$55,1,MATCH($L$10,$F$48:$L$48,0))+((F$100-$L$11)*INDEX($F$49:$L$49,1,MATCH($L$10,$F$48:$L$48,0))*(1-$L$13)))*$F$44)*$D103)-($E$44*$D103)),(($E$44*$D103)*((1+$L$45)^($L$10-$E$48)-1)))*($L$46/(1-$L$46))*$J$45))*$L$46)))/($E$44*(1-$D103)) -> 3.7685158 | K103: =+(((((INDEX($F$55:$L$55,1,MATCH($L$10,$F$48:$L$48,0))+((G$100-$L$11)*INDEX($F$49:$L$49,1,MATCH($L$10,$F$48:$L$48,0))*(1-$L$13)))*$F$44)*(1-$D103))+MIN(MAX(0,MAX(0,(((INDEX($F$55:$L$55,1,MATCH($L$10,$F$48:$L$48,0))+((G$100-$L$11)*INDEX($F$49:$L$49,1,MATCH($L$10,$F$48:$L$48,0))*(1-$L$13)))*$F$44)*$D103)-($E$44*$D103))-MIN(MAX(0,(((INDEX($F$55:$L$55,1,MATCH($L$10,$F$48:$L$48,0))+((G$100-$L$11)*INDEX($F$49:$L$49,1,MATCH($L$10,$F$48:$L$48,0))*(1-$L$13)))*$F$44)*$D103)-($E$44*$D103)),(($E$44*$D103)*((1+$L$45)^($L$10-$E$48)-1)))),MIN(MAX(0,(((INDEX($F$55:$L$55,1,MATCH($L$10,$F$48:$L$48,0))+((G$100-$L$11)*INDEX($F$49:$L$49,1,MATCH($L$10,$F$48:$L$48,0))*(1-$L$13)))*$F$44)*$D103)-($E$44*$D103)),(($E$44*$D103)*((1+$L$45)^($L$10-$E$48)-1)))*($L$46/(1-$L$46))*$J$45)+(MAX(0,MAX(0,(((INDEX($F$55:$L$55,1,MATCH($L$10,$F$48:$L$48,0))+((G$100-$L$11)*INDEX($F$49:$L$49,1,MATCH($L$10,$F$48:$L$48,0))*(1-$L$13)))*$F$44)*$D103)-($E$44*$D103))-MIN(MAX(0,(((INDEX($F$55:$L$55,1,MATCH($L$10,$F$48:$L$48,0))+((G$100-$L$11)*INDEX($F$49:$L$49,1,MATCH($L$10,$F$48:$L$48,0))*(1-$L$13)))*$F$44)*$D103)-($E$44*$D103)),(($E$44*$D103)*((1+$L$45)^($L$10-$E$48)-1)))-MIN(MAX(0,MAX(0,(((INDEX($F$55:$L$55,1,MATCH($L$10,$F$48:$L$48,0))+((G$100-$L$11)*INDEX($F$49:$L$49,1,MATCH($L$10,$F$48:$L$48,0))*(1-$L$13)))*$F$44)*$D103)-($E$44*$D103))-MIN(MAX(0,(((INDEX($F$55:$L$55,1,MATCH($L$10,$F$48:$L$48,0))+((G$100-$L$11)*INDEX($F$49:$L$49,1,MATCH($L$10,$F$48:$L$48,0))*(1-$L$13)))*$F$44)*$D103)-($E$44*$D103)),(($E$44*$D103)*((1+$L$45)^($L$10-$E$48)-1)))),MIN(MAX(0,(((INDEX($F$55:$L$55,1,MATCH($L$10,$F$48:$L$48,0))+((G$100-$L$11)*INDEX($F$49:$L$49,1,MATCH($L$10,$F$48:$L$48,0))*(1-$L$13)))*$F$44)*$D103)-($E$44*$D103)),(($E$44*$D103)*((1+$L$45)^($L$10-$E$48)-1)))*($L$46/(1-$L$46))*$J$45))*$L$46)))/($E$44*(1-$D103)) -> 4.269152
D104: 0.9 | E104: =+(I104)^(1/($L$10-$E$48))-1 -> 0.15956783 | F104: =+(J104)^(1/($L$10-$E$48))-1 -> 0.24489365 | G104: =+(K104)^(1/($L$10-$E$48))-1 -> 0.26870236 | I104: =+(((((INDEX($F$55:$L$55,1,MATCH($L$10,$F$48:$L$48,0))+((E$100-$L$11)*INDEX($F$49:$L$49,1,MATCH($L$10,$F$48:$L$48,0))*(1-$L$13)))*$F$44)*(1-$D104))+MIN(MAX(0,MAX(0,(((INDEX($F$55:$L$55,1,MATCH($L$10,$F$48:$L$48,0))+((E$100-$L$11)*INDEX($F$49:$L$49,1,MATCH($L$10,$F$48:$L$48,0))*(1-$L$13)))*$F$44)*$D104)-($E$44*$D104))-MIN(MAX(0,(((INDEX($F$55:$L$55,1,MATCH($L$10,$F$48:$L$48,0))+((E$100-$L$11)*INDEX($F$49:$L$49,1,MATCH($L$10,$F$48:$L$48,0))*(1-$L$13)))*$F$44)*$D104)-($E$44*$D104)),(($E$44*$D104)*((1+$L$45)^($L$10-$E$48)-1)))),MIN(MAX(0,(((INDEX($F$55:$L$55,1,MATCH($L$10,$F$48:$L$48,0))+((E$100-$L$11)*INDEX($F$49:$L$49,1,MATCH($L$10,$F$48:$L$48,0))*(1-$L$13)))*$F$44)*$D104)-($E$44*$D104)),(($E$44*$D104)*((1+$L$45)^($L$10-$E$48)-1)))*($L$46/(1-$L$46))*$J$45)+(MAX(0,MAX(0,(((INDEX($F$55:$L$55,1,MATCH($L$10,$F$48:$L$48,0))+((E$100-$L$11)*INDEX($F$49:$L$49,1,MATCH($L$10,$F$48:$L$48,0))*(1-$L$13)))*$F$44)*$D104)-($E$44*$D104))-MIN(MAX(0,(((INDEX($F$55:$L$55,1,MATCH($L$10,$F$48:$L$48,0))+((E$100-$L$11)*INDEX($F$49:$L$49,1,MATCH($L$10,$F$48:$L$48,0))*(1-$L$13)))*$F$44)*$D104)-($E$44*$D104)),(($E$44*$D104)*((1+$L$45)^($L$10-$E$48)-1)))-MIN(MAX(0,MAX(0,(((INDEX($F$55:$L$55,1,MATCH($L$10,$F$48:$L$48,0))+((E$100-$L$11)*INDEX($F$49:$L$49,1,MATCH($L$10,$F$48:$L$48,0))*(1-$L$13)))*$F$44)*$D104)-($E$44*$D104))-MIN(MAX(0,(((INDEX($F$55:$L$55,1,MATCH($L$10,$F$48:$L$48,0))+((E$100-$L$11)*INDEX($F$49:$L$49,1,MATCH($L$10,$F$48:$L$48,0))*(1-$L$13)))*$F$44)*$D104)-($E$44*$D104)),(($E$44*$D104)*((1+$L$45)^($L$10-$E$48)-1)))),MIN(MAX(0,(((INDEX($F$55:$L$55,1,MATCH($L$10,$F$48:$L$48,0))+((E$100-$L$11)*INDEX($F$49:$L$49,1,MATCH($L$10,$F$48:$L$48,0))*(1-$L$13)))*$F$44)*$D104)-($E$44*$D104)),(($E$44*$D104)*((1+$L$45)^($L$10-$E$48)-1)))*($L$46/(1-$L$46))*$J$45))*$L$46)))/($E$44*(1-$D104)) -> 2.8188575 | J104: =+(((((INDEX($F$55:$L$55,1,MATCH($L$10,$F$48:$L$48,0))+((F$100-$L$11)*INDEX($F$49:$L$49,1,MATCH($L$10,$F$48:$L$48,0))*(1-$L$13)))*$F$44)*(1-$D104))+MIN(MAX(0,MAX(0,(((INDEX($F$55:$L$55,1,MATCH($L$10,$F$48:$L$48,0))+((F$100-$L$11)*INDEX($F$49:$L$49,1,MATCH($L$10,$F$48:$L$48,0))*(1-$L$13)))*$F$44)*$D104)-($E$44*$D104))-MIN(MAX(0,(((INDEX($F$55:$L$55,1,MATCH($L$10,$F$48:$L$48,0))+((F$100-$L$11)*INDEX($F$49:$L$49,1,MATCH($L$10,$F$48:$L$48,0))*(1-$L$13)))*$F$44)*$D104)-($E$44*$D104)),(($E$44*$D104)*((1+$L$45)^($L$10-$E$48)-1)))),MIN(MAX(0,(((INDEX($F$55:$L$55,1,MATCH($L$10,$F$48:$L$48,0))+((F$100-$L$11)*INDEX($F$49:$L$49,1,MATCH($L$10,$F$48:$L$48,0))*(1-$L$13)))*$F$44)*$D104)-($E$44*$D104)),(($E$44*$D104)*((1+$L$45)^($L$10-$E$48)-1)))*($L$46/(1-$L$46))*$J$45)+(MAX(0,MAX(0,(((INDEX($F$55:$L$55,1,MATCH($L$10,$F$48:$L$48,0))+((F$100-$L$11)*INDEX($F$49:$L$49,1,MATCH($L$10,$F$48:$L$48,0))*(1-$L$13)))*$F$44)*$D104)-($E$44*$D104))-MIN(MAX(0,(((INDEX($F$55:$L$55,1,MATCH($L$10,$F$48:$L$48,0))+((F$100-$L$11)*INDEX($F$49:$L$49,1,MATCH($L$10,$F$48:$L$48,0))*(1-$L$13)))*$F$44)*$D104)-($E$44*$D104)),(($E$44*$D104)*((1+$L$45)^($L$10-$E$48)-1)))-MIN(MAX(0,MAX(0,(((INDEX($F$55:$L$55,1,MATCH($L$10,$F$48:$L$48,0))+((F$100-$L$11)*INDEX($F$49:$L$49,1,MATCH($L$10,$F$48:$L$48,0))*(1-$L$13)))*$F$44)*$D104)-($E$44*$D104))-MIN(MAX(0,(((INDEX($F$55:$L$55,1,MATCH($L$10,$F$48:$L$48,0))+((F$100-$L$11)*INDEX($F$49:$L$49,1,MATCH($L$10,$F$48:$L$48,0))*(1-$L$13)))*$F$44)*$D104)-($E$44*$D104)),(($E$44*$D104)*((1+$L$45)^($L$10-$E$48)-1)))),MIN(MAX(0,(((INDEX($F$55:$L$55,1,MATCH($L$10,$F$48:$L$48,0))+((F$100-$L$11)*INDEX($F$49:$L$49,1,MATCH($L$10,$F$48:$L$48,0))*(1-$L$13)))*$F$44)*$D104)-($E$44*$D104)),(($E$44*$D104)*((1+$L$45)^($L$10-$E$48)-1)))*($L$46/(1-$L$46))*$J$45))*$L$46)))/($E$44*(1-$D104)) -> 4.633677 | K104: =+(((((INDEX($F$55:$L$55,1,MATCH($L$10,$F$48:$L$48,0))+((G$100-$L$11)*INDEX($F$49:$L$49,1,MATCH($L$10,$F$48:$L$48,0))*(1-$L$13)))*$F$44)*(1-$D104))+MIN(MAX(0,MAX(0,(((INDEX($F$55:$L$55,1,MATCH($L$10,$F$48:$L$48,0))+((G$100-$L$11)*INDEX($F$49:$L$49,1,MATCH($L$10,$F$48:$L$48,0))*(1-$L$13)))*$F$44)*$D104)-($E$44*$D104))-MIN(MAX(0,(((INDEX($F$55:$L$55,1,MATCH($L$10,$F$48:$L$48,0))+((G$100-$L$11)*INDEX($F$49:$L$49,1,MATCH($L$10,$F$48:$L$48,0))*(1-$L$13)))*$F$44)*$D104)-($E$44*$D104)),(($E$44*$D104)*((1+$L$45)^($L$10-$E$48)-1)))),MIN(MAX(0,(((INDEX($F$55:$L$55,1,MATCH($L$10,$F$48:$L$48,0))+((G$100-$L$11)*INDEX($F$49:$L$49,1,MATCH($L$10,$F$48:$L$48,0))*(1-$L$13)))*$F$44)*$D104)-($E$44*$D104)),(($E$44*$D104)*((1+$L$45)^($L$10-$E$48)-1)))*($L$46/(1-$L$46))*$J$45)+(MAX(0,MAX(0,(((INDEX($F$55:$L$55,1,MATCH($L$10,$F$48:$L$48,0))+((G$100-$L$11)*INDEX($F$49:$L$49,1,MATCH($L$10,$F$48:$L$48,0))*(1-$L$13)))*$F$44)*$D104)-($E$44*$D104))-MIN(MAX(0,(((INDEX($F$55:$L$55,1,MATCH($L$10,$F$48:$L$48,0))+((G$100-$L$11)*INDEX($F$49:$L$49,1,MATCH($L$10,$F$48:$L$48,0))*(1-$L$13)))*$F$44)*$D104)-($E$44*$D104)),(($E$44*$D104)*((1+$L$45)^($L$10-$E$48)-1)))-MIN(MAX(0,MAX(0,(((INDEX($F$55:$L$55,1,MATCH($L$10,$F$48:$L$48,0))+((G$100-$L$11)*INDEX($F$49:$L$49,1,MATCH($L$10,$F$48:$L$48,0))*(1-$L$13)))*$F$44)*$D104)-($E$44*$D104))-MIN(MAX(0,(((INDEX($F$55:$L$55,1,MATCH($L$10,$F$48:$L$48,0))+((G$100-$L$11)*INDEX($F$49:$L$49,1,MATCH($L$10,$F$48:$L$48,0))*(1-$L$13)))*$F$44)*$D104)-($E$44*$D104)),(($E$44*$D104)*((1+$L$45)^($L$10-$E$48)-1)))),MIN(MAX(0,(((INDEX($F$55:$L$55,1,MATCH($L$10,$F$48:$L$48,0))+((G$100-$L$11)*INDEX($F$49:$L$49,1,MATCH($L$10,$F$48:$L$48,0))*(1-$L$13)))*$F$44)*$D104)-($E$44*$D104)),(($E$44*$D104)*((1+$L$45)^($L$10-$E$48)-1)))*($L$46/(1-$L$46))*$J$45))*$L$46)))/($E$44*(1-$D104)) -> 5.290762
D106: Offer Premium \ Total Debt xEBITDA (Gross Pool IRR) | E106: 7 | F106: =+$G$30 -> 8.1279393 | G106: 9 | I106: =+E106 -> 7 | J106: =+F106 -> 8.1279393 | K106: =+G106 -> 9
D107: 0.08 | E107: =+(I107)^(1/($L$10-$E$48))-1 -> 0.12294722 | F107: =+(J107)^(1/($L$10-$E$48))-1 -> 0.12932945 | G107: =+(K107)^(1/($L$10-$E$48))-1 -> 0.13506421 | I107: =+(((INDEX($F$55:$L$55,1,MATCH($L$10,$F$48:$L$48,0))+((((($F$9*(1+$D107)*$F$12)-$F$19)/$F$7)-$L$11)*INDEX($F$49:$L$49,1,MATCH($L$10,$F$48:$L$48,0))*(1-$L$13))-((E$106-$G$30)*$F$7*(1+($L$10-$E$48)*'Debt & Covenants'!$E$7*(1-0.22)))))*(((($F$9*(1+$D107)*$F$12)*$F$15)*(1+$L$12)+$I$30-(E$106*$F$7)-$F$20)/(((($F$9*(1+$D107)*$F$12)*$F$15)*(1+$L$12)+$I$30-(E$106*$F$7)-$F$20)+(($F$9*(1+$D107)*$F$12)*$F$14))))/((($F$9*(1+$D107)*$F$12)*$F$15)*(1+$L$12)+$I$30-(E$106*$F$7)-$F$20) -> 2.2517253 | J107: =+(((INDEX($F$55:$L$55,1,MATCH($L$10,$F$48:$L$48,0))+((((($F$9*(1+$D107)*$F$12)-$F$19)/$F$7)-$L$11)*INDEX($F$49:$L$49,1,MATCH($L$10,$F$48:$L$48,0))*(1-$L$13))-((F$106-$G$30)*$F$7*(1+($L$10-$E$48)*'Debt & Covenants'!$E$7*(1-0.22)))))*(((($F$9*(1+$D107)*$F$12)*$F$15)*(1+$L$12)+$I$30-(F$106*$F$7)-$F$20)/(((($F$9*(1+$D107)*$F$12)*$F$15)*(1+$L$12)+$I$30-(F$106*$F$7)-$F$20)+(($F$9*(1+$D107)*$F$12)*$F$14))))/((($F$9*(1+$D107)*$F$12)*$F$15)*(1+$L$12)+$I$30-(F$106*$F$7)-$F$20) -> 2.3428505 | K107: =+(((INDEX($F$55:$L$55,1,MATCH($L$10,$F$48:$L$48,0))+((((($F$9*(1+$D107)*$F$12)-$F$19)/$F$7)-$L$11)*INDEX($F$49:$L$49,1,MATCH($L$10,$F$48:$L$48,0))*(1-$L$13))-((G$106-$G$30)*$F$7*(1+($L$10-$E$48)*'Debt & Covenants'!$E$7*(1-0.22)))))*(((($F$9*(1+$D107)*$F$12)*$F$15)*(1+$L$12)+$I$30-(G$106*$F$7)-$F$20)/(((($F$9*(1+$D107)*$F$12)*$F$15)*(1+$L$12)+$I$30-(G$106*$F$7)-$F$20)+(($F$9*(1+$D107)*$F$12)*$F$14))))/((($F$9*(1+$D107)*$F$12)*$F$15)*(1+$L$12)+$I$30-(G$106*$F$7)-$F$20) -> 2.4274093
D108: 0.12 | E108: =+(I108)^(1/($L$10-$E$48))-1 -> 0.12037716 | F108: =+(J108)^(1/($L$10-$E$48))-1 -> 0.12619725 | G108: =+(K108)^(1/($L$10-$E$48))-1 -> 0.13138175 | I108: =+(((INDEX($F$55:$L$55,1,MATCH($L$10,$F$48:$L$48,0))+((((($F$9*(1+$D108)*$F$12)-$F$19)/$F$7)-$L$11)*INDEX($F$49:$L$49,1,MATCH($L$10,$F$48:$L$48,0))*(1-$L$13))-((E$106-$G$30)*$F$7*(1+($L$10-$E$48)*'Debt & Covenants'!$E$7*(1-0.22)))))*(((($F$9*(1+$D108)*$F$12)*$F$15)*(1+$L$12)+$I$30-(E$106*$F$7)-$F$20)/(((($F$9*(1+$D108)*$F$12)*$F$15)*(1+$L$12)+$I$30-(E$106*$F$7)-$F$20)+(($F$9*(1+$D108)*$F$12)*$F$14))))/((($F$9*(1+$D108)*$F$12)*$F$15)*(1+$L$12)+$I$30-(E$106*$F$7)-$F$20) -> 2.2158977 | J108: =+(((INDEX($F$55:$L$55,1,MATCH($L$10,$F$48:$L$48,0))+((((($F$9*(1+$D108)*$F$12)-$F$19)/$F$7)-$L$11)*INDEX($F$49:$L$49,1,MATCH($L$10,$F$48:$L$48,0))*(1-$L$13))-((F$106-$G$30)*$F$7*(1+($L$10-$E$48)*'Debt & Covenants'!$E$7*(1-0.22)))))*(((($F$9*(1+$D108)*$F$12)*$F$15)*(1+$L$12)+$I$30-(F$106*$F$7)-$F$20)/(((($F$9*(1+$D108)*$F$12)*$F$15)*(1+$L$12)+$I$30-(F$106*$F$7)-$F$20)+(($F$9*(1+$D108)*$F$12)*$F$14))))/((($F$9*(1+$D108)*$F$12)*$F$15)*(1+$L$12)+$I$30-(F$106*$F$7)-$F$20) -> 2.2977418 | K108: =+(((INDEX($F$55:$L$55,1,MATCH($L$10,$F$48:$L$48,0))+((((($F$9*(1+$D108)*$F$12)-$F$19)/$F$7)-$L$11)*INDEX($F$49:$L$49,1,MATCH($L$10,$F$48:$L$48,0))*(1-$L$13))-((G$106-$G$30)*$F$7*(1+($L$10-$E$48)*'Debt & Covenants'!$E$7*(1-0.22)))))*(((($F$9*(1+$D108)*$F$12)*$F$15)*(1+$L$12)+$I$30-(G$106*$F$7)-$F$20)/(((($F$9*(1+$D108)*$F$12)*$F$15)*(1+$L$12)+$I$30-(G$106*$F$7)-$F$20)+(($F$9*(1+$D108)*$F$12)*$F$14))))/((($F$9*(1+$D108)*$F$12)*$F$15)*(1+$L$12)+$I$30-(G$106*$F$7)-$F$20) -> 2.3728167
D109: 0.16 | E109: =+(I109)^(1/($L$10-$E$48))-1 -> 0.11805863 | F109: =+(J109)^(1/($L$10-$E$48))-1 -> 0.1233958 | G109: =+(K109)^(1/($L$10-$E$48))-1 -> 0.12811363 | I109: =+(((INDEX($F$55:$L$55,1,MATCH($L$10,$F$48:$L$48,0))+((((($F$9*(1+$D109)*$F$12)-$F$19)/$F$7)-$L$11)*INDEX($F$49:$L$49,1,MATCH($L$10,$F$48:$L$48,0))*(1-$L$13))-((E$106-$G$30)*$F$7*(1+($L$10-$E$48)*'Debt & Covenants'!$E$7*(1-0.22)))))*(((($F$9*(1+$D109)*$F$12)*$F$15)*(1+$L$12)+$I$30-(E$106*$F$7)-$F$20)/(((($F$9*(1+$D109)*$F$12)*$F$15)*(1+$L$12)+$I$30-(E$106*$F$7)-$F$20)+(($F$9*(1+$D109)*$F$12)*$F$14))))/((($F$9*(1+$D109)*$F$12)*$F$15)*(1+$L$12)+$I$30-(E$106*$F$7)-$F$20) -> 2.183997 | J109: =+(((INDEX($F$55:$L$55,1,MATCH($L$10,$F$48:$L$48,0))+((((($F$9*(1+$D109)*$F$12)-$F$19)/$F$7)-$L$11)*INDEX($F$49:$L$49,1,MATCH($L$10,$F$48:$L$48,0))*(1-$L$13))-((F$106-$G$30)*$F$7*(1+($L$10-$E$48)*'Debt & Covenants'!$E$7*(1-0.22)))))*(((($F$9*(1+$D109)*$F$12)*$F$15)*(1+$L$12)+$I$30-(F$106*$F$7)-$F$20)/(((($F$9*(1+$D109)*$F$12)*$F$15)*(1+$L$12)+$I$30-(F$106*$F$7)-$F$20)+(($F$9*(1+$D109)*$F$12)*$F$14))))/((($F$9*(1+$D109)*$F$12)*$F$15)*(1+$L$12)+$I$30-(F$106*$F$7)-$F$20) -> 2.2580292 | K109: =+(((INDEX($F$55:$L$55,1,MATCH($L$10,$F$48:$L$48,0))+((((($F$9*(1+$D109)*$F$12)-$F$19)/$F$7)-$L$11)*INDEX($F$49:$L$49,1,MATCH($L$10,$F$48:$L$48,0))*(1-$L$13))-((G$106-$G$30)*$F$7*(1+($L$10-$E$48)*'Debt & Covenants'!$E$7*(1-0.22)))))*(((($F$9*(1+$D109)*$F$12)*$F$15)*(1+$L$12)+$I$30-(G$106*$F$7)-$F$20)/(((($F$9*(1+$D109)*$F$12)*$F$15)*(1+$L$12)+$I$30-(G$106*$F$7)-$F$20)+(($F$9*(1+$D109)*$F$12)*$F$14))))/((($F$9*(1+$D109)*$F$12)*$F$15)*(1+$L$12)+$I$30-(G$106*$F$7)-$F$20) -> 2.3252515

Sheet Active Case
B1: Project Galicia v3 — Inditex (ITX.MC) | U1: Strictly Private & Confidential
A2: > | B2: Active Case — 100% Inditex Consolidated Operating Model (2022A–2032E), Pre-IFRS 16 Bridge, Negative NOF & Capex Split
A4: > | B4: > | C4: 1. Operating Scenario Drivers & Presets (100% Inditex Consolidated — Zero Minority Leakage)
C6: Drivers | E6: 1 | F6: 2 | G6: 3 | H6: Active: | I6: 31-Jan | J6: 31-Jan | K6: 31-Jan | L6: 31-Jan | M6: 31-Jan | N6: 31-Jan | O6: 31-Jan | P6: 31-Jan | Q6: 31-Jan | R6: 31-Jan | S6: 31-Jan
C7: €m | D7: 100% Inditex Consolidated Line Item | E7: Base | F7: Bull | G7: Bear | H7: =CHOOSE($F$8,E7,F7,G7) -> Base | I7: 2022 | J7: =+I7+1 -> 2023 | K7: =+J7+1 -> 2024 | L7: =+K7+1 -> 2025 | M7: =+L7+1 -> 2026 | N7: =+M7+1 -> 2027 | O7: =+N7+1 -> 2028 | P7: =+O7+1 -> 2029 | Q7: =+P7+1 -> 2030 | ... S7: =+R7+1 -> 2032
B8: 1 | D8: Active Scenario Selector (1=Base, 2=Bull, 3=Bear) | E8: Select -> | F8: 1 | H8: =CHOOSE($F$8,E7,F7,G7) -> Base
D9: Revenue growth (% YoY) | E9: 0.055 | F9: 0.08 | G9: 0.0225 | H9: =CHOOSE($F$8,E9,F9,G9) -> 0.055 | I9: 0.175 | J9: 0.104 | K9: 0.075 | L9: 0.032 | M9: =+$H9 -> 0.055 | N9: =+$H9 -> 0.055 | O9: =+$H9 -> 0.055 | P9: =+$H9 -> 0.055 | Q9: =+$H9 -> 0.055 | R9: =+$H9 -> 0.055 | S9: =+$H9 -> 0.055
D10: Gross margin (% of revenues) | E10: 0.582 | F10: 0.59 | G10: 0.57 | H10: =CHOOSE($F$8,E10,F10,G10) -> 0.582 | I10: =+I23/I$21 -> 0.56983635 | J10: =+J23/J$21 -> 0.57757254 | K10: =+K23/K$21 -> 0.57835473 | L10: =+L23/L$21 -> 0.5825306 | M10: =+$H10 -> 0.582 | N10: =+$H10 -> 0.582 | O10: =+$H10 -> 0.582 | P10: =+$H10 -> 0.582 | Q10: =+$H10 -> 0.582 | R10: =+$H10 -> 0.582 | S10: =+$H10 -> 0.582
D11: OpEx growth (% YoY) | E11: 0.0425 | F11: 0.055 | G11: 0.0325 | H11: =CHOOSE($F$8,E11,F11,G11) -> 0.0425 | I11: 0.109 | J11: 0.1 | K11: 0.065 | L11: 0.028 | M11: =+$H11 -> 0.0425 | N11: =+$H11 -> 0.0425 | O11: =+$H11 -> 0.0425 | P11: =+$H11 -> 0.0425 | Q11: =+$H11 -> 0.0425 | R11: =+$H11 -> 0.0425 | S11: =+$H11 -> 0.0425
D12: Fixed lease cash outflow growth (%) | E12: 0.02 | F12: 0.03 | G12: 0.01 | H12: =CHOOSE($F$8,E12,F12,G12) -> 0.02 | I12: 0.05 | J12: =+J28/I28-1 -> 0.069093152 | K12: =+K28/J28-1 -> 0.039815349 | L12: =+L28/K28-1 -> 0.017758047 | M12: =+$H12 -> 0.02 | N12: =+$H12 -> 0.02 | O12: =+$H12 -> 0.02 | P12: =+$H12 -> 0.02 | Q12: =+$H12 -> 0.02 | R12: =+$H12 -> 0.02 | S12: =+$H12 -> 0.02
D13: Maintenance Capex (% of revenues) | E13: 0.035 | F13: 0.035 | G13: 0.034 | H13: =CHOOSE($F$8,E13,F13,G13) -> 0.035 | I13: =+I52/I$21 -> 0.032239246 | J13: =+J52/J$21 -> 0.034773416 | K13: =+K52/K$21 -> 0.037533651 | L13: =+L52/L$21 -> 0.037126229 | M13: =+$H13 -> 0.035 | N13: =+$H13 -> 0.035 | O13: =+$H13 -> 0.035 | P13: =+$H13 -> 0.035 | Q13: =+$H13 -> 0.035 | R13: =+$H13 -> 0.035 | S13: =+$H13 -> 0.035
D14: Expansion Capex: US Rollout & Logistics (%) | E14: 0.017 | F14: 0.02 | G14: 0.012 | H14: =CHOOSE($F$8,E14,F14,G14) -> 0.017 | I14: =+I53/I$21 -> 0.011206976 | J14: =+J53/J$21 -> 0.017303252 | K14: =+K53/K$21 -> 0.031631808 | L14: =+L53/L$21 -> 0.030905077 | M14: =+$H14 -> 0.017 | N14: =+$H14 -> 0.017 | O14: =+$H14 -> 0.017 | P14: =+$H14 -> 0.017 | Q14: =+$H14 -> 0.017 | R14: =+$H14 -> 0.017 | S14: =+$H14 -> 0.017
D15: Inventory (% of revenues) | E15: 0.0815 | F15: 0.079 | G15: 0.085 | H15: =CHOOSE($F$8,E15,F15,G15) -> 0.0815 | I15: =+I39/I$21 -> 0.097976604 | J15: =+J39/J$21 -> 0.082510362 | K15: =+K39/K$21 -> 0.085965003 | L15: =+L39/L$21 -> 0.081502107 | M15: =+$H15 -> 0.0815 | N15: =+$H15 -> 0.0815 | O15: =+$H15 -> 0.0815 | P15: =+$H15 -> 0.0815 | Q15: =+$H15 -> 0.0815 | R15: =+$H15 -> 0.0815 | S15: =+$H15 -> 0.0815
D16: Receivables (% of revenues) | E16: 0.0292 | F16: 0.0285 | G16: 0.03 | H16: =CHOOSE($F$8,E16,F16,G16) -> 0.0292 | I16: =+I40/I$21 -> 0.026129141 | J16: =+J40/J$21 -> 0.028875845 | K16: =+K40/K$21 -> 0.028163181 | L16: =+L40/L$21 -> 0.029249448 | M16: =+$H16 -> 0.0292 | N16: =+$H16 -> 0.0292 | O16: =+$H16 -> 0.0292 | P16: =+$H16 -> 0.0292 | Q16: =+$H16 -> 0.0292 | R16: =+$H16 -> 0.0292 | S16: =+$H16 -> 0.0292
D17: Payables (% of revenues, negative — NOF) | E17: -0.2154 | F17: -0.2155 | G17: -0.213 | H17: =CHOOSE($F$8,E17,F17,G17) -> -0.2154 | I17: =+I41/I$21 -> -0.20144923 | J17: =+J41/J$21 -> -0.20772248 | K17: =+K41/K$21 -> -0.22235452 | L17: =+L41/L$21 -> -0.21540739 | M17: =+$H17 -> -0.2154 | N17: =+$H17 -> -0.2154 | O17: =+$H17 -> -0.2154 | P17: =+$H17 -> -0.2154 | Q17: =+$H17 -> -0.2154 | R17: =+$H17 -> -0.2154 | S17: =+$H17 -> -0.2154
C19: P&L | I19: 31-Jan | J19: 31-Jan | K19: 31-Jan | L19: 31-Jan | M19: 31-Jan | N19: 31-Jan | O19: 31-Jan | P19: 31-Jan | Q19: 31-Jan | R19: 31-Jan | S19: 31-Jan | T19: CAGR | U19: CAGR
C20: €m | D20: 100% Inditex Consolidated Line Item | I20: 2022 | J20: =+I20+1 -> 2023 | K20: =+J20+1 -> 2024 | L20: =+K20+1 -> 2025 | M20: =+L20+1 -> 2026 | N20: =+M20+1 -> 2027 | O20: =+N20+1 -> 2028 | P20: =+O20+1 -> 2029 | Q20: =+P20+1 -> 2030 | ... S20: =+R20+1 -> 2032 | T20: 22A-25A | U20: 25A-32E
B21: 2 | D21: Net Revenues (100% Inditex) | I21: 32569 | J21: 35947 | K21: 38632 | L21: 39864 | M21: =+L21*(1+M9) -> 42056.52 | N21: =+M21*(1+N9) -> 44369.629 | O21: =+N21*(1+O9) -> 46809.958 | P21: =+O21*(1+P9) -> 49384.506 | Q21: =+P21*(1+Q9) -> 52100.654 | R21: =+Q21*(1+R9) -> 54966.19 | S21: =+R21*(1+S9) -> 57989.33 | T21: =+IFERROR((L21/I21)^(1/(L$20-I$20))-1,0) -> 0.06969217 | U21: =+IFERROR((S21/L21)^(1/(S$20-L$20))-1,0) -> 0.055
D22: COGS | I22: =+I23-I21 -> -14010 | J22: =+J23-J21 -> -15185 | K22: =+K23-K21 -> -16289 | L22: =+L23-L21 -> -16642 | M22: =+M23-M21 -> -17579.625 | N22: =+N23-N21 -> -18546.505 | O22: =+O23-O21 -> -19566.563 | P22: =+P23-P21 -> -20642.723 | ... S22: =+S23-S21 -> -24239.54 | T22: =+IFERROR((L22/I22)^(1/(L$20-I$20))-1,0) -> 0.059064622 | U22: =+IFERROR((S22/L22)^(1/(S$20-L$20))-1,0) -> 0.055191454
D23: Gross Profit | I23: 18559 | J23: 20762 | K23: 22343 | L23: 23222 | M23: =+M21*M10 -> 24476.895 | N23: =+N21*N10 -> 25823.124 | O23: =+O21*O10 -> 27243.396 | P23: =+P21*P10 -> 28741.782 | Q23: =+Q21*Q10 -> 30322.58 | R23: =+R21*R10 -> 31990.322 | S23: =+S21*S10 -> 33749.79 | T23: =+IFERROR((L23/I23)^(1/(L$20-I$20))-1,0) -> 0.077577091 | U23: =+IFERROR((S23/L23)^(1/(S$20-L$20))-1,0) -> 0.054862667
D24: % Gross margin | I24: =+IFERROR(I23/I$21,0) -> 0.56983635 | J24: =+IFERROR(J23/J$21,0) -> 0.57757254 | K24: =+IFERROR(K23/K$21,0) -> 0.57835473 | L24: =+IFERROR(L23/L$21,0) -> 0.5825306 | M24: =+IFERROR(M23/M$21,0) -> 0.582 | N24: =+IFERROR(N23/N$21,0) -> 0.582 | O24: =+IFERROR(O23/O$21,0) -> 0.582 | P24: =+IFERROR(P23/P$21,0) -> 0.582 | ... S24: =+IFERROR(S23/S$21,0) -> 0.582
D25: OpEx (Personnel, variable turnover rent & SG&A) | I25: -9910 | J25: -10912 | K25: -11615 | L25: -11955 | M25: =+L25*(1+M11) -> -12463.087 | N25: =+M25*(1+N11) -> -12992.769 | O25: =+N25*(1+O11) -> -13544.961 | P25: =+O25*(1+P11) -> -14120.622 | Q25: =+P25*(1+Q11) -> -14720.749 | R25: =+Q25*(1+R11) -> -15346.381 | S25: =+R25*(1+S11) -> -15998.602 | T25: =+IFERROR((L25/I25)^(1/(L$20-I$20))-1,0) -> 0.064531806 | U25: =+IFERROR((S25/L25)^(1/(S$20-L$20))-1,0) -> 0.0425
D26: Reported EBITDA (Post-IFRS 16 — 100% Inditex) | I26: =+I23+I25 -> 8649 | J26: =+J23+J25 -> 9850 | K26: =+K23+K25 -> 10728 | L26: =+L23+L25 -> 11267 | M26: =+M23+M25 -> 12013.807 | N26: =+N23+N25 -> 12830.355 | O26: =+O23+O25 -> 13698.434 | P26: =+P23+P25 -> 14621.16 | ... S26: =+S23+S25 -> 17751.188 | T26: =+IFERROR((L26/I26)^(1/(L$20-I$20))-1,0) -> 0.09214625 | U26: =+IFERROR((S26/L26)^(1/(S$20-L$20))-1,0) -> 0.067094138
D27: % Reported EBITDA margin (Post-IFRS 16) | I27: =+IFERROR(I26/I$21,0) -> 0.26555927 | J27: =+IFERROR(J26/J$21,0) -> 0.27401452 | K27: =+IFERROR(K26/K$21,0) -> 0.27769725 | L27: =+IFERROR(L26/L$21,0) -> 0.28263596 | M27: =+IFERROR(M26/M$21,0) -> 0.28565861 | N27: =+IFERROR(N26/N$21,0) -> 0.28916977 | O27: =+IFERROR(O26/O$21,0) -> 0.29263932 | P27: =+IFERROR(P26/P$21,0) -> 0.29606776 | ... S27: =+IFERROR(S26/S$21,0) -> 0.30611129
D28: Less: Fixed cash lease outflow (IFRS 16 Note 16 / CF Statement) | I28: -1621 | J28: -1733 | K28: -1802 | L28: -1834 | M28: =+L28*(1+M12) -> -1870.68 | N28: =+M28*(1+N12) -> -1908.0936 | O28: =+N28*(1+O12) -> -1946.2555 | P28: =+O28*(1+P12) -> -1985.1806 | Q28: =+P28*(1+Q12) -> -2024.8842 | R28: =+Q28*(1+R12) -> -2065.3819 | S28: =+R28*(1+S12) -> -2106.6895 | T28: =+IFERROR((L28/I28)^(1/(L$20-I$20))-1,0) -> 0.042010525 | U28: =+IFERROR((S28/L28)^(1/(S$20-L$20))-1,0) -> 0.02
D29: Plus: Due Diligence Adjustments & Normalizations | I29: 0 | J29: 0 | K29: 0 | L29: 0 | M29: 0 | N29: 0 | O29: 0 | P29: 0 | Q29: 0 | R29: 0 | S29: 0
D30: Pre-IFRS 16 Normalized Cash EBITDA (100% Inditex — LBO Basis) | I30: =+I26+I28+I29 -> 7028 | J30: =+J26+J28+J29 -> 8117 | K30: =+K26+K28+K29 -> 8926 | L30: =+L26+L28+L29 -> 9433 | M30: =+M26+M28+M29 -> 10143.127 | N30: =+N26+N28+N29 -> 10922.262 | O30: =+O26+O28+O29 -> 11752.179 | P30: =+P26+P28+P29 -> 12635.98 | ... S30: =+S26+S28+S29 -> 15644.499 | T30: =+IFERROR((L30/I30)^(1/(L$20-I$20))-1,0) -> 0.1030775 | U30: =+IFERROR((S30/L30)^(1/(S$20-L$20))-1,0) -> 0.074947869
D31: % Pre-IFRS 16 Cash EBITDA margin | I31: =+IFERROR(I30/I$21,0) -> 0.21578802 | J31: =+IFERROR(J30/J$21,0) -> 0.22580466 | K31: =+IFERROR(K30/K$21,0) -> 0.23105198 | L31: =+IFERROR(L30/L$21,0) -> 0.23662954 | M31: =+IFERROR(M30/M$21,0) -> 0.24117847 | N31: =+IFERROR(N30/N$21,0) -> 0.24616527 | O31: =+IFERROR(O30/O$21,0) -> 0.25106151 | P31: =+IFERROR(P30/P$21,0) -> 0.25586931 | ... S31: =+IFERROR(S30/S$21,0) -> 0.26978237
D32: D&A (Owned PP&E & intangibles — 100% Inditex) | I32: =+I49 -> -1417 | J32: =+J49 -> -1558 | K32: =+K49 -> -1638 | L32: =+L49 -> -1674 | M32: =+M49 -> -1387.147 | N32: =+N49 -> -1611.8549 | O32: =+O49 -> -1848.9219 | P32: =+P49 -> -2099.0275 | ... S32: =+S49 -> -2934.947 | T32: =+IFERROR((L32/I32)^(1/(L$20-I$20))-1,0) -> 0.057130333 | U32: =+IFERROR((S32/L32)^(1/(S$20-L$20))-1,0) -> 0.083515113
D33: Operating EBIT (Pre-IFRS 16 — 100% Inditex) | I33: =+I30+I32 -> 5611 | J33: =+J30+J32 -> 6559 | K33: =+K30+K32 -> 7288 | L33: =+L30+L32 -> 7759 | M33: =+M30+M32 -> 8755.9802 | N33: =+N30+N32 -> 9310.4066 | O33: =+O30+O32 -> 9903.2569 | P33: =+P30+P32 -> 10536.952 | ... S33: =+S30+S32 -> 12709.552 | T33: =+IFERROR((L33/I33)^(1/(L$20-I$20))-1,0) -> 0.11409398 | U33: =+IFERROR((S33/L33)^(1/(S$20-L$20))-1,0) -> 0.073044626
C36: NOF / WK | I36: 31-Jan | J36: 31-Jan | K36: 31-Jan | L36: 31-Jan | M36: 31-Jan | N36: 31-Jan | O36: 31-Jan | P36: 31-Jan | Q36: 31-Jan | R36: 31-Jan | S36: 31-Jan
C37: €m | D37: 100% Inditex Consolidated Line Item | I37: 2022 | J37: =+I37+1 -> 2023 | K37: =+J37+1 -> 2024 | L37: =+K37+1 -> 2025 | M37: =+L37+1 -> 2026 | N37: =+M37+1 -> 2027 | O37: =+N37+1 -> 2028 | P37: =+O37+1 -> 2029 | Q37: =+P37+1 -> 2030 | ... S37: =+R37+1 -> 2032
B38: 3 | D38: Operating Working Capital (Structural Negative NOF — 100% Inditex)
D39: Inventory | I39: 3191 | J39: 2966 | K39: 3321 | L39: 3249 | M39: =+M$21*M15 -> 3427.6064 | N39: =+N$21*N15 -> 3616.1247 | O39: =+O$21*O15 -> 3815.0116 | P39: =+P$21*P15 -> 4024.8372 | Q39: =+Q$21*Q15 -> 4246.2033 | R39: =+R$21*R15 -> 4479.7445 | S39: =+S$21*S15 -> 4726.1304
D40: Trade & other receivables | I40: 851 | J40: 1038 | K40: 1088 | L40: 1166 | M40: =+M$21*M16 -> 1228.0504 | N40: =+N$21*N16 -> 1295.5932 | O40: =+O$21*O16 -> 1366.8508 | P40: =+P$21*P16 -> 1442.0276 | Q40: =+Q$21*Q16 -> 1521.3391 | R40: =+R$21*R16 -> 1605.0127 | S40: =+S$21*S16 -> 1693.2884
D41: Trade & other payables (Supplier financing) | I41: -6561 | J41: -7467 | K41: -8590 | L41: -8587 | M41: =+M$21*M17 -> -9058.9744 | N41: =+N$21*N17 -> -9557.218 | O41: =+O$21*O17 -> -10082.865 | P41: =+P$21*P17 -> -10637.423 | Q41: =+Q$21*Q17 -> -11222.481 | R41: =+R$21*R17 -> -11839.717 | S41: =+S$21*S17 -> -12490.902
D42: Net Operating Working Capital (NOF EoP — 100% Inditex) | I42: =+SUM(I39:I41) -> -2519 | J42: =+SUM(J39:J41) -> -3463 | K42: =+SUM(K39:K41) -> -4181 | L42: =+SUM(L39:L41) -> -4172 | M42: =+SUM(M39:M41) -> -4403.3176 | N42: =+SUM(N39:N41) -> -4645.5001 | O42: =+SUM(O39:O41) -> -4901.0026 | P42: =+SUM(P39:P41) -> -5170.5578 | ... S42: =+SUM(S39:S41) -> -6071.4829
D43: NOF % of revenues (Negative = Supplier-funded float) | I43: =+IFERROR(I42/I$21,0) -> -0.077343486 | J43: =+IFERROR(J42/J$21,0) -> -0.096336273 | K43: =+IFERROR(K42/K$21,0) -> -0.10822634 | L43: =+IFERROR(L42/L$21,0) -> -0.10465583 | M43: =+IFERROR(M42/M$21,0) -> -0.1047 | N43: =+IFERROR(N42/N$21,0) -> -0.1047 | O43: =+IFERROR(O42/O$21,0) -> -0.1047 | P43: =+IFERROR(P42/P$21,0) -> -0.1047 | ... S43: =+IFERROR(S42/S$21,0) -> -0.1047
D44: Cash Flow from Working Capital (-ΔNOF — 100% Inditex) | I44: 0 | J44: =+(I42-J42) -> 944 | K44: =+(J42-K42) -> 718 | L44: =+(K42-L42) -> -9 | M44: =+(L42-M42) -> 231.31764 | N44: =+(M42-N42) -> 242.18247 | O44: =+(N42-O42) -> 255.50251 | P44: =+(O42-P42) -> 269.55514 | Q44: =+(P42-Q42) -> 284.38068 | ... S44: =+(R42-S42) -> 316.5228
B46: 4 | D46: Capex Split (Maintenance vs. US/Logistics Expansion) & D&A Schedule (100% Inditex)
D47: BoP Net Fixed Assets (Owned PP&E + Intangibles) | I47: 8383 | J47: =+I50 -> 8401 | K47: =+J50 -> 9560 | L47: =+K50 -> 11416 | M47: =+L50 -> 12778 | N47: =+M50 -> 13577.792 | O47: =+N50 -> 14273.158 | P47: =+O50 -> 14858.354 | Q47: =+P50 -> 15327.321 | ... S47: =+R50 -> 15890.645
D48: Total Capex additions (Maintenance + Expansion) | I48: =+I54 -> 1415 | J48: =+J54 -> 1872 | K48: =+K54 -> 2672 | L48: =+L54 -> 2712 | M48: =+M54 -> 2186.939 | N48: =+N54 -> 2307.2207 | O48: =+O54 -> 2434.1178 | P48: =+P54 -> 2567.9943 | ... S48: =+S54 -> 3015.4452
D49: Total D&A (Owned PP&E + Intangibles) | I49: -1417 | J49: -1558 | K49: -1638 | L49: -1674 | M49: =+M57+M69 -> -1387.147 | N49: =+N57+N69 -> -1611.8549 | O49: =+O57+O69 -> -1848.9219 | P49: =+P57+P69 -> -2099.0275 | Q49: =+Q57+Q69 -> -2362.8889 | R49: =+R57+R69 -> -2641.2627 | S49: =+S57+S69 -> -2934.947
D50: EoP Net Fixed Assets | I50: 8401 | J50: 9560 | K50: 11416 | L50: 12778 | M50: =+M47+M48+M49 -> 13577.792 | N50: =+N47+N48+N49 -> 14273.158 | O50: =+O47+O48+O49 -> 14858.354 | P50: =+P47+P48+P49 -> 15327.321 | Q50: =+Q47+Q48+Q49 -> 15673.666 | R50: =+R47+R48+R49 -> 15890.645 | S50: =+S47+S48+S49 -> 15971.143
D52: 1. Maintenance Capex (Store refurbishments & IT upkeep — 100%) | I52: 1050 | J52: 1250 | K52: 1450 | L52: 1480 | M52: =+M21*M13 -> 1471.9782 | N52: =+N21*N13 -> 1552.937 | O52: =+O21*O13 -> 1638.3485 | P52: =+P21*P13 -> 1728.4577 | Q52: =+Q21*Q13 -> 1823.5229 | R52: =+R21*R13 -> 1923.8166 | S52: =+S21*S13 -> 2029.6266
D53: 2. Expansion Capex (US Flagship Rollout & Logistics Hubs — 100%) | I53: 365 | J53: 622 | K53: 1222 | L53: 1232 | M53: =+M21*M14 -> 714.96084 | N53: =+N21*N14 -> 754.28369 | O53: =+O21*O14 -> 795.76929 | P53: =+P21*P14 -> 839.5366 | Q53: =+Q21*Q14 -> 885.71111 | R53: =+R21*R14 -> 934.42522 | S53: =+S21*S14 -> 985.81861
D54: Total Capex (100% Inditex — Funded Organically) | I54: =+I52+I53 -> 1415 | J54: =+J52+J53 -> 1872 | K54: =+K52+K53 -> 2672 | L54: =+L52+L53 -> 2712 | M54: =+M52+M53 -> 2186.939 | N54: =+N52+N53 -> 2307.2207 | O54: =+O52+O53 -> 2434.1178 | P54: =+P52+P53 -> 2567.9943 | ... S54: =+S52+S53 -> 3015.4452
D56: BoP existing net fixed assets | M56: =+L58 -> 12778 | N56: =+M58 -> 11500.2 | O56: =+N58 -> 10222.4 | P56: =+O58 -> 8944.6 | Q56: =+P58 -> 7666.8 | R56: =+Q58 -> 6389 | S56: =+R58 -> 5111.2
D57: D&A of existing fixed assets | M57: =-MIN(M56,$L$58/$E$59) -> -1277.8 | N57: =-MIN(N56,$L$58/$E$59) -> -1277.8 | O57: =-MIN(O56,$L$58/$E$59) -> -1277.8 | P57: =-MIN(P56,$L$58/$E$59) -> -1277.8 | Q57: =-MIN(Q56,$L$58/$E$59) -> -1277.8 | R57: =-MIN(R56,$L$58/$E$59) -> -1277.8 | S57: =-MIN(S56,$L$58/$E$59) -> -1277.8
D58: EoP existing net fixed assets | L58: =+L50 -> 12778 | M58: =+M56+M57 -> 11500.2 | N58: =+N56+N57 -> 10222.4 | O58: =+O56+O57 -> 8944.6 | P58: =+P56+P57 -> 7666.8 | Q58: =+Q56+Q57 -> 6389 | R58: =+R56+R57 -> 5111.2 | S58: =+S56+S57 -> 3833.4
D59: Asset lifetime (years) | E59: 10
D60: First period D&A impact | E60: 0.5
G61: Vintage | H61: Capex (€m)
G62: =+M$20 -> 2026 | H62: =+M$54 -> 2186.939 | M62: =-(($H62/$E$59*$E$60)) -> -109.34695 | N62: =-(MIN(SUM($H62,$M62:M62),$H62/$E$59)) -> -218.6939 | O62: =-(MIN(SUM($H62,$M62:N62),$H62/$E$59)) -> -218.6939 | P62: =-(MIN(SUM($H62,$M62:O62),$H62/$E$59)) -> -218.6939 | Q62: =-(MIN(SUM($H62,$M62:P62),$H62/$E$59)) -> -218.6939 | R62: =-(MIN(SUM($H62,$M62:Q62),$H62/$E$59)) -> -218.6939 | S62: =-(MIN(SUM($H62,$M62:R62),$H62/$E$59)) -> -218.6939
G63: =+N$20 -> 2027 | H63: =+N$54 -> 2307.2207 | M63: 0 | N63: =-(($H63/$E$59*$E$60)) -> -115.36103 | O63: =-(MIN(SUM($H63,$N63:N63),$H63/$E$59)) -> -230.72207 | P63: =-(MIN(SUM($H63,$N63:O63),$H63/$E$59)) -> -230.72207 | Q63: =-(MIN(SUM($H63,$N63:P63),$H63/$E$59)) -> -230.72207 | R63: =-(MIN(SUM($H63,$N63:Q63),$H63/$E$59)) -> -230.72207 | S63: =-(MIN(SUM($H63,$N63:R63),$H63/$E$59)) -> -230.72207
G64: =+O$20 -> 2028 | H64: =+O$54 -> 2434.1178 | M64: 0 | N64: 0 | O64: =-(($H64/$E$59*$E$60)) -> -121.70589 | P64: =-(MIN(SUM($H64,$O64:O64),$H64/$E$59)) -> -243.41178 | Q64: =-(MIN(SUM($H64,$O64:P64),$H64/$E$59)) -> -243.41178 | R64: =-(MIN(SUM($H64,$O64:Q64),$H64/$E$59)) -> -243.41178 | S64: =-(MIN(SUM($H64,$O64:R64),$H64/$E$59)) -> -243.41178
G65: =+P$20 -> 2029 | H65: =+P$54 -> 2567.9943 | M65: 0 | N65: 0 | O65: 0 | P65: =-(($H65/$E$59*$E$60)) -> -128.39972 | Q65: =-(MIN(SUM($H65,$P65:P65),$H65/$E$59)) -> -256.79943 | R65: =-(MIN(SUM($H65,$P65:Q65),$H65/$E$59)) -> -256.79943 | S65: =-(MIN(SUM($H65,$P65:R65),$H65/$E$59)) -> -256.79943
G66: =+Q$20 -> 2030 | H66: =+Q$54 -> 2709.234 | M66: 0 | N66: 0 | O66: 0 | P66: 0 | Q66: =-(($H66/$E$59*$E$60)) -> -135.4617 | R66: =-(MIN(SUM($H66,$Q66:Q66),$H66/$E$59)) -> -270.9234 | S66: =-(MIN(SUM($H66,$Q66:R66),$H66/$E$59)) -> -270.9234
G67: =+R$20 -> 2031 | H67: =+R$54 -> 2858.2419 | M67: 0 | N67: 0 | O67: 0 | P67: 0 | Q67: 0 | R67: =-(($H67/$E$59*$E$60)) -> -142.91209 | S67: =-(MIN(SUM($H67,$R67:R67),$H67/$E$59)) -> -285.82419
G68: =+S$20 -> 2032 | H68: =+S$54 -> 3015.4452 | M68: 0 | N68: 0 | O68: 0 | P68: 0 | Q68: 0 | R68: 0 | S68: =-(($H68/$E$59*$E$60)) -> -150.77226
G69: Total new capex D&A (100% Inditex) | M69: =SUM(M62:M68) -> -109.34695 | N69: =SUM(N62:N68) -> -334.05494 | O69: =SUM(O62:O68) -> -571.12186 | P69: =SUM(P62:P68) -> -821.22747 | Q69: =SUM(Q62:Q68) -> -1085.0889 | R69: =SUM(R62:R68) -> -1363.4627 | S69: =SUM(S62:S68) -> -1657.147

Sheet Debt & Covenants
B1: Project Galicia v3 — Inditex (ITX.MC) | M1: Strictly Private & Confidential
A2: > | B2: Debt & Covenants — 100% Inditex LBO Debt Schedule (2025A–2032E), RCF Negative-NOF Backstop, WALL, SFA Covenants & DSCR
A4: > | B4: > | C4: 1. Debt Tranche Pricing (Euribor + Spread), Sizing on 100% EBITDA, Tenor & WALL
B6: 4 | D6: Tranche / Facility (BidCo — 100% Consolidated Group) | E6: All-In Rate | F6: xEBITDA | G6: Spread / Fixed | H6: PIK (0=Cash,1=PIK) | I6: Tenor (Yrs) | J6: Drawn (€m) | M6: WALL (Yrs)
D7: Blended Initial Cost of Debt (E7) / Reference Euribor Swap (F7) | E7: =+(J8*E8+J9*E9+J10*E10+J11*E11)/J7 -> 0.068543446 | F7: 0.03354 | J7: =+SUM(J8:J11) -> 76670.851 | M7: =+(J8*M8+J9*M9+J10*M10+J11*M11)/J7 -> 6.6281886
D8: 1A. Senior Term Loan A (TLA — 7y Amortising Bank Debt) | E8: =+$F$7+G8 -> 0.05604 | F8: 2 | G8: 0.0225 | H8: 0 | I8: 7 | J8: ='LBO Summary'!F25 -> 18866 | M8: =+F25*1+G25*2+H25*3+I25*4+J25*5+K25*6+L25*7 -> 4.55
D9: 1B. Senior Term Loan B (TLB — 7y Institutional Bullet) | E9: =+$F$7+G9 -> 0.06604 | F9: 3.5 | G9: 0.0325 | H9: 0 | I9: 7 | J9: ='LBO Summary'!F26 -> 33015.5 | M9: =+I9 -> 7
D10: 2. Subordinated / Mezzanine Debt (Bullet; H10: 0=Cash, 1=PIK) | E10: =10.5% -> 0.105 | F10: 1.5 | G10: =E10-F7 -> 0.07146 | H10: 1 | I10: 7.5 | J10: ='LBO Summary'!F27 -> 14149.5 | M10: =+I10 -> 7.5
D11: 3. Seller Vendor Loan (Sandra Note; H11: 0=Cash, 1=PIK) | E11: =+G11 -> 0.05 | F11: ='LBO Summary'!F13*0.055/'LBO Summary'!F7 -> 1.1279393 | G11: 0.05 | H11: 1 | I11: 8 | J11: ='LBO Summary'!F28 -> 10639.851 | M11: =+I11 -> 8
D12: TLB mandatory annual amortisation (% — 0.0% = Bullet) | E12: 0
D13: TLB optional cash sweep (% — 0.0% = Hold to maturity) | E13: 0.85
D14: 4. RCF Committed Limit (€m — Seasonal Negative-NOF Backstop) | E14: 1000 | G14: 0.02
D15: RCF Drawn Rate (E15) & Undrawn Commitment Fee % p.a. (G15) | E15: =+$F$7+G14 -> 0.05354 | G15: 0.0075
D16: SFA Net Leverage Covenant Headroom % (E16) & Min DSCR (G16) | E16: 0.25 | G16: 1.25
C18: Debt Sched | E18: 31-Jan | F18: 31-Jan | G18: 31-Jan | H18: 31-Jan | I18: 31-Jan | J18: 31-Jan | K18: 31-Jan | L18: 31-Jan
C19: €m | D19: 100% Consolidated Group Line Item | E19: 2025 | F19: =+E19+1 -> 2026 | G19: =+F19+1 -> 2027 | H19: =+G19+1 -> 2028 | I19: =+H19+1 -> 2029 | J19: =+I19+1 -> 2030 | K19: =+J19+1 -> 2031 | L19: =+K19+1 -> 2032
D20: 1A. Senior Term Loan A (TLA — 7y Amortising Bank Tranche)
D21: BoP TLA | E21: 0 | F21: =+E24 -> 18866 | G21: =+F24 -> 17922.7 | H21: =+G24 -> 16036.1 | I21: =+H24 -> 13206.2 | J21: =+I24 -> 10376.3 | K21: =+J24 -> 6603.1 | L21: =+K24 -> 2829.9
D22: Initial draw at closing | E22: =+J8 -> 18866 | F22: 0 | G22: 0 | H22: 0 | I22: 0 | J22: 0 | K22: 0 | L22: 0
D23: Scheduled repayment | E23: 0 | F23: =-MIN(F21,$E$24*F$25) -> -943.3 | G23: =-MIN(G21,$E$24*G$25) -> -1886.6 | H23: =-MIN(H21,$E$24*H$25) -> -2829.9 | I23: =-MIN(I21,$E$24*I$25) -> -2829.9 | J23: =-MIN(J21,$E$24*J$25) -> -3773.2 | K23: =-MIN(K21,$E$24*K$25) -> -3773.2 | L23: =-MIN(L21,$E$24*L$25) -> -2829.9
D24: EoP TLA | E24: =+SUM(E21:E23) -> 18866 | F24: =+SUM(F21:F23) -> 17922.7 | G24: =+SUM(G21:G23) -> 16036.1 | H24: =+SUM(H21:H23) -> 13206.2 | I24: =+SUM(I21:I23) -> 10376.3 | J24: =+SUM(J21:J23) -> 6603.1 | K24: =+SUM(K21:K23) -> 2829.9 | L24: =+SUM(L21:L23) -> 0
D25: TLA scheduled amortisation % | F25: 0.05 | G25: 0.1 | H25: 0.15 | I25: 0.15 | J25: =20% -> 0.2 | K25: 0.2 | L25: =1-SUM(F25:K25) -> 0.15 | M25: =+SUM(F25:L25)-1 -> 0
D26: TLA cash interest (on Average Balance) | F26: =-$E$8*AVERAGE(F21,F24) -> -1030.8194 | G26: =-$E$8*AVERAGE(G21,G24) -> -951.52558 | H26: =-$E$8*AVERAGE(H21,H24) -> -819.36925 | I26: =-$E$8*AVERAGE(I21,I24) -> -660.78165 | J26: =-$E$8*AVERAGE(J21,J24) -> -475.76279 | K26: =-$E$8*AVERAGE(K21,K24) -> -264.31266 | L26: =-$E$8*AVERAGE(L21,L24) -> -79.293798
D28: 1B. Senior Term Loan B (TLB — 7y Institutional Bullet)
D29: BoP TLB | E29: 0 | F29: =+E34 -> 33015.5 | G29: =+F34 -> 30807.81 | H29: =+G34 -> 28378.331 | I29: =+H34 -> 25932.864 | J29: =+I34 -> 22641.863 | K29: =+J34 -> 19075.362 | L29: =+K34 -> 14439.428
D30: Initial draw at closing | E30: =+J9 -> 33015.5 | F30: 0 | G30: 0 | H30: 0 | I30: 0 | J30: 0 | K30: 0 | L30: 0
D31: Mandatory amortisation (% in E12) | E31: 0 | F31: =-MIN(F29,$E$34*F$35) -> 0 | G31: =-MIN(G29,$E$34*G$35) -> 0 | H31: =-MIN(H29,$E$34*H$35) -> 0 | I31: =-MIN(I29,$E$34*I$35) -> 0 | J31: =-MIN(J29,$E$34*J$35) -> 0 | K31: =-MIN(K29,$E$34*K$35) -> 0 | L31: =-MIN(L29,$E$34*L$35) -> 0
D32: TLB balance before optional sweep | E32: =+SUM(E29:E31) -> 33015.5 | F32: =+SUM(F29:F31) -> 33015.5 | G32: =+SUM(G29:G31) -> 30807.81 | H32: =+SUM(H29:H31) -> 28378.331 | I32: =+SUM(I29:I31) -> 25932.864 | J32: =+SUM(J29:J31) -> 22641.863 | K32: =+SUM(K29:K31) -> 19075.362 | L32: =+SUM(L29:L31) -> 14439.428
D33: Optional cash sweep (% in E13 — 85.0% Active) | E33: 0 | F33: =-MIN(F32,MAX(0,F87+F88)*$E$13) -> -2207.6899 | G33: =-MIN(G32,MAX(0,G87+G88)*$E$13) -> -2429.4787 | H33: =-MIN(H32,MAX(0,H87+H88)*$E$13) -> -2445.467 | I33: =-MIN(I32,MAX(0,I87+I88)*$E$13) -> -3291.001 | J33: =-MIN(J32,MAX(0,J87+J88)*$E$13) -> -3566.5015 | K33: =-MIN(K32,MAX(0,K87+K88)*$E$13) -> -4635.9344 | L33: =-MIN(L32,MAX(0,L87+L88)*$E$13) -> -6705.9547
D34: EoP TLB | E34: =+E32+E33 -> 33015.5 | F34: =+F32+F33 -> 30807.81 | G34: =+G32+G33 -> 28378.331 | H34: =+H32+H33 -> 25932.864 | I34: =+I32+I33 -> 22641.863 | J34: =+J32+J33 -> 19075.362 | K34: =+K32+K33 -> 14439.428 | L34: =+L32+L33 -> 7733.4729
D35: TLB mandatory amortisation % | F35: =+$E$12 -> 0 | G35: =+$E$12 -> 0 | H35: =+$E$12 -> 0 | I35: =+$E$12 -> 0 | J35: =+$E$12 -> 0 | K35: =+$E$12 -> 0 | L35: =+$E$12 -> 0
D36: TLB cash interest (on Average Balance) | F36: =-$E$9*AVERAGE(F29,F32) -> -2180.3436 | G36: =-$E$9*AVERAGE(G29,G32) -> -2034.5478 | H36: =-$E$9*AVERAGE(H29,H32) -> -1874.105 | I36: =-$E$9*AVERAGE(I29,I32) -> -1712.6064 | J36: =-$E$9*AVERAGE(J29,J32) -> -1495.2687 | K36: =-$E$9*AVERAGE(K29,K32) -> -1259.7369 | L36: =-$E$9*AVERAGE(L29,L32) -> -953.5798
D38: 2. Subordinated / Mezzanine Debt (Bullet — Cash or PIK Switch in H10)
D39: BoP Subordinated debt | E39: 0 | F39: =+E43 -> 14149.5 | G39: =+F43 -> 15635.198 | H39: =+G43 -> 17276.893 | I39: =+H43 -> 19090.967 | J39: =+I43 -> 21095.519 | K39: =+J43 -> 23310.548 | L39: =+K43 -> 25758.156
D40: Initial draw at closing | E40: =+J10 -> 14149.5 | F40: 0 | G40: 0 | H40: 0 | I40: 0 | J40: 0 | K40: 0 | L40: 0
D41: PIK interest capitalised (if H10 = 1) | E41: 0 | F41: =+IF($H$10=1,F39*$E$10,0) -> 1485.6975 | G41: =+IF($H$10=1,G39*$E$10,0) -> 1641.6957 | H41: =+IF($H$10=1,H39*$E$10,0) -> 1814.0738 | I41: =+IF($H$10=1,I39*$E$10,0) -> 2004.5515 | J41: =+IF($H$10=1,J39*$E$10,0) -> 2215.0294 | K41: =+IF($H$10=1,K39*$E$10,0) -> 2447.6075 | L41: =+IF($H$10=1,L39*$E$10,0) -> 2704.6063
D42: Scheduled repayment (Bullet at maturity) | E42: 0 | F42: 0 | G42: 0 | H42: 0 | I42: 0 | J42: 0 | K42: 0 | L42: 0
D43: EoP Subordinated debt | E43: =+SUM(E39:E42) -> 14149.5 | F43: =+SUM(F39:F42) -> 15635.198 | G43: =+SUM(G39:G42) -> 17276.893 | H43: =+SUM(H39:H42) -> 19090.967 | I43: =+SUM(I39:I42) -> 21095.519 | J43: =+SUM(J39:J42) -> 23310.548 | K43: =+SUM(K39:K42) -> 25758.156 | L43: =+SUM(L39:L42) -> 28462.762
D44: Subordinated cash interest (if H10 = 0) | F44: =+IF($H$10=0,-F39*$E$10,0) -> 0 | G44: =+IF($H$10=0,-G39*$E$10,0) -> 0 | H44: =+IF($H$10=0,-H39*$E$10,0) -> 0 | I44: =+IF($H$10=0,-I39*$E$10,0) -> 0 | J44: =+IF($H$10=0,-J39*$E$10,0) -> 0 | K44: =+IF($H$10=0,-K39*$E$10,0) -> 0 | L44: =+IF($H$10=0,-L39*$E$10,0) -> 0
D45: Subordinated total P&L interest (for Art. 16 LIS Tax Model) | F45: =-F39*$E$10 -> -1485.6975 | G45: =-G39*$E$10 -> -1641.6957 | H45: =-H39*$E$10 -> -1814.0738 | I45: =-I39*$E$10 -> -2004.5515 | J45: =-J39*$E$10 -> -2215.0294 | K45: =-K39*$E$10 -> -2447.6075 | L45: =-L39*$E$10 -> -2704.6063
D47: 3. Seller Vendor Loan (Sandra Deferred Note — Cash or PIK Switch in H11)
D48: BoP Vendor Loan | E48: 0 | F48: =+E52 -> 10639.851 | G48: =+F52 -> 11171.844 | H48: =+G52 -> 11730.436 | I48: =+H52 -> 12316.958 | J48: =+I52 -> 12932.805 | K48: =+J52 -> 13579.446 | L48: =+K52 -> 14258.418
D49: Initial draw at closing | E49: =+J11 -> 10639.851 | F49: 0 | G49: 0 | H49: 0 | I49: 0 | J49: 0 | K49: 0 | L49: 0
D50: PIK interest capitalised (if H11 = 1) | E50: 0 | F50: =+IF($H$11=1,F48*$E$11,0) -> 531.99255 | G50: =+IF($H$11=1,G48*$E$11,0) -> 558.59218 | H50: =+IF($H$11=1,H48*$E$11,0) -> 586.52179 | I50: =+IF($H$11=1,I48*$E$11,0) -> 615.84788 | J50: =+IF($H$11=1,J48*$E$11,0) -> 646.64027 | K50: =+IF($H$11=1,K48*$E$11,0) -> 678.97228 | L50: =+IF($H$11=1,L48*$E$11,0) -> 712.9209
D51: Scheduled repayment (Bullet at exit) | E51: 0 | F51: 0 | G51: 0 | H51: 0 | I51: 0 | J51: 0 | K51: 0 | L51: 0
D52: EoP Vendor Loan | E52: =+SUM(E48:E51) -> 10639.851 | F52: =+SUM(F48:F51) -> 11171.844 | G52: =+SUM(G48:G51) -> 11730.436 | H52: =+SUM(H48:H51) -> 12316.958 | I52: =+SUM(I48:I51) -> 12932.805 | J52: =+SUM(J48:J51) -> 13579.446 | K52: =+SUM(K48:K51) -> 14258.418 | L52: =+SUM(L48:L51) -> 14971.339
D53: Vendor Loan cash interest (if H11 = 0) | F53: =+IF($H$11=0,-F48*$E$11,0) -> 0 | G53: =+IF($H$11=0,-G48*$E$11,0) -> 0 | H53: =+IF($H$11=0,-H48*$E$11,0) -> 0 | I53: =+IF($H$11=0,-I48*$E$11,0) -> 0 | J53: =+IF($H$11=0,-J48*$E$11,0) -> 0 | K53: =+IF($H$11=0,-K48*$E$11,0) -> 0 | L53: =+IF($H$11=0,-L48*$E$11,0) -> 0
D54: Vendor Loan total P&L interest (for Art. 16 LIS Tax Model) | F54: =-F48*$E$11 -> -531.99255 | G54: =-G48*$E$11 -> -558.59218 | H54: =-H48*$E$11 -> -586.52179 | I54: =-I48*$E$11 -> -615.84788 | J54: =-J48*$E$11 -> -646.64027 | K54: =-K48*$E$11 -> -678.97228 | L54: =-L48*$E$11 -> -712.9209
D56: 4. Revolving Credit Facility (RCF — Seasonal Negative-NOF Backstop)
D57: BoP RCF drawn | E57: 0 | F57: =+E59 -> 0 | G57: =+F59 -> 0 | H57: =+G59 -> 0 | I57: =+H59 -> 0 | J57: =+I59 -> 0 | K57: =+J59 -> 0 | L57: =+K59 -> 0
D58: RCF draw / (repayment) | E58: ='LBO Summary'!F29 -> 0 | F58: =+IF(F87<0,MIN($E$14-F57,-F87),-MIN(F57,F87)) -> 0 | G58: =+IF(G87<0,MIN($E$14-G57,-G87),-MIN(G57,G87)) -> 0 | H58: =+IF(H87<0,MIN($E$14-H57,-H87),-MIN(H57,H87)) -> 0 | I58: =+IF(I87<0,MIN($E$14-I57,-I87),-MIN(I57,I87)) -> 0 | J58: =+IF(J87<0,MIN($E$14-J57,-J87),-MIN(J57,J87)) -> 0 | K58: =+IF(K87<0,MIN($E$14-K57,-K87),-MIN(K57,K87)) -> 0 | L58: =+IF(L87<0,MIN($E$14-L57,-L87),-MIN(L57,L87)) -> 0
D59: EoP RCF drawn | E59: =+E57+E58 -> 0 | F59: =+F57+F58 -> 0 | G59: =+G57+G58 -> 0 | H59: =+H57+H58 -> 0 | I59: =+I57+I58 -> 0 | J59: =+J57+J58 -> 0 | K59: =+K57+K58 -> 0 | L59: =+L57+L58 -> 0
D60: Undrawn RCF available (Liquidity buffer for Negative NOF swings) | E60: =+$E$14-E59 -> 1000 | F60: =+MAX(0,$E$14-F59) -> 1000 | G60: =+MAX(0,$E$14-G59) -> 1000 | H60: =+MAX(0,$E$14-H59) -> 1000 | I60: =+MAX(0,$E$14-I59) -> 1000 | J60: =+MAX(0,$E$14-J59) -> 1000 | K60: =+MAX(0,$E$14-K59) -> 1000 | L60: =+MAX(0,$E$14-L59) -> 1000
D61: Total RCF drawn interest & undrawn commitment fee (% in G15) | F61: =-(F57*$E$15+MAX(0,$E$14-F57)*$G$15) -> -7.5 | G61: =-(G57*$E$15+MAX(0,$E$14-G57)*$G$15) -> -7.5 | H61: =-(H57*$E$15+MAX(0,$E$14-H57)*$G$15) -> -7.5 | I61: =-(I57*$E$15+MAX(0,$E$14-I57)*$G$15) -> -7.5 | J61: =-(J57*$E$15+MAX(0,$E$14-J57)*$G$15) -> -7.5 | K61: =-(K57*$E$15+MAX(0,$E$14-K57)*$G$15) -> -7.5 | L61: =-(L57*$E$15+MAX(0,$E$14-L57)*$G$15) -> -7.5
D63: Total LBO Debt Summary (100% Consolidated Group)
D64: BoP Total Gross Debt | E64: 0 | F64: =+F21+F29+F39+F48+F57 -> 76670.851 | G64: =+G21+G29+G39+G48+G57 -> 75537.551 | H64: =+H21+H29+H39+H48+H57 -> 73421.76 | I64: =+I21+I29+I39+I48+I57 -> 70546.989 | J64: =+J21+J29+J39+J48+J57 -> 67046.487 | K64: =+K21+K29+K39+K48+K57 -> 62568.456 | L64: =+L21+L29+L39+L48+L57 -> 57285.901
D65: Mandatory Scheduled Principal Repayment (TLA + TLB) | E65: =+E22+E30+E40+E49+E58 -> 76670.851 | F65: =+F23+F31 -> -943.3 | G65: =+G23+G31 -> -1886.6 | H65: =+H23+H31 -> -2829.9 | I65: =+I23+I31 -> -2829.9 | J65: =+J23+J31 -> -3773.2 | K65: =+K23+K31 -> -3773.2 | L65: =+L23+L31 -> -2829.9
D66: Optional TLB Cash Sweep & RCF Net Change | E66: 0 | F66: =+F33+F58 -> -2207.6899 | G66: =+G33+G58 -> -2429.4787 | H66: =+H33+H58 -> -2445.467 | I66: =+I33+I58 -> -3291.001 | J66: =+J33+J58 -> -3566.5015 | K66: =+K33+K58 -> -4635.9344 | L66: =+L33+L58 -> -6705.9547
D67: EoP Senior Gross Debt (TLA + TLB + RCF) | E67: =+E24+E34+E59 -> 51881.5 | F67: =+F24+F34+F59 -> 48730.51 | G67: =+G24+G34+G59 -> 44414.431 | H67: =+H24+H34+H59 -> 39139.064 | I67: =+I24+I34+I59 -> 33018.163 | J67: =+J24+J34+J59 -> 25678.462 | K67: =+K24+K34+K59 -> 17269.328 | L67: =+L24+L34+L59 -> 7733.4729
D68: EoP Total Gross Financial Debt (incl. Sub & Vendor Loan) | E68: =+E24+E34+E43+E52+E59 -> 76670.851 | F68: =+F24+F34+F43+F52+F59 -> 75537.551 | G68: =+G24+G34+G43+G52+G59 -> 73421.76 | H68: =+H24+H34+H43+H52+H59 -> 70546.989 | I68: =+I24+I34+I43+I52+I59 -> 67046.487 | J68: =+J24+J34+J43+J52+J59 -> 62568.456 | K68: =+K24+K34+K43+K52+K59 -> 57285.901 | L68: =+L24+L34+L43+L52+L59 -> 51167.574
D69: Less: EoP 100% Inditex Cash Balance | E69: =-E93 -> -1000 | F69: =-F93 -> -1389.5923 | G69: =-G93 -> -1428.7315 | H69: =-H93 -> -1431.553 | I69: =-I93 -> -1580.7649 | J69: =-J93 -> -1629.3826 | K69: =-K93 -> -1818.1061 | L69: =-L93 -> -2183.4038
D70: EoP Total Net Financial Debt (100% Consolidated Group) | E70: =+E68+E69 -> 75670.851 | F70: =+F68+F69 -> 74147.959 | G70: =+G68+G69 -> 71993.029 | H70: =+H68+H69 -> 69115.436 | I70: =+I68+I69 -> 65465.723 | J70: =+J68+J69 -> 60939.073 | K70: =+K68+K69 -> 55467.795 | L70: =+L68+L69 -> 48984.17
D71: Total Cash Interest & Commitment Fees Paid (CF Outflow) | F71: =+F26+F36+F44+F53+F61 -> -3218.663 | G71: =+G26+G36+G44+G53+G61 -> -2993.5734 | H71: =+H26+H36+H44+H53+H61 -> -2700.9743 | I71: =+I26+I36+I44+I53+I61 -> -2380.888 | J71: =+J26+J36+J44+J53+J61 -> -1978.5315 | K71: =+K26+K36+K44+K53+K61 -> -1531.5496 | L71: =+L26+L36+L44+L53+L61 -> -1040.3736
D72: Total P&L Financial Expense (Cash + PIK — to Tax & WACC) | F72: =+F26+F36+F45+F54+F61 -> -5236.353 | G72: =+G26+G36+G45+G54+G61 -> -5193.8613 | H72: =+H26+H36+H45+H54+H61 -> -5101.5698 | I72: =+I26+I36+I45+I54+I61 -> -5001.2874 | J72: =+J26+J36+J45+J54+J61 -> -4840.2012 | K72: =+K26+K36+K45+K54+K61 -> -4658.1294 | L72: =+L26+L36+L45+L54+L61 -> -4457.9008
C75: Cash Flow | E75: 31-Jan | F75: 31-Jan | G75: 31-Jan | H75: 31-Jan | I75: 31-Jan | J75: 31-Jan | K75: 31-Jan | L75: 31-Jan
C76: €m | D76: 100% Consolidated Group Line Item | E76: 2025 | F76: =+E76+1 -> 2026 | G76: =+F76+1 -> 2027 | H76: =+G76+1 -> 2028 | I76: =+H76+1 -> 2029 | J76: =+I76+1 -> 2030 | K76: =+J76+1 -> 2031 | L76: =+K76+1 -> 2032
B77: 5 | D77: 100% Inditex Pre-IFRS 16 Cash EBITDA | F77: ='Active Case'!M30 -> 10143.127 | G77: ='Active Case'!N30 -> 10922.262 | H77: ='Active Case'!O30 -> 11752.179 | I77: ='Active Case'!P30 -> 12635.98 | J77: ='Active Case'!Q30 -> 13576.948 | K77: ='Active Case'!R30 -> 14578.56 | L77: ='Active Case'!S30 -> 15644.499
D78: Cash Corporate Income Tax Paid (from Tax & WACC — Art. 16 LIS) | F78: ='Tax & WACC'!F22 -> -1428.2605 | G78: ='Tax & WACC'!G22 -> -1508.432 | H78: ='Tax & WACC'!H22 -> -1594.4008 | I78: ='Tax & WACC'!I22 -> -1686.5396 | J78: ='Tax & WACC'!J22 -> -1785.2436 | K78: ='Tax & WACC'!K22 -> -1890.9323 | L78: ='Tax & WACC'!L22 -> -2004.0506
D79: Cash Flow from Working Capital (-ΔNOF — 100% Inditex) | F79: ='Active Case'!M44 -> 231.31764 | G79: ='Active Case'!N44 -> 242.18247 | H79: ='Active Case'!O44 -> 255.50251 | I79: ='Active Case'!P44 -> 269.55514 | J79: ='Active Case'!Q44 -> 284.38068 | K79: ='Active Case'!R44 -> 300.02161 | L79: ='Active Case'!S44 -> 316.5228
D80: Maintenance Capex (100% Inditex) | F80: =-'Active Case'!M52 -> -1471.9782 | G80: =-'Active Case'!N52 -> -1552.937 | H80: =-'Active Case'!O52 -> -1638.3485 | I80: =-'Active Case'!P52 -> -1728.4577 | J80: =-'Active Case'!Q52 -> -1823.5229 | K80: =-'Active Case'!R52 -> -1923.8166 | L80: =-'Active Case'!S52 -> -2029.6266
D81: CFADS excl. Expansion Capex (Bank DSCR Numerator) | F81: =+SUM(F77:F80) -> 7474.2061 | G81: =+SUM(G77:G80) -> 8103.075 | H81: =+SUM(H77:H80) -> 8774.9319 | I81: =+SUM(I77:I80) -> 9490.5375 | J81: =+SUM(J77:J80) -> 10252.562 | K81: =+SUM(K77:K80) -> 11063.833 | L81: =+SUM(L77:L80) -> 11927.345
D82: Expansion Capex (US Flagships & Logistics — 100% Organic) | F82: =-'Active Case'!M53 -> -714.96084 | G82: =-'Active Case'!N53 -> -754.28369 | H82: =-'Active Case'!O53 -> -795.76929 | I82: =-'Active Case'!P53 -> -839.5366 | J82: =-'Active Case'!Q53 -> -885.71111 | K82: =-'Active Case'!R53 -> -934.42522 | L82: =-'Active Case'!S53 -> -985.81861
D83: Cash Flow Available for Debt Service (100% Consolidated CFADS) | F83: =+F81+F82 -> 6759.2452 | G83: =+G81+G82 -> 7348.7913 | H83: =+H81+H82 -> 7979.1627 | I83: =+I81+I82 -> 8651.0009 | J83: =+J81+J82 -> 9366.8506 | K83: =+K81+K82 -> 10129.407 | L83: =+L81+L82 -> 10941.526
D84: Cash Interest & RCF Commitment Fees Paid | F84: =+F71 -> -3218.663 | G84: =+G71 -> -2993.5734 | H84: =+H71 -> -2700.9743 | I84: =+I71 -> -2380.888 | J84: =+J71 -> -1978.5315 | K84: =+K71 -> -1531.5496 | L84: =+L71 -> -1040.3736
D85: Mandatory Scheduled Debt Amortisation (TLA + TLB) | F85: =+F65 -> -943.3 | G85: =+G65 -> -1886.6 | H85: =+H65 -> -2829.9 | I85: =+I65 -> -2829.9 | J85: =+J65 -> -3773.2 | K85: =+K65 -> -3773.2 | L85: =+L65 -> -2829.9
D86: Free Cash Flow to Equity after Mandatory Debt Service | F86: =+F83+F84+F85 -> 2597.2822 | G86: =+G83+G84+G85 -> 2468.6179 | H86: =+H83+H84+H85 -> 2448.2884 | I86: =+I83+I84+I85 -> 3440.2128 | J86: =+J83+J84+J85 -> 3615.1192 | K86: =+K83+K84+K85 -> 4824.6578 | L86: =+L83+L84+L85 -> 7071.2524
D87: Excess Cash Available above €1,000m Minimum Operational Cash | F87: =+(F92-$E$92)+F86 -> 2597.2822 | G87: =+(G92-$E$92)+G86 -> 2858.2103 | H87: =+(H92-$E$92)+H86 -> 2877.0199 | I87: =+(I92-$E$92)+I86 -> 3871.7658 | J87: =+(J92-$E$92)+J86 -> 4195.8841 | K87: =+(K92-$E$92)+K86 -> 5454.0405 | L87: =+(L92-$E$92)+L86 -> 7889.3585
D88: RCF Draw / (Repayment) | F88: =+F58 -> 0 | G88: =+G58 -> 0 | H88: =+H58 -> 0 | I88: =+I58 -> 0 | J88: =+J58 -> 0 | K88: =+K58 -> 0 | L88: =+L58 -> 0
D89: Optional TLB Cash Sweep (85.0% of Excess Cash) | F89: =+F33 -> -2207.6899 | G89: =+G33 -> -2429.4787 | H89: =+H33 -> -2445.467 | I89: =+I33 -> -3291.001 | J89: =+J33 -> -3566.5015 | K89: =+K33 -> -4635.9344 | L89: =+L33 -> -6705.9547
D90: Net Change in Cash Balance | F90: =+F86+F88+F89 -> 389.59234 | G90: =+G86+G88+G89 -> 39.139203 | H90: =+H86+H88+H89 -> 2.8214526 | I90: =+I86+I88+I89 -> 149.21188 | J90: =+J86+J88+J89 -> 48.617735 | K90: =+K86+K88+K89 -> 188.72346 | L90: =+L86+L88+L89 -> 365.2977
D92: BoP 100% Inditex Cash Balance | E92: ='LBO Summary'!F18 -> 1000 | F92: =+E93 -> 1000 | G92: =+F93 -> 1389.5923 | H92: =+G93 -> 1428.7315 | I92: =+H93 -> 1431.553 | J92: =+I93 -> 1580.7649 | K92: =+J93 -> 1629.3826 | L92: =+K93 -> 1818.1061
D93: EoP 100% Inditex Cash Balance (Retained on Balance Sheet) | E93: =+E92 -> 1000 | F93: =+F92+F90 -> 1389.5923 | G93: =+G92+G90 -> 1428.7315 | H93: =+H92+H90 -> 1431.553 | I93: =+I92+I90 -> 1580.7649 | J93: =+J92+J90 -> 1629.3826 | K93: =+K92+K90 -> 1818.1061 | L93: =+L92+L90 -> 2183.4038
A95: > | B95: > | C95: 4. Financial Covenants Monitoring (SFA Net Leverage Step-Downs, Headroom & DSCR — 2025A–2032E)
B97: 6 | D97: Senior Net Debt / 100% Pre-IFRS 16 EBITDA (x) | E97: =+(E67-E93)/'Active Case'!L30 -> 5.3939892 | F97: =+(F67-F93)/'Active Case'!M30 -> 4.6672902 | G97: =+(G67-G93)/'Active Case'!N30 -> 3.9356043 | H97: =+(H67-H93)/'Active Case'!O30 -> 3.2085549 | I97: =+(I67-I93)/'Active Case'!P30 -> 2.4879273 | J97: =+(J67-J93)/'Active Case'!Q30 -> 1.7713171 | K97: =+(K67-K93)/'Active Case'!R30 -> 1.0598592 | L97: =+(L67-L93)/'Active Case'!S30 -> 0.35476171
D98: Total Bank & Sub Net Debt (excl. Vendor Loan) / EBITDA (x) | E98: =+(E67+E43-E93)/'Active Case'!L30 -> 6.8939892 | F98: =+(F67+F43-F93)/'Active Case'!M30 -> 6.2087475 | G98: =+(G67+G43-G93)/'Active Case'!N30 -> 5.5174098 | H98: =+(H67+H43-H93)/'Active Case'!O30 -> 4.8330169 | I98: =+(I67+I43-I93)/'Active Case'!P30 -> 4.1574076 | J98: =+(J67+J43-J93)/'Active Case'!Q30 -> 3.4882382 | K98: =+(K67+K43-K93)/'Active Case'!R30 -> 2.8267111 | L98: =+(L67+L43-L93)/'Active Case'!S30 -> 2.1741081
D99: Total Net Debt (incl. Vendor Loan) / 100% EBITDA (x) | E99: =+E70/'Active Case'!L30 -> 8.0219284 | F99: =+F70/'Active Case'!M30 -> 7.3101675 | G99: =+G70/'Active Case'!N30 -> 6.5914031 | H99: =+H70/'Active Case'!O30 -> 5.8810742 | I99: =+I70/'Active Case'!P30 -> 5.1808981 | J99: =+J70/'Active Case'!Q30 -> 4.4884222 | K99: =+K70/'Active Case'!R30 -> 3.8047513 | L99: =+L70/'Active Case'!S30 -> 3.1310795
D100: SFA Max Net Leverage Covenant (25% Entry Headroom + Step-Downs) | E100: =+ROUNDUP((E99/(1-$E$16))*20,0)/20 -> 10.7 | F100: =+MAX(2,E100-0.65) -> 10.05 | G100: =+MAX(2,F100-0.65) -> 9.4 | H100: =+MAX(2,G100-0.65) -> 8.75 | I100: =+MAX(2,H100-0.65) -> 8.1 | J100: =+MAX(2,I100-0.65) -> 7.45 | K100: =+MAX(2,J100-0.65) -> 6.8 | L100: =+MAX(2,K100-0.65) -> 6.15
D101: Net Leverage Covenant Cushion (Max Covenant - Actual) | E101: =+E100-E99 -> 2.6780716 | F101: =+F100-F99 -> 2.7398325 | G101: =+G100-G99 -> 2.8085969 | H101: =+H100-H99 -> 2.8689258 | I101: =+I100-I99 -> 2.9191019 | J101: =+J100-J99 -> 2.9615778 | K101: =+K100-K99 -> 2.9952487 | L101: =+L100-L99 -> 3.0189205
D102: Net Leverage Covenant Compliance Check | E102: =IF(E99<=E100,"COMPLIANT","BREACH") -> COMPLIANT | F102: =IF(F99<=F100,"COMPLIANT","BREACH") -> COMPLIANT | G102: =IF(G99<=G100,"COMPLIANT","BREACH") -> COMPLIANT | H102: =IF(H99<=H100,"COMPLIANT","BREACH") -> COMPLIANT | I102: =IF(I99<=I100,"COMPLIANT","BREACH") -> COMPLIANT | J102: =IF(J99<=J100,"COMPLIANT","BREACH") -> COMPLIANT | K102: =IF(K99<=K100,"COMPLIANT","BREACH") -> COMPLIANT | L102: =IF(L99<=L100,"COMPLIANT","BREACH") -> COMPLIANT
D104: Total Debt Service (Cash Interest + Mandatory TLA/TLB Principal) | F104: =-(F84+F85) -> 4161.963 | G104: =-(G84+G85) -> 4880.1734 | H104: =-(H84+H85) -> 5530.8743 | I104: =-(I84+I85) -> 5210.788 | J104: =-(J84+J85) -> 5751.7315 | K104: =-(K84+K85) -> 5304.7496 | L104: =-(L84+L85) -> 3870.2736
D105: DSCR (CFADS excl. Expansion Capex / Debt Service — Project Atlantic) | F105: =+F81/F104 -> 1.7958367 | G105: =+G81/G104 -> 1.6604072 | H105: =+H81/H104 -> 1.5865362 | I105: =+I81/I104 -> 1.8213248 | J105: =+J81/J104 -> 1.7825175 | K105: =+K81/K104 -> 2.0856466 | L105: =+L81/L104 -> 3.0817833
D106: DSCR (Total CFADS after US Expansion Capex / Debt Service) | F106: =+F83/F104 -> 1.6240522 | G106: =+G83/G104 -> 1.5058464 | H106: =+H83/H104 -> 1.4426585 | I106: =+I83/I104 -> 1.6602097 | J106: =+J83/J104 -> 1.6285271 | K106: =+K83/K104 -> 1.9094978 | L106: =+L83/L104 -> 2.8270678
D107: Minimum DSCR Covenant Threshold (G16) | F107: =+$G$16 -> 1.25 | G107: =+$G$16 -> 1.25 | H107: =+$G$16 -> 1.25 | I107: =+$G$16 -> 1.25 | J107: =+$G$16 -> 1.25 | K107: =+$G$16 -> 1.25 | L107: =+$G$16 -> 1.25
D108: DSCR Covenant Compliance Check | F108: =IF(F105>=$G$16,"COMPLIANT","BREACH") -> COMPLIANT | G108: =IF(G105>=$G$16,"COMPLIANT","BREACH") -> COMPLIANT | H108: =IF(H105>=$G$16,"COMPLIANT","BREACH") -> COMPLIANT | I108: =IF(I105>=$G$16,"COMPLIANT","BREACH") -> COMPLIANT | J108: =IF(J105>=$G$16,"COMPLIANT","BREACH") -> COMPLIANT | K108: =IF(K105>=$G$16,"COMPLIANT","BREACH") -> COMPLIANT | L108: =IF(L105>=$G$16,"COMPLIANT","BREACH") -> COMPLIANT
D109: Cash Interest Coverage Ratio (100% EBITDA / Cash Interest) | F109: =+F77/-F84 -> 3.151348 | G109: =+G77/-G84 -> 3.6485699 | H109: =+H77/-H84 -> 4.3510888 | I109: =+I77/-I84 -> 5.3072549 | J109: =+J77/-J84 -> 6.8621338 | K109: =+K77/-K84 -> 9.51883 | L109: =+L77/-L84 -> 15.037386

Sheet Tax & WACC
B1: Project Galicia v3 — Inditex (ITX.MC) | M1: Strictly Private & Confidential
A2: > | B2: Tax & WACC — 100% Fiscal Consolidation (Art. 58, 16.5 & 16.1 LIS) & Dynamic WACC Evolution (2025A–2032E)
A4: > | B4: > | C4: 1. Spanish Corporate Tax Consolidation (Art. 58 LIS), Anti-LBO Test (Art. 16.5) & 30% EBITDA Cap (Art. 16.1)
B6: 7 | D6: Spanish Tax Consolidation & WACC Parameters
D7: Spanish Statutory Corporate Tax Rate (CIT %) | E7: 0.25 | G7: Risk-Free Rate — 10Y Spanish Bono (Rf %) | J7: 0.0315
D8: Art. 16.1 LIS Interest Deductibility Cap (% EBITDA) | E8: 0.3 | G8: Equity Market Risk Premium (ERP %) | J8: 0.055
D9: Art. 16.1 LIS Minimum Deductible Franchise (€m) | E9: 1 | G9: Inditex Unlevered Asset Beta (Beta_U) | J9: 0.78
D10: Art. 16.5 LIS Max LBO Debt / Purchase Value (70%) | E10: 0.7 | G10: Actual BidCo Acquisition Debt / Purchase Value | J10: ='LBO Summary'!L16 -> 0.39633044
D11: Upfront Financing Fees Total (€m — Amortised) | E11: ='LBO Summary'!I30 -> 1141.96 | G11: Amortization Period for Upfront Fees (Yrs) | J11: ='LBO Summary'!L14 -> 7
C12: CIT Model | E12: 31-Jan | F12: 31-Jan | G12: 31-Jan | H12: 31-Jan | I12: 31-Jan | J12: 31-Jan | K12: 31-Jan | L12: 31-Jan
C13: €m | D13: 100% Consolidated Group Line Item | E13: 2025 | F13: =+E13+1 -> 2026 | G13: =+F13+1 -> 2027 | H13: =+G13+1 -> 2028 | I13: =+H13+1 -> 2029 | J13: =+I13+1 -> 2030 | K13: =+J13+1 -> 2031 | L13: =+K13+1 -> 2032
D14: 100% Inditex Pre-IFRS 16 Cash EBITDA (€m) | E14: ='Active Case'!L30 -> 9433 | F14: ='Active Case'!M30 -> 10143.127 | G14: ='Active Case'!N30 -> 10922.262 | H14: ='Active Case'!O30 -> 11752.179 | I14: ='Active Case'!P30 -> 12635.98 | J14: ='Active Case'!Q30 -> 13576.948 | K14: ='Active Case'!R30 -> 14578.56 | L14: ='Active Case'!S30 -> 15644.499
D15: 100% Inditex D&A (Owned PP&E + Intangibles) | E15: ='Active Case'!L32 -> -1674 | F15: ='Active Case'!M32 -> -1387.147 | G15: ='Active Case'!N32 -> -1611.8549 | H15: ='Active Case'!O32 -> -1848.9219 | I15: ='Active Case'!P32 -> -2099.0275 | J15: ='Active Case'!Q32 -> -2362.8889 | K15: ='Active Case'!R32 -> -2641.2627 | L15: ='Active Case'!S32 -> -2934.947
D16: 100% Inditex Operating EBIT (Unlevered Tax Base) | E16: =+E14+E15 -> 7759 | F16: =+F14+F15 -> 8755.9802 | G16: =+G14+G15 -> 9310.4066 | H16: =+H14+H15 -> 9903.2569 | I16: =+I14+I15 -> 10536.952 | J16: =+J14+J15 -> 11214.059 | K16: =+K14+K15 -> 11937.297 | L16: =+L14+L15 -> 12709.552
D17: Gross BidCo LBO Financial Expenses (Cash + PIK Interest) | F17: ='Debt & Covenants'!F72 -> -5236.353 | G17: ='Debt & Covenants'!G72 -> -5193.8613 | H17: ='Debt & Covenants'!H72 -> -5101.5698 | I17: ='Debt & Covenants'!I72 -> -5001.2874 | J17: ='Debt & Covenants'!J72 -> -4840.2012 | K17: ='Debt & Covenants'!K72 -> -4658.1294 | L17: ='Debt & Covenants'!L72 -> -4457.9008
D18: Tax Amortization of Upfront Structuring Fees (Linear over 7y) | F18: =-$E$11/$J$11 -> -163.13714 | G18: =-$E$11/$J$11 -> -163.13714 | H18: =-$E$11/$J$11 -> -163.13714 | I18: =-$E$11/$J$11 -> -163.13714 | J18: =-$E$11/$J$11 -> -163.13714 | K18: =-$E$11/$J$11 -> -163.13714 | L18: =-$E$11/$J$11 -> -163.13714
D19: Consolidated Accounting EBT before Art. 16.1 LIS Cap | F19: =+F16+F17+F18 -> 3356.49 | G19: =+G16+G17+G18 -> 3953.4082 | H19: =+H16+H17+H18 -> 4638.55 | I19: =+I16+I17+I18 -> 5372.5275 | J19: =+J16+J17+J18 -> 6210.7204 | K19: =+K16+K17+K18 -> 7116.0308 | L19: =+L16+L17+L18 -> 8088.5139
D20: Plus: Non-Deductible Interest Added Back (> 30% EBITDA Cap) | F20: =+F30 -> 2356.552 | G20: =+G30 -> 2080.32 | H20: =+H30 -> 1739.0533 | I20: =+I30 -> 1373.6307 | J20: =+J30 -> 930.25404 | K20: =+K30 -> 447.69854 | L20: =+L30 -> 0
D21: Less: Prior-Year Non-Deducted Interest Recovered in Period | F21: =+F34 -> 0 | G21: =+G34 -> 0 | H21: =+H34 -> 0 | I21: =+I34 -> 0 | J21: =+J34 -> 0 | K21: =+K34 -> 0 | L21: =+L34 -> -72.311701
D22: Cash Corporate Income Tax Paid (CIT @ 25% on Consolidated Tax Base) | F22: =-MAX(0,F23)*$E$7 -> -1428.2605 | G22: =-MAX(0,G23)*$E$7 -> -1508.432 | H22: =-MAX(0,H23)*$E$7 -> -1594.4008 | I22: =-MAX(0,I23)*$E$7 -> -1686.5396 | J22: =-MAX(0,J23)*$E$7 -> -1785.2436 | K22: =-MAX(0,K23)*$E$7 -> -1890.9323 | L22: =-MAX(0,L23)*$E$7 -> -2004.0506
D23: Adjusted Consolidated Taxable Income (Base Imponible Fiscal) | F23: =+F19+F20+F21 -> 5713.042 | G23: =+G19+G20+G21 -> 6033.7281 | H23: =+H19+H20+H21 -> 6377.6033 | I23: =+I19+I20+I21 -> 6746.1582 | J23: =+J19+J20+J21 -> 7140.9744 | K23: =+K19+K20+K21 -> 7563.7293 | L23: =+L19+L20+L21 -> 8016.2022
D24: Consolidated Net Income (100% Group Post-CIT) | F24: =+F19+F22 -> 1928.2295 | G24: =+G19+G22 -> 2444.9761 | H24: =+H19+H22 -> 3044.1491 | I24: =+I19+I22 -> 3685.988 | J24: =+J19+J22 -> 4425.4768 | K24: =+K19+K22 -> 5225.0984 | L24: =+L19+L22 -> 6084.4634
D26: Art. 16.1 LIS — 30% Operating EBITDA Cap & Carryforward Schedule
D27: 100% Fiscal Operating EBITDA (Pre-IFRS 16 Cash EBITDA) | F27: =+F14 -> 10143.127 | G27: =+G14 -> 10922.262 | H27: =+H14 -> 11752.179 | I27: =+I14 -> 12635.98 | J27: =+J14 -> 13576.948 | K27: =+K14 -> 14578.56 | L27: =+L14 -> 15644.499
D28: 30% EBITDA Interest Deductibility Limit (MAX 30% EBITDA, €1m) | F28: =+MAX($E$9,$E$8*F27) -> 3042.9381 | G28: =+MAX($E$9,$E$8*G27) -> 3276.6785 | H28: =+MAX($E$9,$E$8*H27) -> 3525.6536 | I28: =+MAX($E$9,$E$8*I27) -> 3790.7939 | J28: =+MAX($E$9,$E$8*J27) -> 4073.0843 | K28: =+MAX($E$9,$E$8*K27) -> 4373.568 | L28: =+MAX($E$9,$E$8*L27) -> 4693.3497
D29: Total Financial Expense Subject to Art. 16.1 LIS (Interest + Fee Amort.) | F29: =-(F17+F18) -> 5399.4902 | G29: =-(G17+G18) -> 5356.9984 | H29: =-(H17+H18) -> 5264.707 | I29: =-(I17+I18) -> 5164.4246 | J29: =-(J17+J18) -> 5003.3383 | K29: =-(K17+K18) -> 4821.2665 | L29: =-(L17+L18) -> 4621.038
D30: Current-Year Non-Deductible Financial Expense (Excess over 30% Cap) | F30: =+MAX(0,F29-F28) -> 2356.552 | G30: =+MAX(0,G29-G28) -> 2080.32 | H30: =+MAX(0,H29-H28) -> 1739.0533 | I30: =+MAX(0,I29-I28) -> 1373.6307 | J30: =+MAX(0,J29-J28) -> 930.25404 | K30: =+MAX(0,K29-K28) -> 447.69854 | L30: =+MAX(0,L29-L28) -> 0
D31: Unused 30% EBITDA Headroom Generated in Year (5-Year Carryforward) | F31: =+MAX(0,F28-F29) -> 0 | G31: =+MAX(0,G28-G29) -> 0 | H31: =+MAX(0,H28-H29) -> 0 | I31: =+MAX(0,I28-I29) -> 0 | J31: =+MAX(0,J28-J29) -> 0 | K31: =+MAX(0,K28-K29) -> 0 | L31: =+MAX(0,L28-L29) -> 72.311701
D32: BoP Non-Deducted Interest Carryforward Balance | F32: =+E35 -> 0 | G32: =+F35 -> 2356.552 | H32: =+G35 -> 4436.872 | I32: =+H35 -> 6175.9253 | J32: =+I35 -> 7549.556 | K32: =+J35 -> 8479.8101 | L32: =+K35 -> 8927.5086
D33: Plus: New Non-Deductible Interest in Year | F33: =+F30 -> 2356.552 | G33: =+G30 -> 2080.32 | H33: =+H30 -> 1739.0533 | I33: =+I30 -> 1373.6307 | J33: =+J30 -> 930.25404 | K33: =+K30 -> 447.69854 | L33: =+L30 -> 0
D34: Less: Carryforward Interest Deducted Using Unused EBITDA Capacity | F34: =-MIN(F32,F31) -> 0 | G34: =-MIN(G32,G31) -> 0 | H34: =-MIN(H32,H31) -> 0 | I34: =-MIN(I32,I31) -> 0 | J34: =-MIN(J32,J31) -> 0 | K34: =-MIN(K32,K31) -> 0 | L34: =-MIN(L32,L31) -> -72.311701
D35: EoP Non-Deducted Interest Carryforward Balance (Tax Asset) | E35: 0 | F35: =+F32+F33+F34 -> 2356.552 | G35: =+G32+G33+G34 -> 4436.872 | H35: =+H32+H33+H34 -> 6175.9253 | I35: =+I32+I33+I34 -> 7549.556 | J35: =+J32+J33+J34 -> 8479.8101 | K35: =+K32+K33+K34 -> 8927.5086 | L35: =+L32+L33+L34 -> 8855.1969
D37: Unlevered Taxes (Hypothetical CIT if Debt = 0) | F37: =-MAX(0,F16)*$E$7 -> -2188.995 | G37: =-MAX(0,G16)*$E$7 -> -2327.6016 | H37: =-MAX(0,H16)*$E$7 -> -2475.8142 | I37: =-MAX(0,I16)*$E$7 -> -2634.238 | J37: =-MAX(0,J16)*$E$7 -> -2803.5147 | K37: =-MAX(0,K16)*$E$7 -> -2984.3243 | L37: =-MAX(0,L16)*$E$7 -> -3177.388
D38: Theoretical Maximum Tax Shield (25% × Total Interest + Fee Amort.) | F38: =+F29*$E$7 -> 1349.8725 | G38: =+G29*$E$7 -> 1339.2496 | H38: =+H29*$E$7 -> 1316.1767 | I38: =+I29*$E$7 -> 1291.1061 | J38: =+J29*$E$7 -> 1250.8346 | K38: =+K29*$E$7 -> 1205.3166 | L38: =+L29*$E$7 -> 1155.2595
D39: Actual Realized Cash Tax Shield (Unlevered CIT - Actual Levered CIT) | F39: =+F22-F37 -> 760.73454 | G39: =+G22-G37 -> 819.16961 | H39: =+H22-H37 -> 881.41341 | I39: =+I22-I37 -> 947.69847 | J39: =+J22-J37 -> 1018.2711 | K39: =+K22-K37 -> 1093.392 | L39: =+L22-L37 -> 1173.3374
D40: Tax Shield Efficiency (% of Theoretical Shield Realized in Cash) | F40: =+IFERROR(F39/F38,0) -> 0.56356027 | G40: =+IFERROR(G39/G38,0) -> 0.61166314 | H40: =+IFERROR(H39/H38,0) -> 0.66967709 | I40: =+IFERROR(I39/I38,0) -> 0.73402057 | J40: =+IFERROR(J39/J38,0) -> 0.81407333 | K40: =+IFERROR(K39/K38,0) -> 0.90714089 | L40: =+IFERROR(L39/L38,0) -> 1.0156484
D41: Effective Tax Shield Rate on Financial Expenses (t_eff %) | F41: =+IFERROR(F39/F29,0) -> 0.14089007 | G41: =+IFERROR(G39/G29,0) -> 0.15291578 | H41: =+IFERROR(H39/H29,0) -> 0.16741927 | I41: =+IFERROR(I39/I29,0) -> 0.18350514 | J41: =+IFERROR(J39/J29,0) -> 0.20351833 | K41: =+IFERROR(K39/K29,0) -> 0.22678522 | L41: =+IFERROR(L39/L29,0) -> 0.25391209
A44: > | B44: > | C44: 2. Dynamic WACC Evolution Due to De-Leveraging & Art. 16.1 LIS Tax Shield (2025A–2032E)
B46: 8 | D46: Implied 100% Inditex Enterprise Value (EV at Entry Multiple) | E46: ='LBO Summary'!E51 -> 182493.84 | F46: ='LBO Summary'!F51 -> 196232.18 | G46: ='LBO Summary'!G51 -> 211305.57 | H46: ='LBO Summary'!H51 -> 227361.41 | I46: ='LBO Summary'!I51 -> 244459.7 | J46: ='LBO Summary'!J51 -> 262663.97 | K46: ='LBO Summary'!K51 -> 282041.49 | L46: ='LBO Summary'!L51 -> 302663.48
D47: 100% Consolidated Net Financial Debt (EoP) | E47: ='Debt & Covenants'!E70 -> 75670.851 | F47: ='Debt & Covenants'!F70 -> 74147.959 | G47: ='Debt & Covenants'!G70 -> 71993.029 | H47: ='Debt & Covenants'!H70 -> 69115.436 | I47: ='Debt & Covenants'!I70 -> 65465.723 | J47: ='Debt & Covenants'!J70 -> 60939.073 | K47: ='Debt & Covenants'!K70 -> 55467.795 | L47: ='Debt & Covenants'!L70 -> 48984.17
D48: Implied 100% TopCo Equity Value (E = EV - Net Debt) | E48: =+E46-E47 -> 106822.99 | F48: =+F46-F47 -> 122084.22 | G48: =+G46-G47 -> 139312.54 | H48: =+H46-H47 -> 158245.98 | I48: =+I46-I47 -> 178993.98 | J48: =+J46-J47 -> 201724.9 | K48: =+K46-K47 -> 226573.69 | L48: =+L46-L47 -> 253679.31
D49: Net Debt / Equity Ratio (D / E) | E49: =+MAX(0,E47/E48) -> 0.70837611 | F49: =+MAX(0,F47/F48) -> 0.60735086 | G49: =+MAX(0,G47/G48) -> 0.51677351 | H49: =+MAX(0,H47/H48) -> 0.43675952 | I49: =+MAX(0,I47/I48) -> 0.36574259 | J49: =+MAX(0,J47/J48) -> 0.30208999 | K49: =+MAX(0,K47/K48) -> 0.24481128 | L49: =+MAX(0,L47/L48) -> 0.19309485
D50: Debt Weight in Capital Structure (D / V) | E50: =+MAX(0,E47/E46) -> 0.4146488 | F50: =+MAX(0,F47/F46) -> 0.3778583 | G50: =+MAX(0,G47/G46) -> 0.34070578 | H50: =+MAX(0,H47/H46) -> 0.3039893 | I50: =+MAX(0,I47/I46) -> 0.2677976 | J50: =+MAX(0,J47/J46) -> 0.23200393 | K50: =+MAX(0,K47/K46) -> 0.19666538 | L50: =+MAX(0,L47/L46) -> 0.16184367
D51: Equity Weight in Capital Structure (E / V) | E51: =1-E50 -> 0.5853512 | F51: =1-F50 -> 0.6221417 | G51: =1-G50 -> 0.65929422 | H51: =1-H50 -> 0.6960107 | I51: =1-I50 -> 0.7322024 | J51: =1-J50 -> 0.76799607 | K51: =1-K50 -> 0.80333462 | L51: =1-L50 -> 0.83815633
D53: Unlevered Cost of Equity (Ku = Rf + Beta_U × ERP) | E53: =+$J$7+$J$9*$J$8 -> 0.0744 | F53: =+$J$7+$J$9*$J$8 -> 0.0744 | G53: =+$J$7+$J$9*$J$8 -> 0.0744 | H53: =+$J$7+$J$9*$J$8 -> 0.0744 | I53: =+$J$7+$J$9*$J$8 -> 0.0744 | J53: =+$J$7+$J$9*$J$8 -> 0.0744 | K53: =+$J$7+$J$9*$J$8 -> 0.0744 | L53: =+$J$7+$J$9*$J$8 -> 0.0744
D54: Dynamic Levered Beta: Beta_L = Beta_U × [1 + (1 - t_eff) × (D/E)] | E54: =+$J$9*(1+(1-$E$7)*E49) -> 1.1944 | F54: =+$J$9*(1+(1-F41)*F49) -> 1.1869893 | G54: =+$J$9*(1+(1-G41)*G49) -> 1.1214455 | H54: =+$J$9*(1+(1-H41)*H49) -> 1.0636373 | I54: =+$J$9*(1+(1-I41)*I49) -> 1.012929 | J54: =+$J$9*(1+(1-J41)*J49) -> 0.96767513 | K54: =+$J$9*(1+(1-K41)*K49) -> 0.92764752 | L54: =+$J$9*(1+(1-L41)*L49) -> 0.89237127
D55: Dynamic Cost of Levered Equity: Ke = Rf + Beta_L × ERP | E55: =+$J$7+E54*$J$8 -> 0.097192001 | F55: =+$J$7+F54*$J$8 -> 0.096784412 | G55: =+$J$7+G54*$J$8 -> 0.093179504 | H55: =+$J$7+H54*$J$8 -> 0.090000051 | I55: =+$J$7+I54*$J$8 -> 0.087211096 | J55: =+$J$7+J54*$J$8 -> 0.084722132 | K55: =+$J$7+K54*$J$8 -> 0.082520614 | L55: =+$J$7+L54*$J$8 -> 0.08058042
D56: Pre-Tax Blended Cost of Debt (Kd Pre-Tax) | E56: ='Debt & Covenants'!$E$7 -> 0.068543446 | F56: =+IFERROR(-F17/'Debt & Covenants'!F64,'Debt & Covenants'!$E$7) -> 0.06829653 | G56: =+IFERROR(-G17/'Debt & Covenants'!G64,'Debt & Covenants'!$E$7) -> 0.068758666 | H56: =+IFERROR(-H17/'Debt & Covenants'!H64,'Debt & Covenants'!$E$7) -> 0.069483077 | I56: =+IFERROR(-I17/'Debt & Covenants'!I64,'Debt & Covenants'!$E$7) -> 0.070892996 | J56: =+IFERROR(-J17/'Debt & Covenants'!J64,'Debt & Covenants'!$E$7) -> 0.072191719 | K56: =+IFERROR(-K17/'Debt & Covenants'!K64,'Debt & Covenants'!$E$7) -> 0.074448527 | L56: =+IFERROR(-L17/'Debt & Covenants'!L64,'Debt & Covenants'!$E$7) -> 0.077818464
D57: Effective Tax Shield Rate (t_eff — Capped/Boosted by Art. 16.1 LIS) | E57: =+$E$7 -> 0.25 | F57: =+F41 -> 0.14089007 | G57: =+G41 -> 0.15291578 | H57: =+H41 -> 0.16741927 | I57: =+I41 -> 0.18350514 | J57: =+J41 -> 0.20351833 | K57: =+K41 -> 0.22678522 | L57: =+L41 -> 0.25391209
D58: After-Tax Effective Cost of Debt: Kd × (1 - t_eff) | E58: =+E56*(1-E57) -> 0.051407584 | F58: =+F56*(1-F57) -> 0.058674227 | G58: =+G56*(1-G57) -> 0.058244381 | H58: =+H56*(1-H57) -> 0.057850271 | I58: =+I56*(1-I57) -> 0.057883767 | J58: =+J56*(1-J57) -> 0.057499381 | K58: =+K56*(1-K57) -> 0.057564702 | L58: =+L56*(1-L57) -> 0.058059415
D59: Dynamic WACC (Modigliani-Miller / Hamada w/ Spanish Tax Cap) | E59: =+E55*E51+E58*E50 -> 0.078207548 | F59: =+F55*F51+F58*F50 -> 0.082384162 | G59: =+G55*G51+G58*G50 -> 0.081276906 | H59: =+H55*H51+H58*H50 -> 0.080226862 | I59: =+I55*I51+I58*I50 -> 0.079357308 | J59: =+J55*J51+J58*J50 -> 0.078406347 | K59: =+K55*K51+K58*K50 -> 0.07761265 | L59: =+L55*L51+L58*L50 -> 0.076935538
D60: WACC Reduction vs. Unlevered Ku (Net Tax Shield Benefit) | E60: =+E59-E53 -> 0.0038075476 | F60: =+F59-F53 -> 0.0079841621 | G60: =+G59-G53 -> 0.0068769056 | H60: =+H59-H53 -> 0.005826862 | I60: =+I59-I53 -> 0.0049573075 | J60: =+J59-J53 -> 0.0040063469 | K60: =+K59-K53 -> 0.00321265 | L60: =+L59-L53 -> 0.0025355379
D62: Cumulative Cash Tax Shield Realized (2026E–2032E, €m) | E62: =+SUM(F39:L39) -> 6694.0165
D63: Present Value of Realized Tax Shields Discounted @ Ku (APV Tax Shield, €m) | E63: =+NPV(E53,F39:L39) -> 4971.7429
D64: Remaining Non-Deducted Interest Tax Asset at 2032E Exit (€m) | E64: =+L35 -> 8855.1969

Sheet Checks
B1: Project Galicia v3 — Inditex (ITX.MC) | F1: Strictly Private & Confidential
A2: > | B2: Master Model Integrity, Legal Take-Private & Spanish Tax Compliance Checks
C4: ID | D4: Audit Check Description | E4: Diff / Metric | F4: Status
C5: 1 | D5: 1. Sources & Uses of Funds Balance Check | E5: ='LBO Summary'!E40-'LBO Summary'!J40 -> 0 | F5: =IF(ABS(E5)<0.01,"OK","CHECK") -> OK
C6: 2 | D6: 2. TopCo Common Equity Ownership Sums to 100.0% | E6: ='LBO Summary'!F45-1 -> 0 | F6: =IF(ABS(E6)<0.0001,"OK","CHECK") -> OK
C7: 3 | D7: 3. Art. 58 LIS Fiscal Consolidation Threshold (>= 75% = 100%) | E7: ='LBO Summary'!F14+'LBO Summary'!F15 -> 1 | F7: =IF(E7>=0.75,"OK","CHECK") -> OK
C8: 4 | D8: 4. Art. 16.5 LIS Anti-LBO Debt Cap (Debt < 70% Purchase Value) | E8: ='Tax & WACC'!J10-'Tax & WACC'!E10 -> -0.30366956 | F8: =IF(E8<=0,"OK","BREACH") -> OK
C9: 5 | D9: 5. Senior TLA Scheduled Amortisation Sums to 100% | E9: ='Debt & Covenants'!M25 -> 0 | F9: =IF(ABS(E9)<0.0001,"OK","CHECK") -> OK
C10: 6 | D10: 6. Minimum Operational Cash Floor (€1,000m) Respected | E10: =MIN('Debt & Covenants'!E93:L93)-'Debt & Covenants'!E92 -> 0 | F10: =IF(E10>=-0.01,"OK","CHECK") -> OK
C11: 7 | D11: 7. Non-Negative Debt Tranche Balances (All Years) | E11: =MIN('Debt & Covenants'!E24:L24,'Debt & Covenants'!E34:L34,'Debt & Covenants'!E43:L43,'Debt & Covenants'!E52:L52) -> 0 | F11: =IF(E11>=-0.01,"OK","CHECK") -> OK
C12: 8 | D12: 8. P&L D&A Reconciled to Capex Vintage Schedule | E12: =MAX(ABS('Active Case'!M32-'Active Case'!M49),ABS('Active Case'!S32-'Active Case'!S49)) -> 0 | F12: =IF(E12<0.01,"OK","CHECK") -> OK
C13: 9 | D13: 9. SFA Net Leverage Covenant Compliance (All Years) | E13: =COUNTIF('Debt & Covenants'!E102:L102,"BREACH") -> 0 | F13: =IF(E13=0,"OK","BREACH") -> OK
C14: 10 | D14: 10. Bank DSCR Covenant Compliance (All Years) | E14: =COUNTIF('Debt & Covenants'!F108:L108,"BREACH") -> 0 | F14: =IF(E14=0,"OK","BREACH") -> OK
C15: 11 | D15: 11. GP + LP Waterfall Proceeds Reconcile to 100% Sponsor Pool | E15: =ABS(SUM('LBO Summary'!E82:L82)+'LBO Summary'!E84+SUM('LBO Summary'!F84:L84)-SUM('LBO Summary'!E73:L73)) -> 1.1641532e-10 | F15: =IF(E15<0.01,"OK","CHECK") -> OK
