Workbook

Sheet Instructions
B1: Project Galicia — Inditex (ITX.MC) | F1: Private & Confidential
B2: Ortega Block Control Buyout — Instructions & Interactive Switches
C4: Step | D4: Reference Block (Linked) | E4: Explanation & Interactive Switches (Soft Yellow / Blue Font = User Input)
C5: 1 | D5: =+LBO!D9 | E5: Operating Scenario Selector (Rows 7-17): Change cell F9 (1 = Base Case, 2 = Bull Case, 3 = Bear Case) to switch operating projections. Rows 21-32, Working Capital, and Capex represent 100% of Inditex Consolidated figures.
C6: 2 | D6: =+LBO!D21 | E6: P&L & Attributable LBO Perimeter (Rows 19-37): Models 100% of Inditex down to Adj. EBIT (Row 32) and scales Attributable Adj. EBIT (Row 33) by the % Stake Acquired (F168, default 64.35% = Amancio + Sandra Ortega) to deduct LBO interest and compute taxes.
C7: 3 | D7: =+LBO!D43 | E7: Operating Working Capital Schedule (Rows 43-49): Models 100% Inditex Inventory, Receivables, and Payables as % of Revenues. Attributable cash flow from WK is scaled by F168 in the Cash Flow Statement.
C8: 4 | D8: =+LBO!D52 | E8: Capex & D&A Schedule (Rows 52-73): Tracks 100% Inditex Owned PP&E and Intangibles (€12,778m at FY25A close) and depreciates existing assets and new Capex vintages over 10 years.
C9: 5 | D9: =+LBO!D76 | E9: 4-Tranche Debt & Liquidity Schedule (Rows 76-135): Models (1A) Senior TLA (amortising), (1B) Senior TLB (bullet by default; adjustable Cash Sweep % in F183), (2) Subordinated Debt (adjustable Cash vs PIK switch in I180), (3) Ortega Family Vendor Loan (adjustable Cash vs PIK switch in I181), and (4) RCF.
C10: 6 | D10: =+LBO!D163 | E10: Adjustable Acquisition Perimeter & Sources & Uses (Rows 162-209): Adjust Stake Acquired % in F168 (default 64.35%), Offer Premium % in F165 (default 5.0%), TLB Cash Sweep % in F183 (default 0% bullet), and Cash/PIK switches in I180:I181 (0 = Cash Interest, 1 = PIK). Sponsor owns 100% of Newco.
C11: 7 | D11: =+LBO!D215 | E11: Exit Valuation, Returns (IRR / MoM) & Integrity Checks (Rows 212-252): Evaluates Attributable Exit EV, net debt, and Sponsor IRR/MoM across FY26E-FY30E. Includes a 3x3 sensitivity table (Offer Premium x Total Debt Leverage) and 6 automated integrity checks.

Sheet LBO
B1: Project Galicia — Inditex (ITX.MC)
A2: > | B2: Control Buyout Model (Ortega Family Stake Acquisition: Senior + Subordinated + Vendor Loan) | U2: Private & Confidential
A5: > | B5: > | C5: Operating model (100% Inditex Consolidated)
B7: > | C7: Drivers | E7: 1 | F7: 2 | G7: 3 | H7: Active Case: | J7: 31-Jan | K7: 31-Jan | L7: 31-Jan | M7: 31-Jan | N7: 31-Jan | O7: 31-Jan | P7: 31-Jan | Q7: 31-Jan | R7: 31-Jan
D8: Operating Driver / Scenario Presets | E8: Base Case | F8: Bull Case | G8: Bear Case | H8: =CHOOSE($F$9,E8,F8,G8) | J8: 2022 | K8: =+J8+1 | L8: =+K8+1 | M8: =+L8+1 | N8: =+M8+1 | O8: =+N8+1 | P8: =+O8+1 | Q8: =+P8+1 | R8: =+Q8+1
B9: 1 | D9: Active Scenario Selector (1=Base, 2=Bull, 3=Bear) | E9: Select 1-3 -> | F9: 1 | H9: =CHOOSE($F$9,E8,F8,G8)
D10: Revenue growth (% YoY) | E10: 0.055 | F10: 0.08 | G10: 0.0225 | H10: =CHOOSE($F$9,E10,F10,G10) | J10: 0.175 | K10: 0.104 | L10: 0.075 | M10: 0.032 | N10: =+$H10 | O10: =+$H10 | P10: =+$H10 | Q10: =+$H10 | R10: =+$H10
D11: Gross margin (% of revenues) | E11: 0.582 | F11: 0.59 | G11: 0.57 | H11: =CHOOSE($F$9,E11,F11,G11) | J11: =+J23/J$21 | K11: =+K23/K$21 | L11: =+L23/L$21 | M11: =+M23/M$21 | N11: =+$H11 | O11: =+$H11 | P11: =+$H11 | Q11: =+$H11 | R11: =+$H11
D12: OpEx growth (% YoY) | E12: 0.0425 | F12: 0.055 | G12: 0.0325 | H12: =CHOOSE($F$9,E12,F12,G12) | J12: 0.109 | K12: 0.1 | L12: 0.065 | M12: 0.028 | N12: =+$H12 | O12: =+$H12 | P12: =+$H12 | Q12: =+$H12 | R12: =+$H12
D13: Fixed lease cash outflow growth (%) | E13: 0.02 | F13: 0.03 | G13: 0.01 | H13: =CHOOSE($F$9,E13,F13,G13) | J13: 0.05 | K13: =+K28/J28-1 | L13: =+L28/K28-1 | M13: =+M28/L28-1 | N13: =+$H13 | O13: =+$H13 | P13: =+$H13 | Q13: =+$H13 | R13: =+$H13
D14: Capex (% of revenues) | E14: 0.052 | F14: 0.0535 | G14: 0.049 | H14: =CHOOSE($F$9,E14,F14,G14) | J14: =+J58/J$21 | K14: =+K58/K$21 | L14: =+L58/L$21 | M14: =+M58/M$21 | N14: =+$H14 | O14: =+$H14 | P14: =+$H14 | Q14: =+$H14 | R14: =+$H14
D15: Inventory (% of revenues) | E15: 0.0815 | F15: 0.079 | G15: 0.085 | H15: =CHOOSE($F$9,E15,F15,G15) | J15: =+J44/J$21 | K15: =+K44/K$21 | L15: =+L44/L$21 | M15: =+M44/M$21 | N15: =+$H15 | O15: =+$H15 | P15: =+$H15 | Q15: =+$H15 | R15: =+$H15
D16: Receivables (% of revenues) | E16: 0.0292 | F16: 0.0285 | G16: 0.03 | H16: =CHOOSE($F$9,E16,F16,G16) | J16: =+J45/J$21 | K16: =+K45/K$21 | L16: =+L45/L$21 | M16: =+M45/M$21 | N16: =+$H16 | O16: =+$H16 | P16: =+$H16 | Q16: =+$H16 | R16: =+$H16
D17: Payables (% of revenues, negative) | E17: -0.2154 | F17: -0.2155 | G17: -0.213 | H17: =CHOOSE($F$9,E17,F17,G17) | J17: =+J46/J$21 | K17: =+K46/K$21 | L17: =+L46/L$21 | M17: =+M46/M$21 | N17: =+$H17 | O17: =+$H17 | P17: =+$H17 | Q17: =+$H17 | R17: =+$H17
B19: > | C19: P&L | J19: 31-Jan | K19: 31-Jan | L19: 31-Jan | M19: 31-Jan | N19: 31-Jan | O19: 31-Jan | P19: 31-Jan | Q19: 31-Jan | R19: 31-Jan | U19: CAGR 22A-25A | V19: CAGR 25A-30E
C20: €m | J20: 2022 | K20: =+J20+1 | L20: =+K20+1 | M20: =+L20+1 | N20: =+M20+1 | O20: =+N20+1 | P20: =+O20+1 | Q20: =+P20+1 | R20: =+Q20+1
B21: 2 | D21: Revenues (100% Inditex) | J21: 32569 | K21: 35947 | L21: 38632 | M21: 39864 | N21: =+M21*(1+N10) | O21: =+N21*(1+O10) | P21: =+O21*(1+P10) | Q21: =+P21*(1+Q10) | R21: =+Q21*(1+R10) | U21: =+IFERROR((M21/J21)^(1/(M$20-J$20))-1,0) | V21: =+IFERROR((R21/M21)^(1/(R$20-M$20))-1,"n.a.")
D22: COGS | J22: =+J23-J21 | K22: =+K23-K21 | L22: =+L23-L21 | M22: =+M23-M21 | N22: =+N23-N21 | O22: =+O23-O21 | P22: =+P23-P21 | Q22: =+Q23-Q21 | R22: =+R23-R21 | U22: =+IFERROR((M22/J22)^(1/(M$20-J$20))-1,0) | V22: =+IFERROR((R22/M22)^(1/(R$20-M$20))-1,"n.a.")
D23: Gross margin | J23: 18559 | K23: 20762 | L23: 22343 | M23: 23222 | N23: =+N21*N11 | O23: =+O21*O11 | P23: =+P21*P11 | Q23: =+Q21*Q11 | R23: =+R21*R11 | U23: =+IFERROR((M23/J23)^(1/(M$20-J$20))-1,0) | V23: =+IFERROR((R23/M23)^(1/(R$20-M$20))-1,"n.a.")
D24: % margin | J24: =+IFERROR(J23/J$21,0) | K24: =+IFERROR(K23/K$21,0) | L24: =+IFERROR(L23/L$21,0) | M24: =+IFERROR(M23/M$21,0) | N24: =+IFERROR(N23/N$21,0) | O24: =+IFERROR(O23/O$21,0) | P24: =+IFERROR(P23/P$21,0) | Q24: =+IFERROR(Q23/Q$21,0) | R24: =+IFERROR(R23/R$21,0) | U24: =+IFERROR((M24/J24)^(1/(M$20-J$20))-1,0) | V24: =+IFERROR((R24/M24)^(1/(R$20-M$20))-1,"n.a.")
D25: Opex (incl. variable turnover rent) | J25: -9910 | K25: -10912 | L25: -11615 | M25: -11955 | N25: =+M25*(1+N12) | O25: =+N25*(1+O12) | P25: =+O25*(1+P12) | Q25: =+P25*(1+Q12) | R25: =+Q25*(1+R12) | U25: =+IFERROR((M25/J25)^(1/(M$20-J$20))-1,0) | V25: =+IFERROR((R25/M25)^(1/(R$20-M$20))-1,"n.a.")
D26: Reported EBITDA (Post-IFRS 16 — 100% Inditex) | J26: =+J23+J25 | K26: =+K23+K25 | L26: =+L23+L25 | M26: =+M23+M25 | N26: =+N23+N25 | O26: =+O23+O25 | P26: =+P23+P25 | Q26: =+Q23+Q25 | R26: =+R23+R25 | U26: =+IFERROR((M26/J26)^(1/(M$20-J$20))-1,0) | V26: =+IFERROR((R26/M26)^(1/(R$20-M$20))-1,"n.a.")
D27: % margin (Post-IFRS 16) | J27: =+IFERROR(J26/J$21,0) | K27: =+IFERROR(K26/K$21,0) | L27: =+IFERROR(L26/L$21,0) | M27: =+IFERROR(M26/M$21,0) | N27: =+IFERROR(N26/N$21,0) | O27: =+IFERROR(O26/O$21,0) | P27: =+IFERROR(P26/P$21,0) | Q27: =+IFERROR(Q26/Q$21,0) | R27: =+IFERROR(R26/R$21,0) | U27: =+IFERROR((M27/J27)^(1/(M$20-J$20))-1,0) | V27: =+IFERROR((R27/M27)^(1/(R$20-M$20))-1,"n.a.")
D28: Less: Fixed cash lease outflow (IFRS 16 store rents) | J28: -1621 | K28: -1733 | L28: -1802 | M28: -1834 | N28: =+M28*(1+N13) | O28: =+N28*(1+O13) | P28: =+O28*(1+P13) | Q28: =+P28*(1+Q13) | R28: =+Q28*(1+R13) | U28: =+IFERROR((M28/J28)^(1/(M$20-J$20))-1,0) | V28: =+IFERROR((R28/M28)^(1/(R$20-M$20))-1,"n.a.")
D29: Pre-IFRS 16 Cash EBITDA (100% Inditex) | J29: =+J26+J28 | K29: =+K26+K28 | L29: =+L26+L28 | M29: =+M26+M28 | N29: =+N26+N28 | O29: =+O26+O28 | P29: =+P26+P28 | Q29: =+Q26+Q28 | R29: =+R26+R28 | U29: =+IFERROR((M29/J29)^(1/(M$20-J$20))-1,0) | V29: =+IFERROR((R29/M29)^(1/(R$20-M$20))-1,"n.a.")
D30: % margin (Pre-IFRS 16) | J30: =+IFERROR(J29/J$21,0) | K30: =+IFERROR(K29/K$21,0) | L30: =+IFERROR(L29/L$21,0) | M30: =+IFERROR(M29/M$21,0) | N30: =+IFERROR(N29/N$21,0) | O30: =+IFERROR(O29/O$21,0) | P30: =+IFERROR(P29/P$21,0) | Q30: =+IFERROR(Q29/Q$21,0) | R30: =+IFERROR(R29/R$21,0) | U30: =+IFERROR((M30/J30)^(1/(M$20-J$20))-1,0) | V30: =+IFERROR((R30/M30)^(1/(R$20-M$20))-1,"n.a.")
D31: D&A (Owned PP&E & intangibles — 100% Inditex) | J31: =+J56 | K31: =+K56 | L31: =+L56 | M31: =+M56 | N31: =+N56 | O31: =+O56 | P31: =+P56 | Q31: =+Q56 | R31: =+R56 | U31: =+IFERROR((M31/J31)^(1/(M$20-J$20))-1,0) | V31: =+IFERROR((R31/M31)^(1/(R$20-M$20))-1,"n.a.")
D32: Adj. EBIT (Pre-IFRS 16 — 100% Inditex) | J32: =+J29+J31 | K32: =+K29+K31 | L32: =+L29+L31 | M32: =+M29+M31 | N32: =+N29+N31 | O32: =+O29+O31 | P32: =+P29+P31 | Q32: =+Q29+Q31 | R32: =+R29+R31 | U32: =+IFERROR((M32/J32)^(1/(M$20-J$20))-1,0) | V32: =+IFERROR((R32/M32)^(1/(R$20-M$20))-1,"n.a.")
D33: Attributable Adj. EBIT (% Stake Acquired) | F33: =+F168 | J33: =+J32*$F$168 | K33: =+K32*$F$168 | L33: =+L32*$F$168 | M33: =+M32*$F$168 | N33: =+N32*$F$168 | O33: =+O32*$F$168 | P33: =+P32*$F$168 | Q33: =+Q32*$F$168 | R33: =+R32*$F$168 | U33: =+IFERROR((M33/J33)^(1/(M$20-J$20))-1,0) | V33: =+IFERROR((R33/M33)^(1/(R$20-M$20))-1,"n.a.")
D34: Interests (Senior + Subordinated + Vendor Loan) | F34: =+F177 | J34: -44.4 | K34: 39.2 | L34: 14.8 | M34: 14.8 | N34: =+N133 | O34: =+O133 | P34: =+P133 | Q34: =+Q133 | R34: =+R133
D35: EBT (Attributable to LBO Perimeter) | J35: =+J33+J34 | K35: =+K33+K34 | L35: =+L33+L34 | M35: =+M33+M34 | N35: =+N33+N34 | O35: =+O33+O34 | P35: =+P33+P34 | Q35: =+Q33+Q34 | R35: =+R33+R34 | U35: =+IFERROR((M35/J35)^(1/(M$20-J$20))-1,0) | V35: =+IFERROR((R35/M35)^(1/(R$20-M$20))-1,"n.a.")
D36: Tax (Attributable to LBO Perimeter) | F36: 0.224 | J36: -779.2 | K36: -949.1 | L36: -1093.9 | M36: -1158.2 | N36: =+IF(N35>0,-N35*$F$36,0) | O36: =+IF(O35>0,-O35*$F$36,0) | P36: =+IF(P35>0,-P35*$F$36,0) | Q36: =+IF(Q35>0,-Q35*$F$36,0) | R36: =+IF(R35>0,-R35*$F$36,0) | U36: =+IFERROR((M36/J36)^(1/(M$20-J$20))-1,0) | V36: =+IFERROR((R36/M36)^(1/(R$20-M$20))-1,"n.a.")
D37: Net income (Attributable to LBO Perimeter) | J37: =+J35+J36 | K37: =+K35+K36 | L37: =+L35+L36 | M37: =+M35+M36 | N37: =+N35+N36 | O37: =+O35+O36 | P37: =+P35+P36 | Q37: =+Q35+Q36 | R37: =+R35+R36 | U37: =+IFERROR((M37/J37)^(1/(M$20-J$20))-1,0) | V37: =+IFERROR((R37/M37)^(1/(R$20-M$20))-1,"n.a.")
B40: > | C40: BS | J40: 31-Jan | K40: 31-Jan | L40: 31-Jan | M40: 31-Jan | N40: 31-Jan | O40: 31-Jan | P40: 31-Jan | Q40: 31-Jan | R40: 31-Jan
C41: €m | J41: =+J20 | K41: =+J41+1 | L41: =+K41+1 | M41: =+L41+1 | N41: =+M41+1 | O41: =+N41+1 | P41: =+O41+1 | Q41: =+P41+1 | R41: =+Q41+1
B43: 3 | C43: > | D43: WK (Operating Working Capital — 100% Inditex)
D44: Inventory | J44: 3191 | K44: 2966 | L44: 3321 | M44: 3249 | N44: =+N$21*N15 | O44: =+O$21*O15 | P44: =+P$21*P15 | Q44: =+Q$21*Q15 | R44: =+R$21*R15
D45: Receivables | J45: 851 | K45: 1038 | L45: 1088 | M45: 1166 | N45: =+N$21*N16 | O45: =+O$21*O16 | P45: =+P$21*P16 | Q45: =+Q$21*Q16 | R45: =+R$21*R16
D46: Payables | J46: -6561 | K46: -7467 | L46: -8590 | M46: -8587 | N46: =+N$21*N17 | O46: =+O$21*O17 | P46: =+P$21*P17 | Q46: =+Q$21*Q17 | R46: =+R$21*R17
D47: Total WK (EoP balance — 100% Inditex) | J47: =+SUM(J44:J46) | K47: =+SUM(K44:K46) | L47: =+SUM(L44:L46) | M47: =+SUM(M44:M46) | N47: =+SUM(N44:N46) | O47: =+SUM(O44:O46) | P47: =+SUM(P44:P46) | Q47: =+SUM(Q44:Q46) | R47: =+SUM(R44:R46)
D48: WK % of revenues | J48: =+IFERROR(J47/J$21,0) | K48: =+IFERROR(K47/K$21,0) | L48: =+IFERROR(L47/L$21,0) | M48: =+IFERROR(M47/M$21,0) | N48: =+IFERROR(N47/N$21,0) | O48: =+IFERROR(O47/O$21,0) | P48: =+IFERROR(P47/P$21,0) | Q48: =+IFERROR(Q47/Q$21,0) | R48: =+IFERROR(R47/R$21,0)
D49: Cash flow from WK (-ΔWK — 100% Inditex) | J49: 0 | K49: =+(J47-K47) | L49: =+(K47-L47) | M49: =+(L47-M47) | N49: =+(M47-N47) | O49: =+(N47-O47) | P49: =+(O47-P47) | Q49: =+(P47-Q47) | R49: =+(Q47-R47)
B52: 4 | C52: > | D52: Capex & D&A (Owned PP&E + Intangibles — 100% Inditex)
D54: BoP Net Fixed Assets | J54: 8383 | K54: =+J57 | L54: =+K57 | M54: =+L57 | N54: =+M57 | O54: =+N57 | P54: =+O57 | Q54: =+P57 | R54: =+Q57
D55: Capex | J55: =+J58 | K55: =+K58 | L55: =+L58 | M55: =+M58 | N55: =+N58 | O55: =+O58 | P55: =+P58 | Q55: =+Q58 | R55: =+R58
D56: D&A | J56: -1417 | K56: -1558 | L56: -1638 | M56: -1674 | N56: =+N62+N73 | O56: =+O62+O73 | P56: =+P62+P73 | Q56: =+Q62+Q73 | R56: =+R62+R73
D57: EoP Net Fixed Assets | J57: 8401 | K57: 9560 | L57: 11416 | M57: 12778 | N57: =+N54+N55+N56 | O57: =+O54+O55+O56 | P57: =+P54+P55+P56 | Q57: =+Q54+Q55+Q56 | R57: =+R54+R55+R56
D58: Capex (Ordinary + Logistics — 100% Inditex) | J58: 1415 | K58: 1872 | L58: 2672 | M58: 2712 | N58: =+N21*N14 | O58: =+O21*O14 | P58: =+P21*P14 | Q58: =+Q21*Q14 | R58: =+R21*R14
D60: Existing fixed assets D&A
D61: BoP existing net assets | N61: =+M63 | O61: =+N63 | P61: =+O63 | Q61: =+P63 | R61: =+Q63
D62: D&A of existing assets | N62: =-MIN(N61,$M$63/$E$65) | O62: =-MIN(O61,$M$63/$E$65) | P62: =-MIN(P61,$M$63/$E$65) | Q62: =-MIN(Q61,$M$63/$E$65) | R62: =-MIN(R61,$M$63/$E$65)
D63: EoP existing net assets | M63: =+M57 | N63: =+N61+N62 | O63: =+O61+O62 | P63: =+P61+P62 | Q63: =+Q61+Q62 | R63: =+R61+R62
D65: Asset lifetime (years) | E65: 10
D66: First period D&A impact | E66: 0.5
G67: Vintage | H67: Capex (€m)
G68: =+N$20 | H68: =+N$58 | N68: =-(($H68/$E$65*$E$66)) | O68: =-(MIN(SUM($H68,$N68:N68),$H68/$E$65)) | P68: =-(MIN(SUM($H68,$N68:O68),$H68/$E$65)) | Q68: =-(MIN(SUM($H68,$N68:P68),$H68/$E$65)) | R68: =-(MIN(SUM($H68,$N68:Q68),$H68/$E$65))
G69: =+O$20 | H69: =+O$58 | N69: 0 | O69: =-(($H69/$E$65*$E$66)) | P69: =-(MIN(SUM($H69,$O69:O69),$H69/$E$65)) | Q69: =-(MIN(SUM($H69,$O69:P69),$H69/$E$65)) | R69: =-(MIN(SUM($H69,$O69:Q69),$H69/$E$65))
G70: =+P$20 | H70: =+P$58 | N70: 0 | O70: 0 | P70: =-(($H70/$E$65*$E$66)) | Q70: =-(MIN(SUM($H70,$P70:P70),$H70/$E$65)) | R70: =-(MIN(SUM($H70,$P70:Q70),$H70/$E$65))
G71: =+Q$20 | H71: =+Q$58 | N71: 0 | O71: 0 | P71: 0 | Q71: =-(($H71/$E$65*$E$66)) | R71: =-(MIN(SUM($H71,$Q71:Q71),$H71/$E$65))
G72: =+R$20 | H72: =+R$58 | N72: 0 | O72: 0 | P72: 0 | Q72: 0 | R72: =-(($H72/$E$65*$E$66))
G73: Total new capex D&A | N73: =SUM(N68:N72) | O73: =SUM(O68:O72) | P73: =SUM(P68:P72) | Q73: =SUM(Q68:Q72) | R73: =SUM(R68:R72)
B76: 5 | C76: > | D76: Debt Schedule (Senior TLA, Senior TLB, Subordinated Debt, Ortega Vendor Loan & RCF)
D78: 1A. Senior Term Loan A (TLA — Amortising)
D79: BoP TLA | M79: 0 | N79: =+M82 | O79: =+N82 | P79: =+O82 | Q79: =+P82 | R79: =+Q82
D80: Initial draw / increase | M80: =+E190 | N80: 0 | O80: 0 | P80: 0 | Q80: 0 | R80: 0
D81: Scheduled repayment | M81: 0 | N81: =-MIN(N79,$M$82*N$83) | O81: =-MIN(O79,$M$82*O$83) | P81: =-MIN(P79,$M$82*P$83) | Q81: =-MIN(Q79,$M$82*Q$83) | R81: =-MIN(R79,$M$82*R$83) | T81: =+SUM(N81:R81)+M82
D82: EoP TLA | M82: =+SUM(M79:M81) | N82: =+SUM(N79:N81) | O82: =+SUM(O79:O81) | P82: =+SUM(P79:P81) | Q82: =+SUM(Q79:Q81) | R82: =+SUM(R79:R81)
D83: TLA scheduled amortisation % | N83: 0.1 | O83: 0.15 | P83: 0.2 | Q83: 0.25 | R83: =1-SUM(N83:Q83) | T83: =+SUM(N83:R83)-1
D84: TLA cash interest | N84: =-$F$178*AVERAGE(N79,N82) | O84: =-$F$178*AVERAGE(O79,O82) | P84: =-$F$178*AVERAGE(P79,P82) | Q84: =-$F$178*AVERAGE(Q79,Q82) | R84: =-$F$178*AVERAGE(R79,R82)
D86: 1B. Senior Term Loan B (TLB — Bullet / Optional Cash Sweep)
D87: BoP TLB | M87: 0 | N87: =+M92 | O87: =+N92 | P87: =+O92 | Q87: =+P92 | R87: =+Q92
D88: Initial draw / increase | M88: =+E191 | N88: 0 | O88: 0 | P88: 0 | Q88: 0 | R88: 0
D89: Mandatory amortisation (% in F182) | M89: 0 | N89: =-MIN(N87,$M$92*N$93) | O89: =-MIN(O87,$M$92*O$93) | P89: =-MIN(P87,$M$92*P$93) | Q89: =-MIN(Q87,$M$92*Q$93) | R89: =-MIN(R87,$M$92*R$93)
D90: TLB balance before optional cash sweep | M90: =+M87+M88+M89 | N90: =+SUM(N87:N89) | O90: =+SUM(O87:O89) | P90: =+SUM(P87:P89) | Q90: =+SUM(Q87:Q89) | R90: =+SUM(R87:R89)
D91: Optional cash sweep repayment (% in F183) | M91: 0 | N91: =-MIN(N90,MAX(0,N150+N151)*$F$183) | O91: =-MIN(O90,MAX(0,O150+O151)*$F$183) | P91: =-MIN(P90,MAX(0,P150+P151)*$F$183) | Q91: =-MIN(Q90,MAX(0,Q150+Q151)*$F$183) | R91: =-MIN(R90,MAX(0,R150+R151)*$F$183)
D92: EoP TLB | M92: =+M90+M91 | N92: =+N90+N91 | O92: =+O90+O91 | P92: =+P90+P91 | Q92: =+Q90+Q91 | R92: =+R90+R91
D93: TLB mandatory amortisation % | N93: =+$F$182 | O93: =+$F$182 | P93: =+$F$182 | Q93: =+$F$182 | R93: =+$F$182
D94: TLB cash interest | N94: =-$F$179*AVERAGE(N87,N90) | O94: =-$F$179*AVERAGE(O87,O90) | P94: =-$F$179*AVERAGE(P87,P90) | Q94: =-$F$179*AVERAGE(Q87,Q90) | R94: =-$F$179*AVERAGE(R87,R90)
D96: 2. Subordinated / Mezzanine Debt (Bullet — Cash or PIK Switch)
D97: BoP Subordinated debt | M97: 0 | N97: =+M101 | O97: =+N101 | P97: =+O101 | Q97: =+P101 | R97: =+Q101
D98: Initial draw / increase | M98: =+E192 | N98: 0 | O98: 0 | P98: 0 | Q98: 0 | R98: 0
D99: PIK interest capitalised (if I180 = 1) | M99: 0 | N99: =+IF($I$180=1,N97*$F$180,0) | O99: =+IF($I$180=1,O97*$F$180,0) | P99: =+IF($I$180=1,P97*$F$180,0) | Q99: =+IF($I$180=1,Q97*$F$180,0) | R99: =+IF($I$180=1,R97*$F$180,0)
D100: Scheduled repayment (Bullet at maturity) | M100: 0 | N100: 0 | O100: 0 | P100: 0 | Q100: 0 | R100: 0
D101: EoP Subordinated debt | M101: =+SUM(M97:M100) | N101: =+SUM(N97:N100) | O101: =+SUM(O97:O100) | P101: =+SUM(P97:P100) | Q101: =+SUM(Q97:Q100) | R101: =+SUM(R97:R100)
D102: Subordinated cash interest (if I180 = 0) | N102: =+IF($I$180=0,-N97*$F$180,0) | O102: =+IF($I$180=0,-O97*$F$180,0) | P102: =+IF($I$180=0,-P97*$F$180,0) | Q102: =+IF($I$180=0,-Q97*$F$180,0) | R102: =+IF($I$180=0,-R97*$F$180,0)
D103: Subordinated total interest (for P&L tax shield) | N103: =-N97*$F$180 | O103: =-O97*$F$180 | P103: =-P97*$F$180 | Q103: =-Q97*$F$180 | R103: =-R97*$F$180
D105: 3. Ortega Family Vendor Loan (Pontegadea — Cash or PIK Switch)
D106: BoP Vendor Loan | M106: 0 | N106: =+M110 | O106: =+N110 | P106: =+O110 | Q106: =+P110 | R106: =+Q110
D107: Initial draw / increase | M107: =+E193 | N107: 0 | O107: 0 | P107: 0 | Q107: 0 | R107: 0
D108: PIK interest capitalised (if I181 = 1) | M108: 0 | N108: =+IF($I$181=1,N106*$F$181,0) | O108: =+IF($I$181=1,O106*$F$181,0) | P108: =+IF($I$181=1,P106*$F$181,0) | Q108: =+IF($I$181=1,Q106*$F$181,0) | R108: =+IF($I$181=1,R106*$F$181,0)
D109: Scheduled repayment (Bullet at exit) | M109: 0 | N109: 0 | O109: 0 | P109: 0 | Q109: 0 | R109: 0
D110: EoP Vendor Loan | M110: =+SUM(M106:M109) | N110: =+SUM(N106:N109) | O110: =+SUM(O106:O109) | P110: =+SUM(P106:P109) | Q110: =+SUM(Q106:Q109) | R110: =+SUM(R106:R109)
D111: Vendor Loan cash interest (if I181 = 0) | N111: =+IF($I$181=0,-N106*$F$181,0) | O111: =+IF($I$181=0,-O106*$F$181,0) | P111: =+IF($I$181=0,-P106*$F$181,0) | Q111: =+IF($I$181=0,-Q106*$F$181,0) | R111: =+IF($I$181=0,-R106*$F$181,0)
D112: Vendor Loan total interest (for P&L tax shield) | N112: =-N106*$F$181 | O112: =-O106*$F$181 | P112: =-P106*$F$181 | Q112: =-Q106*$F$181 | R112: =-R106*$F$181
D114: 4. Revolving Credit Facility (RCF — Liquidity Line)
D115: BoP RCF drawn | M115: 0 | N115: =+M117 | O115: =+N117 | P115: =+O117 | Q115: =+P117 | R115: =+Q117
D116: RCF draw / (repayment) | M116: =+E194 | N116: =+IF(N150<0,MIN($F$184-N115,-N150),-MIN(N115,N150)) | O116: =+IF(O150<0,MIN($F$184-O115,-O150),-MIN(O115,O150)) | P116: =+IF(P150<0,MIN($F$184-P115,-P150),-MIN(P115,P150)) | Q116: =+IF(Q150<0,MIN($F$184-Q115,-Q150),-MIN(Q115,Q150)) | R116: =+IF(R150<0,MIN($F$184-R115,-R150),-MIN(R115,R150))
D117: EoP RCF drawn | M117: =+M115+M116 | N117: =+N115+N116 | O117: =+O115+O116 | P117: =+P115+P116 | Q117: =+Q115+Q116 | R117: =+R115+R116
D118: Undrawn RCF available | M118: =+$F$184-M117 | N118: =+MAX(0,$F$184-N117) | O118: =+MAX(0,$F$184-O117) | P118: =+MAX(0,$F$184-P117) | Q118: =+MAX(0,$F$184-Q117) | R118: =+MAX(0,$F$184-R117)
D119: RCF interest & commitment fee | N119: =-(N115*$F$185+MAX(0,$F$184-N115)*$F$186) | O119: =-(O115*$F$185+MAX(0,$F$184-O115)*$F$186) | P119: =-(P115*$F$185+MAX(0,$F$184-P115)*$F$186) | Q119: =-(Q115*$F$185+MAX(0,$F$184-Q115)*$F$186) | R119: =-(R115*$F$185+MAX(0,$F$184-R115)*$F$186)
...

Sheet Palancas
B1: Plan de creación de valor: panel de control
B2: Cambia las celdas amarillas. El barómetro muestra en qué banda cae cada hipótesis (azul conservador · verde normal · amarillo optimista · rojo agresivo). Todo el modelo LBO se recalcula al instante.
B4: Activar plan de creación de valor (1 = sí, 0 = no) | D4: 1
B5: Caso operativo (se elige en LBO_Rollover50!F9: 1 Base, 2 Bull, 3 Bear, 4 Bank) | D5: =LBO_Rollover50!H9
B7: Resultado (caso seleccionado) | C7: Sin palancas | D7: Con palancas | E7: Diferencia
B8: TIR del sponsor | C8: =INDEX(Business_Plan!N49:N52,LBO_Rollover50!$F$9) | D8: =LBO_Rollover50!F229 | E8: =D8-C8
B9: MoM del sponsor | C9: =INDEX(Business_Plan!O49:O52,LBO_Rollover50!$F$9) | D9: =LBO_Rollover50!F230 | E9: =D9-C9
B10: DSCR mínimo 2026-30 | C10: =INDEX(Business_Plan!P49:P52,LBO_Rollover50!$F$9) | D10: =LBO_Rollover50!Q253 | E10: =D10-C10
B11: EBITDA pre-IFRS 16 2030 (€m) | C11: =INDEX(Business_Plan!Q49:Q52,LBO_Rollover50!$F$9) | D11: =LBO_Rollover50!R29 | E11: =D11-C11
B12: Deuda senior neta / EBITDA 2030 | C12: =INDEX(Business_Plan!R49:R52,LBO_Rollover50!$F$9) | D12: =LBO_Rollover50!R134 | E12: =D12-C12
B13: Capex acumulado 2026-30 (€m) | C13: =INDEX(Business_Plan!S49:S52,LBO_Rollover50!$F$9) | D13: =SUM(LBO_Rollover50!N58:R58) | E13: =D13-C13
B14: Cheque en efectivo del sponsor (€m) | C14: =INDEX(Business_Plan!T49:T52,LBO_Rollover50!$F$9) | D14: =LBO_Rollover50!E208 | E14: =D14-C14
B15: Dividendo del recap (€m) | C15: =0 | D15: =-SUM(LBO_Rollover50!N153:R153) | E15: =D15-C15
B16: «Sin palancas» es el caso operativo elegido sin el plan; «Con palancas» es el modelo en vivo.
B18: Palanca / parámetro | C18: Unidad | D18: Valor | E18: Banda | F18: Barómetro (izquierda = valor bajo · derecha = valor alto) | R18: Rangos por banda | S18: Dato que lo ancla
B19: Expansión en EE. UU. | C19: Activa (1/0) | D19: 1 | R19: Abrir superficie de Zara, Bershka y Massimo Dutti en EE. UU. por encima del plan de Inditex.
B20: Superficie nueva al año | C20: miles m² | D20: 20 | E20: =IF($D20<10.0,"Conservador",IF($D20<25.0,"Normal",IF($D20<45.0,"Optimista","Agresivo"))) | F20: =IF(AND($D20>=0.0,$D20<6.666666666666667),"▼","") | G20: =IF(AND($D20>=6.666666666666667,$D20<13.333333333333334),"▼","") | H20: =IF(AND($D20>=13.333333333333334,$D20<20.0),"▼","") | I20: =IF(AND($D20>=20.0,$D20<26.666666666666668),"▼","") | J20: =IF(AND($D20>=26.666666666666668,$D20<33.333333333333336),"▼","") | K20: =IF(AND($D20>=33.333333333333336,$D20<40.0),"▼","") | L20: =IF(AND($D20>=40.0,$D20<46.66666666666667),"▼","") | M20: =IF(AND($D20>=46.66666666666667,$D20<53.333333333333336),"▼","") | N20: =IF(AND($D20>=53.333333333333336,$D20<60.0),"▼","") | O20: =IF(AND($D20>=60.0,$D20<66.66666666666667),"▼","") | P20: =IF(AND($D20>=66.66666666666667,$D20<73.33333333333334),"▼","") | Q20: =IF(AND($D20>=73.33333333333334,$D20<=80.0),"▼","") | R20: Conservador 0–10 · Normal 10–25 · Optimista 25–45 · Agresivo 45–80 | S20: Inditex prevé ≈ 5 % de espacio bruto en 2026 (≈ 236.000 m² en todo el mundo)
B21: Ventas por m² de una tienda madura | C21: €/m² | D21: 7500 | E21: =IF($D21<6500.0,"Conservador",IF($D21<8500.0,"Normal",IF($D21<10000.0,"Optimista","Agresivo"))) | F21: =IF(AND($D21>=5000.0,$D21<5666.666666666667),"▼","") | G21: =IF(AND($D21>=5666.666666666667,$D21<6333.333333333333),"▼","") | H21: =IF(AND($D21>=6333.333333333333,$D21<7000.0),"▼","") | I21: =IF(AND($D21>=7000.0,$D21<7666.666666666666),"▼","") | J21: =IF(AND($D21>=7666.666666666666,$D21<8333.333333333332),"▼","") | K21: =IF(AND($D21>=8333.333333333332,$D21<9000.0),"▼","") | L21: =IF(AND($D21>=9000.0,$D21<9666.666666666666),"▼","") | M21: =IF(AND($D21>=9666.666666666666,$D21<10333.333333333332),"▼","") | N21: =IF(AND($D21>=10333.333333333332,$D21<11000.0),"▼","") | O21: =IF(AND($D21>=11000.0,$D21<11666.666666666666),"▼","") | P21: =IF(AND($D21>=11666.666666666666,$D21<12333.333333333332),"▼","") | Q21: =IF(AND($D21>=12333.333333333332,$D21<=13000.0),"▼","") | R21: Conservador 5.000–6.500 · Normal 6.500–8.500 · Optimista 8.500–10.000 · Agresivo 10.000–13.000 | S21: Grupo 8.445 €/m²; Zara 8.819 €/m² (FY2025, online incluido)
B22: Margen EBITDA pre-IFRS 16 de la tienda madura | C22: % | D22: 0.17 | E22: =IF($D22<0.14,"Conservador",IF($D22<0.2,"Normal",IF($D22<0.24,"Optimista","Agresivo"))) | F22: =IF(AND($D22>=0.08,$D22<0.09833333333333333),"▼","") | G22: =IF(AND($D22>=0.09833333333333333,$D22<0.11666666666666667),"▼","") | H22: =IF(AND($D22>=0.11666666666666667,$D22<0.135),"▼","") | I22: =IF(AND($D22>=0.135,$D22<0.15333333333333332),"▼","") | J22: =IF(AND($D22>=0.15333333333333332,$D22<0.17166666666666663),"▼","") | K22: =IF(AND($D22>=0.17166666666666663,$D22<0.19),"▼","") | L22: =IF(AND($D22>=0.19,$D22<0.20833333333333331),"▼","") | M22: =IF(AND($D22>=0.20833333333333331,$D22<0.22666666666666663),"▼","") | N22: =IF(AND($D22>=0.22666666666666663,$D22<0.245),"▼","") | O22: =IF(AND($D22>=0.245,$D22<0.2633333333333333),"▼","") | P22: =IF(AND($D22>=0.2633333333333333,$D22<0.2816666666666666),"▼","") | Q22: =IF(AND($D22>=0.2816666666666666,$D22<=0.3),"▼","") | R22: Conservador 8%–14% · Normal 14%–20% · Optimista 20%–24% · Agresivo 24%–30% | S22: Grupo 23,7 %. EE. UU. ganó 396 M€ antes de impuestos, -5 % en 2025
B23: Capex por m² abierto | C23: €/m² | D23: 6000 | E23: =IF($D23<3500.0,"Agresivo",IF($D23<5000.0,"Optimista",IF($D23<7000.0,"Normal","Conservador"))) | F23: =IF(AND($D23>=2000.0,$D23<2583.3333333333335),"▼","") | G23: =IF(AND($D23>=2583.3333333333335,$D23<3166.666666666667),"▼","") | H23: =IF(AND($D23>=3166.666666666667,$D23<3750.0),"▼","") | I23: =IF(AND($D23>=3750.0,$D23<4333.333333333334),"▼","") | J23: =IF(AND($D23>=4333.333333333334,$D23<4916.666666666667),"▼","") | K23: =IF(AND($D23>=4916.666666666667,$D23<5500.0),"▼","") | L23: =IF(AND($D23>=5500.0,$D23<6083.333333333334),"▼","") | M23: =IF(AND($D23>=6083.333333333334,$D23<6666.666666666667),"▼","") | N23: =IF(AND($D23>=6666.666666666667,$D23<7250.0),"▼","") | O23: =IF(AND($D23>=7250.0,$D23<7833.333333333334),"▼","") | P23: =IF(AND($D23>=7833.333333333334,$D23<8416.666666666668),"▼","") | Q23: =IF(AND($D23>=8416.666666666668,$D23<=9000.0),"▼","") | R23: Conservador 7.000–9.000 · Normal 5.000–7.000 · Optimista 3.500–5.000 · Agresivo 2.000–3.500 | S23: Capex ordinario 2025 / m² brutos abiertos ≈ 7.400 €/m² (con IT)
B24: Canibalización (ventas que se quitan a otras tiendas y al online) | C24: % | D24: 0.15 | E24: =IF($D24<0.05,"Agresivo",IF($D24<0.1,"Optimista",IF($D24<0.25,"Normal","Conservador"))) | F24: =IF(AND($D24>=0.0,$D24<0.03333333333333333),"▼","") | G24: =IF(AND($D24>=0.03333333333333333,$D24<0.06666666666666667),"▼","") | H24: =IF(AND($D24>=0.06666666666666667,$D24<0.1),"▼","") | I24: =IF(AND($D24>=0.1,$D24<0.13333333333333333),"▼","") | J24: =IF(AND($D24>=0.13333333333333333,$D24<0.16666666666666666),"▼","") | K24: =IF(AND($D24>=0.16666666666666666,$D24<0.2),"▼","") | L24: =IF(AND($D24>=0.2,$D24<0.23333333333333334),"▼","") | M24: =IF(AND($D24>=0.23333333333333334,$D24<0.26666666666666666),"▼","") | N24: =IF(AND($D24>=0.26666666666666666,$D24<0.3),"▼","") | O24: =IF(AND($D24>=0.3,$D24<0.3333333333333333),"▼","") | P24: =IF(AND($D24>=0.3333333333333333,$D24<0.36666666666666664),"▼","") | Q24: =IF(AND($D24>=0.36666666666666664,$D24<=0.4),"▼","") | R24: Conservador 25%–40% · Normal 10%–25% · Optimista 5%–10% · Agresivo 0%–5% | S24: Online = 27 % de las ventas: una tienda nueva le quita clientes
B26: Marcas jóvenes (Stradivarius, Oysho, Bershka) | C26: Activa (1/0) | D26: 1 | R26: Acelerar aperturas de las marcas con mayor ROCE y crecimiento en mercados donde ya están.
B27: Superficie nueva al año | C27: miles m² | D27: 25 | E27: =IF($D27<15.0,"Conservador",IF($D27<35.0,"Normal",IF($D27<60.0,"Optimista","Agresivo"))) | F27: =IF(AND($D27>=0.0,$D27<8.333333333333334),"▼","") | G27: =IF(AND($D27>=8.333333333333334,$D27<16.666666666666668),"▼","") | H27: =IF(AND($D27>=16.666666666666668,$D27<25.0),"▼","") | I27: =IF(AND($D27>=25.0,$D27<33.333333333333336),"▼","") | J27: =IF(AND($D27>=33.333333333333336,$D27<41.66666666666667),"▼","") | K27: =IF(AND($D27>=41.66666666666667,$D27<50.0),"▼","") | L27: =IF(AND($D27>=50.0,$D27<58.333333333333336),"▼","") | M27: =IF(AND($D27>=58.333333333333336,$D27<66.66666666666667),"▼","") | N27: =IF(AND($D27>=66.66666666666667,$D27<75.0),"▼","") | O27: =IF(AND($D27>=75.0,$D27<83.33333333333334),"▼","") | P27: =IF(AND($D27>=83.33333333333334,$D27<91.66666666666667),"▼","") | Q27: =IF(AND($D27>=91.66666666666667,$D27<=100.0),"▼","") | R27: Conservador 0–15 · Normal 15–35 · Optimista 35–60 · Agresivo 60–100 | S27: Las tres marcas suman 918.000 m²; crecer un 3-4 % son 30-35.000 m²
B28: Ventas por m² de una tienda madura | C28: €/m² | D28: 7900 | E28: =IF($D28<6800.0,"Conservador",IF($D28<8500.0,"Normal",IF($D28<10000.0,"Optimista","Agresivo"))) | F28: =IF(AND($D28>=5500.0,$D28<6041.666666666667),"▼","") | G28: =IF(AND($D28>=6041.666666666667,$D28<6583.333333333333),"▼","") | H28: =IF(AND($D28>=6583.333333333333,$D28<7125.0),"▼","") | I28: =IF(AND($D28>=7125.0,$D28<7666.666666666666),"▼","") | J28: =IF(AND($D28>=7666.666666666666,$D28<8208.333333333332),"▼","") | K28: =IF(AND($D28>=8208.333333333332,$D28<8750.0),"▼","") | L28: =IF(AND($D28>=8750.0,$D28<9291.666666666666),"▼","") | M28: =IF(AND($D28>=9291.666666666666,$D28<9833.333333333332),"▼","") | N28: =IF(AND($D28>=9833.333333333332,$D28<10375.0),"▼","") | O28: =IF(AND($D28>=10375.0,$D28<10916.666666666666),"▼","") | P28: =IF(AND($D28>=10916.666666666666,$D28<11458.333333333332),"▼","") | Q28: =IF(AND($D28>=11458.333333333332,$D28<=12000.0),"▼","") | R28: Conservador 5.500–6.800 · Normal 6.800–8.500 · Optimista 8.500–10.000 · Agresivo 10.000–12.000 | S28: Media ponderada FY2025: Bershka 6.656, Stradivarius 9.149, Oysho 10.009 €/m²
B29: Margen EBITDA pre-IFRS 16 de la tienda madura | C29: % | D29: 0.24 | E29: =IF($D29<0.22,"Conservador",IF($D29<0.27,"Normal",IF($D29<0.31,"Optimista","Agresivo"))) | F29: =IF(AND($D29>=0.15,$D29<0.16749999999999998),"▼","") | G29: =IF(AND($D29>=0.16749999999999998,$D29<0.185),"▼","") | H29: =IF(AND($D29>=0.185,$D29<0.20249999999999999),"▼","") | I29: =IF(AND($D29>=0.20249999999999999,$D29<0.21999999999999997),"▼","") | J29: =IF(AND($D29>=0.21999999999999997,$D29<0.2375),"▼","") | K29: =IF(AND($D29>=0.2375,$D29<0.255),"▼","") | L29: =IF(AND($D29>=0.255,$D29<0.27249999999999996),"▼","") | M29: =IF(AND($D29>=0.27249999999999996,$D29<0.29),"▼","") | N29: =IF(AND($D29>=0.29,$D29<0.3075),"▼","") | O29: =IF(AND($D29>=0.3075,$D29<0.32499999999999996),"▼","") | P29: =IF(AND($D29>=0.32499999999999996,$D29<0.34249999999999997),"▼","") | Q29: =IF(AND($D29>=0.34249999999999997,$D29<=0.36),"▼","") | R29: Conservador 15%–22% · Normal 22%–27% · Optimista 27%–31% · Agresivo 31%–36% | S29: ROCE FY2025: Stradivarius 72 %, Oysho 63 %, Bershka 50 % (grupo 40 %)
B30: Capex por m² abierto | C30: €/m² | D30: 4200 | E30: =IF($D30<2500.0,"Agresivo",IF($D30<3500.0,"Optimista",IF($D30<5000.0,"Normal","Conservador"))) | F30: =IF(AND($D30>=1500.0,$D30<1916.6666666666667),"▼","") | G30: =IF(AND($D30>=1916.6666666666667,$D30<2333.3333333333335),"▼","") | H30: =IF(AND($D30>=2333.3333333333335,$D30<2750.0),"▼","") | I30: =IF(AND($D30>=2750.0,$D30<3166.666666666667),"▼","") | J30: =IF(AND($D30>=3166.666666666667,$D30<3583.3333333333335),"▼","") | K30: =IF(AND($D30>=3583.3333333333335,$D30<4000.0),"▼","") | L30: =IF(AND($D30>=4000.0,$D30<4416.666666666667),"▼","") | M30: =IF(AND($D30>=4416.666666666667,$D30<4833.333333333334),"▼","") | N30: =IF(AND($D30>=4833.333333333334,$D30<5250.0),"▼","") | O30: =IF(AND($D30>=5250.0,$D30<5666.666666666667),"▼","") | P30: =IF(AND($D30>=5666.666666666667,$D30<6083.333333333334),"▼","") | Q30: =IF(AND($D30>=6083.333333333334,$D30<=6500.0),"▼","") | R30: Conservador 5.000–6.500 · Normal 3.500–5.000 · Optimista 2.500–3.500 · Agresivo 1.500–2.500 | S30: Tiendas más pequeñas y baratas de montar que un flagship de Zara
B31: Canibalización (ventas que se quitan a otras tiendas y al online) | C31: % | D31: 0.2 | E31: =IF($D31<0.05,"Agresivo",IF($D31<0.15,"Optimista",IF($D31<0.3,"Normal","Conservador"))) | F31: =IF(AND($D31>=0.0,$D31<0.0375),"▼","") | G31: =IF(AND($D31>=0.0375,$D31<0.075),"▼","") | H31: =IF(AND($D31>=0.075,$D31<0.11249999999999999),"▼","") | I31: =IF(AND($D31>=0.11249999999999999,$D31<0.15),"▼","") | J31: =IF(AND($D31>=0.15,$D31<0.1875),"▼","") | K31: =IF(AND($D31>=0.1875,$D31<0.22499999999999998),"▼","") | L31: =IF(AND($D31>=0.22499999999999998,$D31<0.2625),"▼","") | M31: =IF(AND($D31>=0.2625,$D31<0.3),"▼","") | N31: =IF(AND($D31>=0.3,$D31<0.33749999999999997),"▼","") | O31: =IF(AND($D31>=0.33749999999999997,$D31<0.375),"▼","") | P31: =IF(AND($D31>=0.375,$D31<0.4125),"▼","") | Q31: =IF(AND($D31>=0.4125,$D31<=0.44999999999999996),"▼","") | R31: Conservador 30%–45% · Normal 15%–30% · Optimista 5%–15% · Agresivo 0%–5% | S31: Mismos mercados y clientela parecida a Zara y Pull&Bear
B33: Lefties frente a Shein y Temu | C33: Activa (1/0) | D33: 1 | R33: Formato de precio bajo para defender cuota frente a la moda ultrarrápida online.
B34: Superficie nueva al año | C34: miles m² | D34: 10 | E34: =IF($D34<5.0,"Conservador",IF($D34<20.0,"Normal",IF($D34<40.0,"Optimista","Agresivo"))) | F34: =IF(AND($D34>=0.0,$D34<5.833333333333333),"▼","") | G34: =IF(AND($D34>=5.833333333333333,$D34<11.666666666666666),"▼","") | H34: =IF(AND($D34>=11.666666666666666,$D34<17.5),"▼","") | I34: =IF(AND($D34>=17.5,$D34<23.333333333333332),"▼","") | J34: =IF(AND($D34>=23.333333333333332,$D34<29.166666666666664),"▼","") | K34: =IF(AND($D34>=29.166666666666664,$D34<35.0),"▼","") | L34: =IF(AND($D34>=35.0,$D34<40.83333333333333),"▼","") | M34: =IF(AND($D34>=40.83333333333333,$D34<46.666666666666664),"▼","") | N34: =IF(AND($D34>=46.666666666666664,$D34<52.5),"▼","") | O34: =IF(AND($D34>=52.5,$D34<58.33333333333333),"▼","") | P34: =IF(AND($D34>=58.33333333333333,$D34<64.16666666666666),"▼","") | Q34: =IF(AND($D34>=64.16666666666666,$D34<=70.0),"▼","") | R34: Conservador 0–5 · Normal 5–20 · Optimista 20–40 · Agresivo 40–70 | S34: 215 tiendas Lefties a cierre de 2025 (209 en 2024)
B35: Ventas por m² de una tienda madura | C35: €/m² | D35: 4800 | E35: =IF($D35<4000.0,"Conservador",IF($D35<5500.0,"Normal",IF($D35<7000.0,"Optimista","Agresivo"))) | F35: =IF(AND($D35>=3000.0,$D35<3458.3333333333335),"▼","") | G35: =IF(AND($D35>=3458.3333333333335,$D35<3916.6666666666665),"▼","") | H35: =IF(AND($D35>=3916.6666666666665,$D35<4375.0),"▼","") | I35: =IF(AND($D35>=4375.0,$D35<4833.333333333333),"▼","") | J35: =IF(AND($D35>=4833.333333333333,$D35<5291.666666666666),"▼","") | K35: =IF(AND($D35>=5291.666666666666,$D35<5750.0),"▼","") | L35: =IF(AND($D35>=5750.0,$D35<6208.333333333333),"▼","") | M35: =IF(AND($D35>=6208.333333333333,$D35<6666.666666666666),"▼","") | N35: =IF(AND($D35>=6666.666666666666,$D35<7125.0),"▼","") | O35: =IF(AND($D35>=7125.0,$D35<7583.333333333333),"▼","") | P35: =IF(AND($D35>=7583.333333333333,$D35<8041.666666666666),"▼","") | Q35: =IF(AND($D35>=8041.666666666666,$D35<=8500.0),"▼","") | R35: Conservador 3.000–4.000 · Normal 4.000–5.500 · Optimista 5.500–7.000 · Agresivo 7.000–8.500 | S35: Precio medio muy inferior a Zara: densidad por debajo del grupo
B36: Margen EBITDA pre-IFRS 16 de la tienda madura | C36: % | D36: 0.14 | E36: =IF($D36<0.12,"Conservador",IF($D36<0.17,"Normal",IF($D36<0.21,"Optimista","Agresivo"))) | F36: =IF(AND($D36>=0.06,$D36<0.07583333333333334),"▼","") | G36: =IF(AND($D36>=0.07583333333333334,$D36<0.09166666666666667),"▼","") | H36: =IF(AND($D36>=0.09166666666666667,$D36<0.1075),"▼","") | I36: =IF(AND($D36>=0.1075,$D36<0.12333333333333334),"▼","") | J36: =IF(AND($D36>=0.12333333333333334,$D36<0.13916666666666666),"▼","") | K36: =IF(AND($D36>=0.13916666666666666,$D36<0.155),"▼","") | L36: =IF(AND($D36>=0.155,$D36<0.17083333333333334),"▼","") | M36: =IF(AND($D36>=0.17083333333333334,$D36<0.18666666666666668),"▼","") | N36: =IF(AND($D36>=0.18666666666666668,$D36<0.2025),"▼","") | O36: =IF(AND($D36>=0.2025,$D36<0.21833333333333335),"▼","") | P36: =IF(AND($D36>=0.21833333333333335,$D36<0.2341666666666667),"▼","") | Q36: =IF(AND($D36>=0.2341666666666667,$D36<=0.25),"▼","") | R36: Conservador 6%–12% · Normal 12%–17% · Optimista 17%–21% · Agresivo 21%–25% | S36: Margen bruto menor que el grupo (precio bajo)
B37: Capex por m² abierto | C37: €/m² | D37: 3000 | E37: =IF($D37<1800.0,"Agresivo",IF($D37<2500.0,"Optimista",IF($D37<3500.0,"Normal","Conservador"))) | F37: =IF(AND($D37>=1000.0,$D37<1291.6666666666667),"▼","") | G37: =IF(AND($D37>=1291.6666666666667,$D37<1583.3333333333335),"▼","") | H37: =IF(AND($D37>=1583.3333333333335,$D37<1875.0),"▼","") | I37: =IF(AND($D37>=1875.0,$D37<2166.666666666667),"▼","") | J37: =IF(AND($D37>=2166.666666666667,$D37<2458.3333333333335),"▼","") | K37: =IF(AND($D37>=2458.3333333333335,$D37<2750.0),"▼","") | L37: =IF(AND($D37>=2750.0,$D37<3041.666666666667),"▼","") | M37: =IF(AND($D37>=3041.666666666667,$D37<3333.3333333333335),"▼","") | N37: =IF(AND($D37>=3333.3333333333335,$D37<3625.0),"▼","") | O37: =IF(AND($D37>=3625.0,$D37<3916.666666666667),"▼","") | P37: =IF(AND($D37>=3916.666666666667,$D37<4208.333333333334),"▼","") | Q37: =IF(AND($D37>=4208.333333333334,$D37<=4500.0),"▼","") | R37: Conservador 3.500–4.500 · Normal 2.500–3.500 · Optimista 1.800–2.500 · Agresivo 1.000–1.800 | S37: Tiendas de formato sencillo
B38: Canibalización (ventas que se quitan a otras tiendas y al online) | C38: % | D38: 0.3 | E38: =IF($D38<0.1,"Agresivo",IF($D38<0.25,"Optimista",IF($D38<0.4,"Normal","Conservador"))) | F38: =IF(AND($D38>=0.0,$D38<0.049999999999999996),"▼","") | G38: =IF(AND($D38>=0.049999999999999996,$D38<0.09999999999999999),"▼","") | H38: =IF(AND($D38>=0.09999999999999999,$D38<0.15),"▼","") | I38: =IF(AND($D38>=0.15,$D38<0.19999999999999998),"▼","") | J38: =IF(AND($D38>=0.19999999999999998,$D38<0.24999999999999997),"▼","") | K38: =IF(AND($D38>=0.24999999999999997,$D38<0.3),"▼","") | L38: =IF(AND($D38>=0.3,$D38<0.35),"▼","") | M38: =IF(AND($D38>=0.35,$D38<0.39999999999999997),"▼","") | N38: =IF(AND($D38>=0.39999999999999997,$D38<0.44999999999999996),"▼","") | O38: =IF(AND($D38>=0.44999999999999996,$D38<0.49999999999999994),"▼","") | P38: =IF(AND($D38>=0.49999999999999994,$D38<0.5499999999999999),"▼","") | Q38: =IF(AND($D38>=0.5499999999999999,$D38<=0.6),"▼","") | R38: Conservador 40%–60% · Normal 25%–40% · Optimista 10%–25% · Agresivo 0%–10% | S38: Riesgo alto de quitar ventas a Zara y Bershka
B40: Optimización de tiendas adicional | C40: Activa (1/0) | D40: 1 | R40: Más reformas y ampliaciones que las ya previstas (las actuales ya están en el plan base).
B41: Superficie reformada o ampliada adicional al año | C41: miles m² | D41: 40 | E41: =IF($D41<20.0,"Conservador",IF($D41<60.0,"Normal",IF($D41<120.0,"Optimista","Agresivo"))) | F41: =IF(AND($D41>=0.0,$D41<16.666666666666668),"▼","") | G41: =IF(AND($D41>=16.666666666666668,$D41<33.333333333333336),"▼","") | H41: =IF(AND($D41>=33.333333333333336,$D41<50.0),"▼","") | I41: =IF(AND($D41>=50.0,$D41<66.66666666666667),"▼","") | J41: =IF(AND($D41>=66.66666666666667,$D41<83.33333333333334),"▼","") | K41: =IF(AND($D41>=83.33333333333334,$D41<100.0),"▼","") | L41: =IF(AND($D41>=100.0,$D41<116.66666666666667),"▼","") | M41: =IF(AND($D41>=116.66666666666667,$D41<133.33333333333334),"▼","") | N41: =IF(AND($D41>=133.33333333333334,$D41<150.0),"▼","") | O41: =IF(AND($D41>=150.0,$D41<166.66666666666669),"▼","") | P41: =IF(AND($D41>=166.66666666666669,$D41<183.33333333333334),"▼","") | Q41: =IF(AND($D41>=183.33333333333334,$D41<=200.0),"▼","") | R41: Conservador 0–20 · Normal 20–60 · Optimista 60–120 · Agresivo 120–200 | S41: 2025: 217 reformas (96 ampliaciones) y 293 absorciones
B42: Aumento de ventas por m² en lo reformado | C42: % | D42: 0.12 | E42: =IF($D42<0.08,"Conservador",IF($D42<0.15,"Normal",IF($D42<0.25,"Optimista","Agresivo"))) | F42: =IF(AND($D42>=0.03,$D42<0.060833333333333336),"▼","") | G42: =IF(AND($D42>=0.060833333333333336,$D42<0.09166666666666667),"▼","") | H42: =IF(AND($D42>=0.09166666666666667,$D42<0.1225),"▼","") | I42: =IF(AND($D42>=0.1225,$D42<0.15333333333333332),"▼","") | J42: =IF(AND($D42>=0.15333333333333332,$D42<0.18416666666666667),"▼","") | K42: =IF(AND($D42>=0.18416666666666667,$D42<0.215),"▼","") | L42: =IF(AND($D42>=0.215,$D42<0.24583333333333335),"▼","") | M42: =IF(AND($D42>=0.24583333333333335,$D42<0.27666666666666667),"▼","") | N42: =IF(AND($D42>=0.27666666666666667,$D42<0.3075),"▼","") | O42: =IF(AND($D42>=0.3075,$D42<0.3383333333333334),"▼","") | P42: =IF(AND($D42>=0.3383333333333334,$D42<0.36916666666666664),"▼","") | Q42: =IF(AND($D42>=0.36916666666666664,$D42<=0.4),"▼","") | R42: Conservador 3%–8% · Normal 8%–15% · Optimista 15%–25% · Agresivo 25%–40% | S42: 3 últimos años: tiendas -6 %, superficie +6 %, ventas +22 %
B43: Capex por m² reformado | C43: €/m² | D43: 2000 | E43: =IF($D43<1000.0,"Agresivo",IF($D43<1500.0,"Optimista",IF($D43<2500.0,"Normal","Conservador"))) | F43: =IF(AND($D43>=500.0,$D43<750.0),"▼","") | G43: =IF(AND($D43>=750.0,$D43<1000.0),"▼","") | H43: =IF(AND($D43>=1000.0,$D43<1250.0),"▼","") | I43: =IF(AND($D43>=1250.0,$D43<1500.0),"▼","") | J43: =IF(AND($D43>=1500.0,$D43<1750.0),"▼","") | K43: =IF(AND($D43>=1750.0,$D43<2000.0),"▼","") | L43: =IF(AND($D43>=2000.0,$D43<2250.0),"▼","") | M43: =IF(AND($D43>=2250.0,$D43<2500.0),"▼","") | N43: =IF(AND($D43>=2500.0,$D43<2750.0),"▼","") | O43: =IF(AND($D43>=2750.0,$D43<3000.0),"▼","") | P43: =IF(AND($D43>=3000.0,$D43<3250.0),"▼","") | Q43: =IF(AND($D43>=3250.0,$D43<=3500.0),"▼","") | R43: Conservador 2.500–3.500 · Normal 1.500–2.500 · Optimista 1.000–1.500 · Agresivo 500–1.000 | S43: Reforma: una fracción del coste de abrir
B44: Margen sobre las ventas incrementales | C44: % | D44: 0.3 | E44: =IF($D44<0.25,"Conservador",IF($D44<0.35,"Normal",IF($D44<0.45,"Optimista","Agresivo"))) | F44: =IF(AND($D44>=0.15,$D44<0.18333333333333332),"▼","") | G44: =IF(AND($D44>=0.18333333333333332,$D44<0.21666666666666667),"▼","") | H44: =IF(AND($D44>=0.21666666666666667,$D44<0.25),"▼","") | I44: =IF(AND($D44>=0.25,$D44<0.2833333333333333),"▼","") | J44: =IF(AND($D44>=0.2833333333333333,$D44<0.31666666666666665),"▼","") | K44: =IF(AND($D44>=0.31666666666666665,$D44<0.35),"▼","") | L44: =IF(AND($D44>=0.35,$D44<0.3833333333333333),"▼","") | M44: =IF(AND($D44>=0.3833333333333333,$D44<0.41666666666666663),"▼","") | N44: =IF(AND($D44>=0.41666666666666663,$D44<0.44999999999999996),"▼","") | O44: =IF(AND($D44>=0.44999999999999996,$D44<0.4833333333333333),"▼","") | P44: =IF(AND($D44>=0.4833333333333333,$D44<0.5166666666666666),"▼","") | Q44: =IF(AND($D44>=0.5166666666666666,$D44<=0.55),"▼","") | R44: Conservador 15%–25% · Normal 25%–35% · Optimista 35%–45% · Agresivo 45%–55% | S44: La tienda ya existe: alquiler y plantilla casi fijos
B46: Eficiencia operativa | C46: Activa (1/0) | D46: 1 | R46: Rentabilizar el plan logístico de 1.800 M€ (2024-25), RFID y automatización de tienda.
B47: Ahorro de gastos a régimen | C47: pb de ventas | D47: 40 | E47: =IF($D47<25.0,"Conservador",IF($D47<60.0,"Normal",IF($D47<100.0,"Optimista","Agresivo"))) | F47: =IF(AND($D47>=0.0,$D47<16.666666666666668),"▼","") | G47: =IF(AND($D47>=16.666666666666668,$D47<33.333333333333336),"▼","") | H47: =IF(AND($D47>=33.333333333333336,$D47<50.0),"▼","") | I47: =IF(AND($D47>=50.0,$D47<66.66666666666667),"▼","") | J47: =IF(AND($D47>=66.66666666666667,$D47<83.33333333333334),"▼","") | K47: =IF(AND($D47>=83.33333333333334,$D47<100.0),"▼","") | L47: =IF(AND($D47>=100.0,$D47<116.66666666666667),"▼","") | M47: =IF(AND($D47>=116.66666666666667,$D47<133.33333333333334),"▼","") | N47: =IF(AND($D47>=133.33333333333334,$D47<150.0),"▼","") | O47: =IF(AND($D47>=150.0,$D47<166.66666666666669),"▼","") | P47: =IF(AND($D47>=166.66666666666669,$D47<183.33333333333334),"▼","") | Q47: =IF(AND($D47>=183.33333333333334,$D47<=200.0),"▼","") | R47: Conservador 0–25 · Normal 25–60 · Optimista 60–100 · Agresivo 100–200 | S47: Gastos/ventas: mínimo histórico 34,6 %; más de 60 pb es terreno nunca visto
B48: Años hasta alcanzar el ahorro completo | C48: años | D48: 3 | E48: =IF($D48<2.0,"Agresivo",IF($D48<3.0,"Optimista",IF($D48<4.0,"Normal","Conservador"))) | F48: =IF(AND($D48>=1.0,$D48<1.3333333333333333),"▼","") | G48: =IF(AND($D48>=1.3333333333333333,$D48<1.6666666666666665),"▼","") | H48: =IF(AND($D48>=1.6666666666666665,$D48<2.0),"▼","") | I48: =IF(AND($D48>=2.0,$D48<2.333333333333333),"▼","") | J48: =IF(AND($D48>=2.333333333333333,$D48<2.6666666666666665),"▼","") | K48: =IF(AND($D48>=2.6666666666666665,$D48<3.0),"▼","") | L48: =IF(AND($D48>=3.0,$D48<3.333333333333333),"▼","") | M48: =IF(AND($D48>=3.333333333333333,$D48<3.6666666666666665),"▼","") | N48: =IF(AND($D48>=3.6666666666666665,$D48<4.0),"▼","") | O48: =IF(AND($D48>=4.0,$D48<4.333333333333333),"▼","") | P48: =IF(AND($D48>=4.333333333333333,$D48<4.666666666666666),"▼","") | Q48: =IF(AND($D48>=4.666666666666666,$D48<=5.0),"▼","") | R48: Conservador 4–5 · Normal 3–4 · Optimista 2–3 · Agresivo 1–2 | S48: Los planes de eficiencia suelen tardar 2-4 años
B49: Coste de implantación | C49: × ahorro anual | D49: 1 | E49: =IF($D49<0.4,"Agresivo",IF($D49<0.75,"Optimista",IF($D49<1.5,"Normal","Conservador"))) | F49: =IF(AND($D49>=0.0,$D49<0.20833333333333334),"▼","") | G49: =IF(AND($D49>=0.20833333333333334,$D49<0.4166666666666667),"▼","") | H49: =IF(AND($D49>=0.4166666666666667,$D49<0.625),"▼","") | I49: =IF(AND($D49>=0.625,$D49<0.8333333333333334),"▼","") | J49: =IF(AND($D49>=0.8333333333333334,$D49<1.0416666666666667),"▼","") | K49: =IF(AND($D49>=1.0416666666666667,$D49<1.25),"▼","") | L49: =IF(AND($D49>=1.25,$D49<1.4583333333333335),"▼","") | M49: =IF(AND($D49>=1.4583333333333335,$D49<1.6666666666666667),"▼","") | N49: =IF(AND($D49>=1.6666666666666667,$D49<1.875),"▼","") | O49: =IF(AND($D49>=1.875,$D49<2.0833333333333335),"▼","") | P49: =IF(AND($D49>=2.0833333333333335,$D49<2.291666666666667),"▼","") | Q49: =IF(AND($D49>=2.291666666666667,$D49<=2.5),"▼","") | R49: Conservador 1,5–2,5 · Normal 0,75–1,5 · Optimista 0,4–0,75 · Agresivo 0–0,4 | S49: Se paga en 2026-27 (consultoría, despidos, sistemas)
B51: Circulante | C51: Activa (1/0) | D51: 1 | R51: Alargar el pago a proveedores y reducir stock (RFID, mejor reposición).
B52: Más proveedores sobre ventas | C52: pp | D52: 1 | E52: =IF($D52<0.5,"Conservador",IF($D52<1.5,"Normal",IF($D52<2.5,"Optimista","Agresivo"))) | F52: =IF(AND($D52>=0.0,$D52<0.3333333333333333),"▼","") | G52: =IF(AND($D52>=0.3333333333333333,$D52<0.6666666666666666),"▼","") | H52: =IF(AND($D52>=0.6666666666666666,$D52<1.0),"▼","") | I52: =IF(AND($D52>=1.0,$D52<1.3333333333333333),"▼","") | J52: =IF(AND($D52>=1.3333333333333333,$D52<1.6666666666666665),"▼","") | K52: =IF(AND($D52>=1.6666666666666665,$D52<2.0),"▼","") | L52: =IF(AND($D52>=2.0,$D52<2.333333333333333),"▼","") | M52: =IF(AND($D52>=2.333333333333333,$D52<2.6666666666666665),"▼","") | N52: =IF(AND($D52>=2.6666666666666665,$D52<3.0),"▼","") | O52: =IF(AND($D52>=3.0,$D52<3.333333333333333),"▼","") | P52: =IF(AND($D52>=3.333333333333333,$D52<3.6666666666666665),"▼","") | Q52: =IF(AND($D52>=3.6666666666666665,$D52<=4.0),"▼","") | R52: Conservador 0–0,5 · Normal 0,5–1,5 · Optimista 1,5–2,5 · Agresivo 2,5–4 | S52: Proveedores / ventas: 20,1 % (2022) a 22,2 % (2024); 21,5 % en 2025
B53: Menos existencias sobre ventas | C53: pp | D53: 0.4 | E53: =IF($D53<0.2,"Conservador",IF($D53<0.6,"Normal",IF($D53<1.0,"Optimista","Agresivo"))) | F53: =IF(AND($D53>=0.0,$D53<0.15),"▼","") | G53: =IF(AND($D53>=0.15,$D53<0.3),"▼","") | H53: =IF(AND($D53>=0.3,$D53<0.44999999999999996),"▼","") | I53: =IF(AND($D53>=0.44999999999999996,$D53<0.6),"▼","") | J53: =IF(AND($D53>=0.6,$D53<0.75),"▼","") | K53: =IF(AND($D53>=0.75,$D53<0.8999999999999999),"▼","") | L53: =IF(AND($D53>=0.8999999999999999,$D53<1.05),"▼","") | M53: =IF(AND($D53>=1.05,$D53<1.2),"▼","") | N53: =IF(AND($D53>=1.2,$D53<1.3499999999999999),"▼","") | O53: =IF(AND($D53>=1.3499999999999999,$D53<1.5),"▼","") | P53: =IF(AND($D53>=1.5,$D53<1.65),"▼","") | Q53: =IF(AND($D53>=1.65,$D53<=1.7999999999999998),"▼","") | R53: Conservador 0–0,2 · Normal 0,2–0,6 · Optimista 0,6–1 · Agresivo 1–1,8 | S53: Existencias / ventas: 8,2 % en 2025 (9,8 % en 2022)
B55: Venta y realquiler de inmuebles (PropCo) | C55: Activa (1/0) | D55: 1 | R55: Vender terrenos y edificios propios y realquilarlos: caja hoy a cambio de alquiler para siempre.
B56: Parte de terrenos y construcciones vendida | C56: % | D56: 0.35 | E56: =IF($D56<0.2,"Conservador",IF($D56<0.5,"Normal",IF($D56<0.8,"Optimista","Agresivo"))) | F56: =IF(AND($D56>=0.0,$D56<0.08333333333333333),"▼","") | G56: =IF(AND($D56>=0.08333333333333333,$D56<0.16666666666666666),"▼","") | H56: =IF(AND($D56>=0.16666666666666666,$D56<0.25),"▼","") | I56: =IF(AND($D56>=0.25,$D56<0.3333333333333333),"▼","") | J56: =IF(AND($D56>=0.3333333333333333,$D56<0.41666666666666663),"▼","") | K56: =IF(AND($D56>=0.41666666666666663,$D56<0.5),"▼","") | L56: =IF(AND($D56>=0.5,$D56<0.5833333333333333),"▼","") | M56: =IF(AND($D56>=0.5833333333333333,$D56<0.6666666666666666),"▼","") | N56: =IF(AND($D56>=0.6666666666666666,$D56<0.75),"▼","") | O56: =IF(AND($D56>=0.75,$D56<0.8333333333333333),"▼","") | P56: =IF(AND($D56>=0.8333333333333333,$D56<0.9166666666666666),"▼","") | Q56: =IF(AND($D56>=0.9166666666666666,$D56<=1.0),"▼","") | R56: Conservador 0%–20% · Normal 20%–50% · Optimista 50%–80% · Agresivo 80%–100% | S56: Valor neto contable a 31-01-2026: 2.404 M€
B57: Valor de mercado / valor contable | C57: x | D57: 1.5 | E57: =IF($D57<1.3,"Conservador",IF($D57<1.8,"Normal",IF($D57<2.5,"Optimista","Agresivo"))) | F57: =IF(AND($D57>=1.0,$D57<1.2083333333333333),"▼","") | G57: =IF(AND($D57>=1.2083333333333333,$D57<1.4166666666666667),"▼","") | H57: =IF(AND($D57>=1.4166666666666667,$D57<1.625),"▼","") | I57: =IF(AND($D57>=1.625,$D57<1.8333333333333335),"▼","") | J57: =IF(AND($D57>=1.8333333333333335,$D57<2.041666666666667),"▼","") | K57: =IF(AND($D57>=2.041666666666667,$D57<2.25),"▼","") | L57: =IF(AND($D57>=2.25,$D57<2.4583333333333335),"▼","") | M57: =IF(AND($D57>=2.4583333333333335,$D57<2.666666666666667),"▼","") | N57: =IF(AND($D57>=2.666666666666667,$D57<2.875),"▼","") | O57: =IF(AND($D57>=2.875,$D57<3.0833333333333335),"▼","") | P57: =IF(AND($D57>=3.0833333333333335,$D57<3.291666666666667),"▼","") | Q57: =IF(AND($D57>=3.291666666666667,$D57<=3.5),"▼","") | R57: Conservador 1–1,3 · Normal 1,3–1,8 · Optimista 1,8–2,5 · Agresivo 2,5–3,5 | S57: El suelo está a coste histórico: el valor de mercado suele ser mayor
B58: Rentabilidad que exige el comprador (cap rate) | C58: % | D58: 0.0575 | E58: =IF($D58<0.045,"Agresivo",IF($D58<0.0525,"Optimista",IF($D58<0.065,"Normal","Conservador"))) | F58: =IF(AND($D58>=0.035,$D58<0.03875000000000001),"▼","") | G58: =IF(AND($D58>=0.03875000000000001,$D58<0.0425),"▼","") | H58: =IF(AND($D58>=0.0425,$D58<0.04625),"▼","") | I58: =IF(AND($D58>=0.04625,$D58<0.05),"▼","") | J58: =IF(AND($D58>=0.05,$D58<0.053750000000000006),"▼","") | K58: =IF(AND($D58>=0.053750000000000006,$D58<0.0575),"▼","") | L58: =IF(AND($D58>=0.0575,$D58<0.06125),"▼","") | M58: =IF(AND($D58>=0.06125,$D58<0.065),"▼","") | N58: =IF(AND($D58>=0.065,$D58<0.06875),"▼","") | O58: =IF(AND($D58>=0.06875,$D58<0.07250000000000001),"▼","") | P58: =IF(AND($D58>=0.07250000000000001,$D58<0.07625),"▼","") | Q58: =IF(AND($D58>=0.07625,$D58<=0.08),"▼","") | R58: Conservador 6%–8% · Normal 5%–6% · Optimista 4%–5% · Agresivo 4%–4% | S58: Logística y retail prime en Europa ≈ 4,5-6,5 %
B60: Dividendo financiado con deuda (recap) | C60: Activa (1/0) | D60: 1 | R60: Volver a endeudar la senior para pagar un dividendo al fondo antes de la salida.
B61: Deuda senior neta objetivo tras el recap | C61: x EBITDA | D61: 2.5 | E61: =IF($D61<2.0,"Conservador",IF($D61<3.0,"Normal",IF($D61<3.75,"Optimista","Agresivo"))) | F61: =IF(AND($D61>=0.0,$D61<0.375),"▼","") | G61: =IF(AND($D61>=0.375,$D61<0.75),"▼","") | H61: =IF(AND($D61>=0.75,$D61<1.125),"▼","") | I61: =IF(AND($D61>=1.125,$D61<1.5),"▼","") | J61: =IF(AND($D61>=1.5,$D61<1.875),"▼","") | K61: =IF(AND($D61>=1.875,$D61<2.25),"▼","") | L61: =IF(AND($D61>=2.25,$D61<2.625),"▼","") | M61: =IF(AND($D61>=2.625,$D61<3.0),"▼","") | N61: =IF(AND($D61>=3.0,$D61<3.375),"▼","") | O61: =IF(AND($D61>=3.375,$D61<3.75),"▼","") | P61: =IF(AND($D61>=3.75,$D61<4.125),"▼","") | Q61: =IF(AND($D61>=4.125,$D61<=4.5),"▼","") | R61: Conservador 0–2 · Normal 2–3 · Optimista 3–3,75 · Agresivo 3,75–4,5 | S61: Al cierre la senior es 4,5x; en el caso base baja a ≈ 2,5x en 2027
B62: Año del recap | C62: año | D62: 2028 | R62: 2027, 2028 o 2029 (el recap en el año de salida no cuenta) | S62: 2027, 2028 o 2029
B65: Contribución de cada palanca
B66: Palanca | C66: Δ ventas 2030 | D66: Δ EBITDA 2030 | E66: Capex 26-30
B67: Expansión en EE. UU. | C67: =Palancas_calc!H35 | D67: =Palancas_calc!H36 | E67: =SUM(Palancas_calc!D37:H37)
B68: Marcas jóvenes (Stradivarius, Oysho, Bershka) | C68: =Palancas_calc!H38 | D68: =Palancas_calc!H39 | E68: =SUM(Palancas_calc!D40:H40)
B69: Lefties frente a Shein y Temu | C69: =Palancas_calc!H41 | D69: =Palancas_calc!H42 | E69: =SUM(Palancas_calc!D43:H43)
B70: Optimización de tiendas adicional | C70: =Palancas_calc!H44 | D70: =Palancas_calc!H45 | E70: =SUM(Palancas_calc!D46:H46)
B71: Eficiencia operativa | C71: - | D71: =Palancas_calc!H47 | E71: -
B72: Venta y realquiler de inmuebles (PropCo) | C72: - | D72: =Palancas_calc!H52 | E72: -
B73: Circulante: caja liberada acumulada | E73: =Palancas_calc!C65
B74: PropCo: caja recibida al cierre | E74: =Palancas_calc!$C$50

Sheet LBO_Rollover50
B1: Project Galicia — Inditex (ITX.MC)
A2: > | B2: Control Buyout Model — OPA por el 100% con rollover del 50% de Pontegadea (Senior TLA/TLB + HoldCo PIK + Vendor Loan 1x) | U2: Private & Confidential
A5: > | B5: > | C5: Operating model (100% Inditex Consolidated)
B7: > | C7: Drivers | E7: 1 | F7: 2 | G7: 3 | H7: Active Case: | I7: 4 | J7: 31-Jan | K7: 31-Jan | L7: 31-Jan | M7: 31-Jan | N7: 31-Jan | O7: 31-Jan | P7: 31-Jan | Q7: 31-Jan | R7: 31-Jan
D8: Operating Driver / Scenario Presets | E8: Base Case | F8: Bull Case | G8: Bear Case | H8: =CHOOSE($F$9,E8,F8,G8,I8) | I8: Bank Case | J8: 2022 | K8: =+J8+1 | L8: =+K8+1 | M8: =+L8+1 | N8: =+M8+1 | O8: =+N8+1 | P8: =+O8+1 | Q8: =+P8+1 | R8: =+Q8+1
B9: 1 | D9: Active Scenario Selector (1=Base, 2=Bull, 3=Bear, 4=Bank) | E9: Select 1-4 -> | F9: 1 | H9: =CHOOSE($F$9,E8,F8,G8,I8)
D10: Revenue growth (% YoY) | E10: 0.055 | F10: 0.08 | G10: 0.0225 | H10: =CHOOSE($F$9,E10,F10,G10,I10) | I10: 0.013112001 | J10: 0.175 | K10: 0.104 | L10: 0.075 | M10: 0.032 | N10: =Palancas_calc!D68 | O10: =Palancas_calc!E68 | P10: =Palancas_calc!F68 | Q10: =Palancas_calc!G68 | R10: =Palancas_calc!H68
D11: Gross margin (% of revenues) | E11: 0.582 | F11: 0.59 | G11: 0.57 | H11: =CHOOSE($F$9,E11,F11,G11,I11) | I11: 0.57420307 | J11: =+J23/J$21 | K11: =+K23/K$21 | L11: =+L23/L$21 | M11: =+M23/M$21 | N11: =Palancas_calc!D69 | O11: =Palancas_calc!E69 | P11: =Palancas_calc!F69 | Q11: =Palancas_calc!G69 | R11: =Palancas_calc!H69
D12: OpEx growth (% YoY) | E12: 0.0425 | F12: 0.055 | G12: 0.0325 | H12: =CHOOSE($F$9,E12,F12,G12,I12) | I12: 0.01442869 | J12: 0.109 | K12: 0.1 | L12: 0.065 | M12: 0.028 | N12: =Palancas_calc!D70 | O12: =Palancas_calc!E70 | P12: =Palancas_calc!F70 | Q12: =Palancas_calc!G70 | R12: =Palancas_calc!H70
D13: Fixed lease cash outflow growth (%) | E13: 0.02 | F13: 0.03 | G13: 0.01 | H13: =CHOOSE($F$9,E13,F13,G13,I13) | I13: 0.036920956 | J13: 0.05 | K13: =+K28/J28-1 | L13: =+L28/K28-1 | M13: =+M28/L28-1 | N13: =Palancas_calc!D71 | O13: =Palancas_calc!E71 | P13: =Palancas_calc!F71 | Q13: =Palancas_calc!G71 | R13: =Palancas_calc!H71
D14: Capex (% of revenues) | E14: 0.052 | F14: 0.0535 | G14: 0.049 | H14: =CHOOSE($F$9,E14,F14,G14,I14) | I14: 0.049826635 | J14: =+J58/J$21 | K14: =+K58/K$21 | L14: =+L58/L$21 | M14: =+M58/M$21 | N14: =Palancas_calc!D72 | O14: =Palancas_calc!E72 | P14: =Palancas_calc!F72 | Q14: =Palancas_calc!G72 | R14: =Palancas_calc!H72
D15: Inventory (% of revenues) | E15: 0.0815 | F15: 0.079 | G15: 0.085 | H15: =CHOOSE($F$9,E15,F15,G15,I15) | I15: 0.083698018 | J15: =+J44/J$21 | K15: =+K44/K$21 | L15: =+L44/L$21 | M15: =+M44/M$21 | N15: =Palancas_calc!D73 | O15: =Palancas_calc!E73 | P15: =Palancas_calc!F73 | Q15: =Palancas_calc!G73 | R15: =Palancas_calc!H73
D16: Receivables (% of revenues) | E16: 0.0292 | F16: 0.0285 | G16: 0.03 | H16: =CHOOSE($F$9,E16,F16,G16,I16) | I16: 0.028752787 | J16: =+J45/J$21 | K16: =+K45/K$21 | L16: =+L45/L$21 | M16: =+M45/M$21 | N16: =Palancas_calc!D74 | O16: =Palancas_calc!E74 | P16: =Palancas_calc!F74 | Q16: =Palancas_calc!G74 | R16: =Palancas_calc!H74
D17: Payables (% of revenues, negative) | E17: -0.2154 | F17: -0.2155 | G17: -0.213 | H17: =CHOOSE($F$9,E17,F17,G17,I17) | I17: -0.21496235 | J17: =+J46/J$21 | K17: =+K46/K$21 | L17: =+L46/L$21 | M17: =+M46/M$21 | N17: =Palancas_calc!D75 | O17: =Palancas_calc!E75 | P17: =Palancas_calc!F75 | Q17: =Palancas_calc!G75 | R17: =Palancas_calc!H75
D18: Drivers source (1 = Business_Plan año a año, 0 = presets planos E:I) | F18: 1
B19: > | C19: P&L | J19: 31-Jan | K19: 31-Jan | L19: 31-Jan | M19: 31-Jan | N19: 31-Jan | O19: 31-Jan | P19: 31-Jan | Q19: 31-Jan | R19: 31-Jan | U19: CAGR 22A-25A | V19: CAGR 25A-30E
C20: €m | J20: 2022 | K20: =+J20+1 | L20: =+K20+1 | M20: =+L20+1 | N20: =+M20+1 | O20: =+N20+1 | P20: =+O20+1 | Q20: =+P20+1 | R20: =+Q20+1
B21: 2 | D21: Revenues (100% Inditex) | J21: 32569 | K21: 35947 | L21: 38632 | M21: 39864 | N21: =+M21*(1+N10) | O21: =+N21*(1+O10) | P21: =+O21*(1+P10) | Q21: =+P21*(1+Q10) | R21: =+Q21*(1+R10) | U21: =+IFERROR((M21/J21)^(1/(M$20-J$20))-1,0) | V21: =+IFERROR((R21/M21)^(1/(R$20-M$20))-1,"n.a.")
D22: COGS | J22: =+J23-J21 | K22: =+K23-K21 | L22: =+L23-L21 | M22: =+M23-M21 | N22: =+N23-N21 | O22: =+O23-O21 | P22: =+P23-P21 | Q22: =+Q23-Q21 | R22: =+R23-R21 | U22: =+IFERROR((M22/J22)^(1/(M$20-J$20))-1,0) | V22: =+IFERROR((R22/M22)^(1/(R$20-M$20))-1,"n.a.")
D23: Gross margin | J23: 18559 | K23: 20762 | L23: 22343 | M23: 23222 | N23: =+N21*N11 | O23: =+O21*O11 | P23: =+P21*P11 | Q23: =+Q21*Q11 | R23: =+R21*R11 | U23: =+IFERROR((M23/J23)^(1/(M$20-J$20))-1,0) | V23: =+IFERROR((R23/M23)^(1/(R$20-M$20))-1,"n.a.")
D24: % margin | J24: =+IFERROR(J23/J$21,0) | K24: =+IFERROR(K23/K$21,0) | L24: =+IFERROR(L23/L$21,0) | M24: =+IFERROR(M23/M$21,0) | N24: =+IFERROR(N23/N$21,0) | O24: =+IFERROR(O23/O$21,0) | P24: =+IFERROR(P23/P$21,0) | Q24: =+IFERROR(Q23/Q$21,0) | R24: =+IFERROR(R23/R$21,0) | U24: =+IFERROR((M24/J24)^(1/(M$20-J$20))-1,0) | V24: =+IFERROR((R24/M24)^(1/(R$20-M$20))-1,"n.a.")
D25: Opex (incl. variable turnover rent) | J25: -9910 | K25: -10912 | L25: -11615 | M25: -11955 | N25: =+M25*(1+N12) | O25: =+N25*(1+O12) | P25: =+O25*(1+P12) | Q25: =+P25*(1+Q12) | R25: =+Q25*(1+R12) | U25: =+IFERROR((M25/J25)^(1/(M$20-J$20))-1,0) | V25: =+IFERROR((R25/M25)^(1/(R$20-M$20))-1,"n.a.")
D26: Reported EBITDA (Post-IFRS 16 — 100% Inditex) | J26: =+J23+J25 | K26: =+K23+K25 | L26: =+L23+L25 | M26: =+M23+M25 | N26: =+N23+N25 | O26: =+O23+O25 | P26: =+P23+P25 | Q26: =+Q23+Q25 | R26: =+R23+R25 | U26: =+IFERROR((M26/J26)^(1/(M$20-J$20))-1,0) | V26: =+IFERROR((R26/M26)^(1/(R$20-M$20))-1,"n.a.")
D27: % margin (Post-IFRS 16) | J27: =+IFERROR(J26/J$21,0) | K27: =+IFERROR(K26/K$21,0) | L27: =+IFERROR(L26/L$21,0) | M27: =+IFERROR(M26/M$21,0) | N27: =+IFERROR(N26/N$21,0) | O27: =+IFERROR(O26/O$21,0) | P27: =+IFERROR(P26/P$21,0) | Q27: =+IFERROR(Q26/Q$21,0) | R27: =+IFERROR(R26/R$21,0) | U27: =+IFERROR((M27/J27)^(1/(M$20-J$20))-1,0) | V27: =+IFERROR((R27/M27)^(1/(R$20-M$20))-1,"n.a.")
D28: Less: Fixed cash lease outflow (IFRS 16 store rents) | J28: -1621 | K28: -1733 | L28: -1802 | M28: -1834 | N28: =+M28*(1+N13) | O28: =+N28*(1+O13) | P28: =+O28*(1+P13) | Q28: =+P28*(1+Q13) | R28: =+Q28*(1+R13) | U28: =+IFERROR((M28/J28)^(1/(M$20-J$20))-1,0) | V28: =+IFERROR((R28/M28)^(1/(R$20-M$20))-1,"n.a.")
D29: Pre-IFRS 16 Cash EBITDA (100% Inditex) | J29: =+J26+J28 | K29: =+K26+K28 | L29: =+L26+L28 | M29: =+M26+M28 | N29: =+N26+N28 | O29: =+O26+O28 | P29: =+P26+P28 | Q29: =+Q26+Q28 | R29: =+R26+R28 | U29: =+IFERROR((M29/J29)^(1/(M$20-J$20))-1,0) | V29: =+IFERROR((R29/M29)^(1/(R$20-M$20))-1,"n.a.")
D30: % margin (Pre-IFRS 16) | J30: =+IFERROR(J29/J$21,0) | K30: =+IFERROR(K29/K$21,0) | L30: =+IFERROR(L29/L$21,0) | M30: =+IFERROR(M29/M$21,0) | N30: =+IFERROR(N29/N$21,0) | O30: =+IFERROR(O29/O$21,0) | P30: =+IFERROR(P29/P$21,0) | Q30: =+IFERROR(Q29/Q$21,0) | R30: =+IFERROR(R29/R$21,0) | U30: =+IFERROR((M30/J30)^(1/(M$20-J$20))-1,0) | V30: =+IFERROR((R30/M30)^(1/(R$20-M$20))-1,"n.a.")
D31: D&A (Owned PP&E & intangibles — 100% Inditex) | J31: =+J56 | K31: =+K56 | L31: =+L56 | M31: =+M56 | N31: =+N56 | O31: =+O56 | P31: =+P56 | Q31: =+Q56 | R31: =+R56 | U31: =+IFERROR((M31/J31)^(1/(M$20-J$20))-1,0) | V31: =+IFERROR((R31/M31)^(1/(R$20-M$20))-1,"n.a.")
D32: Adj. EBIT (Pre-IFRS 16 — 100% Inditex) | J32: =+J29+J31 | K32: =+K29+K31 | L32: =+L29+L31 | M32: =+M29+M31 | N32: =+N29+N31 | O32: =+O29+O31 | P32: =+P29+P31 | Q32: =+Q29+Q31 | R32: =+R29+R31 | U32: =+IFERROR((M32/J32)^(1/(M$20-J$20))-1,0) | V32: =+IFERROR((R32/M32)^(1/(R$20-M$20))-1,"n.a.")
D33: Attributable Adj. EBIT (% Stake Acquired) | F33: =+F168 | J33: =+J32*$F$168 | K33: =+K32*$F$168 | L33: =+L32*$F$168 | M33: =+M32*$F$168 | N33: =+N32*$F$168 | O33: =+O32*$F$168 | P33: =+P32*$F$168 | Q33: =+Q32*$F$168 | R33: =+R32*$F$168 | U33: =+IFERROR((M33/J33)^(1/(M$20-J$20))-1,0) | V33: =+IFERROR((R33/M33)^(1/(R$20-M$20))-1,"n.a.")
D34: Interests (Senior + Subordinated + Vendor Loan) | F34: =+F177 | J34: -44.4 | K34: 39.2 | L34: 14.8 | M34: 14.8 | N34: =+N133 | O34: =+O133 | P34: =+P133 | Q34: =+Q133 | R34: =+R133
D35: EBT (Attributable to LBO Perimeter) | J35: =+J33+J34 | K35: =+K33+K34 | L35: =+L33+L34 | M35: =+M33+M34 | N35: =+N33+N34 | O35: =+O33+O34 | P35: =+P33+P34 | Q35: =+Q33+Q34 | R35: =+R33+R34 | U35: =+IFERROR((M35/J35)^(1/(M$20-J$20))-1,0) | V35: =+IFERROR((R35/M35)^(1/(R$20-M$20))-1,"n.a.")
D36: Tax (Attributable to LBO Perimeter) | F36: 0.224 | J36: -779.2 | K36: -949.1 | L36: -1093.9 | M36: -1158.2 | N36: =+IF(N33+MAX(N34,-$K$174*N26)>0,-(N33+MAX(N34,-$K$174*N26))*$F$36,0) | O36: =+IF(O33+MAX(O34,-$K$174*O26)>0,-(O33+MAX(O34,-$K$174*O26))*$F$36,0) | P36: =+IF(P33+MAX(P34,-$K$174*P26)>0,-(P33+MAX(P34,-$K$174*P26))*$F$36,0) | Q36: =+IF(Q33+MAX(Q34,-$K$174*Q26)>0,-(Q33+MAX(Q34,-$K$174*Q26))*$F$36,0) | R36: =+IF(R33+MAX(R34,-$K$174*R26)>0,-(R33+MAX(R34,-$K$174*R26))*$F$36,0) | U36: =+IFERROR((M36/J36)^(1/(M$20-J$20))-1,0) | V36: =+IFERROR((R36/M36)^(1/(R$20-M$20))-1,"n.a.")
D37: Net income (Attributable to LBO Perimeter) | J37: =+J35+J36 | K37: =+K35+K36 | L37: =+L35+L36 | M37: =+M35+M36 | N37: =+N35+N36 | O37: =+O35+O36 | P37: =+P35+P36 | Q37: =+Q35+Q36 | R37: =+R35+R36 | U37: =+IFERROR((M37/J37)^(1/(M$20-J$20))-1,0) | V37: =+IFERROR((R37/M37)^(1/(R$20-M$20))-1,"n.a.")
B40: > | C40: BS | J40: 31-Jan | K40: 31-Jan | L40: 31-Jan | M40: 31-Jan | N40: 31-Jan | O40: 31-Jan | P40: 31-Jan | Q40: 31-Jan | R40: 31-Jan
C41: €m | J41: =+J20 | K41: =+J41+1 | L41: =+K41+1 | M41: =+L41+1 | N41: =+M41+1 | O41: =+N41+1 | P41: =+O41+1 | Q41: =+P41+1 | R41: =+Q41+1
B43: 3 | C43: > | D43: WK (Operating Working Capital — 100% Inditex)
D44: Inventory | J44: 3191 | K44: 2966 | L44: 3321 | M44: 3249 | N44: =+N$21*N15 | O44: =+O$21*O15 | P44: =+P$21*P15 | Q44: =+Q$21*Q15 | R44: =+R$21*R15
D45: Receivables | J45: 851 | K45: 1038 | L45: 1088 | M45: 1166 | N45: =+N$21*N16 | O45: =+O$21*O16 | P45: =+P$21*P16 | Q45: =+Q$21*Q16 | R45: =+R$21*R16
D46: Payables | J46: -6561 | K46: -7467 | L46: -8590 | M46: -8587 | N46: =+N$21*N17 | O46: =+O$21*O17 | P46: =+P$21*P17 | Q46: =+Q$21*Q17 | R46: =+R$21*R17
D47: Total WK (EoP balance — 100% Inditex) | J47: =+SUM(J44:J46) | K47: =+SUM(K44:K46) | L47: =+SUM(L44:L46) | M47: =+SUM(M44:M46) | N47: =+SUM(N44:N46) | O47: =+SUM(O44:O46) | P47: =+SUM(P44:P46) | Q47: =+SUM(Q44:Q46) | R47: =+SUM(R44:R46)
D48: WK % of revenues | J48: =+IFERROR(J47/J$21,0) | K48: =+IFERROR(K47/K$21,0) | L48: =+IFERROR(L47/L$21,0) | M48: =+IFERROR(M47/M$21,0) | N48: =+IFERROR(N47/N$21,0) | O48: =+IFERROR(O47/O$21,0) | P48: =+IFERROR(P47/P$21,0) | Q48: =+IFERROR(Q47/Q$21,0) | R48: =+IFERROR(R47/R$21,0)
D49: Cash flow from WK (-ΔWK — 100% Inditex) | J49: 0 | K49: =+(J47-K47) | L49: =+(K47-L47) | M49: =+(L47-M47) | N49: =+(M47-N47) | O49: =+(N47-O47) | P49: =+(O47-P47) | Q49: =+(P47-Q47) | R49: =+(Q47-R47)
B52: 4 | C52: > | D52: Capex & D&A (Owned PP&E + Intangibles — 100% Inditex)
D54: BoP Net Fixed Assets | J54: 8383 | K54: =+J57 | L54: =+K57 | M54: =+L57 | N54: =+M57 | O54: =+N57 | P54: =+O57 | Q54: =+P57 | R54: =+Q57
D55: Capex | J55: =+J58 | K55: =+K58 | L55: =+L58 | M55: =+M58 | N55: =+N58 | O55: =+O58 | P55: =+P58 | Q55: =+Q58 | R55: =+R58
D56: D&A | J56: -1417 | K56: -1558 | L56: -1638 | M56: -1674 | N56: =+N62+N73 | O56: =+O62+O73 | P56: =+P62+P73 | Q56: =+Q62+Q73 | R56: =+R62+R73
D57: EoP Net Fixed Assets | J57: 8401 | K57: 9560 | L57: 11416 | M57: 12778 | N57: =+N54+N55+N56 | O57: =+O54+O55+O56 | P57: =+P54+P55+P56 | Q57: =+Q54+Q55+Q56 | R57: =+R54+R55+R56
D58: Capex (Ordinary + Logistics — 100% Inditex) | J58: 1415 | K58: 1872 | L58: 2672 | M58: 2712 | N58: =+N21*N14 | O58: =+O21*O14 | P58: =+P21*P14 | Q58: =+Q21*Q14 | R58: =+R21*R14
D60: Existing fixed assets D&A
D61: BoP existing net assets | N61: =+M63 | O61: =+N63 | P61: =+O63 | Q61: =+P63 | R61: =+Q63
D62: D&A of existing assets | N62: =-MIN(N61,$M$63/$E$65) | O62: =-MIN(O61,$M$63/$E$65) | P62: =-MIN(P61,$M$63/$E$65) | Q62: =-MIN(Q61,$M$63/$E$65) | R62: =-MIN(R61,$M$63/$E$65)
D63: EoP existing net assets | M63: =+M57 | N63: =+N61+N62 | O63: =+O61+O62 | P63: =+P61+P62 | Q63: =+Q61+Q62 | R63: =+R61+R62
D65: Asset lifetime (years) | E65: 10
D66: First period D&A impact | E66: 0.5
G67: Vintage | H67: Capex (€m)
G68: =+N$20 | H68: =+N$58 | N68: =-(($H68/$E$65*$E$66)) | O68: =-(MIN(SUM($H68,$N68:N68),$H68/$E$65)) | P68: =-(MIN(SUM($H68,$N68:O68),$H68/$E$65)) | Q68: =-(MIN(SUM($H68,$N68:P68),$H68/$E$65)) | R68: =-(MIN(SUM($H68,$N68:Q68),$H68/$E$65))
G69: =+O$20 | H69: =+O$58 | N69: 0 | O69: =-(($H69/$E$65*$E$66)) | P69: =-(MIN(SUM($H69,$O69:O69),$H69/$E$65)) | Q69: =-(MIN(SUM($H69,$O69:P69),$H69/$E$65)) | R69: =-(MIN(SUM($H69,$O69:Q69),$H69/$E$65))
G70: =+P$20 | H70: =+P$58 | N70: 0 | O70: 0 | P70: =-(($H70/$E$65*$E$66)) | Q70: =-(MIN(SUM($H70,$P70:P70),$H70/$E$65)) | R70: =-(MIN(SUM($H70,$P70:Q70),$H70/$E$65))
G71: =+Q$20 | H71: =+Q$58 | N71: 0 | O71: 0 | P71: 0 | Q71: =-(($H71/$E$65*$E$66)) | R71: =-(MIN(SUM($H71,$Q71:Q71),$H71/$E$65))
G72: =+R$20 | H72: =+R$58 | N72: 0 | O72: 0 | P72: 0 | Q72: 0 | R72: =-(($H72/$E$65*$E$66))
G73: Total new capex D&A | N73: =SUM(N68:N72) | O73: =SUM(O68:O72) | P73: =SUM(P68:P72) | Q73: =SUM(Q68:Q72) | R73: =SUM(R68:R72)
B76: 5 | C76: > | D76: Debt Schedule (Senior TLA, Senior TLB, Subordinated Debt, Ortega Vendor Loan & RCF)
D78: 1A. Senior Term Loan A (TLA — Amortising)
D79: BoP TLA | M79: 0 | N79: =+M82 | O79: =+N82 | P79: =+O82 | Q79: =+P82 | R79: =+Q82
D80: Initial draw / increase | M80: =+E190 | N80: 0 | O80: 0 | P80: 0 | Q80: 0 | R80: 0
D81: Scheduled repayment | M81: 0 | N81: =-MIN(N79,$M$82*N$83) | O81: =-MIN(O79,$M$82*O$83) | P81: =-MIN(P79,$M$82*P$83) | Q81: =-MIN(Q79,$M$82*Q$83) | R81: =-MIN(R79,$M$82*R$83) | T81: =+SUM(N81:R81)+M82
D82: EoP TLA | M82: =+SUM(M79:M81) | N82: =+SUM(N79:N81) | O82: =+SUM(O79:O81) | P82: =+SUM(P79:P81) | Q82: =+SUM(Q79:Q81) | R82: =+SUM(R79:R81)
D83: TLA scheduled amortisation % | N83: 0 | O83: 0.1 | P83: 0.15 | Q83: 0.2 | R83: 0.25 | T83: =+SUM(N83:R83)-1
D84: TLA cash interest | N84: =-$F$178*AVERAGE(N79,N82) | O84: =-$F$178*AVERAGE(O79,O82) | P84: =-$F$178*AVERAGE(P79,P82) | Q84: =-$F$178*AVERAGE(Q79,Q82) | R84: =-$F$178*AVERAGE(R79,R82)
D86: 1B. Senior Term Loan B (TLB — Bullet / Optional Cash Sweep)
D87: BoP TLB | M87: 0 | N87: =+M92 | O87: =+N92 | P87: =+O92 | Q87: =+P92 | R87: =+Q92
D88: Initial draw / increase | M88: =+E191 | N88: =IF(AND(Palancas_calc!$C$53=1,N$8=Palancas!$D$62),MAX(0,Palancas!$D$61*M29-(M82+M92+M117-M157)),0) | O88: =IF(AND(Palancas_calc!$C$53=1,O$8=Palancas!$D$62),MAX(0,Palancas!$D$61*N29-(N82+N92+N117-N157)),0) | P88: =IF(AND(Palancas_calc!$C$53=1,P$8=Palancas!$D$62),MAX(0,Palancas!$D$61*O29-(O82+O92+O117-O157)),0) | Q88: =IF(AND(Palancas_calc!$C$53=1,Q$8=Palancas!$D$62),MAX(0,Palancas!$D$61*P29-(P82+P92+P117-P157)),0) | R88: =IF(AND(Palancas_calc!$C$53=1,R$8=Palancas!$D$62),MAX(0,Palancas!$D$61*Q29-(Q82+Q92+Q117-Q157)),0)
D89: Mandatory amortisation (% in F182) | M89: 0 | N89: =-MIN(N87,$M$92*N$93) | O89: =-MIN(O87,$M$92*O$93) | P89: =-MIN(P87,$M$92*P$93) | Q89: =-MIN(Q87,$M$92*Q$93) | R89: =-MIN(R87,$M$92*R$93)
D90: TLB balance before optional cash sweep | M90: =+M87+M88+M89 | N90: =+SUM(N87:N89) | O90: =+SUM(O87:O89) | P90: =+SUM(P87:P89) | Q90: =+SUM(Q87:Q89) | R90: =+SUM(R87:R89)
D91: Optional cash sweep repayment (% in F183) | M91: 0 | N91: =-MIN(N90,MAX(0,N150+N151)*$F$183) | O91: =-MIN(O90,MAX(0,O150+O151)*$F$183) | P91: =-MIN(P90,MAX(0,P150+P151)*$F$183) | Q91: =-MIN(Q90,MAX(0,Q150+Q151)*$F$183) | R91: =-MIN(R90,MAX(0,R150+R151)*$F$183)
D92: EoP TLB | M92: =+M90+M91 | N92: =+N90+N91 | O92: =+O90+O91 | P92: =+P90+P91 | Q92: =+Q90+Q91 | R92: =+R90+R91
D93: TLB mandatory amortisation % | N93: =+$F$182 | O93: =+$F$182 | P93: =+$F$182 | Q93: =+$F$182 | R93: =+$F$182
D94: TLB cash interest | N94: =-$F$179*AVERAGE(N87,N90) | O94: =-$F$179*AVERAGE(O87,O90) | P94: =-$F$179*AVERAGE(P87,P90) | Q94: =-$F$179*AVERAGE(Q87,Q90) | R94: =-$F$179*AVERAGE(R87,R90)
D96: 2. Subordinated / Mezzanine Debt (Bullet — Cash or PIK Switch)
D97: BoP Subordinated debt | M97: 0 | N97: =+M101 | O97: =+N101 | P97: =+O101 | Q97: =+P101 | R97: =+Q101
D98: Initial draw / increase | M98: =+E192 | N98: 0 | O98: 0 | P98: 0 | Q98: 0 | R98: 0
D99: PIK interest capitalised (if I180 = 1) | M99: 0 | N99: =+IF($I$180=1,N97*$F$180,0) | O99: =+IF($I$180=1,O97*$F$180,0) | P99: =+IF($I$180=1,P97*$F$180,0) | Q99: =+IF($I$180=1,Q97*$F$180,0) | R99: =+IF($I$180=1,R97*$F$180,0)
D100: Scheduled repayment (Bullet at maturity) | M100: 0 | N100: 0 | O100: 0 | P100: 0 | Q100: 0 | R100: 0
D101: EoP Subordinated debt | M101: =+SUM(M97:M100) | N101: =+SUM(N97:N100) | O101: =+SUM(O97:O100) | P101: =+SUM(P97:P100) | Q101: =+SUM(Q97:Q100) | R101: =+SUM(R97:R100)
D102: Subordinated cash interest (if I180 = 0) | N102: =+IF($I$180=0,-N97*$F$180,0) | O102: =+IF($I$180=0,-O97*$F$180,0) | P102: =+IF($I$180=0,-P97*$F$180,0) | Q102: =+IF($I$180=0,-Q97*$F$180,0) | R102: =+IF($I$180=0,-R97*$F$180,0)
D103: Subordinated total interest (for P&L tax shield) | N103: =-N97*$F$180 | O103: =-O97*$F$180 | P103: =-P97*$F$180 | Q103: =-Q97*$F$180 | R103: =-R97*$F$180
D105: 3. Ortega Family Vendor Loan (Pontegadea — Cash or PIK Switch)
D106: BoP Vendor Loan | M106: 0 | N106: =+M110 | O106: =+N110 | P106: =+O110 | Q106: =+P110 | R106: =+Q110
D107: Initial draw / increase | M107: =+E193 | N107: 0 | O107: 0 | P107: 0 | Q107: 0 | R107: 0
D108: PIK interest capitalised (if I181 = 1) | M108: 0 | N108: =+IF($I$181=1,N106*$F$181,0) | O108: =+IF($I$181=1,O106*$F$181,0) | P108: =+IF($I$181=1,P106*$F$181,0) | Q108: =+IF($I$181=1,Q106*$F$181,0) | R108: =+IF($I$181=1,R106*$F$181,0)
D109: Scheduled repayment (Bullet at exit) | M109: 0 | N109: 0 | O109: 0 | P109: 0 | Q109: 0 | R109: 0
D110: EoP Vendor Loan | M110: =+SUM(M106:M109) | N110: =+SUM(N106:N109) | O110: =+SUM(O106:O109) | P110: =+SUM(P106:P109) | Q110: =+SUM(Q106:Q109) | R110: =+SUM(R106:R109)
D111: Vendor Loan cash interest (if I181 = 0) | N111: =+IF($I$181=0,-N106*$F$181,0) | O111: =+IF($I$181=0,-O106*$F$181,0) | P111: =+IF($I$181=0,-P106*$F$181,0) | Q111: =+IF($I$181=0,-Q106*$F$181,0) | R111: =+IF($I$181=0,-R106*$F$181,0)
D112: Vendor Loan total interest (for P&L tax shield) | N112: =-N106*$F$181 | O112: =-O106*$F$181 | P112: =-P106*$F$181 | Q112: =-Q106*$F$181 | R112: =-R106*$F$181
D114: 4. Revolving Credit Facility (RCF — Liquidity Line)
D115: BoP RCF drawn | M115: 0 | N115: =+M117 | O115: =+N117 | P115: =+O117 | Q115: =+P117 | R115: =+Q117
D116: RCF draw / (repayment) | M116: =+E194 | N116: =+IF(N150<0,MIN($F$184-N115,-N150),-MIN(N115,N150)) | O116: =+IF(O150<0,MIN($F$184-O115,-O150),-MIN(O115,O150)) | P116: =+IF(P150<0,MIN($F$184-P115,-P150),-MIN(P115,P150)) | Q116: =+IF(Q150<0,MIN($F$184-Q115,-Q150),-MIN(Q115,Q150)) | R116: =+IF(R150<0,MIN($F$184-R115,-R150),-MIN(R115,R150))
D117: EoP RCF drawn | M117: =+M115+M116 | N117: =+N115+N116 | O117: =+O115+O116 | P117: =+P115+P116 | Q117: =+Q115+Q116 | R117: =+R115+R116
D118: Undrawn RCF available | M118: =+$F$184-M117 | N118: =+MAX(0,$F$184-N117) | O118: =+MAX(0,$F$184-O117) | P118: =+MAX(0,$F$184-P117) | Q118: =+MAX(0,$F$184-Q117) | R118: =+MAX(0,$F$184-R117)
...

Sheet Business_Plan
B1: Business plan año a año (simulación de Monte Carlo, 20.000 caminos)
B2: Cada caso es la mediana, año a año, de los drivers de los caminos cuyo EBITDA 2030 cae en su percentil (Bull P80, Base P50, Bear P20, Bank case P10). Fuente: carpeta Business Plan/ del repositorio.
D4: 1. Base (P50) | N4: 2026 | O4: 2027 | P4: 2028 | Q4: 2029 | R4: 2030
D5: Revenue growth (% YoY) | N5: 0.043215525 | O5: 0.035743916 | P5: 0.033012872 | Q5: 0.037448658 | R5: 0.036827931
D6: Gross margin (% of revenues) | N6: 0.58180712 | O6: 0.58106109 | P6: 0.58023095 | Q6: 0.58007572 | R6: 0.58019156
D7: OpEx growth (% YoY) | N7: 0.047504034 | O7: 0.039549133 | P7: 0.035082023 | Q7: 0.036845537 | R7: 0.036736371
D8: Fixed lease cash outflow growth (%) | N8: 0.038378631 | O8: 0.038360397 | P8: 0.038120975 | Q8: 0.038167826 | R8: 0.038104162
D9: Capex (% of revenues) | N9: 0.055078674 | O9: 0.048330623 | P9: 0.04830797 | Q9: 0.048357082 | R9: 0.048300395
D10: Inventory (% of revenues) | N10: 0.083933171 | O10: 0.083619755 | P10: 0.083875692 | Q10: 0.083792991 | R10: 0.083489452
D11: Receivables (% of revenues) | N11: 0.028798433 | O11: 0.028775752 | P11: 0.028748948 | Q11: 0.028711384 | R11: 0.028767583
D12: Payables (% of revenues, negative) | N12: -0.21536743 | O12: -0.21550022 | P12: -0.21507213 | Q12: -0.21495725 | R12: -0.21509229
D15: 2. Bull (P80) | N15: 2026 | O15: 2027 | P15: 2028 | Q15: 2029 | R15: 2030
D16: Revenue growth (% YoY) | N16: 0.056953003 | O16: 0.048395115 | P16: 0.051991778 | Q16: 0.051455476 | R16: 0.053327244
D17: Gross margin (% of revenues) | N17: 0.5830169 | O17: 0.58346308 | P17: 0.58471636 | Q17: 0.58574181 | R17: 0.58658062
... D45: Payables (% of revenues, negative) | N45: -0.21492881 | O45: -0.21481953 | P45: -0.21518895 | Q45: -0.21506928 | R45: -0.21480519
D48: Control: resultados esperados (motor Python, mismas fórmulas) | N48: TIR sponsor | O48: MoM | P48: DSCR mínimo | Q48: EBITDA pre-IFRS 16 2030 | R48: Deuda senior neta / EBITDA 2030 | S48: Capex acumulado 2026-30 | T48: Cheque del sponsor
D49: 1. Base | N49: 0.051724659 | O49: 1.2869755 | P49: 1.1732586 | Q49: 11071.829 | R49: 1.3440281 | S49: 11065.734 | T49: 75214.042
D50: 2. Bull | N50: 0.085422177 | O50: 1.5069227 | P50: 1.347896 | Q50: 12365.787 | R50: 0.93938765 | S50: 11568.234 | T50: 75214.042
D51: 3. Bear | N51: 0.014758773 | O51: 1.0760477 | P51: 1.0111291 | Q51: 9827.9052 | R51: 1.8263174 | S51: 10626.307 | T51: 75214.042
D52: 4. Bank case | N52: -0.0079360533 | O52: 0.96092359 | P52: 0.91311032 | Q52: 9149.6027 | R52: 2.1461501 | S52: 10385.006 | T52: 75214.042

Sheet Palancas_calc
B1: Cálculo de las palancas (no tocar: se alimenta de la hoja Palancas)
C3: 2025 | D3: 2026 | E3: 2027 | F3: 2028 | G3: 2029 | H3: 2030
B4: 1. Drivers del caso seleccionado (sin palancas)
B5: Crecimiento de ventas | D5: =IF(LBO_Rollover50!$F$18=1,CHOOSE(LBO_Rollover50!$F$9,Business_Plan!N5,Business_Plan!N16,Business_Plan!N27,Business_Plan!N38),LBO_Rollover50!$H$10) | E5: =IF(LBO_Rollover50!$F$18=1,CHOOSE(LBO_Rollover50!$F$9,Business_Plan!O5,Business_Plan!O16,Business_Plan!O27,Business_Plan!O38),LBO_Rollover50!$H$10) | F5: =IF(LBO_Rollover50!$F$18=1,CHOOSE(LBO_Rollover50!$F$9,Business_Plan!P5,Business_Plan!P16,Business_Plan!P27,Business_Plan!P38),LBO_Rollover50!$H$10) | G5: =IF(LBO_Rollover50!$F$18=1,CHOOSE(LBO_Rollover50!$F$9,Business_Plan!Q5,Business_Plan!Q16,Business_Plan!Q27,Business_Plan!Q38),LBO_Rollover50!$H$10) | H5: =IF(LBO_Rollover50!$F$18=1,CHOOSE(LBO_Rollover50!$F$9,Business_Plan!R5,Business_Plan!R16,Business_Plan!R27,Business_Plan!R38),LBO_Rollover50!$H$10)
B6: Margen bruto | D6: =IF(LBO_Rollover50!$F$18=1,CHOOSE(LBO_Rollover50!$F$9,Business_Plan!N6,Business_Plan!N17,Business_Plan!N28,Business_Plan!N39),LBO_Rollover50!$H$11) | E6: =IF(LBO_Rollover50!$F$18=1,CHOOSE(LBO_Rollover50!$F$9,Business_Plan!O6,Business_Plan!O17,Business_Plan!O28,Business_Plan!O39),LBO_Rollover50!$H$11) | F6: =IF(LBO_Rollover50!$F$18=1,CHOOSE(LBO_Rollover50!$F$9,Business_Plan!P6,Business_Plan!P17,Business_Plan!P28,Business_Plan!P39),LBO_Rollover50!$H$11) | G6: =IF(LBO_Rollover50!$F$18=1,CHOOSE(LBO_Rollover50!$F$9,Business_Plan!Q6,Business_Plan!Q17,Business_Plan!Q28,Business_Plan!Q39),LBO_Rollover50!$H$11) | H6: =IF(LBO_Rollover50!$F$18=1,CHOOSE(LBO_Rollover50!$F$9,Business_Plan!R6,Business_Plan!R17,Business_Plan!R28,Business_Plan!R39),LBO_Rollover50!$H$11)
B7: Crecimiento de gastos (sin alquileres fijos) | D7: =IF(LBO_Rollover50!$F$18=1,CHOOSE(LBO_Rollover50!$F$9,Business_Plan!N7,Business_Plan!N18,Business_Plan!N29,Business_Plan!N40),LBO_Rollover50!$H$12) | E7: =IF(LBO_Rollover50!$F$18=1,CHOOSE(LBO_Rollover50!$F$9,Business_Plan!O7,Business_Plan!O18,Business_Plan!O29,Business_Plan!O40),LBO_Rollover50!$H$12) | F7: =IF(LBO_Rollover50!$F$18=1,CHOOSE(LBO_Rollover50!$F$9,Business_Plan!P7,Business_Plan!P18,Business_Plan!P29,Business_Plan!P40),LBO_Rollover50!$H$12) | G7: =IF(LBO_Rollover50!$F$18=1,CHOOSE(LBO_Rollover50!$F$9,Business_Plan!Q7,Business_Plan!Q18,Business_Plan!Q29,Business_Plan!Q40),LBO_Rollover50!$H$12) | H7: =IF(LBO_Rollover50!$F$18=1,CHOOSE(LBO_Rollover50!$F$9,Business_Plan!R7,Business_Plan!R18,Business_Plan!R29,Business_Plan!R40),LBO_Rollover50!$H$12)
B8: Crecimiento de alquileres fijos | D8: =IF(LBO_Rollover50!$F$18=1,CHOOSE(LBO_Rollover50!$F$9,Business_Plan!N8,Business_Plan!N19,Business_Plan!N30,Business_Plan!N41),LBO_Rollover50!$H$13) | E8: =IF(LBO_Rollover50!$F$18=1,CHOOSE(LBO_Rollover50!$F$9,Business_Plan!O8,Business_Plan!O19,Business_Plan!O30,Business_Plan!O41),LBO_Rollover50!$H$13) | F8: =IF(LBO_Rollover50!$F$18=1,CHOOSE(LBO_Rollover50!$F$9,Business_Plan!P8,Business_Plan!P19,Business_Plan!P30,Business_Plan!P41),LBO_Rollover50!$H$13) | G8: =IF(LBO_Rollover50!$F$18=1,CHOOSE(LBO_Rollover50!$F$9,Business_Plan!Q8,Business_Plan!Q19,Business_Plan!Q30,Business_Plan!Q41),LBO_Rollover50!$H$13) | H8: =IF(LBO_Rollover50!$F$18=1,CHOOSE(LBO_Rollover50!$F$9,Business_Plan!R8,Business_Plan!R19,Business_Plan!R30,Business_Plan!R41),LBO_Rollover50!$H$13)
B9: Capex / ventas | D9: =IF(LBO_Rollover50!$F$18=1,CHOOSE(LBO_Rollover50!$F$9,Business_Plan!N9,Business_Plan!N20,Business_Plan!N31,Business_Plan!N42),LBO_Rollover50!$H$14) | E9: =IF(LBO_Rollover50!$F$18=1,CHOOSE(LBO_Rollover50!$F$9,Business_Plan!O9,Business_Plan!O20,Business_Plan!O31,Business_Plan!O42),LBO_Rollover50!$H$14) | F9: =IF(LBO_Rollover50!$F$18=1,CHOOSE(LBO_Rollover50!$F$9,Business_Plan!P9,Business_Plan!P20,Business_Plan!P31,Business_Plan!P42),LBO_Rollover50!$H$14) | G9: =IF(LBO_Rollover50!$F$18=1,CHOOSE(LBO_Rollover50!$F$9,Business_Plan!Q9,Business_Plan!Q20,Business_Plan!Q31,Business_Plan!Q42),LBO_Rollover50!$H$14) | H9: =IF(LBO_Rollover50!$F$18=1,CHOOSE(LBO_Rollover50!$F$9,Business_Plan!R9,Business_Plan!R20,Business_Plan!R31,Business_Plan!R42),LBO_Rollover50!$H$14)
B10: Existencias / ventas | D10: =IF(LBO_Rollover50!$F$18=1,CHOOSE(LBO_Rollover50!$F$9,Business_Plan!N10,Business_Plan!N21,Business_Plan!N32,Business_Plan!N43),LBO_Rollover50!$H$15) | E10: =IF(LBO_Rollover50!$F$18=1,CHOOSE(LBO_Rollover50!$F$9,Business_Plan!O10,Business_Plan!O21,Business_Plan!O32,Business_Plan!O43),LBO_Rollover50!$H$15) | F10: =IF(LBO_Rollover50!$F$18=1,CHOOSE(LBO_Rollover50!$F$9,Business_Plan!P10,Business_Plan!P21,Business_Plan!P32,Business_Plan!P43),LBO_Rollover50!$H$15) | G10: =IF(LBO_Rollover50!$F$18=1,CHOOSE(LBO_Rollover50!$F$9,Business_Plan!Q10,Business_Plan!Q21,Business_Plan!Q32,Business_Plan!Q43),LBO_Rollover50!$H$15) | H10: =IF(LBO_Rollover50!$F$18=1,CHOOSE(LBO_Rollover50!$F$9,Business_Plan!R10,Business_Plan!R21,Business_Plan!R32,Business_Plan!R43),LBO_Rollover50!$H$15)
B11: Clientes / ventas | D11: =IF(LBO_Rollover50!$F$18=1,CHOOSE(LBO_Rollover50!$F$9,Business_Plan!N11,Business_Plan!N22,Business_Plan!N33,Business_Plan!N44),LBO_Rollover50!$H$16) | E11: =IF(LBO_Rollover50!$F$18=1,CHOOSE(LBO_Rollover50!$F$9,Business_Plan!O11,Business_Plan!O22,Business_Plan!O33,Business_Plan!O44),LBO_Rollover50!$H$16) | F11: =IF(LBO_Rollover50!$F$18=1,CHOOSE(LBO_Rollover50!$F$9,Business_Plan!P11,Business_Plan!P22,Business_Plan!P33,Business_Plan!P44),LBO_Rollover50!$H$16) | G11: =IF(LBO_Rollover50!$F$18=1,CHOOSE(LBO_Rollover50!$F$9,Business_Plan!Q11,Business_Plan!Q22,Business_Plan!Q33,Business_Plan!Q44),LBO_Rollover50!$H$16) | H11: =IF(LBO_Rollover50!$F$18=1,CHOOSE(LBO_Rollover50!$F$9,Business_Plan!R11,Business_Plan!R22,Business_Plan!R33,Business_Plan!R44),LBO_Rollover50!$H$16)
B12: Proveedores / ventas | D12: =IF(LBO_Rollover50!$F$18=1,CHOOSE(LBO_Rollover50!$F$9,Business_Plan!N12,Business_Plan!N23,Business_Plan!N34,Business_Plan!N45),LBO_Rollover50!$H$17) | E12: =IF(LBO_Rollover50!$F$18=1,CHOOSE(LBO_Rollover50!$F$9,Business_Plan!O12,Business_Plan!O23,Business_Plan!O34,Business_Plan!O45),LBO_Rollover50!$H$17) | F12: =IF(LBO_Rollover50!$F$18=1,CHOOSE(LBO_Rollover50!$F$9,Business_Plan!P12,Business_Plan!P23,Business_Plan!P34,Business_Plan!P45),LBO_Rollover50!$H$17) | G12: =IF(LBO_Rollover50!$F$18=1,CHOOSE(LBO_Rollover50!$F$9,Business_Plan!Q12,Business_Plan!Q23,Business_Plan!Q34,Business_Plan!Q45),LBO_Rollover50!$H$17) | H12: =IF(LBO_Rollover50!$F$18=1,CHOOSE(LBO_Rollover50!$F$9,Business_Plan!R12,Business_Plan!R23,Business_Plan!R34,Business_Plan!R45),LBO_Rollover50!$H$17)
B14: 2. Caso seleccionado en euros (€m)
B15: Ventas | C15: 39864 | D15: =C15*(1+D5) | E15: =D15*(1+E5) | F15: =E15*(1+F5) | G15: =F15*(1+G5) | H15: =G15*(1+H5)
B16: Margen bruto | D16: =D15*D6 | E16: =E15*E6 | F16: =F15*F6 | G16: =G15*G6 | H16: =H15*H6
B17: Gastos (sin alquileres fijos) | C17: 11955 | D17: =C17*(1+D7) | E17: =D17*(1+E7) | F17: =E17*(1+F7) | G17: =F17*(1+G7) | H17: =G17*(1+H7)
B18: Alquileres fijos | C18: 1834 | D18: =C18*(1+D8) | E18: =D18*(1+E8) | F18: =E18*(1+F8) | G18: =F18*(1+G8) | H18: =G18*(1+H8)
B19: EBITDA pre-IFRS 16 | C19: 9433 | D19: =D16-D17-D18 | E19: =E16-E17-E18 | F19: =F16-F17-F18 | G19: =G16-G17-G18 | H19: =H16-H17-H18
B20: Capex | D20: =D15*D9 | E20: =E15*E9 | F20: =F15*F9 | G20: =G15*G9 | H20: =H15*H9
B22: 3. Constantes del modelo de palancas
B23: Factor de añadas: ventas (rampa 60/85/100 %, -3 % por añada) | D23: 0.6 | E23: 1.432 | F23: 2.38904 | G23: 3.3173688 | H23: 4.2178477
B24: Factor de añadas: ventas × margen (rampa de margen 50/80/100 %) | D24: 0.3 | E24: 0.971 | F24: 1.94187 | G24: 2.8836139 | H24: 3.7971055
B25: Factor de añadas sin pérdida por añada (reformas) | D25: 0.6 | E25: 1.45 | F25: 2.45 | G25: 3.45 | H25: 4.45
B26: Año del plan (1-5) | D26: 1 | E26: 2 | F26: 3 | G26: 4 | H26: 5
B27: Calendario de la mejora de circulante | D27: 0.5 | E27: 1 | F27: 1 | G27: 1 | H27: 1
B28: Indexación del alquiler de la PropCo (2 % anual) | D28: 1 | E28: 1.02 | F28: 1.0404 | G28: 1.061208 | H28: 1.0824322
B29: Margen EBITDA pre-IFRS 16 del grupo FY2025 (canibalización) | C29: 0.23662954
B30: Alquileres fijos / ventas FY2025 | C30: 0.046006422
B31: Ventas por m² del grupo FY2025 (€/m²) | C31: 8444.505
B32: Terrenos y construcciones, valor neto contable (€m) | C32: 2404
B34: 4. Efecto de cada palanca (€m)
B35: Expansión en EE. UU.: ventas | D35: =(Palancas!$D$4*Palancas!$D$19)*Palancas!$D$20*Palancas!$D$21/1000*D$23*(1-Palancas!$D$24) | E35: =(Palancas!$D$4*Palancas!$D$19)*Palancas!$D$20*Palancas!$D$21/1000*E$23*(1-Palancas!$D$24) | F35: =(Palancas!$D$4*Palancas!$D$19)*Palancas!$D$20*Palancas!$D$21/1000*F$23*(1-Palancas!$D$24) | G35: =(Palancas!$D$4*Palancas!$D$19)*Palancas!$D$20*Palancas!$D$21/1000*G$23*(1-Palancas!$D$24) | H35: =(Palancas!$D$4*Palancas!$D$19)*Palancas!$D$20*Palancas!$D$21/1000*H$23*(1-Palancas!$D$24)
B36: Expansión en EE. UU.: EBITDA | D36: =(Palancas!$D$4*Palancas!$D$19)*Palancas!$D$20*Palancas!$D$21/1000*(Palancas!$D$22*D$24-Palancas!$D$24*$C$29*D$23) | E36: =(Palancas!$D$4*Palancas!$D$19)*Palancas!$D$20*Palancas!$D$21/1000*(Palancas!$D$22*E$24-Palancas!$D$24*$C$29*E$23) | F36: =(Palancas!$D$4*Palancas!$D$19)*Palancas!$D$20*Palancas!$D$21/1000*(Palancas!$D$22*F$24-Palancas!$D$24*$C$29*F$23) | G36: =(Palancas!$D$4*Palancas!$D$19)*Palancas!$D$20*Palancas!$D$21/1000*(Palancas!$D$22*G$24-Palancas!$D$24*$C$29*G$23) | H36: =(Palancas!$D$4*Palancas!$D$19)*Palancas!$D$20*Palancas!$D$21/1000*(Palancas!$D$22*H$24-Palancas!$D$24*$C$29*H$23)
B37: Expansión en EE. UU.: capex | D37: =(Palancas!$D$4*Palancas!$D$19)*Palancas!$D$20*Palancas!$D$23/1000 | E37: =(Palancas!$D$4*Palancas!$D$19)*Palancas!$D$20*Palancas!$D$23/1000 | F37: =(Palancas!$D$4*Palancas!$D$19)*Palancas!$D$20*Palancas!$D$23/1000 | G37: =(Palancas!$D$4*Palancas!$D$19)*Palancas!$D$20*Palancas!$D$23/1000 | H37: =(Palancas!$D$4*Palancas!$D$19)*Palancas!$D$20*Palancas!$D$23/1000
B38: Marcas jóvenes (Stradivarius, Oysho, Bershka): ventas | D38: =(Palancas!$D$4*Palancas!$D$26)*Palancas!$D$27*Palancas!$D$28/1000*D$23*(1-Palancas!$D$31) | E38: =(Palancas!$D$4*Palancas!$D$26)*Palancas!$D$27*Palancas!$D$28/1000*E$23*(1-Palancas!$D$31) | F38: =(Palancas!$D$4*Palancas!$D$26)*Palancas!$D$27*Palancas!$D$28/1000*F$23*(1-Palancas!$D$31) | G38: =(Palancas!$D$4*Palancas!$D$26)*Palancas!$D$27*Palancas!$D$28/1000*G$23*(1-Palancas!$D$31) | H38: =(Palancas!$D$4*Palancas!$D$26)*Palancas!$D$27*Palancas!$D$28/1000*H$23*(1-Palancas!$D$31)
B39: Marcas jóvenes (Stradivarius, Oysho, Bershka): EBITDA | D39: =(Palancas!$D$4*Palancas!$D$26)*Palancas!$D$27*Palancas!$D$28/1000*(Palancas!$D$29*D$24-Palancas!$D$31*$C$29*D$23) | E39: =(Palancas!$D$4*Palancas!$D$26)*Palancas!$D$27*Palancas!$D$28/1000*(Palancas!$D$29*E$24-Palancas!$D$31*$C$29*E$23) | F39: =(Palancas!$D$4*Palancas!$D$26)*Palancas!$D$27*Palancas!$D$28/1000*(Palancas!$D$29*F$24-Palancas!$D$31*$C$29*F$23) | G39: =(Palancas!$D$4*Palancas!$D$26)*Palancas!$D$27*Palancas!$D$28/1000*(Palancas!$D$29*G$24-Palancas!$D$31*$C$29*G$23) | H39: =(Palancas!$D$4*Palancas!$D$26)*Palancas!$D$27*Palancas!$D$28/1000*(Palancas!$D$29*H$24-Palancas!$D$31*$C$29*H$23)
B40: Marcas jóvenes (Stradivarius, Oysho, Bershka): capex | D40: =(Palancas!$D$4*Palancas!$D$26)*Palancas!$D$27*Palancas!$D$30/1000 | E40: =(Palancas!$D$4*Palancas!$D$26)*Palancas!$D$27*Palancas!$D$30/1000 | F40: =(Palancas!$D$4*Palancas!$D$26)*Palancas!$D$27*Palancas!$D$30/1000 | G40: =(Palancas!$D$4*Palancas!$D$26)*Palancas!$D$27*Palancas!$D$30/1000 | H40: =(Palancas!$D$4*Palancas!$D$26)*Palancas!$D$27*Palancas!$D$30/1000
B41: Lefties frente a Shein y Temu: ventas | D41: =(Palancas!$D$4*Palancas!$D$33)*Palancas!$D$34*Palancas!$D$35/1000*D$23*(1-Palancas!$D$38) | E41: =(Palancas!$D$4*Palancas!$D$33)*Palancas!$D$34*Palancas!$D$35/1000*E$23*(1-Palancas!$D$38) | F41: =(Palancas!$D$4*Palancas!$D$33)*Palancas!$D$34*Palancas!$D$35/1000*F$23*(1-Palancas!$D$38) | G41: =(Palancas!$D$4*Palancas!$D$33)*Palancas!$D$34*Palancas!$D$35/1000*G$23*(1-Palancas!$D$38) | H41: =(Palancas!$D$4*Palancas!$D$33)*Palancas!$D$34*Palancas!$D$35/1000*H$23*(1-Palancas!$D$38)
B42: Lefties frente a Shein y Temu: EBITDA | D42: =(Palancas!$D$4*Palancas!$D$33)*Palancas!$D$34*Palancas!$D$35/1000*(Palancas!$D$36*D$24-Palancas!$D$38*$C$29*D$23) | E42: =(Palancas!$D$4*Palancas!$D$33)*Palancas!$D$34*Palancas!$D$35/1000*(Palancas!$D$36*E$24-Palancas!$D$38*$C$29*E$23) | F42: =(Palancas!$D$4*Palancas!$D$33)*Palancas!$D$34*Palancas!$D$35/1000*(Palancas!$D$36*F$24-Palancas!$D$38*$C$29*F$23) | G42: =(Palancas!$D$4*Palancas!$D$33)*Palancas!$D$34*Palancas!$D$35/1000*(Palancas!$D$36*G$24-Palancas!$D$38*$C$29*G$23) | H42: =(Palancas!$D$4*Palancas!$D$33)*Palancas!$D$34*Palancas!$D$35/1000*(Palancas!$D$36*H$24-Palancas!$D$38*$C$29*H$23)
B43: Lefties frente a Shein y Temu: capex | D43: =(Palancas!$D$4*Palancas!$D$33)*Palancas!$D$34*Palancas!$D$37/1000 | E43: =(Palancas!$D$4*Palancas!$D$33)*Palancas!$D$34*Palancas!$D$37/1000 | F43: =(Palancas!$D$4*Palancas!$D$33)*Palancas!$D$34*Palancas!$D$37/1000 | G43: =(Palancas!$D$4*Palancas!$D$33)*Palancas!$D$34*Palancas!$D$37/1000 | H43: =(Palancas!$D$4*Palancas!$D$33)*Palancas!$D$34*Palancas!$D$37/1000
B44: Optimización de tiendas: ventas | D44: =(Palancas!$D$4*Palancas!$D$40)*Palancas!$D$41*$C$31/1000*Palancas!$D$42*D$25 | E44: =(Palancas!$D$4*Palancas!$D$40)*Palancas!$D$41*$C$31/1000*Palancas!$D$42*E$25 | F44: =(Palancas!$D$4*Palancas!$D$40)*Palancas!$D$41*$C$31/1000*Palancas!$D$42*F$25 | G44: =(Palancas!$D$4*Palancas!$D$40)*Palancas!$D$41*$C$31/1000*Palancas!$D$42*G$25 | H44: =(Palancas!$D$4*Palancas!$D$40)*Palancas!$D$41*$C$31/1000*Palancas!$D$42*H$25
B45: Optimización de tiendas: EBITDA | D45: =D44*Palancas!$D$44 | E45: =E44*Palancas!$D$44 | F45: =F44*Palancas!$D$44 | G45: =G44*Palancas!$D$44 | H45: =H44*Palancas!$D$44
B46: Optimización de tiendas: capex | D46: =(Palancas!$D$4*Palancas!$D$40)*Palancas!$D$41*Palancas!$D$43/1000 | E46: =(Palancas!$D$4*Palancas!$D$40)*Palancas!$D$41*Palancas!$D$43/1000 | F46: =(Palancas!$D$4*Palancas!$D$40)*Palancas!$D$41*Palancas!$D$43/1000 | G46: =(Palancas!$D$4*Palancas!$D$40)*Palancas!$D$41*Palancas!$D$43/1000 | H46: =(Palancas!$D$4*Palancas!$D$40)*Palancas!$D$41*Palancas!$D$43/1000
B47: Eficiencia operativa: EBITDA | D47: =(Palancas!$D$4*Palancas!$D$46)*(Palancas!$D$47/10000*D15*MIN(1,D$26/Palancas!$D$48)-IF(D$26<=2,0.5*Palancas!$D$49*Palancas!$D$47/10000*$D15,0)) | E47: =(Palancas!$D$4*Palancas!$D$46)*(Palancas!$D$47/10000*E15*MIN(1,E$26/Palancas!$D$48)-IF(E$26<=2,0.5*Palancas!$D$49*Palancas!$D$47/10000*$D15,0)) | F47: =(Palancas!$D$4*Palancas!$D$46)*(Palancas!$D$47/10000*F15*MIN(1,F$26/Palancas!$D$48)-IF(F$26<=2,0.5*Palancas!$D$49*Palancas!$D$47/10000*$D15,0)) | G47: =(Palancas!$D$4*Palancas!$D$46)*(Palancas!$D$47/10000*G15*MIN(1,G$26/Palancas!$D$48)-IF(G$26<=2,0.5*Palancas!$D$49*Palancas!$D$47/10000*$D15,0)) | H47: =(Palancas!$D$4*Palancas!$D$46)*(Palancas!$D$47/10000*H15*MIN(1,H$26/Palancas!$D$48)-IF(H$26<=2,0.5*Palancas!$D$49*Palancas!$D$47/10000*$D15,0))
B48: Circulante: cambio en existencias / ventas | D48: =-(Palancas!$D$4*Palancas!$D$51)*Palancas!$D$53/100*D$27 | E48: =-(Palancas!$D$4*Palancas!$D$51)*Palancas!$D$53/100*E$27 | F48: =-(Palancas!$D$4*Palancas!$D$51)*Palancas!$D$53/100*F$27 | G48: =-(Palancas!$D$4*Palancas!$D$51)*Palancas!$D$53/100*G$27 | H48: =-(Palancas!$D$4*Palancas!$D$51)*Palancas!$D$53/100*H$27
B49: Circulante: cambio en proveedores / ventas | D49: =-(Palancas!$D$4*Palancas!$D$51)*Palancas!$D$52/100*D$27 | E49: =-(Palancas!$D$4*Palancas!$D$51)*Palancas!$D$52/100*E$27 | F49: =-(Palancas!$D$4*Palancas!$D$51)*Palancas!$D$52/100*F$27 | G49: =-(Palancas!$D$4*Palancas!$D$51)*Palancas!$D$52/100*G$27 | H49: =-(Palancas!$D$4*Palancas!$D$51)*Palancas!$D$52/100*H$27
B50: PropCo: ingresos por la venta de inmuebles (fuente al cierre) | C50: =(Palancas!$D$4*Palancas!$D$55)*$C$32*Palancas!$D$56*Palancas!$D$57
B51: PropCo: nuevo alquiler fijo | D51: =$C$50*Palancas!$D$58*D$28 | E51: =$C$50*Palancas!$D$58*E$28 | F51: =$C$50*Palancas!$D$58*F$28 | G51: =$C$50*Palancas!$D$58*G$28 | H51: =$C$50*Palancas!$D$58*H$28
B52: PropCo: EBITDA | D52: =-D51 | E52: =-E51 | F52: =-F51 | G52: =-G51 | H52: =-H51
B53: Recap: activo (1/0) | C53: =(Palancas!$D$4*Palancas!$D$60)
B55: 5. Caso con palancas (€m)
B56: Ventas incrementales | D56: =D35+D38+D41+D44 | E56: =E35+E38+E41+E44 | F56: =F35+F38+F41+F44 | G56: =G35+G38+G41+G44 | H56: =H35+H38+H41+H44
B57: EBITDA pre-IFRS 16 incremental | D57: =D36+D39+D42+D45+D47+D52 | E57: =E36+E39+E42+E45+E47+E52 | F57: =F36+F39+F42+F45+F47+F52 | G57: =G36+G39+G42+G45+G47+G52 | H57: =H36+H39+H42+H45+H47+H52
B58: Capex incremental | D58: =D37+D40+D43+D46 | E58: =E37+E40+E43+E46 | F58: =F37+F40+F43+F46 | G58: =G37+G40+G43+G46 | H58: =H37+H40+H43+H46
B59: Ventas | C59: 39864 | D59: =D15+D56 | E59: =E15+E56 | F59: =F15+F56 | G59: =G15+G56 | H59: =H15+H56
B60: Margen bruto | D60: =D16+D56*D16/D15 | E60: =E16+E56*E16/E15 | F60: =F16+F56*F16/F15 | G60: =G16+G56*G16/G15 | H60: =H16+H56*H16/H15
B61: Alquileres fijos | C61: 1834 | D61: =D18+D56*$C$30+D51 | E61: =E18+E56*$C$30+E51 | F61: =F18+F56*$C$30+F51 | G61: =G18+G56*$C$30+G51 | H61: =H18+H56*$C$30+H51
B62: EBITDA pre-IFRS 16 | C62: 9433 | D62: =D19+D57 | E62: =E19+E57 | F62: =F19+F57 | G62: =G19+G57 | H62: =H19+H57
B63: Gastos (sin alquileres fijos) | C63: 11955 | D63: =D60-D62-D61 | E63: =E60-E62-E61 | F63: =F60-F62-F61 | G63: =G60-G62-G61 | H63: =H60-H62-H61
B64: Capex | D64: =D20+D58 | E64: =E20+E58 | F64: =F20+F58 | G64: =G20+G58 | H64: =H20+H58
B65: Circulante: caja liberada acumulada 2026-30 (€m) | C65: =-H59*(H48+H49)
B67: 6. Drivers finales (alimentan LBO_Rollover50!N10:R17)
B68: Crecimiento de ventas | D68: =D59/C59-1 | E68: =E59/D59-1 | F68: =F59/E59-1 | G68: =G59/F59-1 | H68: =H59/G59-1
B69: Margen bruto | D69: =D60/D59 | E69: =E60/E59 | F69: =F60/F59 | G69: =G60/G59 | H69: =H60/H59
B70: Crecimiento de gastos (sin alquileres fijos) | D70: =D63/C63-1 | E70: =E63/D63-1 | F70: =F63/E63-1 | G70: =G63/F63-1 | H70: =H63/G63-1
B71: Crecimiento de alquileres fijos | D71: =D61/C61-1 | E71: =E61/D61-1 | F71: =F61/E61-1 | G71: =G61/F61-1 | H71: =H61/G61-1
B72: Capex / ventas | D72: =D64/D59 | E72: =E64/E59 | F72: =F64/F59 | G72: =G64/G59 | H72: =H64/H59
B73: Existencias / ventas | D73: =D10+D48 | E73: =E10+E48 | F73: =F10+F48 | G73: =G10+G48 | H73: =H10+H48
B74: Clientes / ventas | D74: =D11 | E74: =E11 | F74: =F11 | G74: =G11 | H74: =H11
B75: Proveedores / ventas | D75: =D12+D49 | E75: =E12+E49 | F75: =F12+F49 | G75: =G12+G49 | H75: =H12+H49

Sheet Cambios
C2: Qué es | E2: Copia del Excel del grupo. La hoja LBO_Rollover50 es una copia exacta de la hoja LBO (mismo formato, mismas filas y fórmulas) en la que solo se han cambiado las celdas indicadas abajo. La hoja LBO original no se ha tocado y las dos hojas no están enlazadas.
C3: Tema | D3: Celdas | E3: Hoja LBO (original) | F3: Hoja LBO_Rollover50
C4: Perímetro | D4: F168 | E4: 64,35% (Amancio + Sandra) | F4: 100% (OPA obligatoria; incluye el rollover)
C5: Rollover | D5: H171:K173, E207, E208, D196 | E5: Sin rollover | F5: Amancio aporta el 50% de su 59,294% a la TopCo (≈ €53.800m). Fila 196 = equity total (sponsor + rollover); fila 208 = efectivo del sponsor
C6: Veces EBITDA | D6: G178:G181 | E6: 1,5 / 3,0 / 2,0 / 4,0 = 10,5x | F6: 2,0 / 2,0 / 1,0 / 1,0 = 6,0x (apuntes de Borja)
C7: Euribor | D7: G177 | E7: 3,00% | F7: 2,59% (3M, 1-oct-2026)
C8: Márgenes senior | D8: H178, H179 | E8: TLA +2,50% / TLB +3,50% | F8: TLA +3,25% / TLB +4,25%
C9: Subordinada | D9: F180, H180, I180 | E9: E + 4,75% en efectivo | F9: HoldCo PIK al 10,5% fijo (I180 = 1)
C10: Vendor loan | D10: H181, I181 | E10: 5,5% en efectivo | F10: 10% PIK (I181 = 1)
C11: Amortización TLA | D11: N83:R83, R251 | E11: 10/15/20/25/30% | F11: 0/10/15/20/25%; el 30% restante se repaga en la salida
C12: Cash sweep TLB | D12: F183 | E12: 0% | F12: 75%
C13: RCF | D13: F184, H185, F186 | E13: €2.000m, E + 2,25%, 0,35% | F13: €4.000m, E + 3,00%, 1,05% (35% del margen)
C14: Comisiones de financiación | D14: K169 | E14: 1,5% | F14: 2,25%
... C19: Sin cambios | D19: Filas 7–73 | E19: Business plan del grupo | F19: Igual (copiado tal cual)
B21: Business plan (Álvaro) | C21: Hoja Business_Plan | D21: — | E21: Drivers año a año de 4 casos (Base P50, Bull P80, Bear P20, Bank case P10) de la simulación de Monte Carlo
B22: Business plan (Álvaro) | C22: N10:R17, F18 | D22: =+$H10 (constante) | E22: =Palancas_calc!… (caso elegido + palancas). F18 = 0 vuelve a los presets planos
B23: Plan de creación de valor | C23: Hojas Palancas y Palancas_calc | D23: — | E23: Panel de control con 8 palancas y barómetro. Palancas!D4 = 0 desactiva el plan
B24: Plan de creación de valor | C24: E195 | D24: =+F173 | E24: =+F173 + caja de la PropCo
B25: Plan de creación de valor | C25: N88:R88, N153:R154 | D25: 0 / sin recap | E25: Recap: nueva TLB en el año elegido hasta la deuda senior neta objetivo; se paga como dividendo
B26: Business plan (Álvaro) | C26: F9, I7:I17, H8:H17 | D26: Selector 1-3 | E26: Selector 1-4 (4 = Bank case)
B27: Estructura del grupo | C27: F165 | D27: 5 % | E27: 20% (prima acordada)
B28: Estructura del grupo | C28: G178:G181 | D28: 2,0 / 2,0 / 1,0 / 1,0 = 6,0x | E28: 2.25 / 2.25 / 1.50 / 1.00 = 7.0x (senior 4,5x). El check 8 (senior < 4,0x) sale CHECK a propósito
