Workbook

Sheet Instructions
B1: Project Galicia v3 — Inditex (ITX.MC) | F1: Strictly Private & Confidential
A2: > | B2: Institutional Multi-Sheet LBO Model — 100% Take-Private + Amancio Ortega Rollover (2025A–2032E)
C4: Tab | D4: Worksheet Name | E4: Key Legal, Financial & Tax Features + Interactive Switches (Blue Font / Soft Yellow Fill)
C5: 1 | D5: LBO Summary | E5: 100% Take-Private Executive Dashboard: Amancio Ortega rolls over his 59.29% stake (F14) into TopCo under the tax-neutral FEAC regime (Art. 87 LIS), while BidCo acquires the remaining 40.71% (35.65% Free Float + 5.05% Sandra Ortega) via a mandatory Take-Private OPA (RD 1066/2007). Includes Per-Tranche Upfront Fees, TopCo Equity split (88.1% Amancio / 11.9% Sponsor), 7-Year Exit Valuation Matrix (2026E–2032E), native IRR/MOIC Cash Flow Matrix, and 3x3 Sensitivity Table.
C6: 2 | D6: Active Case | E6: 100% Inditex Consolidated Operating Model (2022A–2032E): Because BidCo owns 100.0% of Inditex post-squeeze-out, there is zero minority leakage. Includes Scenario Selector (F8: 1=Base, 2=Bull, 3=Bear), P&L with Pre-IFRS 16 Cash EBITDA Bridge (€9,433m in 2025A), Structural Negative Working Capital (NOF), and Capex split into Maintenance Capex (3.5% rev) vs. US & Logistics Expansion Capex (1.7% rev, funded 100% organically).
C7: 3 | D7: Debt & Covenants | E7: Multi-Tranche Debt & Covenant Schedule (2025A–2032E, 5.50x 100% EBITDA = €51,882m): Pricing split into Reference Euribor Swap (F7 = 2.75%) + Spread, Weighted Average Life of Loan (WALL), Interest on Average Balances (zero circularity), Senior TLA (1.5x, 5y amortising), Senior TLB (2.5x, 7y bullet), Subordinated Debt (1.0x, Cash/PIK switch in H10), Sandra Vendor Loan (0.5x, Cash/PIK switch in H11), €3,500m RCF as Seasonal Negative-NOF Backstop with Commitment Fee (G15), SFA Net Leverage Covenant with 25% Headroom (E16), and Bank DSCR.
C8: 4 | D8: Tax & WACC | E8: 100% Fiscal Consolidation (Art. 58, 16.5 & 16.1 LIS) & Dynamic WACC (2025A–2032E): Tests the Spanish Anti-LBO Debt Cap (Art. 16.5 LIS: Acquisition Debt is 28.6% of total purchase value, well below the 70% statutory limit) and applies the 30% Operating EBITDA interest cap (Art. 16.1 LIS) with 5-year carryforwards and 7-year upfront fee amortization. Tracks Dynamic Levered Beta (Beta_L), Cost of Equity (Ke), Effective Tax Shield Rate (t_eff), and Dynamic WACC from 2025A to 2032E.
C9: 5 | D9: Checks | E9: Automated Legal, Financial & Tax Audit Panel: 10 real-time cross-sheet integrity checks verifying Sources & Uses balance, TopCo 100% equity sum, Art. 58 LIS (>=75%) consolidation, Art. 16.5 LIS (<70%) anti-LBO debt cap, TLA 100% amortisation, €1,500m Minimum Cash floor, Non-negative debt balances, D&A reconciliation, SFA Leverage Covenant, and DSCR compliance.

Sheet LBO Summary
B1: Project Galicia v3 — Inditex (ITX.MC) | N1: Strictly Private & Confidential
A2: > | B2: LBO Summary — 100% Take-Private (OPA Exclusión) with Amancio Ortega Rollover to TopCo (Exits 2026E–2032E)
A4: > | B4: > | C4: 1. Transaction Structure: 100% Take-Private via Free Float + Sandra Buyout & Amancio Rollover
B6: 1 | D6: Deal Valuation & Ownership Perimeter (100% Inditex) | F6: Value / Input | H6: Multiples, Fees & Headline Returns | L6: Value / Input
D7: 100% Inditex FY25A Pre-IFRS 16 Cash EBITDA (€m) | F7: ='Active Case'!L30 -> 9433 | H7: Implied 100% Offer Enterprise Value (EV, €m) | L7: =+F13-F19 -> 170403.1
D8: 100% Inditex FY25A Reported Post-IFRS 16 EBITDA (€m) | F8: ='Active Case'!L26 -> 11267 | H8: Implied Entry EV / Pre-IFRS 16 Cash EBITDA | L8: =+L7/F7 -> 18.064571
D9: Current undisturbed share price (€/sh) | F9: 55.42 | H9: Implied Entry EV / Reported Post-IFRS 16 EBITDA | L9: =+L7/F8 -> 15.124088
D10: Take-Private OPA Offer Premium (%) | F10: 0.05 | H10: Selected Exit Year (2026 to 2032) | L10: 2030
D11: OPA Offer Price per share (€/sh) | F11: =+F9*(1+F10) -> 58.191 | H11: ="Exit Multiple (Pre-IFRS 16 EBITDA @ "&L10&"E)" -> Exit Multiple (Pre-IFRS 16 EBITDA @ 2030E) | L11: =+L8 -> 18.064571
D12: Total diluted shares outstanding (m) | F12: 3116.652 | H12: M&A / OPA Advisory Entry Fees (% of Cash Takeover) | L12: 0.01
D13: Implied 100% Inditex Offer Equity Value (€m) | F13: =+F11*F12 -> 181361.1 | H13: Exit Transaction / Re-IPO Underwriting Fees (% EV) | L13: 0.0075
D14: Amancio Ortega Rollover Stake to TopCo (%) [Pontegadea] | F14: 0.59294 | H14: Upfront Debt Fee Tax Amortization Horizon (years) | L14: 7
D15: Cash Takeover Stake (%) [35.65% Free Float + 5.05% Sandra] | F15: =1-F14 -> 0.40706 | H15: Active Operating Scenario | L15: ='Active Case'!H8 -> Base
D16: Amancio Ortega Rollover Equity Value in TopCo (€m) | F16: =+F13*F14 -> 107536.25 | H16: Art. 16.5 LIS Debt / Total Equity Value (< 70% Cap) | L16: =+F30/F13 -> 0.28606741
D17: Cash Takeover Purchase Price (Free Float + Sandra, €m) | F17: =+F13*F15 -> 73824.848
D18: Minimum operational cash retained on 100% BS (€m) | F18: 1500 | H18: Sponsor IRR @ Selected Exit Year | L18: =+M69 -> 0.12419088
D19: Existing statutory net cash on 100% BS (€m) | F19: 10958 | H19: Sponsor MOIC (Cash-on-Cash) @ Selected Exit Year | L19: =+N69 -> 1.7955615
D20: 100% Inditex Excess BS Cash Deployed at Close (€m) | F20: =+MAX(0,F19-F18) -> 9458 | H20: Sponsor Net Profit (€m) @ Selected Exit Year | L20: =+INDEX(F56:L56,1,MATCH($L$10,F48:L48,0))-E44 -> 11185.914
A22: > | B22: > | C22: 2. Debt Package (Sized on 100% EBITDA), Per-Tranche Upfront Fees, Sources & Uses & TopCo Equity
B24: 2 | D24: LBO Debt Tranche / Facility (BidCo — 100% Inditex EBITDA) | E24: Committed (€m) | F24: Drawn (€m) | G24: xEBITDA (100%) | H24: Upfront Fee % | I24: Upfront Fee (€m)
D25: 1A. Senior Term Loan A (TLA — 5y Amortising Bank Debt) | E25: =+F25 -> 14149.5 | F25: ='Debt & Covenants'!F8*$F$7 -> 14149.5 | G25: ='Debt & Covenants'!F8 -> 1.5 | H25: 0.0125 | I25: =+E25*H25 -> 176.86875
D26: 1B. Senior Term Loan B (TLB — 7y Institutional Bullet) | E26: =+F26 -> 23582.5 | F26: ='Debt & Covenants'!F9*$F$7 -> 23582.5 | G26: ='Debt & Covenants'!F9 -> 2.5 | H26: 0.0175 | I26: =+E26*H26 -> 412.69375
D27: 2. Subordinated / Mezzanine Debt (7.5y Bullet) | E27: =+F27 -> 9433 | F27: ='Debt & Covenants'!F10*$F$7 -> 9433 | G27: ='Debt & Covenants'!F10 -> 1 | H27: 0.0225 | I27: =+E27*H27 -> 212.2425
D28: 3. Seller Vendor Loan (Sandra Ortega Deferred Note) | E28: =+F28 -> 4716.5 | F28: ='Debt & Covenants'!F11*$F$7 -> 4716.5 | G28: ='Debt & Covenants'!F11 -> 0.5 | H28: 0 | I28: =+E28*H28 -> 0
D29: 4. Revolving Credit Facility (RCF — Negative NOF Line) | E29: ='Debt & Covenants'!E14 -> 3500 | F29: 0 | G29: =+E29/$F$7 -> 0.37103785 | H29: 0.01 | I29: =+E29*H29 -> 35
D30: Total LBO Debt Package & Upfront Structuring Fees | E30: =+SUM(E25:E29) -> 55381.5 | F30: =+SUM(F25:F29) -> 51881.5 | G30: =+SUM(G25:G28) -> 5.5 | H30: =+I30/E30 -> 0.015109829 | I30: =+SUM(I25:I29) -> 836.805
D32: Sources of Funds (100% Take-Private) | E32: €m | F32: % | G32: xEBITDA | H32: Uses of Funds (100% Take-Private) | J32: €m | K32: % | L32: xEBITDA
D33: 1A. Senior Term Loan A (TLA) | E33: =+F25 -> 14149.5 | F33: =+E33/$E$40 -> 0.077346659 | G33: =+E33/$F$7 -> 1.5 | H33: Cash OPA for Free Float + Sandra Stake (40.71%) | J33: =+F17 -> 73824.848 | K33: =+J33/$J$40 -> 0.40355527 | L33: =+J33/$F$7 -> 7.8262322
D34: 1B. Senior Term Loan B (TLB) | E34: =+F26 -> 23582.5 | F34: =+E34/$E$40 -> 0.1289111 | G34: =+E34/$F$7 -> 2.5 | H34: Amancio Ortega Rollover Shares Contributed (59.29%) | J34: =+F16 -> 107536.25 | K34: =+J34/$J$40 -> 0.58783487 | L34: =+J34/$F$7 -> 11.400005
D35: 2. Subordinated / Mezzanine Debt | E35: =+F27 -> 9433 | F35: =+E35/$E$40 -> 0.051564439 | G35: =+E35/$F$7 -> 1 | H35: Upfront Debt Structuring Fees (TLA/TLB/Sub/RCF) | J35: =+I30 -> 836.805 | K35: =+J35/$J$40 -> 0.0045743009 | L35: =+J35/$F$7 -> 0.088710378
D36: 3. Seller Vendor Loan (Sandra Deferred Note) | E36: =+F28 -> 4716.5 | F36: =+E36/$E$40 -> 0.02578222 | G36: =+E36/$F$7 -> 0.5 | H36: M&A, Legal & OPA Advisory Costs (% Cash Takeover) | J36: =+F17*L12 -> 738.24848 | K36: =+J36/$J$40 -> 0.0040355527 | L36: =+J36/$F$7 -> 0.078262322
D37: 100% Inditex Excess BS Cash Deployed at Close | E37: =+F20 -> 9458 | F37: =+E37/$E$40 -> 0.051701099 | G37: =+E37/$F$7 -> 1.0026503 | H37: Minimum Operational Cash Retained on BS (€1,500m) | J37: 0 | K37: =+J37/$J$40 -> 0 | L37: =+J37/$F$7 -> 0
D38: Amancio Ortega Equity Rollover into TopCo | E38: =+F16 -> 107536.25 | F38: =+E38/$E$40 -> 0.58783487 | G38: =+E38/$F$7 -> 11.400005
D39: Sponsor Cash Equity Ticket (Plug) | E39: =+E40-SUM(E33:E38) -> 14060.401 | F39: =+E39/$E$40 -> 0.076859612 | G39: =+E39/$F$7 -> 1.4905546
D40: Total Sources of Funds | E40: =+J40 -> 182936.15 | F40: =+SUM(F33:F39) -> 1 | G40: =+SUM(G33:G39) -> 19.39321 | H40: Total Uses of Funds | J40: =+SUM(J33:J37) -> 182936.15 | K40: =+SUM(K33:K37) -> 1 | L40: =+SUM(L33:L37) -> 19.39321
D42: TopCo Common Equity Ownership (100% Owner of BidCo / Inditex) | E42: Equity (€m) | F42: % TopCo | G42: xEBITDA
D43: Amancio Ortega (Pontegadea Rollover Equity in TopCo) | E43: =+E38 -> 107536.25 | F43: =+E43/$E$45 -> 0.88436851 | G43: =+E43/$F$7 -> 11.400005
D44: Sponsor PE Consortium (Cash Equity Ticket in TopCo) | E44: =+E39 -> 14060.401 | F44: =+E44/$E$45 -> 0.11563149 | G44: =+E44/$F$7 -> 1.4905546
D45: Total TopCo Common Equity (100% Inditex Ownership) | E45: =+E43+E44 -> 121596.65 | F45: =+F43+F44 -> 1 | G45: =+G43+G44 -> 12.89056
A47: > | B47: > | C47: 3. Multi-Year Exit Valuation (100% Inditex), Exit Fees & Sponsor Returns Matrix (2026E–2032E)
D48: Exit Valuation & Proceeds Breakdown (€m) | E48: 2025 | F48: =+E48+1 -> 2026 | G48: =+F48+1 -> 2027 | H48: =+G48+1 -> 2028 | I48: =+H48+1 -> 2029 | J48: =+I48+1 -> 2030 | K48: =+J48+1 -> 2031 | L48: =+K48+1 -> 2032
B49: 3 | D49: 100% Inditex Pre-IFRS 16 Cash EBITDA (€m) | E49: ='Active Case'!L30 -> 9433 | F49: ='Active Case'!M30 -> 10143.127 | G49: ='Active Case'!N30 -> 10922.262 | H49: ='Active Case'!O30 -> 11752.179 | I49: ='Active Case'!P30 -> 12635.98 | J49: ='Active Case'!Q30 -> 13576.948 | K49: ='Active Case'!R30 -> 14578.56 | L49: ='Active Case'!S30 -> 15644.499
D50: Exit Multiple (Pre-IFRS 16 EBITDAx) | E50: =+$L$11 -> 18.064571 | F50: =+$L$11 -> 18.064571 | G50: =+$L$11 -> 18.064571 | H50: =+$L$11 -> 18.064571 | I50: =+$L$11 -> 18.064571 | J50: =+$L$11 -> 18.064571 | K50: =+$L$11 -> 18.064571 | L50: =+$L$11 -> 18.064571
D51: Gross Enterprise Value at Exit (100% Inditex EV) | E51: =+E49*E50 -> 170403.1 | F51: =+F49*F50 -> 183231.24 | G51: =+G49*G50 -> 197305.97 | H51: =+H49*H50 -> 212298.07 | I51: =+I49*I50 -> 228263.55 | J51: =+J49*J50 -> 245261.73 | K51: =+K49*K50 -> 263355.43 | L51: =+L49*L50 -> 282611.16
D52: Less: Exit Transaction / Re-IPO Fees (% in L13) | E52: =-E51*$L$13 -> -1278.0232 | F52: =-F51*$L$13 -> -1374.2343 | G52: =-G51*$L$13 -> -1479.7948 | H52: =-H51*$L$13 -> -1592.2355 | I52: =-I51*$L$13 -> -1711.9766 | J52: =-J51*$L$13 -> -1839.463 | K52: =-K51*$L$13 -> -1975.1657 | L52: =-L51*$L$13 -> -2119.5837
D53: Less: EoP Gross LBO Debt (TLA + TLB + Sub + Vendor Loan + RCF) | E53: =-'Debt & Covenants'!E68 -> -51881.5 | F53: =-'Debt & Covenants'!F68 -> -50466.55 | G53: =-'Debt & Covenants'!G68 -> -48344.125 | H53: =-'Debt & Covenants'!H68 -> -45514.225 | I53: =-'Debt & Covenants'!I68 -> -41976.85 | J53: =-'Debt & Covenants'!J68 -> -37732 | K53: =-'Debt & Covenants'!K68 -> -37732 | L53: =-'Debt & Covenants'!L68 -> -37732
D54: Plus: EoP 100% Inditex Cash Balance (incl. €1,500m Min Cash) | E54: =+'Debt & Covenants'!E93 -> 1500 | F54: =+'Debt & Covenants'!F93 -> 3787.694 | G54: =+'Debt & Covenants'!G93 -> 6031.9531 | H54: =+'Debt & Covenants'!H93 -> 8196.4191 | I54: =+'Debt & Covenants'!I93 -> 10378.35 | J54: =+'Debt & Covenants'!J93 -> 12643.999 | K54: =+'Debt & Covenants'!K93 -> 19921.526 | L54: =+'Debt & Covenants'!L93 -> 27931.225
D55: Total TopCo Net Equity Value at Exit (100% Inditex) | E55: =+SUM(E51:E54) -> 118743.57 | F55: =+SUM(F51:F54) -> 135178.15 | G55: =+SUM(G51:G54) -> 153514 | H55: =+SUM(H51:H54) -> 173388.02 | I55: =+SUM(I51:I54) -> 194953.07 | J55: =+SUM(J51:J54) -> 218334.27 | K55: =+SUM(K51:K54) -> 243569.79 | L55: =+SUM(L51:L54) -> 270690.8
D56: Sponsor PE Exit Equity Proceeds (% TopCo in F44) | E56: =+E55*$F$44 -> 13730.496 | F56: =+F55*$F$44 -> 15630.85 | G56: =+G55*$F$44 -> 17751.052 | H56: =+H55*$F$44 -> 20049.115 | I56: =+I55*$F$44 -> 22542.713 | J56: =+J55*$F$44 -> 25246.316 | K56: =+K55*$F$44 -> 28164.337 | L56: =+L55*$F$44 -> 31300.38
D57: Amancio Ortega Rollover Exit Equity Proceeds (% TopCo in F43) | E57: =+E55*$F$43 -> 105013.08 | F57: =+F55*$F$43 -> 119547.3 | G57: =+G55*$F$43 -> 135762.95 | H57: =+H55*$F$43 -> 153338.91 | I57: =+I55*$F$43 -> 172410.36 | J57: =+J55*$F$43 -> 193087.95 | K57: =+K55*$F$43 -> 215405.45 | L57: =+L55*$F$43 -> 239390.42
D58: Implied Sponsor IRR if Exited in Year (%) | F58: =+M62 -> 0.11169303 | G58: =+M63 -> 0.12360377 | H58: =+M64 -> 0.12555269 | I58: =+M65 -> 0.12525802 | J58: =+M66 -> 0.12419088 | K58: =+M67 -> 0.12275148 | L58: =+M68 -> 0.12111527
D59: Implied Sponsor MOIC (Cash-on-Cash) if Exited in Year (x) | F59: =+N62 -> 1.111693 | G59: =+N63 -> 1.2624854 | H59: =+N64 -> 1.4259276 | I59: =+N65 -> 1.6032767 | J59: =+N66 -> 1.7955615 | K59: =+N67 -> 2.0030962 | L59: =+N68 -> 2.226137
D61: Sponsor Cash Flow Schedule by Exit Year (2026E–2032E) | E61: =+E48 -> 2025 | F61: =+F48 -> 2026 | G61: =+G48 -> 2027 | H61: =+H48 -> 2028 | I61: =+I48 -> 2029 | J61: =+J48 -> 2030 | K61: =+K48 -> 2031 | L61: =+L48 -> 2032 | M61: Sponsor IRR | N61: Sponsor MOIC
D62: =+F61 -> 2026 | E62: =-$E$44 -> -14060.401 | F62: =+F$56 -> 15630.85 | G62: 0 | H62: 0 | I62: 0 | J62: 0 | K62: 0 | L62: 0 | M62: =+IFERROR((N62)^(1/(F$61-$E$61))-1,0) -> 0.11169303 | N62: =+IFERROR(-SUM(F62:F62)/E62,0) -> 1.111693
D63: =+G61 -> 2027 | E63: =-$E$44 -> -14060.401 | F63: 0 | G63: =+G$56 -> 17751.052 | H63: 0 | I63: 0 | J63: 0 | K63: 0 | L63: 0 | M63: =+IFERROR((N63)^(1/(G$61-$E$61))-1,0) -> 0.12360377 | N63: =+IFERROR(-SUM(F63:G63)/E63,0) -> 1.2624854
D64: =+H61 -> 2028 | E64: =-$E$44 -> -14060.401 | F64: 0 | G64: 0 | H64: =+H$56 -> 20049.115 | I64: 0 | J64: 0 | K64: 0 | L64: 0 | M64: =+IFERROR((N64)^(1/(H$61-$E$61))-1,0) -> 0.12555269 | N64: =+IFERROR(-SUM(F64:H64)/E64,0) -> 1.4259276
D65: =+I61 -> 2029 | E65: =-$E$44 -> -14060.401 | F65: 0 | G65: 0 | H65: 0 | I65: =+I$56 -> 22542.713 | J65: 0 | K65: 0 | L65: 0 | M65: =+IFERROR((N65)^(1/(I$61-$E$61))-1,0) -> 0.12525802 | N65: =+IFERROR(-SUM(F65:I65)/E65,0) -> 1.6032767
D66: =+J61 -> 2030 | E66: =-$E$44 -> -14060.401 | F66: 0 | G66: 0 | H66: 0 | I66: 0 | J66: =+J$56 -> 25246.316 | K66: 0 | L66: 0 | M66: =+IFERROR((N66)^(1/(J$61-$E$61))-1,0) -> 0.12419088 | N66: =+IFERROR(-SUM(F66:J66)/E66,0) -> 1.7955615
D67: =+K61 -> 2031 | E67: =-$E$44 -> -14060.401 | F67: 0 | G67: 0 | H67: 0 | I67: 0 | J67: 0 | K67: =+K$56 -> 28164.337 | L67: 0 | M67: =+IFERROR((N67)^(1/(K$61-$E$61))-1,0) -> 0.12275148 | N67: =+IFERROR(-SUM(F67:K67)/E67,0) -> 2.0030962
D68: =+L61 -> 2032 | E68: =-$E$44 -> -14060.401 | F68: 0 | G68: 0 | H68: 0 | I68: 0 | J68: 0 | K68: 0 | L68: =+L$56 -> 31300.38 | M68: =+IFERROR((N68)^(1/(L$61-$E$61))-1,0) -> 0.12111527 | N68: =+IFERROR(-SUM(F68:L68)/E68,0) -> 2.226137
D69: ="Active Selected Exit Cash Flows @ "&L10&"E" -> Active Selected Exit Cash Flows @ 2030E | E69: =+INDEX(E62:E68,MATCH($L$10,$D$62:$D$68,0)) -> -14060.401 | F69: =+INDEX(F62:F68,MATCH($L$10,$D$62:$D$68,0)) -> 0 | G69: =+INDEX(G62:G68,MATCH($L$10,$D$62:$D$68,0)) -> 0 | H69: =+INDEX(H62:H68,MATCH($L$10,$D$62:$D$68,0)) -> 0 | I69: =+INDEX(I62:I68,MATCH($L$10,$D$62:$D$68,0)) -> 0 | J69: =+INDEX(J62:J68,MATCH($L$10,$D$62:$D$68,0)) -> 25246.316 | K69: =+INDEX(K62:K68,MATCH($L$10,$D$62:$D$68,0)) -> 0 | L69: =+INDEX(L62:L68,MATCH($L$10,$D$62:$D$68,0)) -> 0 | ... N69: =+INDEX(N62:N68,MATCH($L$10,$D$62:$D$68,0)) -> 1.7955615
A71: > | B71: > | C71: 4. Sensitivity Analysis: OPA Offer Premium vs. Total Debt xEBITDA (@ Selected Exit Year)
D73: Offer Premium \ Total Debt xEBITDA (Sponsor IRR) | E73: 4.5 | F73: 5.5 | G73: 6.5 | I73: 4.5x (MOIC) | J73: 5.5x (MOIC) | K73: 6.5x (MOIC)
D74: 0 | E74: =+(I74)^(1/($L$10-$E$48))-1 -> 0.12203603 | F74: =+(J74)^(1/($L$10-$E$48))-1 -> 0.12775328 | G74: =+(K74)^(1/($L$10-$E$48))-1 -> 0.13436656 | I74: =+(((INDEX($F$55:$L$55,1,MATCH($L$10,$F$48:$L$48,0))+((((($F$9*(1+$D74)*$F$12)-$F$19)/$F$7)-$L$11)*INDEX($F$49:$L$49,1,MATCH($L$10,$F$48:$L$48,0))*(1-$L$13))-((E$73-$G$30)*$F$7*(1+($L$10-$E$48)*'Debt & Covenants'!$E$7*(1-0.22)))))*(((($F$9*(1+$D74)*$F$12)*$F$15)*(1+$L$12)+$I$30-(E$73*$F$7)-$F$20)/(((($F$9*(1+$D74)*$F$12)*$F$15)*(1+$L$12)+$I$30-(E$73*$F$7)-$F$20)+(($F$9*(1+$D74)*$F$12)*$F$14))))/((($F$9*(1+$D74)*$F$12)*$F$15)*(1+$L$12)+$I$30-(E$73*$F$7)-$F$20) -> 1.7784187 | J74: =+(((INDEX($F$55:$L$55,1,MATCH($L$10,$F$48:$L$48,0))+((((($F$9*(1+$D74)*$F$12)-$F$19)/$F$7)-$L$11)*INDEX($F$49:$L$49,1,MATCH($L$10,$F$48:$L$48,0))*(1-$L$13))-((F$73-$G$30)*$F$7*(1+($L$10-$E$48)*'Debt & Covenants'!$E$7*(1-0.22)))))*(((($F$9*(1+$D74)*$F$12)*$F$15)*(1+$L$12)+$I$30-(F$73*$F$7)-$F$20)/(((($F$9*(1+$D74)*$F$12)*$F$15)*(1+$L$12)+$I$30-(F$73*$F$7)-$F$20)+(($F$9*(1+$D74)*$F$12)*$F$14))))/((($F$9*(1+$D74)*$F$12)*$F$15)*(1+$L$12)+$I$30-(F$73*$F$7)-$F$20) -> 1.8241918 | K74: =+(((INDEX($F$55:$L$55,1,MATCH($L$10,$F$48:$L$48,0))+((((($F$9*(1+$D74)*$F$12)-$F$19)/$F$7)-$L$11)*INDEX($F$49:$L$49,1,MATCH($L$10,$F$48:$L$48,0))*(1-$L$13))-((G$73-$G$30)*$F$7*(1+($L$10-$E$48)*'Debt & Covenants'!$E$7*(1-0.22)))))*(((($F$9*(1+$D74)*$F$12)*$F$15)*(1+$L$12)+$I$30-(G$73*$F$7)-$F$20)/(((($F$9*(1+$D74)*$F$12)*$F$15)*(1+$L$12)+$I$30-(G$73*$F$7)-$F$20)+(($F$9*(1+$D74)*$F$12)*$F$14))))/((($F$9*(1+$D74)*$F$12)*$F$15)*(1+$L$12)+$I$30-(G$73*$F$7)-$F$20) -> 1.8783091
D75: 0.05 | E75: =+(I75)^(1/($L$10-$E$48))-1 -> 0.11904982 | F75: =+(J75)^(1/($L$10-$E$48))-1 -> 0.12419088 | G75: =+(K75)^(1/($L$10-$E$48))-1 -> 0.13007997 | I75: =+(((INDEX($F$55:$L$55,1,MATCH($L$10,$F$48:$L$48,0))+((((($F$9*(1+$D75)*$F$12)-$F$19)/$F$7)-$L$11)*INDEX($F$49:$L$49,1,MATCH($L$10,$F$48:$L$48,0))*(1-$L$13))-((E$73-$G$30)*$F$7*(1+($L$10-$E$48)*'Debt & Covenants'!$E$7*(1-0.22)))))*(((($F$9*(1+$D75)*$F$12)*$F$15)*(1+$L$12)+$I$30-(E$73*$F$7)-$F$20)/(((($F$9*(1+$D75)*$F$12)*$F$15)*(1+$L$12)+$I$30-(E$73*$F$7)-$F$20)+(($F$9*(1+$D75)*$F$12)*$F$14))))/((($F$9*(1+$D75)*$F$12)*$F$15)*(1+$L$12)+$I$30-(E$73*$F$7)-$F$20) -> 1.7548787 | J75: =+(((INDEX($F$55:$L$55,1,MATCH($L$10,$F$48:$L$48,0))+((((($F$9*(1+$D75)*$F$12)-$F$19)/$F$7)-$L$11)*INDEX($F$49:$L$49,1,MATCH($L$10,$F$48:$L$48,0))*(1-$L$13))-((F$73-$G$30)*$F$7*(1+($L$10-$E$48)*'Debt & Covenants'!$E$7*(1-0.22)))))*(((($F$9*(1+$D75)*$F$12)*$F$15)*(1+$L$12)+$I$30-(F$73*$F$7)-$F$20)/(((($F$9*(1+$D75)*$F$12)*$F$15)*(1+$L$12)+$I$30-(F$73*$F$7)-$F$20)+(($F$9*(1+$D75)*$F$12)*$F$14))))/((($F$9*(1+$D75)*$F$12)*$F$15)*(1+$L$12)+$I$30-(F$73*$F$7)-$F$20) -> 1.7955615 | K75: =+(((INDEX($F$55:$L$55,1,MATCH($L$10,$F$48:$L$48,0))+((((($F$9*(1+$D75)*$F$12)-$F$19)/$F$7)-$L$11)*INDEX($F$49:$L$49,1,MATCH($L$10,$F$48:$L$48,0))*(1-$L$13))-((G$73-$G$30)*$F$7*(1+($L$10-$E$48)*'Debt & Covenants'!$E$7*(1-0.22)))))*(((($F$9*(1+$D75)*$F$12)*$F$15)*(1+$L$12)+$I$30-(G$73*$F$7)-$F$20)/(((($F$9*(1+$D75)*$F$12)*$F$15)*(1+$L$12)+$I$30-(G$73*$F$7)-$F$20)+(($F$9*(1+$D75)*$F$12)*$F$14))))/((($F$9*(1+$D75)*$F$12)*$F$15)*(1+$L$12)+$I$30-(G$73*$F$7)-$F$20) -> 1.8430872
D76: 0.1 | E76: =+(I76)^(1/($L$10-$E$48))-1 -> 0.11640789 | F76: =+(J76)^(1/($L$10-$E$48))-1 -> 0.12106579 | G76: =+(K76)^(1/($L$10-$E$48))-1 -> 0.1263562 | I76: =+(((INDEX($F$55:$L$55,1,MATCH($L$10,$F$48:$L$48,0))+((((($F$9*(1+$D76)*$F$12)-$F$19)/$F$7)-$L$11)*INDEX($F$49:$L$49,1,MATCH($L$10,$F$48:$L$48,0))*(1-$L$13))-((E$73-$G$30)*$F$7*(1+($L$10-$E$48)*'Debt & Covenants'!$E$7*(1-0.22)))))*(((($F$9*(1+$D76)*$F$12)*$F$15)*(1+$L$12)+$I$30-(E$73*$F$7)-$F$20)/(((($F$9*(1+$D76)*$F$12)*$F$15)*(1+$L$12)+$I$30-(E$73*$F$7)-$F$20)+(($F$9*(1+$D76)*$F$12)*$F$14))))/((($F$9*(1+$D76)*$F$12)*$F$15)*(1+$L$12)+$I$30-(E$73*$F$7)-$F$20) -> 1.7342611 | J76: =+(((INDEX($F$55:$L$55,1,MATCH($L$10,$F$48:$L$48,0))+((((($F$9*(1+$D76)*$F$12)-$F$19)/$F$7)-$L$11)*INDEX($F$49:$L$49,1,MATCH($L$10,$F$48:$L$48,0))*(1-$L$13))-((F$73-$G$30)*$F$7*(1+($L$10-$E$48)*'Debt & Covenants'!$E$7*(1-0.22)))))*(((($F$9*(1+$D76)*$F$12)*$F$15)*(1+$L$12)+$I$30-(F$73*$F$7)-$F$20)/(((($F$9*(1+$D76)*$F$12)*$F$15)*(1+$L$12)+$I$30-(F$73*$F$7)-$F$20)+(($F$9*(1+$D76)*$F$12)*$F$14))))/((($F$9*(1+$D76)*$F$12)*$F$15)*(1+$L$12)+$I$30-(F$73*$F$7)-$F$20) -> 1.7707428 | K76: =+(((INDEX($F$55:$L$55,1,MATCH($L$10,$F$48:$L$48,0))+((((($F$9*(1+$D76)*$F$12)-$F$19)/$F$7)-$L$11)*INDEX($F$49:$L$49,1,MATCH($L$10,$F$48:$L$48,0))*(1-$L$13))-((G$73-$G$30)*$F$7*(1+($L$10-$E$48)*'Debt & Covenants'!$E$7*(1-0.22)))))*(((($F$9*(1+$D76)*$F$12)*$F$15)*(1+$L$12)+$I$30-(G$73*$F$7)-$F$20)/(((($F$9*(1+$D76)*$F$12)*$F$15)*(1+$L$12)+$I$30-(G$73*$F$7)-$F$20)+(($F$9*(1+$D76)*$F$12)*$F$14))))/((($F$9*(1+$D76)*$F$12)*$F$15)*(1+$L$12)+$I$30-(G$73*$F$7)-$F$20) -> 1.8129205

Sheet Active Case
B1: Project Galicia v3 — Inditex (ITX.MC) | U1: Strictly Private & Confidential
A2: > | B2: Active Case — 100% Inditex Consolidated Operating Model (2022A–2032E), Pre-IFRS 16 Bridge, Negative NOF & Capex Split
A4: > | B4: > | C4: 1. Operating Scenario Drivers & Presets (100% Inditex Consolidated — Zero Minority Leakage)
C6: Drivers | E6: 1 | F6: 2 | G6: 3 | H6: Active: | I6: 31-Jan | J6: 31-Jan | K6: 31-Jan | L6: 31-Jan | M6: 31-Jan | N6: 31-Jan | O6: 31-Jan | P6: 31-Jan | Q6: 31-Jan | R6: 31-Jan | S6: 31-Jan
C7: €m | D7: 100% Inditex Consolidated Line Item | E7: Base | F7: Bull | G7: Bear | H7: =CHOOSE($F$8,E7,F7,G7) -> Base | I7: 2022 | J7: =+I7+1 -> 2023 | K7: =+J7+1 -> 2024 | L7: =+K7+1 -> 2025 | M7: =+L7+1 -> 2026 | N7: =+M7+1 -> 2027 | O7: =+N7+1 -> 2028 | P7: =+O7+1 -> 2029 | Q7: =+P7+1 -> 2030 | ... S7: =+R7+1 -> 2032
B8: 1 | D8: Active Scenario Selector (1=Base, 2=Bull, 3=Bear) | E8: Select -> | F8: 1 | H8: =CHOOSE($F$8,E7,F7,G7) -> Base
D9: Revenue growth (% YoY) | E9: 0.055 | F9: 0.08 | G9: 0.0225 | H9: =CHOOSE($F$8,E9,F9,G9) -> 0.055 | I9: 0.175 | J9: 0.104 | K9: 0.075 | L9: 0.032 | M9: =+$H9 -> 0.055 | N9: =+$H9 -> 0.055 | O9: =+$H9 -> 0.055 | P9: =+$H9 -> 0.055 | Q9: =+$H9 -> 0.055 | R9: =+$H9 -> 0.055 | S9: =+$H9 -> 0.055
D10: Gross margin (% of revenues) | E10: 0.582 | F10: 0.59 | G10: 0.57 | H10: =CHOOSE($F$8,E10,F10,G10) -> 0.582 | I10: =+I23/I$21 -> 0.56983635 | J10: =+J23/J$21 -> 0.57757254 | K10: =+K23/K$21 -> 0.57835473 | L10: =+L23/L$21 -> 0.5825306 | M10: =+$H10 -> 0.582 | N10: =+$H10 -> 0.582 | O10: =+$H10 -> 0.582 | P10: =+$H10 -> 0.582 | Q10: =+$H10 -> 0.582 | R10: =+$H10 -> 0.582 | S10: =+$H10 -> 0.582
D11: OpEx growth (% YoY) | E11: 0.0425 | F11: 0.055 | G11: 0.0325 | H11: =CHOOSE($F$8,E11,F11,G11) -> 0.0425 | I11: 0.109 | J11: 0.1 | K11: 0.065 | L11: 0.028 | M11: =+$H11 -> 0.0425 | N11: =+$H11 -> 0.0425 | O11: =+$H11 -> 0.0425 | P11: =+$H11 -> 0.0425 | Q11: =+$H11 -> 0.0425 | R11: =+$H11 -> 0.0425 | S11: =+$H11 -> 0.0425
D12: Fixed lease cash outflow growth (%) | E12: 0.02 | F12: 0.03 | G12: 0.01 | H12: =CHOOSE($F$8,E12,F12,G12) -> 0.02 | I12: 0.05 | J12: =+J28/I28-1 -> 0.069093152 | K12: =+K28/J28-1 -> 0.039815349 | L12: =+L28/K28-1 -> 0.017758047 | M12: =+$H12 -> 0.02 | N12: =+$H12 -> 0.02 | O12: =+$H12 -> 0.02 | P12: =+$H12 -> 0.02 | Q12: =+$H12 -> 0.02 | R12: =+$H12 -> 0.02 | S12: =+$H12 -> 0.02
D13: Maintenance Capex (% of revenues) | E13: 0.035 | F13: 0.035 | G13: 0.034 | H13: =CHOOSE($F$8,E13,F13,G13) -> 0.035 | I13: =+I52/I$21 -> 0.032239246 | J13: =+J52/J$21 -> 0.034773416 | K13: =+K52/K$21 -> 0.037533651 | L13: =+L52/L$21 -> 0.037126229 | M13: =+$H13 -> 0.035 | N13: =+$H13 -> 0.035 | O13: =+$H13 -> 0.035 | P13: =+$H13 -> 0.035 | Q13: =+$H13 -> 0.035 | R13: =+$H13 -> 0.035 | S13: =+$H13 -> 0.035
D14: Expansion Capex: US Rollout & Logistics (%) | E14: 0.017 | F14: 0.02 | G14: 0.012 | H14: =CHOOSE($F$8,E14,F14,G14) -> 0.017 | I14: =+I53/I$21 -> 0.011206976 | J14: =+J53/J$21 -> 0.017303252 | K14: =+K53/K$21 -> 0.031631808 | L14: =+L53/L$21 -> 0.030905077 | M14: =+$H14 -> 0.017 | N14: =+$H14 -> 0.017 | O14: =+$H14 -> 0.017 | P14: =+$H14 -> 0.017 | Q14: =+$H14 -> 0.017 | R14: =+$H14 -> 0.017 | S14: =+$H14 -> 0.017
D15: Inventory (% of revenues) | E15: 0.0815 | F15: 0.079 | G15: 0.085 | H15: =CHOOSE($F$8,E15,F15,G15) -> 0.0815 | I15: =+I39/I$21 -> 0.097976604 | J15: =+J39/J$21 -> 0.082510362 | K15: =+K39/K$21 -> 0.085965003 | L15: =+L39/L$21 -> 0.081502107 | M15: =+$H15 -> 0.0815 | N15: =+$H15 -> 0.0815 | O15: =+$H15 -> 0.0815 | P15: =+$H15 -> 0.0815 | Q15: =+$H15 -> 0.0815 | R15: =+$H15 -> 0.0815 | S15: =+$H15 -> 0.0815
D16: Receivables (% of revenues) | E16: 0.0292 | F16: 0.0285 | G16: 0.03 | H16: =CHOOSE($F$8,E16,F16,G16) -> 0.0292 | I16: =+I40/I$21 -> 0.026129141 | J16: =+J40/J$21 -> 0.028875845 | K16: =+K40/K$21 -> 0.028163181 | L16: =+L40/L$21 -> 0.029249448 | M16: =+$H16 -> 0.0292 | N16: =+$H16 -> 0.0292 | O16: =+$H16 -> 0.0292 | P16: =+$H16 -> 0.0292 | Q16: =+$H16 -> 0.0292 | R16: =+$H16 -> 0.0292 | S16: =+$H16 -> 0.0292
D17: Payables (% of revenues, negative — NOF) | E17: -0.2154 | F17: -0.2155 | G17: -0.213 | H17: =CHOOSE($F$8,E17,F17,G17) -> -0.2154 | I17: =+I41/I$21 -> -0.20144923 | J17: =+J41/J$21 -> -0.20772248 | K17: =+K41/K$21 -> -0.22235452 | L17: =+L41/L$21 -> -0.21540739 | M17: =+$H17 -> -0.2154 | N17: =+$H17 -> -0.2154 | O17: =+$H17 -> -0.2154 | P17: =+$H17 -> -0.2154 | Q17: =+$H17 -> -0.2154 | R17: =+$H17 -> -0.2154 | S17: =+$H17 -> -0.2154
C19: P&L | I19: 31-Jan | J19: 31-Jan | K19: 31-Jan | L19: 31-Jan | M19: 31-Jan | N19: 31-Jan | O19: 31-Jan | P19: 31-Jan | Q19: 31-Jan | R19: 31-Jan | S19: 31-Jan | T19: CAGR | U19: CAGR
C20: €m | D20: 100% Inditex Consolidated Line Item | I20: 2022 | J20: =+I20+1 -> 2023 | K20: =+J20+1 -> 2024 | L20: =+K20+1 -> 2025 | M20: =+L20+1 -> 2026 | N20: =+M20+1 -> 2027 | O20: =+N20+1 -> 2028 | P20: =+O20+1 -> 2029 | Q20: =+P20+1 -> 2030 | ... S20: =+R20+1 -> 2032 | T20: 22A-25A | U20: 25A-32E
B21: 2 | D21: Net Revenues (100% Inditex) | I21: 32569 | J21: 35947 | K21: 38632 | L21: 39864 | M21: =+L21*(1+M9) -> 42056.52 | N21: =+M21*(1+N9) -> 44369.629 | O21: =+N21*(1+O9) -> 46809.958 | P21: =+O21*(1+P9) -> 49384.506 | Q21: =+P21*(1+Q9) -> 52100.654 | R21: =+Q21*(1+R9) -> 54966.19 | S21: =+R21*(1+S9) -> 57989.33 | T21: =+IFERROR((L21/I21)^(1/(L$20-I$20))-1,0) -> 0.06969217 | U21: =+IFERROR((S21/L21)^(1/(S$20-L$20))-1,0) -> 0.055
D22: COGS | I22: =+I23-I21 -> -14010 | J22: =+J23-J21 -> -15185 | K22: =+K23-K21 -> -16289 | L22: =+L23-L21 -> -16642 | M22: =+M23-M21 -> -17579.625 | N22: =+N23-N21 -> -18546.505 | O22: =+O23-O21 -> -19566.563 | P22: =+P23-P21 -> -20642.723 | ... S22: =+S23-S21 -> -24239.54 | T22: =+IFERROR((L22/I22)^(1/(L$20-I$20))-1,0) -> 0.059064622 | U22: =+IFERROR((S22/L22)^(1/(S$20-L$20))-1,0) -> 0.055191454
D23: Gross Profit | I23: 18559 | J23: 20762 | K23: 22343 | L23: 23222 | M23: =+M21*M10 -> 24476.895 | N23: =+N21*N10 -> 25823.124 | O23: =+O21*O10 -> 27243.396 | P23: =+P21*P10 -> 28741.782 | Q23: =+Q21*Q10 -> 30322.58 | R23: =+R21*R10 -> 31990.322 | S23: =+S21*S10 -> 33749.79 | T23: =+IFERROR((L23/I23)^(1/(L$20-I$20))-1,0) -> 0.077577091 | U23: =+IFERROR((S23/L23)^(1/(S$20-L$20))-1,0) -> 0.054862667
D24: % Gross margin | I24: =+IFERROR(I23/I$21,0) -> 0.56983635 | J24: =+IFERROR(J23/J$21,0) -> 0.57757254 | K24: =+IFERROR(K23/K$21,0) -> 0.57835473 | L24: =+IFERROR(L23/L$21,0) -> 0.5825306 | M24: =+IFERROR(M23/M$21,0) -> 0.582 | N24: =+IFERROR(N23/N$21,0) -> 0.582 | O24: =+IFERROR(O23/O$21,0) -> 0.582 | P24: =+IFERROR(P23/P$21,0) -> 0.582 | ... S24: =+IFERROR(S23/S$21,0) -> 0.582
D25: OpEx (Personnel, variable turnover rent & SG&A) | I25: -9910 | J25: -10912 | K25: -11615 | L25: -11955 | M25: =+L25*(1+M11) -> -12463.087 | N25: =+M25*(1+N11) -> -12992.769 | O25: =+N25*(1+O11) -> -13544.961 | P25: =+O25*(1+P11) -> -14120.622 | Q25: =+P25*(1+Q11) -> -14720.749 | R25: =+Q25*(1+R11) -> -15346.381 | S25: =+R25*(1+S11) -> -15998.602 | T25: =+IFERROR((L25/I25)^(1/(L$20-I$20))-1,0) -> 0.064531806 | U25: =+IFERROR((S25/L25)^(1/(S$20-L$20))-1,0) -> 0.0425
D26: Reported EBITDA (Post-IFRS 16 — 100% Inditex) | I26: =+I23+I25 -> 8649 | J26: =+J23+J25 -> 9850 | K26: =+K23+K25 -> 10728 | L26: =+L23+L25 -> 11267 | M26: =+M23+M25 -> 12013.807 | N26: =+N23+N25 -> 12830.355 | O26: =+O23+O25 -> 13698.434 | P26: =+P23+P25 -> 14621.16 | ... S26: =+S23+S25 -> 17751.188 | T26: =+IFERROR((L26/I26)^(1/(L$20-I$20))-1,0) -> 0.09214625 | U26: =+IFERROR((S26/L26)^(1/(S$20-L$20))-1,0) -> 0.067094138
D27: % Reported EBITDA margin (Post-IFRS 16) | I27: =+IFERROR(I26/I$21,0) -> 0.26555927 | J27: =+IFERROR(J26/J$21,0) -> 0.27401452 | K27: =+IFERROR(K26/K$21,0) -> 0.27769725 | L27: =+IFERROR(L26/L$21,0) -> 0.28263596 | M27: =+IFERROR(M26/M$21,0) -> 0.28565861 | N27: =+IFERROR(N26/N$21,0) -> 0.28916977 | O27: =+IFERROR(O26/O$21,0) -> 0.29263932 | P27: =+IFERROR(P26/P$21,0) -> 0.29606776 | ... S27: =+IFERROR(S26/S$21,0) -> 0.30611129
D28: Less: Fixed cash lease outflow (IFRS 16 Note 16 / CF Statement) | I28: -1621 | J28: -1733 | K28: -1802 | L28: -1834 | M28: =+L28*(1+M12) -> -1870.68 | N28: =+M28*(1+N12) -> -1908.0936 | O28: =+N28*(1+O12) -> -1946.2555 | P28: =+O28*(1+P12) -> -1985.1806 | Q28: =+P28*(1+Q12) -> -2024.8842 | R28: =+Q28*(1+R12) -> -2065.3819 | S28: =+R28*(1+S12) -> -2106.6895 | T28: =+IFERROR((L28/I28)^(1/(L$20-I$20))-1,0) -> 0.042010525 | U28: =+IFERROR((S28/L28)^(1/(S$20-L$20))-1,0) -> 0.02
D29: Plus: Due Diligence Adjustments & Normalizations | I29: 0 | J29: 0 | K29: 0 | L29: 0 | M29: 0 | N29: 0 | O29: 0 | P29: 0 | Q29: 0 | R29: 0 | S29: 0
D30: Pre-IFRS 16 Normalized Cash EBITDA (100% Inditex — LBO Basis) | I30: =+I26+I28+I29 -> 7028 | J30: =+J26+J28+J29 -> 8117 | K30: =+K26+K28+K29 -> 8926 | L30: =+L26+L28+L29 -> 9433 | M30: =+M26+M28+M29 -> 10143.127 | N30: =+N26+N28+N29 -> 10922.262 | O30: =+O26+O28+O29 -> 11752.179 | P30: =+P26+P28+P29 -> 12635.98 | ... S30: =+S26+S28+S29 -> 15644.499 | T30: =+IFERROR((L30/I30)^(1/(L$20-I$20))-1,0) -> 0.1030775 | U30: =+IFERROR((S30/L30)^(1/(S$20-L$20))-1,0) -> 0.074947869
D31: % Pre-IFRS 16 Cash EBITDA margin | I31: =+IFERROR(I30/I$21,0) -> 0.21578802 | J31: =+IFERROR(J30/J$21,0) -> 0.22580466 | K31: =+IFERROR(K30/K$21,0) -> 0.23105198 | L31: =+IFERROR(L30/L$21,0) -> 0.23662954 | M31: =+IFERROR(M30/M$21,0) -> 0.24117847 | N31: =+IFERROR(N30/N$21,0) -> 0.24616527 | O31: =+IFERROR(O30/O$21,0) -> 0.25106151 | P31: =+IFERROR(P30/P$21,0) -> 0.25586931 | ... S31: =+IFERROR(S30/S$21,0) -> 0.26978237
D32: D&A (Owned PP&E & intangibles — 100% Inditex) | I32: =+I49 -> -1417 | J32: =+J49 -> -1558 | K32: =+K49 -> -1638 | L32: =+L49 -> -1674 | M32: =+M49 -> -1387.147 | N32: =+N49 -> -1611.8549 | O32: =+O49 -> -1848.9219 | P32: =+P49 -> -2099.0275 | ... S32: =+S49 -> -2934.947 | T32: =+IFERROR((L32/I32)^(1/(L$20-I$20))-1,0) -> 0.057130333 | U32: =+IFERROR((S32/L32)^(1/(S$20-L$20))-1,0) -> 0.083515113
D33: Operating EBIT (Pre-IFRS 16 — 100% Inditex) | I33: =+I30+I32 -> 5611 | J33: =+J30+J32 -> 6559 | K33: =+K30+K32 -> 7288 | L33: =+L30+L32 -> 7759 | M33: =+M30+M32 -> 8755.9802 | N33: =+N30+N32 -> 9310.4066 | O33: =+O30+O32 -> 9903.2569 | P33: =+P30+P32 -> 10536.952 | ... S33: =+S30+S32 -> 12709.552 | T33: =+IFERROR((L33/I33)^(1/(L$20-I$20))-1,0) -> 0.11409398 | U33: =+IFERROR((S33/L33)^(1/(S$20-L$20))-1,0) -> 0.073044626
C36: NOF / WK | I36: 31-Jan | J36: 31-Jan | K36: 31-Jan | L36: 31-Jan | M36: 31-Jan | N36: 31-Jan | O36: 31-Jan | P36: 31-Jan | Q36: 31-Jan | R36: 31-Jan | S36: 31-Jan
C37: €m | D37: 100% Inditex Consolidated Line Item | I37: 2022 | J37: =+I37+1 -> 2023 | K37: =+J37+1 -> 2024 | L37: =+K37+1 -> 2025 | M37: =+L37+1 -> 2026 | N37: =+M37+1 -> 2027 | O37: =+N37+1 -> 2028 | P37: =+O37+1 -> 2029 | Q37: =+P37+1 -> 2030 | ... S37: =+R37+1 -> 2032
B38: 3 | D38: Operating Working Capital (Structural Negative NOF — 100% Inditex)
D39: Inventory | I39: 3191 | J39: 2966 | K39: 3321 | L39: 3249 | M39: =+M$21*M15 -> 3427.6064 | N39: =+N$21*N15 -> 3616.1247 | O39: =+O$21*O15 -> 3815.0116 | P39: =+P$21*P15 -> 4024.8372 | Q39: =+Q$21*Q15 -> 4246.2033 | R39: =+R$21*R15 -> 4479.7445 | S39: =+S$21*S15 -> 4726.1304
D40: Trade & other receivables | I40: 851 | J40: 1038 | K40: 1088 | L40: 1166 | M40: =+M$21*M16 -> 1228.0504 | N40: =+N$21*N16 -> 1295.5932 | O40: =+O$21*O16 -> 1366.8508 | P40: =+P$21*P16 -> 1442.0276 | Q40: =+Q$21*Q16 -> 1521.3391 | R40: =+R$21*R16 -> 1605.0127 | S40: =+S$21*S16 -> 1693.2884
D41: Trade & other payables (Supplier financing) | I41: -6561 | J41: -7467 | K41: -8590 | L41: -8587 | M41: =+M$21*M17 -> -9058.9744 | N41: =+N$21*N17 -> -9557.218 | O41: =+O$21*O17 -> -10082.865 | P41: =+P$21*P17 -> -10637.423 | Q41: =+Q$21*Q17 -> -11222.481 | R41: =+R$21*R17 -> -11839.717 | S41: =+S$21*S17 -> -12490.902
D42: Net Operating Working Capital (NOF EoP — 100% Inditex) | I42: =+SUM(I39:I41) -> -2519 | J42: =+SUM(J39:J41) -> -3463 | K42: =+SUM(K39:K41) -> -4181 | L42: =+SUM(L39:L41) -> -4172 | M42: =+SUM(M39:M41) -> -4403.3176 | N42: =+SUM(N39:N41) -> -4645.5001 | O42: =+SUM(O39:O41) -> -4901.0026 | P42: =+SUM(P39:P41) -> -5170.5578 | ... S42: =+SUM(S39:S41) -> -6071.4829
D43: NOF % of revenues (Negative = Supplier-funded float) | I43: =+IFERROR(I42/I$21,0) -> -0.077343486 | J43: =+IFERROR(J42/J$21,0) -> -0.096336273 | K43: =+IFERROR(K42/K$21,0) -> -0.10822634 | L43: =+IFERROR(L42/L$21,0) -> -0.10465583 | M43: =+IFERROR(M42/M$21,0) -> -0.1047 | N43: =+IFERROR(N42/N$21,0) -> -0.1047 | O43: =+IFERROR(O42/O$21,0) -> -0.1047 | P43: =+IFERROR(P42/P$21,0) -> -0.1047 | ... S43: =+IFERROR(S42/S$21,0) -> -0.1047
D44: Cash Flow from Working Capital (-ΔNOF — 100% Inditex) | I44: 0 | J44: =+(I42-J42) -> 944 | K44: =+(J42-K42) -> 718 | L44: =+(K42-L42) -> -9 | M44: =+(L42-M42) -> 231.31764 | N44: =+(M42-N42) -> 242.18247 | O44: =+(N42-O42) -> 255.50251 | P44: =+(O42-P42) -> 269.55514 | Q44: =+(P42-Q42) -> 284.38068 | ... S44: =+(R42-S42) -> 316.5228
B46: 4 | D46: Capex Split (Maintenance vs. US/Logistics Expansion) & D&A Schedule (100% Inditex)
D47: BoP Net Fixed Assets (Owned PP&E + Intangibles) | I47: 8383 | J47: =+I50 -> 8401 | K47: =+J50 -> 9560 | L47: =+K50 -> 11416 | M47: =+L50 -> 12778 | N47: =+M50 -> 13577.792 | O47: =+N50 -> 14273.158 | P47: =+O50 -> 14858.354 | Q47: =+P50 -> 15327.321 | ... S47: =+R50 -> 15890.645
D48: Total Capex additions (Maintenance + Expansion) | I48: =+I54 -> 1415 | J48: =+J54 -> 1872 | K48: =+K54 -> 2672 | L48: =+L54 -> 2712 | M48: =+M54 -> 2186.939 | N48: =+N54 -> 2307.2207 | O48: =+O54 -> 2434.1178 | P48: =+P54 -> 2567.9943 | ... S48: =+S54 -> 3015.4452
D49: Total D&A (Owned PP&E + Intangibles) | I49: -1417 | J49: -1558 | K49: -1638 | L49: -1674 | M49: =+M57+M69 -> -1387.147 | N49: =+N57+N69 -> -1611.8549 | O49: =+O57+O69 -> -1848.9219 | P49: =+P57+P69 -> -2099.0275 | Q49: =+Q57+Q69 -> -2362.8889 | R49: =+R57+R69 -> -2641.2627 | S49: =+S57+S69 -> -2934.947
D50: EoP Net Fixed Assets | I50: 8401 | J50: 9560 | K50: 11416 | L50: 12778 | M50: =+M47+M48+M49 -> 13577.792 | N50: =+N47+N48+N49 -> 14273.158 | O50: =+O47+O48+O49 -> 14858.354 | P50: =+P47+P48+P49 -> 15327.321 | Q50: =+Q47+Q48+Q49 -> 15673.666 | R50: =+R47+R48+R49 -> 15890.645 | S50: =+S47+S48+S49 -> 15971.143
D52: 1. Maintenance Capex (Store refurbishments & IT upkeep — 100%) | I52: 1050 | J52: 1250 | K52: 1450 | L52: 1480 | M52: =+M21*M13 -> 1471.9782 | N52: =+N21*N13 -> 1552.937 | O52: =+O21*O13 -> 1638.3485 | P52: =+P21*P13 -> 1728.4577 | Q52: =+Q21*Q13 -> 1823.5229 | R52: =+R21*R13 -> 1923.8166 | S52: =+S21*S13 -> 2029.6266
D53: 2. Expansion Capex (US Flagship Rollout & Logistics Hubs — 100%) | I53: 365 | J53: 622 | K53: 1222 | L53: 1232 | M53: =+M21*M14 -> 714.96084 | N53: =+N21*N14 -> 754.28369 | O53: =+O21*O14 -> 795.76929 | P53: =+P21*P14 -> 839.5366 | Q53: =+Q21*Q14 -> 885.71111 | R53: =+R21*R14 -> 934.42522 | S53: =+S21*S14 -> 985.81861
D54: Total Capex (100% Inditex — Funded Organically) | I54: =+I52+I53 -> 1415 | J54: =+J52+J53 -> 1872 | K54: =+K52+K53 -> 2672 | L54: =+L52+L53 -> 2712 | M54: =+M52+M53 -> 2186.939 | N54: =+N52+N53 -> 2307.2207 | O54: =+O52+O53 -> 2434.1178 | P54: =+P52+P53 -> 2567.9943 | ... S54: =+S52+S53 -> 3015.4452
D56: BoP existing net fixed assets | M56: =+L58 -> 12778 | N56: =+M58 -> 11500.2 | O56: =+N58 -> 10222.4 | P56: =+O58 -> 8944.6 | Q56: =+P58 -> 7666.8 | R56: =+Q58 -> 6389 | S56: =+R58 -> 5111.2
D57: D&A of existing fixed assets | M57: =-MIN(M56,$L$58/$E$59) -> -1277.8 | N57: =-MIN(N56,$L$58/$E$59) -> -1277.8 | O57: =-MIN(O56,$L$58/$E$59) -> -1277.8 | P57: =-MIN(P56,$L$58/$E$59) -> -1277.8 | Q57: =-MIN(Q56,$L$58/$E$59) -> -1277.8 | R57: =-MIN(R56,$L$58/$E$59) -> -1277.8 | S57: =-MIN(S56,$L$58/$E$59) -> -1277.8
D58: EoP existing net fixed assets | L58: =+L50 -> 12778 | M58: =+M56+M57 -> 11500.2 | N58: =+N56+N57 -> 10222.4 | O58: =+O56+O57 -> 8944.6 | P58: =+P56+P57 -> 7666.8 | Q58: =+Q56+Q57 -> 6389 | R58: =+R56+R57 -> 5111.2 | S58: =+S56+S57 -> 3833.4
D59: Asset lifetime (years) | E59: 10
D60: First period D&A impact | E60: 0.5
G61: Vintage | H61: Capex (€m)
G62: =+M$20 -> 2026 | H62: =+M$54 -> 2186.939 | M62: =-(($H62/$E$59*$E$60)) -> -109.34695 | N62: =-(MIN(SUM($H62,$M62:M62),$H62/$E$59)) -> -218.6939 | O62: =-(MIN(SUM($H62,$M62:N62),$H62/$E$59)) -> -218.6939 | P62: =-(MIN(SUM($H62,$M62:O62),$H62/$E$59)) -> -218.6939 | Q62: =-(MIN(SUM($H62,$M62:P62),$H62/$E$59)) -> -218.6939 | R62: =-(MIN(SUM($H62,$M62:Q62),$H62/$E$59)) -> -218.6939 | S62: =-(MIN(SUM($H62,$M62:R62),$H62/$E$59)) -> -218.6939
G63: =+N$20 -> 2027 | H63: =+N$54 -> 2307.2207 | M63: 0 | N63: =-(($H63/$E$59*$E$60)) -> -115.36103 | O63: =-(MIN(SUM($H63,$N63:N63),$H63/$E$59)) -> -230.72207 | P63: =-(MIN(SUM($H63,$N63:O63),$H63/$E$59)) -> -230.72207 | Q63: =-(MIN(SUM($H63,$N63:P63),$H63/$E$59)) -> -230.72207 | R63: =-(MIN(SUM($H63,$N63:Q63),$H63/$E$59)) -> -230.72207 | S63: =-(MIN(SUM($H63,$N63:R63),$H63/$E$59)) -> -230.72207
G64: =+O$20 -> 2028 | H64: =+O$54 -> 2434.1178 | M64: 0 | N64: 0 | O64: =-(($H64/$E$59*$E$60)) -> -121.70589 | P64: =-(MIN(SUM($H64,$O64:O64),$H64/$E$59)) -> -243.41178 | Q64: =-(MIN(SUM($H64,$O64:P64),$H64/$E$59)) -> -243.41178 | R64: =-(MIN(SUM($H64,$O64:Q64),$H64/$E$59)) -> -243.41178 | S64: =-(MIN(SUM($H64,$O64:R64),$H64/$E$59)) -> -243.41178
G65: =+P$20 -> 2029 | H65: =+P$54 -> 2567.9943 | M65: 0 | N65: 0 | O65: 0 | P65: =-(($H65/$E$59*$E$60)) -> -128.39972 | Q65: =-(MIN(SUM($H65,$P65:P65),$H65/$E$59)) -> -256.79943 | R65: =-(MIN(SUM($H65,$P65:Q65),$H65/$E$59)) -> -256.79943 | S65: =-(MIN(SUM($H65,$P65:R65),$H65/$E$59)) -> -256.79943
G66: =+Q$20 -> 2030 | H66: =+Q$54 -> 2709.234 | M66: 0 | N66: 0 | O66: 0 | P66: 0 | Q66: =-(($H66/$E$59*$E$60)) -> -135.4617 | R66: =-(MIN(SUM($H66,$Q66:Q66),$H66/$E$59)) -> -270.9234 | S66: =-(MIN(SUM($H66,$Q66:R66),$H66/$E$59)) -> -270.9234
G67: =+R$20 -> 2031 | H67: =+R$54 -> 2858.2419 | M67: 0 | N67: 0 | O67: 0 | P67: 0 | Q67: 0 | R67: =-(($H67/$E$59*$E$60)) -> -142.91209 | S67: =-(MIN(SUM($H67,$R67:R67),$H67/$E$59)) -> -285.82419
G68: =+S$20 -> 2032 | H68: =+S$54 -> 3015.4452 | M68: 0 | N68: 0 | O68: 0 | P68: 0 | Q68: 0 | R68: 0 | S68: =-(($H68/$E$59*$E$60)) -> -150.77226
G69: Total new capex D&A (100% Inditex) | M69: =SUM(M62:M68) -> -109.34695 | N69: =SUM(N62:N68) -> -334.05494 | O69: =SUM(O62:O68) -> -571.12186 | P69: =SUM(P62:P68) -> -821.22747 | Q69: =SUM(Q62:Q68) -> -1085.0889 | R69: =SUM(R62:R68) -> -1363.4627 | S69: =SUM(S62:S68) -> -1657.147

Sheet Debt & Covenants
B1: Project Galicia v3 — Inditex (ITX.MC) | M1: Strictly Private & Confidential
A2: > | B2: Debt & Covenants — 100% Inditex LBO Debt Schedule (2025A–2032E), RCF Negative-NOF Backstop, WALL, SFA Covenants & DSCR
A4: > | B4: > | C4: 1. Debt Tranche Pricing (Euribor + Spread), Sizing on 100% EBITDA, Tenor & WALL
B6: 4 | D6: Tranche / Facility (BidCo — 100% Consolidated Group) | E6: All-In Rate | F6: xEBITDA | G6: Spread / Fixed | H6: PIK (0=Cash,1=PIK) | I6: Tenor (Yrs) | J6: Drawn (€m) | M6: WALL (Yrs)
D7: Blended Initial Cost of Debt (E7) / Reference Euribor Swap (F7) | E7: =+(J8*E8+J9*E9+J10*E10+J11*E11)/J7 -> 0.059090909 | F7: 0.0275 | J7: =+SUM(J8:J11) -> 51881.5 | M7: =+(J8*M8+J9*M9+J10*M10+J11*M11)/J7 -> 6.2272727
D8: 1A. Senior Term Loan A (TLA — 5y Amortising Bank Debt) | E8: =+$F$7+G8 -> 0.05 | F8: 1.5 | G8: 0.0225 | H8: 0 | I8: 5 | J8: ='LBO Summary'!F25 -> 14149.5 | M8: =+F25*1+G25*2+H25*3+I25*4+J25*5+K25*6+L25*7 -> 3.5
D9: 1B. Senior Term Loan B (TLB — 7y Institutional Bullet) | E9: =+$F$7+G9 -> 0.06 | F9: 2.5 | G9: 0.0325 | H9: 0 | I9: 7 | J9: ='LBO Summary'!F26 -> 23582.5 | M9: =+I9 -> 7
D10: 2. Subordinated / Mezzanine Debt (Bullet; H10: 0=Cash, 1=PIK) | E10: =+$F$7+G10 -> 0.075 | F10: 1 | G10: 0.0475 | H10: 0 | I10: 7.5 | J10: ='LBO Summary'!F27 -> 9433 | M10: =+I10 -> 7.5
D11: 3. Seller Vendor Loan (Sandra Note; H11: 0=Cash, 1=PIK) | E11: =+G11 -> 0.05 | F11: 0.5 | G11: 0.05 | H11: 0 | I11: 8 | J11: ='LBO Summary'!F28 -> 4716.5 | M11: =+I11 -> 8
D12: TLB mandatory annual amortisation (% — 0.0% = Bullet) | E12: 0
D13: TLB optional cash sweep (% — 0.0% = Hold to maturity) | E13: 0
D14: 4. RCF Committed Limit (€m — Seasonal Negative-NOF Backstop) | E14: 3500 | G14: 0.02
D15: RCF Drawn Rate (E15) & Undrawn Commitment Fee % p.a. (G15) | E15: =+$F$7+G14 -> 0.0475 | G15: 0.0075
D16: SFA Net Leverage Covenant Headroom % (E16) & Min DSCR (G16) | E16: 0.25 | G16: 1.25
C18: Debt Sched | E18: 31-Jan | F18: 31-Jan | G18: 31-Jan | H18: 31-Jan | I18: 31-Jan | J18: 31-Jan | K18: 31-Jan | L18: 31-Jan
C19: €m | D19: 100% Consolidated Group Line Item | E19: 2025 | F19: =+E19+1 -> 2026 | G19: =+F19+1 -> 2027 | H19: =+G19+1 -> 2028 | I19: =+H19+1 -> 2029 | J19: =+I19+1 -> 2030 | K19: =+J19+1 -> 2031 | L19: =+K19+1 -> 2032
D20: 1A. Senior Term Loan A (TLA — 5y Amortising Bank Tranche)
D21: BoP TLA | E21: 0 | F21: =+E24 -> 14149.5 | G21: =+F24 -> 12734.55 | H21: =+G24 -> 10612.125 | I21: =+H24 -> 7782.225 | J21: =+I24 -> 4244.85 | K21: =+J24 -> 0 | L21: =+K24 -> 0
D22: Initial draw at closing | E22: =+J8 -> 14149.5 | F22: 0 | G22: 0 | H22: 0 | I22: 0 | J22: 0 | K22: 0 | L22: 0
D23: Scheduled repayment | E23: 0 | F23: =-MIN(F21,$E$24*F$25) -> -1414.95 | G23: =-MIN(G21,$E$24*G$25) -> -2122.425 | H23: =-MIN(H21,$E$24*H$25) -> -2829.9 | I23: =-MIN(I21,$E$24*I$25) -> -3537.375 | J23: =-MIN(J21,$E$24*J$25) -> -4244.85 | K23: =-MIN(K21,$E$24*K$25) -> 0 | L23: =-MIN(L21,$E$24*L$25) -> 0
D24: EoP TLA | E24: =+SUM(E21:E23) -> 14149.5 | F24: =+SUM(F21:F23) -> 12734.55 | G24: =+SUM(G21:G23) -> 10612.125 | H24: =+SUM(H21:H23) -> 7782.225 | I24: =+SUM(I21:I23) -> 4244.85 | J24: =+SUM(J21:J23) -> 0 | K24: =+SUM(K21:K23) -> 0 | L24: =+SUM(L21:L23) -> 0
D25: TLA scheduled amortisation % | F25: 0.1 | G25: 0.15 | H25: 0.2 | I25: 0.25 | J25: =1-SUM(F25:I25) -> 0.3 | K25: 0 | L25: 0 | M25: =+SUM(F25:L25)-1 -> 0
D26: TLA cash interest (on Average Balance) | F26: =-$E$8*AVERAGE(F21,F24) -> -672.10125 | G26: =-$E$8*AVERAGE(G21,G24) -> -583.66688 | H26: =-$E$8*AVERAGE(H21,H24) -> -459.85875 | I26: =-$E$8*AVERAGE(I21,I24) -> -300.67688 | J26: =-$E$8*AVERAGE(J21,J24) -> -106.12125 | K26: =-$E$8*AVERAGE(K21,K24) -> 0 | L26: =-$E$8*AVERAGE(L21,L24) -> 0
D28: 1B. Senior Term Loan B (TLB — 7y Institutional Bullet)
D29: BoP TLB | E29: 0 | F29: =+E34 -> 23582.5 | G29: =+F34 -> 23582.5 | H29: =+G34 -> 23582.5 | I29: =+H34 -> 23582.5 | J29: =+I34 -> 23582.5 | K29: =+J34 -> 23582.5 | L29: =+K34 -> 23582.5
D30: Initial draw at closing | E30: =+J9 -> 23582.5 | F30: 0 | G30: 0 | H30: 0 | I30: 0 | J30: 0 | K30: 0 | L30: 0
D31: Mandatory amortisation (% in E12) | E31: 0 | F31: =-MIN(F29,$E$34*F$35) -> 0 | G31: =-MIN(G29,$E$34*G$35) -> 0 | H31: =-MIN(H29,$E$34*H$35) -> 0 | I31: =-MIN(I29,$E$34*I$35) -> 0 | J31: =-MIN(J29,$E$34*J$35) -> 0 | K31: =-MIN(K29,$E$34*K$35) -> 0 | L31: =-MIN(L29,$E$34*L$35) -> 0
D32: TLB balance before optional sweep | E32: =+SUM(E29:E31) -> 23582.5 | F32: =+SUM(F29:F31) -> 23582.5 | G32: =+SUM(G29:G31) -> 23582.5 | H32: =+SUM(H29:H31) -> 23582.5 | I32: =+SUM(I29:I31) -> 23582.5 | J32: =+SUM(J29:J31) -> 23582.5 | K32: =+SUM(K29:K31) -> 23582.5 | L32: =+SUM(L29:L31) -> 23582.5
D33: Optional cash sweep (% in E13 — 0% default) | E33: 0 | F33: =-MIN(F32,MAX(0,F87+F88)*$E$13) -> 0 | G33: =-MIN(G32,MAX(0,G87+G88)*$E$13) -> 0 | H33: =-MIN(H32,MAX(0,H87+H88)*$E$13) -> 0 | I33: =-MIN(I32,MAX(0,I87+I88)*$E$13) -> 0 | J33: =-MIN(J32,MAX(0,J87+J88)*$E$13) -> 0 | K33: =-MIN(K32,MAX(0,K87+K88)*$E$13) -> 0 | L33: =-MIN(L32,MAX(0,L87+L88)*$E$13) -> 0
D34: EoP TLB | E34: =+E32+E33 -> 23582.5 | F34: =+F32+F33 -> 23582.5 | G34: =+G32+G33 -> 23582.5 | H34: =+H32+H33 -> 23582.5 | I34: =+I32+I33 -> 23582.5 | J34: =+J32+J33 -> 23582.5 | K34: =+K32+K33 -> 23582.5 | L34: =+L32+L33 -> 23582.5
D35: TLB mandatory amortisation % | F35: =+$E$12 -> 0 | G35: =+$E$12 -> 0 | H35: =+$E$12 -> 0 | I35: =+$E$12 -> 0 | J35: =+$E$12 -> 0 | K35: =+$E$12 -> 0 | L35: =+$E$12 -> 0
D36: TLB cash interest (on Average Balance) | F36: =-$E$9*AVERAGE(F29,F32) -> -1414.95 | G36: =-$E$9*AVERAGE(G29,G32) -> -1414.95 | H36: =-$E$9*AVERAGE(H29,H32) -> -1414.95 | I36: =-$E$9*AVERAGE(I29,I32) -> -1414.95 | J36: =-$E$9*AVERAGE(J29,J32) -> -1414.95 | K36: =-$E$9*AVERAGE(K29,K32) -> -1414.95 | L36: =-$E$9*AVERAGE(L29,L32) -> -1414.95
D38: 2. Subordinated / Mezzanine Debt (Bullet — Cash or PIK Switch in H10)
D39: BoP Subordinated debt | E39: 0 | F39: =+E43 -> 9433 | G39: =+F43 -> 9433 | H39: =+G43 -> 9433 | I39: =+H43 -> 9433 | J39: =+I43 -> 9433 | K39: =+J43 -> 9433 | L39: =+K43 -> 9433
D40: Initial draw at closing | E40: =+J10 -> 9433 | F40: 0 | G40: 0 | H40: 0 | I40: 0 | J40: 0 | K40: 0 | L40: 0
D41: PIK interest capitalised (if H10 = 1) | E41: 0 | F41: =+IF($H$10=1,F39*$E$10,0) -> 0 | G41: =+IF($H$10=1,G39*$E$10,0) -> 0 | H41: =+IF($H$10=1,H39*$E$10,0) -> 0 | I41: =+IF($H$10=1,I39*$E$10,0) -> 0 | J41: =+IF($H$10=1,J39*$E$10,0) -> 0 | K41: =+IF($H$10=1,K39*$E$10,0) -> 0 | L41: =+IF($H$10=1,L39*$E$10,0) -> 0
D42: Scheduled repayment (Bullet at maturity) | E42: 0 | F42: 0 | G42: 0 | H42: 0 | I42: 0 | J42: 0 | K42: 0 | L42: 0
D43: EoP Subordinated debt | E43: =+SUM(E39:E42) -> 9433 | F43: =+SUM(F39:F42) -> 9433 | G43: =+SUM(G39:G42) -> 9433 | H43: =+SUM(H39:H42) -> 9433 | I43: =+SUM(I39:I42) -> 9433 | J43: =+SUM(J39:J42) -> 9433 | K43: =+SUM(K39:K42) -> 9433 | L43: =+SUM(L39:L42) -> 9433
D44: Subordinated cash interest (if H10 = 0) | F44: =+IF($H$10=0,-F39*$E$10,0) -> -707.475 | G44: =+IF($H$10=0,-G39*$E$10,0) -> -707.475 | H44: =+IF($H$10=0,-H39*$E$10,0) -> -707.475 | I44: =+IF($H$10=0,-I39*$E$10,0) -> -707.475 | J44: =+IF($H$10=0,-J39*$E$10,0) -> -707.475 | K44: =+IF($H$10=0,-K39*$E$10,0) -> -707.475 | L44: =+IF($H$10=0,-L39*$E$10,0) -> -707.475
D45: Subordinated total P&L interest (for Art. 16 LIS Tax Model) | F45: =-F39*$E$10 -> -707.475 | G45: =-G39*$E$10 -> -707.475 | H45: =-H39*$E$10 -> -707.475 | I45: =-I39*$E$10 -> -707.475 | J45: =-J39*$E$10 -> -707.475 | K45: =-K39*$E$10 -> -707.475 | L45: =-L39*$E$10 -> -707.475
D47: 3. Seller Vendor Loan (Sandra Deferred Note — Cash or PIK Switch in H11)
D48: BoP Vendor Loan | E48: 0 | F48: =+E52 -> 4716.5 | G48: =+F52 -> 4716.5 | H48: =+G52 -> 4716.5 | I48: =+H52 -> 4716.5 | J48: =+I52 -> 4716.5 | K48: =+J52 -> 4716.5 | L48: =+K52 -> 4716.5
D49: Initial draw at closing | E49: =+J11 -> 4716.5 | F49: 0 | G49: 0 | H49: 0 | I49: 0 | J49: 0 | K49: 0 | L49: 0
D50: PIK interest capitalised (if H11 = 1) | E50: 0 | F50: =+IF($H$11=1,F48*$E$11,0) -> 0 | G50: =+IF($H$11=1,G48*$E$11,0) -> 0 | H50: =+IF($H$11=1,H48*$E$11,0) -> 0 | I50: =+IF($H$11=1,I48*$E$11,0) -> 0 | J50: =+IF($H$11=1,J48*$E$11,0) -> 0 | K50: =+IF($H$11=1,K48*$E$11,0) -> 0 | L50: =+IF($H$11=1,L48*$E$11,0) -> 0
D51: Scheduled repayment (Bullet at exit) | E51: 0 | F51: 0 | G51: 0 | H51: 0 | I51: 0 | J51: 0 | K51: 0 | L51: 0
D52: EoP Vendor Loan | E52: =+SUM(E48:E51) -> 4716.5 | F52: =+SUM(F48:F51) -> 4716.5 | G52: =+SUM(G48:G51) -> 4716.5 | H52: =+SUM(H48:H51) -> 4716.5 | I52: =+SUM(I48:I51) -> 4716.5 | J52: =+SUM(J48:J51) -> 4716.5 | K52: =+SUM(K48:K51) -> 4716.5 | L52: =+SUM(L48:L51) -> 4716.5
D53: Vendor Loan cash interest (if H11 = 0) | F53: =+IF($H$11=0,-F48*$E$11,0) -> -235.825 | G53: =+IF($H$11=0,-G48*$E$11,0) -> -235.825 | H53: =+IF($H$11=0,-H48*$E$11,0) -> -235.825 | I53: =+IF($H$11=0,-I48*$E$11,0) -> -235.825 | J53: =+IF($H$11=0,-J48*$E$11,0) -> -235.825 | K53: =+IF($H$11=0,-K48*$E$11,0) -> -235.825 | L53: =+IF($H$11=0,-L48*$E$11,0) -> -235.825
D54: Vendor Loan total P&L interest (for Art. 16 LIS Tax Model) | F54: =-F48*$E$11 -> -235.825 | G54: =-G48*$E$11 -> -235.825 | H54: =-H48*$E$11 -> -235.825 | I54: =-I48*$E$11 -> -235.825 | J54: =-J48*$E$11 -> -235.825 | K54: =-K48*$E$11 -> -235.825 | L54: =-L48*$E$11 -> -235.825
D56: 4. Revolving Credit Facility (RCF — Seasonal Negative-NOF Backstop)
D57: BoP RCF drawn | E57: 0 | F57: =+E59 -> 0 | G57: =+F59 -> 0 | H57: =+G59 -> 0 | I57: =+H59 -> 0 | J57: =+I59 -> 0 | K57: =+J59 -> 0 | L57: =+K59 -> 0
D58: RCF draw / (repayment) | E58: ='LBO Summary'!F29 -> 0 | F58: =+IF(F87<0,MIN($E$14-F57,-F87),-MIN(F57,F87)) -> 0 | G58: =+IF(G87<0,MIN($E$14-G57,-G87),-MIN(G57,G87)) -> 0 | H58: =+IF(H87<0,MIN($E$14-H57,-H87),-MIN(H57,H87)) -> 0 | I58: =+IF(I87<0,MIN($E$14-I57,-I87),-MIN(I57,I87)) -> 0 | J58: =+IF(J87<0,MIN($E$14-J57,-J87),-MIN(J57,J87)) -> 0 | K58: =+IF(K87<0,MIN($E$14-K57,-K87),-MIN(K57,K87)) -> 0 | L58: =+IF(L87<0,MIN($E$14-L57,-L87),-MIN(L57,L87)) -> 0
D59: EoP RCF drawn | E59: =+E57+E58 -> 0 | F59: =+F57+F58 -> 0 | G59: =+G57+G58 -> 0 | H59: =+H57+H58 -> 0 | I59: =+I57+I58 -> 0 | J59: =+J57+J58 -> 0 | K59: =+K57+K58 -> 0 | L59: =+L57+L58 -> 0
D60: Undrawn RCF available (Liquidity buffer for Negative NOF swings) | E60: =+$E$14-E59 -> 3500 | F60: =+MAX(0,$E$14-F59) -> 3500 | G60: =+MAX(0,$E$14-G59) -> 3500 | H60: =+MAX(0,$E$14-H59) -> 3500 | I60: =+MAX(0,$E$14-I59) -> 3500 | J60: =+MAX(0,$E$14-J59) -> 3500 | K60: =+MAX(0,$E$14-K59) -> 3500 | L60: =+MAX(0,$E$14-L59) -> 3500
D61: Total RCF drawn interest & undrawn commitment fee (% in G15) | F61: =-(F57*$E$15+MAX(0,$E$14-F57)*$G$15) -> -26.25 | G61: =-(G57*$E$15+MAX(0,$E$14-G57)*$G$15) -> -26.25 | H61: =-(H57*$E$15+MAX(0,$E$14-H57)*$G$15) -> -26.25 | I61: =-(I57*$E$15+MAX(0,$E$14-I57)*$G$15) -> -26.25 | J61: =-(J57*$E$15+MAX(0,$E$14-J57)*$G$15) -> -26.25 | K61: =-(K57*$E$15+MAX(0,$E$14-K57)*$G$15) -> -26.25 | L61: =-(L57*$E$15+MAX(0,$E$14-L57)*$G$15) -> -26.25
D63: Total LBO Debt Summary (100% Consolidated Group)
D64: BoP Total Gross Debt | E64: 0 | F64: =+F21+F29+F39+F48+F57 -> 51881.5 | G64: =+G21+G29+G39+G48+G57 -> 50466.55 | H64: =+H21+H29+H39+H48+H57 -> 48344.125 | I64: =+I21+I29+I39+I48+I57 -> 45514.225 | J64: =+J21+J29+J39+J48+J57 -> 41976.85 | K64: =+K21+K29+K39+K48+K57 -> 37732 | L64: =+L21+L29+L39+L48+L57 -> 37732
D65: Mandatory Scheduled Principal Repayment (TLA + TLB) | E65: =+E22+E30+E40+E49+E58 -> 51881.5 | F65: =+F23+F31 -> -1414.95 | G65: =+G23+G31 -> -2122.425 | H65: =+H23+H31 -> -2829.9 | I65: =+I23+I31 -> -3537.375 | J65: =+J23+J31 -> -4244.85 | K65: =+K23+K31 -> 0 | L65: =+L23+L31 -> 0
D66: Optional TLB Cash Sweep & RCF Net Change | E66: 0 | F66: =+F33+F58 -> 0 | G66: =+G33+G58 -> 0 | H66: =+H33+H58 -> 0 | I66: =+I33+I58 -> 0 | J66: =+J33+J58 -> 0 | K66: =+K33+K58 -> 0 | L66: =+L33+L58 -> 0
D67: EoP Senior Gross Debt (TLA + TLB + RCF) | E67: =+E24+E34+E59 -> 37732 | F67: =+F24+F34+F59 -> 36317.05 | G67: =+G24+G34+G59 -> 34194.625 | H67: =+H24+H34+H59 -> 31364.725 | I67: =+I24+I34+I59 -> 27827.35 | J67: =+J24+J34+J59 -> 23582.5 | K67: =+K24+K34+K59 -> 23582.5 | L67: =+L24+L34+L59 -> 23582.5
D68: EoP Total Gross Financial Debt (incl. Sub & Vendor Loan) | E68: =+E24+E34+E43+E52+E59 -> 51881.5 | F68: =+F24+F34+F43+F52+F59 -> 50466.55 | G68: =+G24+G34+G43+G52+G59 -> 48344.125 | H68: =+H24+H34+H43+H52+H59 -> 45514.225 | I68: =+I24+I34+I43+I52+I59 -> 41976.85 | J68: =+J24+J34+J43+J52+J59 -> 37732 | K68: =+K24+K34+K43+K52+K59 -> 37732 | L68: =+L24+L34+L43+L52+L59 -> 37732
D69: Less: EoP 100% Inditex Cash Balance | E69: =-E93 -> -1500 | F69: =-F93 -> -3787.694 | G69: =-G93 -> -6031.9531 | H69: =-H93 -> -8196.4191 | I69: =-I93 -> -10378.35 | J69: =-J93 -> -12643.999 | K69: =-K93 -> -19921.526 | L69: =-L93 -> -27931.225
D70: EoP Total Net Financial Debt (100% Consolidated Group) | E70: =+E68+E69 -> 50381.5 | F70: =+F68+F69 -> 46678.856 | G70: =+G68+G69 -> 42312.172 | H70: =+H68+H69 -> 37317.806 | I70: =+I68+I69 -> 31598.5 | J70: =+J68+J69 -> 25088.001 | K70: =+K68+K69 -> 17810.474 | L70: =+L68+L69 -> 9800.7749
D71: Total Cash Interest & Commitment Fees Paid (CF Outflow) | F71: =+F26+F36+F44+F53+F61 -> -3056.6012 | G71: =+G26+G36+G44+G53+G61 -> -2968.1669 | H71: =+H26+H36+H44+H53+H61 -> -2844.3587 | I71: =+I26+I36+I44+I53+I61 -> -2685.1769 | J71: =+J26+J36+J44+J53+J61 -> -2490.6212 | K71: =+K26+K36+K44+K53+K61 -> -2384.5 | L71: =+L26+L36+L44+L53+L61 -> -2384.5
D72: Total P&L Financial Expense (Cash + PIK — to Tax & WACC) | F72: =+F26+F36+F45+F54+F61 -> -3056.6012 | G72: =+G26+G36+G45+G54+G61 -> -2968.1669 | H72: =+H26+H36+H45+H54+H61 -> -2844.3587 | I72: =+I26+I36+I45+I54+I61 -> -2685.1769 | J72: =+J26+J36+J45+J54+J61 -> -2490.6212 | K72: =+K26+K36+K45+K54+K61 -> -2384.5 | L72: =+L26+L36+L45+L54+L61 -> -2384.5
C75: Cash Flow | E75: 31-Jan | F75: 31-Jan | G75: 31-Jan | H75: 31-Jan | I75: 31-Jan | J75: 31-Jan | K75: 31-Jan | L75: 31-Jan
C76: €m | D76: 100% Consolidated Group Line Item | E76: 2025 | F76: =+E76+1 -> 2026 | G76: =+F76+1 -> 2027 | H76: =+G76+1 -> 2028 | I76: =+H76+1 -> 2029 | J76: =+I76+1 -> 2030 | K76: =+J76+1 -> 2031 | L76: =+K76+1 -> 2032
B77: 5 | D77: 100% Inditex Pre-IFRS 16 Cash EBITDA | F77: ='Active Case'!M30 -> 10143.127 | G77: ='Active Case'!N30 -> 10922.262 | H77: ='Active Case'!O30 -> 11752.179 | I77: ='Active Case'!P30 -> 12635.98 | J77: ='Active Case'!Q30 -> 13576.948 | K77: ='Active Case'!R30 -> 14578.56 | L77: ='Active Case'!S30 -> 15644.499
D78: Cash Corporate Income Tax Paid (from Tax & WACC — Art. 16 LIS) | F78: ='Tax & WACC'!F22 -> -1428.2605 | G78: ='Tax & WACC'!G22 -> -1522.3724 | H78: ='Tax & WACC'!H22 -> -1734.8387 | I78: ='Tax & WACC'!I22 -> -1933.0579 | J78: ='Tax & WACC'!J22 -> -2150.9735 | K78: ='Tax & WACC'!K22 -> -2358.3134 | L78: ='Tax & WACC'!L22 -> -2551.3771
D79: Cash Flow from Working Capital (-ΔNOF — 100% Inditex) | F79: ='Active Case'!M44 -> 231.31764 | G79: ='Active Case'!N44 -> 242.18247 | H79: ='Active Case'!O44 -> 255.50251 | I79: ='Active Case'!P44 -> 269.55514 | J79: ='Active Case'!Q44 -> 284.38068 | K79: ='Active Case'!R44 -> 300.02161 | L79: ='Active Case'!S44 -> 316.5228
D80: Maintenance Capex (100% Inditex) | F80: =-'Active Case'!M52 -> -1471.9782 | G80: =-'Active Case'!N52 -> -1552.937 | H80: =-'Active Case'!O52 -> -1638.3485 | I80: =-'Active Case'!P52 -> -1728.4577 | J80: =-'Active Case'!Q52 -> -1823.5229 | K80: =-'Active Case'!R52 -> -1923.8166 | L80: =-'Active Case'!S52 -> -2029.6266
D81: CFADS excl. Expansion Capex (Bank DSCR Numerator) | F81: =+SUM(F77:F80) -> 7474.2061 | G81: =+SUM(G77:G80) -> 8089.1346 | H81: =+SUM(H77:H80) -> 8634.4941 | I81: =+SUM(I77:I80) -> 9244.0191 | J81: =+SUM(J77:J80) -> 9886.8319 | K81: =+SUM(K77:K80) -> 10596.452 | L81: =+SUM(L77:L80) -> 11380.018
D82: Expansion Capex (US Flagships & Logistics — 100% Organic) | F82: =-'Active Case'!M53 -> -714.96084 | G82: =-'Active Case'!N53 -> -754.28369 | H82: =-'Active Case'!O53 -> -795.76929 | I82: =-'Active Case'!P53 -> -839.5366 | J82: =-'Active Case'!Q53 -> -885.71111 | K82: =-'Active Case'!R53 -> -934.42522 | L82: =-'Active Case'!S53 -> -985.81861
D83: Cash Flow Available for Debt Service (100% Consolidated CFADS) | F83: =+F81+F82 -> 6759.2452 | G83: =+G81+G82 -> 7334.8509 | H83: =+H81+H82 -> 7838.7248 | I83: =+I81+I82 -> 8404.4825 | J83: =+J81+J82 -> 9001.1208 | K83: =+K81+K82 -> 9662.0263 | L83: =+L81+L82 -> 10394.199
D84: Cash Interest & RCF Commitment Fees Paid | F84: =+F71 -> -3056.6012 | G84: =+G71 -> -2968.1669 | H84: =+H71 -> -2844.3587 | I84: =+I71 -> -2685.1769 | J84: =+J71 -> -2490.6212 | K84: =+K71 -> -2384.5 | L84: =+L71 -> -2384.5
D85: Mandatory Scheduled Debt Amortisation (TLA + TLB) | F85: =+F65 -> -1414.95 | G85: =+G65 -> -2122.425 | H85: =+H65 -> -2829.9 | I85: =+I65 -> -3537.375 | J85: =+J65 -> -4244.85 | K85: =+K65 -> 0 | L85: =+L65 -> 0
D86: Free Cash Flow to Equity after Mandatory Debt Service | F86: =+F83+F84+F85 -> 2287.694 | G86: =+G83+G84+G85 -> 2244.2591 | H86: =+H83+H84+H85 -> 2164.4661 | I86: =+I83+I84+I85 -> 2181.9306 | J86: =+J83+J84+J85 -> 2265.6495 | K86: =+K83+K84+K85 -> 7277.5263 | L86: =+L83+L84+L85 -> 8009.6995
D87: Excess Cash Available above €1,500m Minimum Operational Cash | F87: =+(F92-$E$92)+F86 -> 2287.694 | G87: =+(G92-$E$92)+G86 -> 4531.9531 | H87: =+(H92-$E$92)+H86 -> 6696.4191 | I87: =+(I92-$E$92)+I86 -> 8878.3498 | J87: =+(J92-$E$92)+J86 -> 11143.999 | K87: =+(K92-$E$92)+K86 -> 18421.526 | L87: =+(L92-$E$92)+L86 -> 26431.225
D88: RCF Draw / (Repayment) | F88: =+F58 -> 0 | G88: =+G58 -> 0 | H88: =+H58 -> 0 | I88: =+I58 -> 0 | J88: =+J58 -> 0 | K88: =+K58 -> 0 | L88: =+L58 -> 0
D89: Optional TLB Cash Sweep (0% Default) | F89: =+F33 -> 0 | G89: =+G33 -> 0 | H89: =+H33 -> 0 | I89: =+I33 -> 0 | J89: =+J33 -> 0 | K89: =+K33 -> 0 | L89: =+L33 -> 0
D90: Net Change in Cash Balance | F90: =+F86+F88+F89 -> 2287.694 | G90: =+G86+G88+G89 -> 2244.2591 | H90: =+H86+H88+H89 -> 2164.4661 | I90: =+I86+I88+I89 -> 2181.9306 | J90: =+J86+J88+J89 -> 2265.6495 | K90: =+K86+K88+K89 -> 7277.5263 | L90: =+L86+L88+L89 -> 8009.6995
D92: BoP 100% Inditex Cash Balance | E92: ='LBO Summary'!F18 -> 1500 | F92: =+E93 -> 1500 | G92: =+F93 -> 3787.694 | H92: =+G93 -> 6031.9531 | I92: =+H93 -> 8196.4191 | J92: =+I93 -> 10378.35 | K92: =+J93 -> 12643.999 | L92: =+K93 -> 19921.526
D93: EoP 100% Inditex Cash Balance (Retained on Balance Sheet) | E93: =+E92 -> 1500 | F93: =+F92+F90 -> 3787.694 | G93: =+G92+G90 -> 6031.9531 | H93: =+H92+H90 -> 8196.4191 | I93: =+I92+I90 -> 10378.35 | J93: =+J92+J90 -> 12643.999 | K93: =+K92+K90 -> 19921.526 | L93: =+L92+L90 -> 27931.225
A95: > | B95: > | C95: 4. Financial Covenants Monitoring (SFA Net Leverage Step-Downs, Headroom & DSCR — 2025A–2032E)
B97: 6 | D97: Senior Net Debt / 100% Pre-IFRS 16 EBITDA (x) | E97: =+(E67-E93)/'Active Case'!L30 -> 3.8409838 | F97: =+(F67-F93)/'Active Case'!M30 -> 3.2070342 | G97: =+(G67-G93)/'Active Case'!N30 -> 2.5784653 | H97: =+(H67-H93)/'Active Case'!O30 -> 1.9714052 | I97: =+(I67-I93)/'Active Case'!P30 -> 1.3808981 | J97: =+(J67-J93)/'Active Case'!Q30 -> 0.80566715 | K97: =+(K67-K93)/'Active Case'!R30 -> 0.25112044 | L97: =+(L67-L93)/'Active Case'!S30 -> -0.27797152
D98: Total Bank & Sub Net Debt (excl. Vendor Loan) / EBITDA (x) | E98: =+(E67+E43-E93)/'Active Case'!L30 -> 4.8409838 | F98: =+(F67+F43-F93)/'Active Case'!M30 -> 4.1370236 | G98: =+(G67+G43-G93)/'Active Case'!N30 -> 3.4421142 | H98: =+(H67+H43-H93)/'Active Case'!O30 -> 2.7740648 | I98: =+(I67+I43-I93)/'Active Case'!P30 -> 2.1274172 | J98: =+(J67+J43-J93)/'Active Case'!Q30 -> 1.5004478 | K98: =+(K67+K43-K93)/'Active Case'!R30 -> 0.89816651 | L98: =+(L67+L43-L93)/'Active Case'!S30 -> 0.32498803
D99: Total Net Debt (incl. Vendor Loan) / 100% EBITDA (x) | E99: =+E70/'Active Case'!L30 -> 5.3409838 | F99: =+F70/'Active Case'!M30 -> 4.6020182 | G99: =+G70/'Active Case'!N30 -> 3.8739387 | H99: =+H70/'Active Case'!O30 -> 3.1753947 | I99: =+I70/'Active Case'!P30 -> 2.5006767 | J99: =+J70/'Active Case'!Q30 -> 1.8478381 | K99: =+K70/'Active Case'!R30 -> 1.2216896 | L99: =+L70/'Active Case'!S30 -> 0.62646781
D100: SFA Max Net Leverage Covenant (25% Entry Headroom + Step-Downs) | E100: =+ROUNDUP((E99/(1-$E$16))*20,0)/20 -> 7.15 | F100: =+MAX(2,E100-0.65) -> 6.5 | G100: =+MAX(2,F100-0.65) -> 5.85 | H100: =+MAX(2,G100-0.65) -> 5.2 | I100: =+MAX(2,H100-0.65) -> 4.55 | J100: =+MAX(2,I100-0.65) -> 3.9 | K100: =+MAX(2,J100-0.65) -> 3.25 | L100: =+MAX(2,K100-0.65) -> 2.6
D101: Net Leverage Covenant Cushion (Max Covenant - Actual) | E101: =+E100-E99 -> 1.8090162 | F101: =+F100-F99 -> 1.8979818 | G101: =+G100-G99 -> 1.9760613 | H101: =+H100-H99 -> 2.0246053 | I101: =+I100-I99 -> 2.0493233 | J101: =+J100-J99 -> 2.0521619 | K101: =+K100-K99 -> 2.0283104 | L101: =+L100-L99 -> 1.9735322
D102: Net Leverage Covenant Compliance Check | E102: =IF(E99<=E100,"COMPLIANT","BREACH") -> COMPLIANT | F102: =IF(F99<=F100,"COMPLIANT","BREACH") -> COMPLIANT | G102: =IF(G99<=G100,"COMPLIANT","BREACH") -> COMPLIANT | H102: =IF(H99<=H100,"COMPLIANT","BREACH") -> COMPLIANT | I102: =IF(I99<=I100,"COMPLIANT","BREACH") -> COMPLIANT | J102: =IF(J99<=J100,"COMPLIANT","BREACH") -> COMPLIANT | K102: =IF(K99<=K100,"COMPLIANT","BREACH") -> COMPLIANT | L102: =IF(L99<=L100,"COMPLIANT","BREACH") -> COMPLIANT
D104: Total Debt Service (Cash Interest + Mandatory TLA/TLB Principal) | F104: =-(F84+F85) -> 4471.5512 | G104: =-(G84+G85) -> 5090.5919 | H104: =-(H84+H85) -> 5674.2587 | I104: =-(I84+I85) -> 6222.5519 | J104: =-(J84+J85) -> 6735.4713 | K104: =-(K84+K85) -> 2384.5 | L104: =-(L84+L85) -> 2384.5
D105: DSCR (CFADS excl. Expansion Capex / Debt Service — Project Atlantic) | F105: =+F81/F104 -> 1.6715018 | G105: =+G81/G104 -> 1.5890362 | H105: =+H81/H104 -> 1.5216955 | I105: =+I81/I104 -> 1.4855672 | J105: =+J81/J104 -> 1.4678753 | K105: =+K81/K104 -> 4.4438882 | L105: =+L81/L104 -> 4.7724966
D106: DSCR (Total CFADS after US Expansion Capex / Debt Service) | F106: =+F83/F104 -> 1.5116108 | G106: =+G83/G104 -> 1.4408641 | H106: =+H83/H104 -> 1.3814535 | I106: =+I83/I104 -> 1.3506488 | J106: =+J83/J104 -> 1.3363758 | K106: =+K83/K104 -> 4.0520135 | L106: =+L83/L104 -> 4.3590688
D107: Minimum DSCR Covenant Threshold (G16) | F107: =+$G$16 -> 1.25 | G107: =+$G$16 -> 1.25 | H107: =+$G$16 -> 1.25 | I107: =+$G$16 -> 1.25 | J107: =+$G$16 -> 1.25 | K107: =+$G$16 -> 1.25 | L107: =+$G$16 -> 1.25
D108: DSCR Covenant Compliance Check | F108: =IF(F105>=$G$16,"COMPLIANT","BREACH") -> COMPLIANT | G108: =IF(G105>=$G$16,"COMPLIANT","BREACH") -> COMPLIANT | H108: =IF(H105>=$G$16,"COMPLIANT","BREACH") -> COMPLIANT | I108: =IF(I105>=$G$16,"COMPLIANT","BREACH") -> COMPLIANT | J108: =IF(J105>=$G$16,"COMPLIANT","BREACH") -> COMPLIANT | K108: =IF(K105>=$G$16,"COMPLIANT","BREACH") -> COMPLIANT | L108: =IF(L105>=$G$16,"COMPLIANT","BREACH") -> COMPLIANT
D109: Cash Interest Coverage Ratio (100% EBITDA / Cash Interest) | F109: =+F77/-F84 -> 3.3184332 | G109: =+G77/-G84 -> 3.6798004 | H109: =+H77/-H84 -> 4.1317498 | I109: =+I77/-I84 -> 4.7058277 | J109: =+J77/-J84 -> 5.4512293 | K109: =+K77/-K84 -> 6.1138855 | L109: =+L77/-L84 -> 6.5609138

Sheet Tax & WACC
B1: Project Galicia v3 — Inditex (ITX.MC) | M1: Strictly Private & Confidential
A2: > | B2: Tax & WACC — 100% Fiscal Consolidation (Art. 58, 16.5 & 16.1 LIS) & Dynamic WACC Evolution (2025A–2032E)
A4: > | B4: > | C4: 1. Spanish Corporate Tax Consolidation (Art. 58 LIS), Anti-LBO Test (Art. 16.5) & 30% EBITDA Cap (Art. 16.1)
B6: 7 | D6: Spanish Tax Consolidation & WACC Parameters
D7: Spanish Statutory Corporate Tax Rate (CIT %) | E7: 0.25 | G7: Risk-Free Rate — 10Y Spanish Bono (Rf %) | J7: 0.0315
D8: Art. 16.1 LIS Interest Deductibility Cap (% EBITDA) | E8: 0.3 | G8: Equity Market Risk Premium (ERP %) | J8: 0.055
D9: Art. 16.1 LIS Minimum Deductible Franchise (€m) | E9: 1 | G9: Inditex Unlevered Asset Beta (Beta_U) | J9: 0.78
D10: Art. 16.5 LIS Max LBO Debt / Purchase Value (70%) | E10: 0.7 | G10: Actual BidCo Acquisition Debt / Purchase Value | J10: ='LBO Summary'!L16 -> 0.28606741
D11: Upfront Financing Fees Total (€m — Amortised) | E11: ='LBO Summary'!I30 -> 836.805 | G11: Amortization Period for Upfront Fees (Yrs) | J11: ='LBO Summary'!L14 -> 7
C12: CIT Model | E12: 31-Jan | F12: 31-Jan | G12: 31-Jan | H12: 31-Jan | I12: 31-Jan | J12: 31-Jan | K12: 31-Jan | L12: 31-Jan
C13: €m | D13: 100% Consolidated Group Line Item | E13: 2025 | F13: =+E13+1 -> 2026 | G13: =+F13+1 -> 2027 | H13: =+G13+1 -> 2028 | I13: =+H13+1 -> 2029 | J13: =+I13+1 -> 2030 | K13: =+J13+1 -> 2031 | L13: =+K13+1 -> 2032
D14: 100% Inditex Pre-IFRS 16 Cash EBITDA (€m) | E14: ='Active Case'!L30 -> 9433 | F14: ='Active Case'!M30 -> 10143.127 | G14: ='Active Case'!N30 -> 10922.262 | H14: ='Active Case'!O30 -> 11752.179 | I14: ='Active Case'!P30 -> 12635.98 | J14: ='Active Case'!Q30 -> 13576.948 | K14: ='Active Case'!R30 -> 14578.56 | L14: ='Active Case'!S30 -> 15644.499
D15: 100% Inditex D&A (Owned PP&E + Intangibles) | E15: ='Active Case'!L32 -> -1674 | F15: ='Active Case'!M32 -> -1387.147 | G15: ='Active Case'!N32 -> -1611.8549 | H15: ='Active Case'!O32 -> -1848.9219 | I15: ='Active Case'!P32 -> -2099.0275 | J15: ='Active Case'!Q32 -> -2362.8889 | K15: ='Active Case'!R32 -> -2641.2627 | L15: ='Active Case'!S32 -> -2934.947
D16: 100% Inditex Operating EBIT (Unlevered Tax Base) | E16: =+E14+E15 -> 7759 | F16: =+F14+F15 -> 8755.9802 | G16: =+G14+G15 -> 9310.4066 | H16: =+H14+H15 -> 9903.2569 | I16: =+I14+I15 -> 10536.952 | J16: =+J14+J15 -> 11214.059 | K16: =+K14+K15 -> 11937.297 | L16: =+L14+L15 -> 12709.552
D17: Gross BidCo LBO Financial Expenses (Cash + PIK Interest) | F17: ='Debt & Covenants'!F72 -> -3056.6012 | G17: ='Debt & Covenants'!G72 -> -2968.1669 | H17: ='Debt & Covenants'!H72 -> -2844.3587 | I17: ='Debt & Covenants'!I72 -> -2685.1769 | J17: ='Debt & Covenants'!J72 -> -2490.6212 | K17: ='Debt & Covenants'!K72 -> -2384.5 | L17: ='Debt & Covenants'!L72 -> -2384.5
D18: Tax Amortization of Upfront Structuring Fees (Linear over 7y) | F18: =-$E$11/$J$11 -> -119.54357 | G18: =-$E$11/$J$11 -> -119.54357 | H18: =-$E$11/$J$11 -> -119.54357 | I18: =-$E$11/$J$11 -> -119.54357 | J18: =-$E$11/$J$11 -> -119.54357 | K18: =-$E$11/$J$11 -> -119.54357 | L18: =-$E$11/$J$11 -> -119.54357
D19: Consolidated Accounting EBT before Art. 16.1 LIS Cap | F19: =+F16+F17+F18 -> 5579.8354 | G19: =+G16+G17+G18 -> 6222.6961 | H19: =+H16+H17+H18 -> 6939.3546 | I19: =+I16+I17+I18 -> 7732.2317 | J19: =+J16+J17+J18 -> 8603.8939 | K19: =+K16+K17+K18 -> 9433.2537 | L19: =+L16+L17+L18 -> 10205.508
D20: Plus: Non-Deductible Interest Added Back (> 30% EBITDA Cap) | F20: =+F30 -> 133.20668 | G20: =+G30 -> 0 | H20: =+H30 -> 0 | I20: =+I30 -> 0 | J20: =+J30 -> 0 | K20: =+K30 -> 0 | L20: =+L30 -> 0
D21: Less: Prior-Year Non-Deducted Interest Recovered in Period | F21: =+F34 -> 0 | G21: =+G34 -> -133.20668 | H21: =+H34 -> 0 | I21: =+I34 -> 0 | J21: =+J34 -> 0 | K21: =+K34 -> 0 | L21: =+L34 -> 0
D22: Cash Corporate Income Tax Paid (CIT @ 25% on Consolidated Tax Base) | F22: =-MAX(0,F23)*$E$7 -> -1428.2605 | G22: =-MAX(0,G23)*$E$7 -> -1522.3724 | H22: =-MAX(0,H23)*$E$7 -> -1734.8387 | I22: =-MAX(0,I23)*$E$7 -> -1933.0579 | J22: =-MAX(0,J23)*$E$7 -> -2150.9735 | K22: =-MAX(0,K23)*$E$7 -> -2358.3134 | L22: =-MAX(0,L23)*$E$7 -> -2551.3771
D23: Adjusted Consolidated Taxable Income (Base Imponible Fiscal) | F23: =+F19+F20+F21 -> 5713.042 | G23: =+G19+G20+G21 -> 6089.4895 | H23: =+H19+H20+H21 -> 6939.3546 | I23: =+I19+I20+I21 -> 7732.2317 | J23: =+J19+J20+J21 -> 8603.8939 | K23: =+K19+K20+K21 -> 9433.2537 | L23: =+L19+L20+L21 -> 10205.508
D24: Consolidated Net Income (100% Group Post-CIT) | F24: =+F19+F22 -> 4151.5749 | G24: =+G19+G22 -> 4700.3238 | H24: =+H19+H22 -> 5204.516 | I24: =+I19+I22 -> 5799.1738 | J24: =+J19+J22 -> 6452.9204 | K24: =+K19+K22 -> 7074.9403 | L24: =+L19+L22 -> 7654.1312
D26: Art. 16.1 LIS — 30% Operating EBITDA Cap & Carryforward Schedule
D27: 100% Fiscal Operating EBITDA (Pre-IFRS 16 Cash EBITDA) | F27: =+F14 -> 10143.127 | G27: =+G14 -> 10922.262 | H27: =+H14 -> 11752.179 | I27: =+I14 -> 12635.98 | J27: =+J14 -> 13576.948 | K27: =+K14 -> 14578.56 | L27: =+L14 -> 15644.499
D28: 30% EBITDA Interest Deductibility Limit (MAX 30% EBITDA, €1m) | F28: =+MAX($E$9,$E$8*F27) -> 3042.9381 | G28: =+MAX($E$9,$E$8*G27) -> 3276.6785 | H28: =+MAX($E$9,$E$8*H27) -> 3525.6536 | I28: =+MAX($E$9,$E$8*I27) -> 3790.7939 | J28: =+MAX($E$9,$E$8*J27) -> 4073.0843 | K28: =+MAX($E$9,$E$8*K27) -> 4373.568 | L28: =+MAX($E$9,$E$8*L27) -> 4693.3497
D29: Total Financial Expense Subject to Art. 16.1 LIS (Interest + Fee Amort.) | F29: =-(F17+F18) -> 3176.1448 | G29: =-(G17+G18) -> 3087.7104 | H29: =-(H17+H18) -> 2963.9023 | I29: =-(I17+I18) -> 2804.7204 | J29: =-(J17+J18) -> 2610.1648 | K29: =-(K17+K18) -> 2504.0436 | L29: =-(L17+L18) -> 2504.0436
D30: Current-Year Non-Deductible Financial Expense (Excess over 30% Cap) | F30: =+MAX(0,F29-F28) -> 133.20668 | G30: =+MAX(0,G29-G28) -> 0 | H30: =+MAX(0,H29-H28) -> 0 | I30: =+MAX(0,I29-I28) -> 0 | J30: =+MAX(0,J29-J28) -> 0 | K30: =+MAX(0,K29-K28) -> 0 | L30: =+MAX(0,L29-L28) -> 0
D31: Unused 30% EBITDA Headroom Generated in Year (5-Year Carryforward) | F31: =+MAX(0,F28-F29) -> 0 | G31: =+MAX(0,G28-G29) -> 188.96801 | H31: =+MAX(0,H28-H29) -> 561.75132 | I31: =+MAX(0,I28-I29) -> 986.07343 | J31: =+MAX(0,J28-J29) -> 1462.9194 | K31: =+MAX(0,K28-K29) -> 1869.5244 | L31: =+MAX(0,L28-L29) -> 2189.3061
D32: BoP Non-Deducted Interest Carryforward Balance | F32: =+E35 -> 0 | G32: =+F35 -> 133.20668 | H32: =+G35 -> 0 | I32: =+H35 -> 0 | J32: =+I35 -> 0 | K32: =+J35 -> 0 | L32: =+K35 -> 0
D33: Plus: New Non-Deductible Interest in Year | F33: =+F30 -> 133.20668 | G33: =+G30 -> 0 | H33: =+H30 -> 0 | I33: =+I30 -> 0 | J33: =+J30 -> 0 | K33: =+K30 -> 0 | L33: =+L30 -> 0
D34: Less: Carryforward Interest Deducted Using Unused EBITDA Capacity | F34: =-MIN(F32,F31) -> 0 | G34: =-MIN(G32,G31) -> -133.20668 | H34: =-MIN(H32,H31) -> 0 | I34: =-MIN(I32,I31) -> 0 | J34: =-MIN(J32,J31) -> 0 | K34: =-MIN(K32,K31) -> 0 | L34: =-MIN(L32,L31) -> 0
D35: EoP Non-Deducted Interest Carryforward Balance (Tax Asset) | E35: 0 | F35: =+F32+F33+F34 -> 133.20668 | G35: =+G32+G33+G34 -> 0 | H35: =+H32+H33+H34 -> 0 | I35: =+I32+I33+I34 -> 0 | J35: =+J32+J33+J34 -> 0 | K35: =+K32+K33+K34 -> 0 | L35: =+L32+L33+L34 -> 0
D37: Unlevered Taxes (Hypothetical CIT if Debt = 0) | F37: =-MAX(0,F16)*$E$7 -> -2188.995 | G37: =-MAX(0,G16)*$E$7 -> -2327.6016 | H37: =-MAX(0,H16)*$E$7 -> -2475.8142 | I37: =-MAX(0,I16)*$E$7 -> -2634.238 | J37: =-MAX(0,J16)*$E$7 -> -2803.5147 | K37: =-MAX(0,K16)*$E$7 -> -2984.3243 | L37: =-MAX(0,L16)*$E$7 -> -3177.388
D38: Theoretical Maximum Tax Shield (25% × Total Interest + Fee Amort.) | F38: =+F29*$E$7 -> 794.03621 | G38: =+G29*$E$7 -> 771.92761 | H38: =+H29*$E$7 -> 740.97558 | I38: =+I29*$E$7 -> 701.18011 | J38: =+J29*$E$7 -> 652.54121 | K38: =+K29*$E$7 -> 626.01089 | L38: =+L29*$E$7 -> 626.01089
D39: Actual Realized Cash Tax Shield (Unlevered CIT - Actual Levered CIT) | F39: =+F22-F37 -> 760.73454 | G39: =+G22-G37 -> 805.22928 | H39: =+H22-H37 -> 740.97558 | I39: =+I22-I37 -> 701.18011 | J39: =+J22-J37 -> 652.54121 | K39: =+K22-K37 -> 626.01089 | L39: =+L22-L37 -> 626.01089
D40: Tax Shield Efficiency (% of Theoretical Shield Realized in Cash) | F40: =+IFERROR(F39/F38,0) -> 0.95806026 | G40: =+IFERROR(G39/G38,0) -> 1.0431409 | H40: =+IFERROR(H39/H38,0) -> 1 | I40: =+IFERROR(I39/I38,0) -> 1 | J40: =+IFERROR(J39/J38,0) -> 1 | K40: =+IFERROR(K39/K38,0) -> 1 | L40: =+IFERROR(L39/L38,0) -> 1
D41: Effective Tax Shield Rate on Financial Expenses (t_eff %) | F41: =+IFERROR(F39/F29,0) -> 0.23951507 | G41: =+IFERROR(G39/G29,0) -> 0.26078523 | H41: =+IFERROR(H39/H29,0) -> 0.25 | I41: =+IFERROR(I39/I29,0) -> 0.25 | J41: =+IFERROR(J39/J29,0) -> 0.25 | K41: =+IFERROR(K39/K29,0) -> 0.25 | L41: =+IFERROR(L39/L29,0) -> 0.25
A44: > | B44: > | C44: 2. Dynamic WACC Evolution Due to De-Leveraging & Art. 16.1 LIS Tax Shield (2025A–2032E)
B46: 8 | D46: Implied 100% Inditex Enterprise Value (EV at Entry Multiple) | E46: ='LBO Summary'!E51 -> 170403.1 | F46: ='LBO Summary'!F51 -> 183231.24 | G46: ='LBO Summary'!G51 -> 197305.97 | H46: ='LBO Summary'!H51 -> 212298.07 | I46: ='LBO Summary'!I51 -> 228263.55 | J46: ='LBO Summary'!J51 -> 245261.73 | K46: ='LBO Summary'!K51 -> 263355.43 | L46: ='LBO Summary'!L51 -> 282611.16
D47: 100% Consolidated Net Financial Debt (EoP) | E47: ='Debt & Covenants'!E70 -> 50381.5 | F47: ='Debt & Covenants'!F70 -> 46678.856 | G47: ='Debt & Covenants'!G70 -> 42312.172 | H47: ='Debt & Covenants'!H70 -> 37317.806 | I47: ='Debt & Covenants'!I70 -> 31598.5 | J47: ='Debt & Covenants'!J70 -> 25088.001 | K47: ='Debt & Covenants'!K70 -> 17810.474 | L47: ='Debt & Covenants'!L70 -> 9800.7749
D48: Implied 100% TopCo Equity Value (E = EV - Net Debt) | E48: =+E46-E47 -> 120021.6 | F48: =+F46-F47 -> 136552.38 | G48: =+G46-G47 -> 154993.79 | H48: =+H46-H47 -> 174980.26 | I48: =+I46-I47 -> 196665.05 | J48: =+J46-J47 -> 220173.73 | K48: =+K46-K47 -> 245544.95 | L48: =+L46-L47 -> 272810.38
D49: Net Debt / Equity Ratio (D / E) | E49: =+MAX(0,E47/E48) -> 0.41977029 | F49: =+MAX(0,F47/F48) -> 0.34183846 | G49: =+MAX(0,G47/G48) -> 0.27299268 | H49: =+MAX(0,H47/H48) -> 0.21326866 | I49: =+MAX(0,I47/I48) -> 0.16067166 | J49: =+MAX(0,J47/J48) -> 0.11394639 | K49: =+MAX(0,K47/K48) -> 0.072534475 | L49: =+MAX(0,L47/L48) -> 0.035925227
D50: Debt Weight in Capital Structure (D / V) | E50: =+MAX(0,E47/E46) -> 0.29566071 | F50: =+MAX(0,F47/F46) -> 0.25475381 | G50: =+MAX(0,G47/G46) -> 0.21444953 | H50: =+MAX(0,H47/H46) -> 0.17578024 | I50: =+MAX(0,I47/I46) -> 0.1384299 | J50: =+MAX(0,J47/J46) -> 0.10229073 | K50: =+MAX(0,K47/K46) -> 0.067629038 | L50: =+MAX(0,L47/L46) -> 0.034679363
D51: Equity Weight in Capital Structure (E / V) | E51: =1-E50 -> 0.70433929 | F51: =1-F50 -> 0.74524619 | G51: =1-G50 -> 0.78555047 | H51: =1-H50 -> 0.82421976 | I51: =1-I50 -> 0.8615701 | J51: =1-J50 -> 0.89770927 | K51: =1-K50 -> 0.93237096 | L51: =1-L50 -> 0.96532064
D53: Unlevered Cost of Equity (Ku = Rf + Beta_U × ERP) | E53: =+$J$7+$J$9*$J$8 -> 0.0744 | F53: =+$J$7+$J$9*$J$8 -> 0.0744 | G53: =+$J$7+$J$9*$J$8 -> 0.0744 | H53: =+$J$7+$J$9*$J$8 -> 0.0744 | I53: =+$J$7+$J$9*$J$8 -> 0.0744 | J53: =+$J$7+$J$9*$J$8 -> 0.0744 | K53: =+$J$7+$J$9*$J$8 -> 0.0744 | L53: =+$J$7+$J$9*$J$8 -> 0.0744
D54: Dynamic Levered Beta: Beta_L = Beta_U × [1 + (1 - t_eff) × (D/E)] | E54: =+$J$9*(1+(1-$E$7)*E49) -> 1.0255656 | F54: =+$J$9*(1+(1-F41)*F49) -> 0.98277114 | G54: =+$J$9*(1+(1-G41)*G49) -> 0.93740417 | H54: =+$J$9*(1+(1-H41)*H49) -> 0.90476217 | I54: =+$J$9*(1+(1-I41)*I49) -> 0.87399292 | J54: =+$J$9*(1+(1-J41)*J49) -> 0.84665864 | K54: =+$J$9*(1+(1-K41)*K49) -> 0.82243267 | L54: =+$J$9*(1+(1-L41)*L49) -> 0.80101626
D55: Dynamic Cost of Levered Equity: Ke = Rf + Beta_L × ERP | E55: =+$J$7+E54*$J$8 -> 0.087906109 | F55: =+$J$7+F54*$J$8 -> 0.085552413 | G55: =+$J$7+G54*$J$8 -> 0.08305723 | H55: =+$J$7+H54*$J$8 -> 0.081261919 | I55: =+$J$7+I54*$J$8 -> 0.079569611 | J55: =+$J$7+J54*$J$8 -> 0.078066225 | K55: =+$J$7+K54*$J$8 -> 0.076733797 | L55: =+$J$7+L54*$J$8 -> 0.075555894
D56: Pre-Tax Blended Cost of Debt (Kd Pre-Tax) | E56: ='Debt & Covenants'!$E$7 -> 0.059090909 | F56: =+IFERROR(-F17/'Debt & Covenants'!F64,'Debt & Covenants'!$E$7) -> 0.058915052 | G56: =+IFERROR(-G17/'Debt & Covenants'!G64,'Debt & Covenants'!$E$7) -> 0.058814539 | H56: =+IFERROR(-H17/'Debt & Covenants'!H64,'Debt & Covenants'!$E$7) -> 0.058835665 | I56: =+IFERROR(-I17/'Debt & Covenants'!I64,'Debt & Covenants'!$E$7) -> 0.058996432 | J56: =+IFERROR(-J17/'Debt & Covenants'!J64,'Debt & Covenants'!$E$7) -> 0.05933321 | K56: =+IFERROR(-K17/'Debt & Covenants'!K64,'Debt & Covenants'!$E$7) -> 0.063195696 | L56: =+IFERROR(-L17/'Debt & Covenants'!L64,'Debt & Covenants'!$E$7) -> 0.063195696
D57: Effective Tax Shield Rate (t_eff — Capped/Boosted by Art. 16.1 LIS) | E57: =+$E$7 -> 0.25 | F57: =+F41 -> 0.23951507 | G57: =+G41 -> 0.26078523 | H57: =+H41 -> 0.25 | I57: =+I41 -> 0.25 | J57: =+J41 -> 0.25 | K57: =+K41 -> 0.25 | L57: =+L41 -> 0.25
D58: After-Tax Effective Cost of Debt: Kd × (1 - t_eff) | E58: =+E56*(1-E57) -> 0.044318182 | F58: =+F56*(1-F57) -> 0.044804009 | G58: =+G56*(1-G57) -> 0.043476576 | H58: =+H56*(1-H57) -> 0.044126749 | I58: =+I56*(1-I57) -> 0.044247324 | J58: =+J56*(1-J57) -> 0.044499907 | K58: =+K56*(1-K57) -> 0.047396772 | L58: =+L56*(1-L57) -> 0.047396772
D59: Dynamic WACC (Modigliani-Miller / Hamada w/ Spanish Tax Cap) | E59: =+E55*E51+E58*E50 -> 0.075018872 | F59: =+F55*F51+F58*F50 -> 0.075171602 | G59: =+G55*G51+G58*G50 -> 0.074569177 | H59: =+H55*H51+H58*H50 -> 0.07473429 | I59: =+I55*I51+I58*I50 -> 0.07467995 | J59: =+J55*J51+J58*J50 -> 0.074632702 | K59: =+K55*K51+K58*K50 -> 0.074749762 | L59: =+L55*L51+L58*L50 -> 0.074579354
D60: WACC Reduction vs. Unlevered Ku (Net Tax Shield Benefit) | E60: =+E59-E53 -> 0.00061887162 | F60: =+F59-F53 -> 0.00077160161 | G60: =+G59-G53 -> 0.00016917698 | H60: =+H59-H53 -> 0.00033428988 | I60: =+I59-I53 -> 0.0002799501 | J60: =+J59-J53 -> 0.00023270193 | K60: =+K59-K53 -> 0.00034976196 | L60: =+L59-L53 -> 0.00017935376
D62: Cumulative Cash Tax Shield Realized (2026E–2032E, €m) | E62: =+SUM(F39:L39) -> 4912.6825
D63: Present Value of Realized Tax Shields Discounted @ Ku (APV Tax Shield, €m) | E63: =+NPV(E53,F39:L39) -> 3770.9031
D64: Remaining Non-Deducted Interest Tax Asset at 2032E Exit (€m) | E64: =+L35 -> 0

Sheet Checks
B1: Project Galicia v3 — Inditex (ITX.MC) | F1: Strictly Private & Confidential
A2: > | B2: Master Model Integrity, Legal Take-Private & Spanish Tax Compliance Checks
C4: ID | D4: Audit Check Description | E4: Diff / Metric | F4: Status
C5: 1 | D5: 1. Sources & Uses of Funds Balance Check | E5: ='LBO Summary'!E40-'LBO Summary'!J40 -> 0 | F5: =IF(ABS(E5)<0.01,"OK","CHECK") -> OK
C6: 2 | D6: 2. TopCo Common Equity Ownership Sums to 100.0% | E6: ='LBO Summary'!F45-1 -> 0 | F6: =IF(ABS(E6)<0.0001,"OK","CHECK") -> OK
C7: 3 | D7: 3. Art. 58 LIS Fiscal Consolidation Threshold (>= 75% = 100%) | E7: ='LBO Summary'!F14+'LBO Summary'!F15 -> 1 | F7: =IF(E7>=0.75,"OK","CHECK") -> OK
C8: 4 | D8: 4. Art. 16.5 LIS Anti-LBO Debt Cap (Debt < 70% Purchase Value) | E8: ='Tax & WACC'!J10-'Tax & WACC'!E10 -> -0.41393259 | F8: =IF(E8<=0,"OK","BREACH") -> OK
C9: 5 | D9: 5. Senior TLA Scheduled Amortisation Sums to 100% | E9: ='Debt & Covenants'!M25 -> 0 | F9: =IF(ABS(E9)<0.0001,"OK","CHECK") -> OK
C10: 6 | D10: 6. Minimum Operational Cash Floor (€1,500m) Respected | E10: =MIN('Debt & Covenants'!E93:L93)-'Debt & Covenants'!E92 -> 0 | F10: =IF(E10>=-0.01,"OK","CHECK") -> OK
C11: 7 | D11: 7. Non-Negative Debt Tranche Balances (All Years) | E11: =MIN('Debt & Covenants'!E24:L24,'Debt & Covenants'!E34:L34,'Debt & Covenants'!E43:L43,'Debt & Covenants'!E52:L52) -> 0 | F11: =IF(E11>=-0.01,"OK","CHECK") -> OK
C12: 8 | D12: 8. P&L D&A Reconciled to Capex Vintage Schedule | E12: =MAX(ABS('Active Case'!M32-'Active Case'!M49),ABS('Active Case'!S32-'Active Case'!S49)) -> 0 | F12: =IF(E12<0.01,"OK","CHECK") -> OK
C13: 9 | D13: 9. SFA Net Leverage Covenant Compliance (All Years) | E13: =COUNTIF('Debt & Covenants'!E102:L102,"BREACH") -> 0 | F13: =IF(E13=0,"OK","BREACH") -> OK
C14: 10 | D14: 10. Bank DSCR Covenant Compliance (All Years) | E14: =COUNTIF('Debt & Covenants'!F108:L108,"BREACH") -> 0 | F14: =IF(E14=0,"OK","BREACH") -> OK
